Workbook

Sheet Liverpool vs Path Comms
A1: FactorType | B1: FactorName | C1: NodeColor | D1: =VLOOKUP(C1,CATA!A:B,2,FALSE) -> HexColor | E1: Attribute | F1: HexColorAtt | G1: Orden | I1: Path = Right
A2: Path | B2: Facilidad flexibilidad y ágil | C2: Kantar Orange | D2: =_xlfn.IFNA(VLOOKUP(C2,Table1[],2,FALSE),"") -> #FF5000 | E2: Acepta devoluciones fácilmente | F2: #FF5000 | G2: 41 | I2: Tracking = Left
A3: Path | B3: Facilidad flexibilidad y ágil | C3: Kantar Orange | D3: =_xlfn.IFNA(VLOOKUP(C3,Table1[],2,FALSE),"") -> #FF5000 | E3: Cuenta con la mejor tarjeta de crédito | F3: #FF5000 | G3: 59 | L3: Confianza & Cercanía
A4: Path | B4: Servicio de calidad en tienda física | C4: Kantar Yellow | D4: =_xlfn.IFNA(VLOOKUP(C4,Table1[],2,FALSE),"") -> #FEDB00 | E4: El personal me apoya a comparar en línea si el producto no está | F4: #FEDB00 | G4: 52 | L4: Confianza & Cercanía
A5: Path | B5: Servicio de calidad en tienda física | C5: Kantar Yellow | D5: =_xlfn.IFNA(VLOOKUP(C5,Table1[],2,FALSE),"") -> #FEDB00 | E5: El personal resuelve problemas y dudas | F5: #FEDB00 | G5: 38 | L5: Confianza & Cercanía
A6: Path | B6: Confianza, calidad y vanguardia | C6: Kantar Purple | D6: =_xlfn.IFNA(VLOOKUP(C6,Table1[],2,FALSE),"") -> #802AB7 | E6: Encuentra variedad de tallas | F6: #802AB7 | G6: 34 | L6: Confianza & Cercanía
A7: Path | B7: Conexión emocional | C7: Kantar Teal | D7: =_xlfn.IFNA(VLOOKUP(C7,Table1[],2,FALSE),"") -> #00E5BA | E7: Es un lugar donde encuentro todo lo que necesito y/o busco | F7: #00E5BA | G7: 48 | L7: Confianza & Cercanía
A8: Path | B8: Servicio de calidad en tienda física | C8: Kantar Yellow | D8: =_xlfn.IFNA(VLOOKUP(C8,Table1[],2,FALSE),"") -> #FEDB00 | E8: Es un lugar donde le atienden rápido | F8: #FEDB00 | G8: 37 | L8: Confianza & Cercanía | M8: Es una tienda que me invita a visitarla
A9: Path | B9: Estatus vigente y renovado | C9: Kantar Blue | D9: =_xlfn.IFNA(VLOOKUP(C9,Table1[],2,FALSE),"") -> #0060FF | E9: Es una marca actual y vigente | F9: #0060FF | G9: 57 | L9: Confianza & Cercanía
A10: Path | B10: Confianza, calidad y vanguardia | C10: Kantar Purple | D10: =_xlfn.IFNA(VLOOKUP(C10,Table1[],2,FALSE),"") -> #802AB7 | E10: Es una marca que me transmite confianza tanto en tienda como en línea | F10: #802AB7 | G10: 49 | L10: Conexión Emocional
A11: Path | B11: Medio Ambiente | C11: Kantar Light Grey | D11: =_xlfn.IFNA(VLOOKUP(C11,Table1[],2,FALSE),"") -> #D9D9D9 | E11: Es una marca que se preocupa por el medio ambiente | F11: #D9D9D9 | G11: 43 | L11: Conexión Emocional
A12: Path | B12: Confianza, calidad y vanguardia | C12: Kantar Purple | D12: =_xlfn.IFNA(VLOOKUP(C12,Table1[],2,FALSE),"") -> #802AB7 | E12: Es una tienda autorizada y respaldada por marcas de calidad | F12: #802AB7 | G12: 51 | L12: Conexión Emocional
A13: Path | B13: Confianza, calidad y vanguardia | C13: Kantar Purple | D13: =_xlfn.IFNA(VLOOKUP(C13,Table1[],2,FALSE),"") -> #802AB7 | E13: Es una tienda innovadora | F13: #802AB7 | G13: 32 | L13: Conveniente
A14: Path | B14: Conexión emocional | C14: Kantar Teal | D14: =_xlfn.IFNA(VLOOKUP(C14,Table1[],2,FALSE),"") -> #00E5BA | E14: Es una tienda para mí / con la que me identifico | F14: #00E5BA | G14: 60 | L14: Conveniente
A15: Path | B15: Conexión emocional | C15: Kantar Teal | D15: =_xlfn.IFNA(VLOOKUP(C15,Table1[],2,FALSE),"") -> #00E5BA | E15: Hace posible que viva mejor cada día | F15: #00E5BA | G15: 62 | L15: Conveniente
A16: Path | B16: Conveniencia online | C16: Kantar Green | D16: =_xlfn.IFNA(VLOOKUP(C16,Table1[],2,FALSE),"") -> #00B600 | E16: La tienda online tiene reseñas reales que la hacen confiable | F16: #00B600 | G16: 36 | L16: Conveniente
A17: Path | B17: Estatus vigente y renovado | C17: Kantar Blue | D17: =_xlfn.IFNA(VLOOKUP(C17,Table1[],2,FALSE),"") -> #0060FF | E17: Me ayuda a reflejar mi éxito | F17: #0060FF | G17: 56 | L17: Conveniente
A18: Path | B18: Estatus vigente y renovado | C18: Kantar Blue | D18: =_xlfn.IFNA(VLOOKUP(C18,Table1[],2,FALSE),"") -> #0060FF | E18: Me da mayor estatus social | F18: #0060FF | G18: 40 | L18: Facilidad & Flexibilidad
A19: Path | B19: Conexión emocional | C19: Kantar Teal | D19: =_xlfn.IFNA(VLOOKUP(C19,Table1[],2,FALSE),"") -> #00E5BA | E19: Me ha acompañado a lo largo de mi vida | F19: #00E5BA | G19: 61 | L19: Facilidad & Flexibilidad
A20: Path | B20: Conveniencia online | C20: Kantar Green | D20: =_xlfn.IFNA(VLOOKUP(C20,Table1[],2,FALSE),"") -> #00B600 | E20: Ofrece las mejores garantías | F20: #00B600 | G20: 39 | L20: Practicidad
A21: Path | B21: Servicio de calidad en tienda física | C21: Kantar Yellow | D21: =_xlfn.IFNA(VLOOKUP(C21,Table1[],2,FALSE),"") -> #FEDB00 | E21: Ofrece un servicio cálido, cercano, respetuoso y atento | F21: #FEDB00 | G21: 54 | L21: Practicidad | M21: Me permite hacer compras de manera práctica y cómoda
A22: Path | B22: Precios | C22: Kantar Red | D22: =_xlfn.IFNA(VLOOKUP(C22,Table1[],2,FALSE),"") -> #FA0028 | E22: Ropa/calzado y accesorios valen el precio que se paga | F22: #FA0028 | G22: 44 | L22: Practicidad
A23: Path | B23: Conveniencia online | C23: Kantar Green | D23: =_xlfn.IFNA(VLOOKUP(C23,Table1[],2,FALSE),"") -> #00B600 | E23: Su página web / app es segura, fácil y sencilla de navegar | F23: #00B600 | G23: 46 | L23: Estatus Renovado
A24: Path | B24: Estatus vigente y renovado | C24: Kantar Blue | D24: =_xlfn.IFNA(VLOOKUP(C24,Table1[],2,FALSE),"") -> #0060FF | E24: Su publicidad me dice algo relevante de la marca | F24: #0060FF | G24: 58 | L24: Estatus Renovado | M24: En su última campaña, la marca transmite una sensación de renovación
A25: Path | B25: Conveniencia online | C25: Kantar Green | D25: =_xlfn.IFNA(VLOOKUP(C25,Table1[],2,FALSE),"") -> #00B600 | E25: Su sitio online tiene las mejores descripciones de productos | F25: #00B600 | G25: 47
A26: Path | B26: Precios | C26: Kantar Red | D26: =_xlfn.IFNA(VLOOKUP(C26,Table1[],2,FALSE),"") -> #FA0028 | E26: Tiene las mejores promociones | F26: #FA0028 | G26: 53
A27: Path | B27: Confianza, calidad y vanguardia | C27: Kantar Purple | D27: =_xlfn.IFNA(VLOOKUP(C27,Table1[],2,FALSE),"") -> #802AB7 | E27: Tiene las opciones de pago adecuadas (crédito, efectivo, pagos digitales) | F27: #802AB7 | G27: 35
A28: Path | B28: Confianza, calidad y vanguardia | C28: Kantar Purple | D28: =_xlfn.IFNA(VLOOKUP(C28,Table1[],2,FALSE),"") -> #802AB7 | E28: Tiene lo último de la moda | F28: #802AB7 | G28: 33
A29: Path | B29: Precios | C29: Kantar Red | D29: =_xlfn.IFNA(VLOOKUP(C29,Table1[],2,FALSE),"") -> #FA0028 | E29: Tiene los mejores precios | F29: #FA0028 | G29: 45
A30: Path | B30: Facilidad flexibilidad y ágil | C30: Kantar Orange | D30: =_xlfn.IFNA(VLOOKUP(C30,Table1[],2,FALSE),"") -> #FF5000 | E30: Tiene los mejores tiempos de entrega | F30: #FF5000 | G30: 42
A31: Path | B31: Servicio de calidad en tienda física | C31: Kantar Yellow | D31: =_xlfn.IFNA(VLOOKUP(C31,Table1[],2,FALSE),"") -> #FEDB00 | E31: Tiene un ambiente e instalaciones agradables | F31: #FEDB00 | G31: 55
A32: Path | B32: Confianza, calidad y vanguardia | C32: Kantar Purple | D32: =_xlfn.IFNA(VLOOKUP(C32,Table1[],2,FALSE),"") -> #802AB7 | E32: Tiene una amplia variedad de productos de calidad | F32: #802AB7 | G32: 50
A33: Tracking | B33: Facilidad y Flexibilidad | C33: Kantar Yellow | D33: =_xlfn.IFNA(VLOOKUP(C33,Table1[],2,FALSE),"") -> #FEDB00 | E33: Acepta devoluciones fácilmente | F33: #FF5000 | G33: 15
A34: Tracking | B34: Facilidad y Flexibilidad | C34: Kantar Yellow | D34: =_xlfn.IFNA(VLOOKUP(C34,Table1[],2,FALSE),"") -> #FEDB00 | E34: Cuenta con la mejor tarjeta de crédito | F34: #FF5000 | G34: 14
A35: Tracking | B35: NA | C35: Kantar Sand | D35: =_xlfn.IFNA(VLOOKUP(C35,Table1[],2,FALSE),"") -> #AEAE9F | E35: El personal me apoya a comparar en línea si el producto no está | F35: #FEDB00 | G35: 28
A36: Tracking | B36: NA | C36: Kantar Sand | D36: =_xlfn.IFNA(VLOOKUP(C36,Table1[],2,FALSE),"") -> #AEAE9F | E36: El personal resuelve problemas y dudas | F36: #FEDB00 | G36: 13
... A63: Tracking | B63: Confianza y cercanía | C63: Kantar Purple | D63: =_xlfn.IFNA(VLOOKUP(C63,Table1[],2,FALSE),"") -> #802AB7 | E63: Tiene una amplia variedad de productos de calidad | F63: #802AB7 | G63: 8

Sheet Liverpool vs Cat
A1: FactorType | B1: FactorName | C1: NodeColor | D1: =VLOOKUP(C1,CATA!A:B,2,FALSE) -> HexColor | E1: Attribute | F1: Orden | H1: Path = Right
A2: Path | B2: Conexión emocional | C2: Kantar Teal | D2: =_xlfn.IFNA(VLOOKUP(C2,Table1[],2,FALSE),"") -> #00E5BA | E2: Es una tienda para mí / con la que me identifico | F2: 32 | H2: Tracking = Left
A3: Path | B3: Conexión emocional | C3: Kantar Teal | D3: =_xlfn.IFNA(VLOOKUP(C3,Table1[],2,FALSE),"") -> #00E5BA | E3: Me ha acompañado a lo largo de mi vida | F3: 33
A4: Path | B4: Conexión emocional | C4: Kantar Teal | D4: =_xlfn.IFNA(VLOOKUP(C4,Table1[],2,FALSE),"") -> #00E5BA | E4: Hace posible que viva mejor cada día | F4: 34
A5: Path | B5: Conexión emocional | C5: Kantar Teal | D5: =_xlfn.IFNA(VLOOKUP(C5,Table1[],2,FALSE),"") -> #00E5BA | E5: Es un lugar donde encuentro todo lo que necesito y/o busco | F5: 35
A6: Path | B6: Confianza, calidad y vanguardia | C6: Kantar Purple | D6: =_xlfn.IFNA(VLOOKUP(C6,Table1[],2,FALSE),"") -> #802AB7 | E6: Es una marca que me transmite confianza tanto en tienda como en línea | F6: 36
A7: Path | B7: Confianza, calidad y vanguardia | C7: Kantar Purple | D7: =_xlfn.IFNA(VLOOKUP(C7,Table1[],2,FALSE),"") -> #802AB7 | E7: Tiene una amplia variedad de productos de calidad | F7: 37
A8: Path | B8: Confianza, calidad y vanguardia | C8: Kantar Purple | D8: =_xlfn.IFNA(VLOOKUP(C8,Table1[],2,FALSE),"") -> #802AB7 | E8: Es una tienda autorizada y respaldada por marcas de calidad | F8: 38
A9: Path | B9: Confianza, calidad y vanguardia | C9: Kantar Purple | D9: =_xlfn.IFNA(VLOOKUP(C9,Table1[],2,FALSE),"") -> #802AB7 | E9: Es una tienda innovadora | F9: 39
A10: Path | B10: Confianza, calidad y vanguardia | C10: Kantar Purple | D10: =_xlfn.IFNA(VLOOKUP(C10,Table1[],2,FALSE),"") -> #802AB7 | E10: Tiene lo último de la moda | F10: 40 | I10: Emocional | J10: Es una tienda para mí / con la que me identifico
A11: Path | B11: Confianza, calidad y vanguardia | C11: Kantar Purple | D11: =_xlfn.IFNA(VLOOKUP(C11,Table1[],2,FALSE),"") -> #802AB7 | E11: Encuentra variedad de tallas | F11: 41 | I11: Emocional | J11: Hace posible que viva mejor cada día
A12: Path | B12: Confianza, calidad y vanguardia | C12: Kantar Purple | D12: =_xlfn.IFNA(VLOOKUP(C12,Table1[],2,FALSE),"") -> #802AB7 | E12: Tiene las opciones de pago adecuadas (crédito, efectivo, pagos digitales) | F12: 42 | I12: Emocional | J12: Me ha acompañado a lo largo de mi vida
A13: Path | B13: Conveniencia online | C13: Kantar Green | D13: =_xlfn.IFNA(VLOOKUP(C13,Table1[],2,FALSE),"") -> #00B600 | E13: La tienda online tiene reseñas de otros clientes, con calificaciones e imágenes reales que la hacen confiable | F13: 43 | I13: Emocional | J13: Es una marca que me transmite confianza tanto en tienda como en línea
A14: Path | B14: Conveniencia online | C14: Kantar Green | D14: =_xlfn.IFNA(VLOOKUP(C14,Table1[],2,FALSE),"") -> #00B600 | E14: Su página web / app es segura, fácil y sencilla de navegar | F14: 44 | I14: Emocional | J14: Ofrece un servicio cálido, cercano, respetuoso y atento
A15: Path | B15: Conveniencia online | C15: Kantar Green | D15: =_xlfn.IFNA(VLOOKUP(C15,Table1[],2,FALSE),"") -> #00B600 | E15: Su sitio online tiene las mejores descripciones de productos | F15: 45 | I15: Emocional | J15: Me ayuda a reflejar mi éxito
A16: Path | B16: Conveniencia online | C16: Kantar Green | D16: =_xlfn.IFNA(VLOOKUP(C16,Table1[],2,FALSE),"") -> #00B600 | E16: Ofrece las mejores garantías | F16: 46 | I16: Emocional | J16: Es una marca que se preocupa por el medio ambiente
A17: Path | B17: Estatus vigente y renovado | C17: Kantar Blue | D17: =_xlfn.IFNA(VLOOKUP(C17,Table1[],2,FALSE),"") -> #0060FF | E17: Me da mayor estatus social | F17: 47 | I17: Emocional | J17: Tiene un ambiente e instalaciones agradables
A18: Path | B18: Estatus vigente y renovado | C18: Kantar Blue | D18: =_xlfn.IFNA(VLOOKUP(C18,Table1[],2,FALSE),"") -> #0060FF | E18: Me ayuda a reflejar mi éxito | F18: 48 | I18: Emocional | J18: Me da mayor estatus social
A19: Path | B19: Estatus vigente y renovado | C19: Kantar Blue | D19: =_xlfn.IFNA(VLOOKUP(C19,Table1[],2,FALSE),"") -> #0060FF | E19: Es una marca actual y vigente | F19: 49
A20: Path | B20: Estatus vigente y renovado | C20: Kantar Blue | D20: =_xlfn.IFNA(VLOOKUP(C20,Table1[],2,FALSE),"") -> #0060FF | E20: Su publicidad me dice algo relevante de la marca | F20: 50 | I20: Funcional | J20: Es un lugar donde encuentro todo lo que necesito y/o busco
A21: Path | B21: Facilidad flexibilidad y ágil | C21: Kantar Orange | D21: =_xlfn.IFNA(VLOOKUP(C21,Table1[],2,FALSE),"") -> #FF5000 | E21: Cuenta con la mejor tarjeta de crédito | F21: 51 | I21: Funcional | J21: Tiene una amplia variedad de productos de calidad
A22: Path | B22: Facilidad flexibilidad y ágil | C22: Kantar Orange | D22: =_xlfn.IFNA(VLOOKUP(C22,Table1[],2,FALSE),"") -> #FF5000 | E22: Acepta devoluciones fácilmente | F22: 52 | I22: Funcional | J22: Es una marca actual y vigente
A23: Path | B23: Facilidad flexibilidad y ágil | C23: Kantar Orange | D23: =_xlfn.IFNA(VLOOKUP(C23,Table1[],2,FALSE),"") -> #FF5000 | E23: Tiene los mejores tiempos de entrega | F23: 53 | I23: Funcional | J23: Su publicidad me dice algo relevante de la marca
A24: Path | B24: Medio Ambiente | C24: Kantar Light Grey | D24: =_xlfn.IFNA(VLOOKUP(C24,Table1[],2,FALSE),"") -> #D9D9D9 | E24: Es una marca que se preocupa por el medio ambiente | F24: 54 | I24: Funcional | J24: Es una tienda autorizada y respaldada por marcas de calidad
A25: Path | B25: Precios | C25: Kantar Red | D25: =_xlfn.IFNA(VLOOKUP(C25,Table1[],2,FALSE),"") -> #FA0028 | E25: Ropa/calzado y accesorios valen el precio que se paga | F25: 55 | I25: Funcional | J25: Es una tienda innovadora
A26: Path | B26: Precios | C26: Kantar Red | D26: =_xlfn.IFNA(VLOOKUP(C26,Table1[],2,FALSE),"") -> #FA0028 | E26: Tiene los mejores precios | F26: 56 | I26: Funcional | J26: Encuentra variedad de tallas
A27: Path | B27: Precios | C27: Kantar Red | D27: =_xlfn.IFNA(VLOOKUP(C27,Table1[],2,FALSE),"") -> #FA0028 | E27: Tiene las mejores promociones | F27: 57 | I27: Funcional | J27: Cuenta con la mejor tarjeta de crédito
A28: Path | B28: Servicio de calidad en tienda física | C28: Kantar Yellow | D28: =_xlfn.IFNA(VLOOKUP(C28,Table1[],2,FALSE),"") -> #FEDB00 | E28: Ofrece un servicio cálido, cercano, respetuoso y atento | F28: 58 | I28: Funcional | J28: Tiene lo último de la moda
A29: Path | B29: Servicio de calidad en tienda física | C29: Kantar Yellow | D29: =_xlfn.IFNA(VLOOKUP(C29,Table1[],2,FALSE),"") -> #FEDB00 | E29: Tiene un ambiente e instalaciones agradables | F29: 59
A30: Path | B30: Servicio de calidad en tienda física | C30: Kantar Yellow | D30: =_xlfn.IFNA(VLOOKUP(C30,Table1[],2,FALSE),"") -> #FEDB00 | E30: Es un lugar donde le atienden rápido | F30: 60 | I30: Digital | J30: Su página web / app es segura, fácil y sencilla de navegar
A31: Path | B31: Servicio de calidad en tienda física | C31: Kantar Yellow | D31: =_xlfn.IFNA(VLOOKUP(C31,Table1[],2,FALSE),"") -> #FEDB00 | E31: El personal resuelve problemas y dudas | F31: 61 | I31: Digital | J31: Su sitio online tiene las mejores descripciones de productos
A32: Path | B32: Servicio de calidad en tienda física | C32: Kantar Yellow | D32: =_xlfn.IFNA(VLOOKUP(C32,Table1[],2,FALSE),"") -> #FEDB00 | E32: El personal me apoya a comparar en línea si el producto no está disponible en tienda | F32: 62 | I32: Digital | J32: La tienda online tiene reseñas de otros clientes, con calificaciones e imágenes reales que la hacen confiable
A33: Tracking | B33: Digital | C33: Kantar Green | D33: =_xlfn.IFNA(VLOOKUP(C33,Table1[],2,FALSE),"") -> #00B600 | E33: La tienda online tiene reseñas de otros clientes, con calificaciones e imágenes reales que la hacen confiable | F33: 12
A34: Tracking | B34: Digital | C34: Kantar Green | D34: =_xlfn.IFNA(VLOOKUP(C34,Table1[],2,FALSE),"") -> #00B600 | E34: Su página web / app es segura, fácil y sencilla de navegar | F34: 13 | I34: Servicios | J34: Tiene los mejores tiempos de entrega
A35: Tracking | B35: Digital | C35: Kantar Green | D35: =_xlfn.IFNA(VLOOKUP(C35,Table1[],2,FALSE),"") -> #00B600 | E35: Su sitio online tiene las mejores descripciones de productos | F35: 14 | I35: Servicios | J35: Acepta devoluciones fácilmente
A36: Tracking | B36: Emocional | C36: Kantar Teal | D36: =_xlfn.IFNA(VLOOKUP(C36,Table1[],2,FALSE),"") -> #00E5BA | E36: Es una tienda para mí / con la que me identifico | F36: 1 | I36: Servicios | J36: Ofrece las mejores garantías
A37: Tracking | B37: Emocional | C37: Kantar Teal | D37: =_xlfn.IFNA(VLOOKUP(C37,Table1[],2,FALSE),"") -> #00E5BA | E37: Me ha acompañado a lo largo de mi vida | F37: 2 | I37: Servicios | J37: Es un lugar donde le atienden rápido
A38: Tracking | B38: Emocional | C38: Kantar Teal | D38: =_xlfn.IFNA(VLOOKUP(C38,Table1[],2,FALSE),"") -> #00E5BA | E38: Hace posible que viva mejor cada día | F38: 3 | I38: Servicios | J38: Tiene las opciones de pago adecuadas (crédito, efectivo, pagos digitales)
A39: Tracking | B39: Emocional | C39: Kantar Teal | D39: =_xlfn.IFNA(VLOOKUP(C39,Table1[],2,FALSE),"") -> #00E5BA | E39: Es una marca que me transmite confianza tanto en tienda como en línea | F39: 5 | I39: Servicios | J39: El personal resuelve problemas y dudas
A40: Tracking | B40: Emocional | C40: Kantar Teal | D40: =_xlfn.IFNA(VLOOKUP(C40,Table1[],2,FALSE),"") -> #00E5BA | E40: Me da mayor estatus social | F40: 16 | I40: Servicios | J40: El personal me apoya a comparar en línea si el producto no está disponible en tienda
A41: Tracking | B41: Emocional | C41: Kantar Teal | D41: =_xlfn.IFNA(VLOOKUP(C41,Table1[],2,FALSE),"") -> #00E5BA | E41: Me ayuda a reflejar mi éxito | F41: 17
A42: Tracking | B42: Emocional | C42: Kantar Teal | D42: =_xlfn.IFNA(VLOOKUP(C42,Table1[],2,FALSE),"") -> #00E5BA | E42: Es una marca que se preocupa por el medio ambiente | F42: 23 | I42: Precios | J42: Tiene las mejores promociones
A43: Tracking | B43: Emocional | C43: Kantar Teal | D43: =_xlfn.IFNA(VLOOKUP(C43,Table1[],2,FALSE),"") -> #00E5BA | E43: Ofrece un servicio cálido, cercano, respetuoso y atento | F43: 27 | I43: Precios | J43: Tiene los mejores precios
A44: Tracking | B44: Emocional | C44: Kantar Teal | D44: =_xlfn.IFNA(VLOOKUP(C44,Table1[],2,FALSE),"") -> #00E5BA | E44: Tiene un ambiente e instalaciones agradables | F44: 28 | I44: Precios | J44: Ropa/calzado y accesorios valen el precio que se paga
A45: Tracking | B45: Funcional | C45: Kantar Purple | D45: =_xlfn.IFNA(VLOOKUP(C45,Table1[],2,FALSE),"") -> #802AB7 | E45: Es un lugar donde encuentro todo lo que necesito y/o busco | F45: 4
A46: Tracking | B46: Funcional | C46: Kantar Purple | D46: =_xlfn.IFNA(VLOOKUP(C46,Table1[],2,FALSE),"") -> #802AB7 | E46: Tiene una amplia variedad de productos de calidad | F46: 6
A47: Tracking | B47: Funcional | C47: Kantar Purple | D47: =_xlfn.IFNA(VLOOKUP(C47,Table1[],2,FALSE),"") -> #802AB7 | E47: Es una tienda autorizada y respaldada por marcas de calidad | F47: 7
A48: Tracking | B48: Funcional | C48: Kantar Purple | D48: =_xlfn.IFNA(VLOOKUP(C48,Table1[],2,FALSE),"") -> #802AB7 | E48: Es una tienda innovadora | F48: 8
A49: Tracking | B49: Funcional | C49: Kantar Purple | D49: =_xlfn.IFNA(VLOOKUP(C49,Table1[],2,FALSE),"") -> #802AB7 | E49: Tiene lo último de la moda | F49: 9
A50: Tracking | B50: Funcional | C50: Kantar Purple | D50: =_xlfn.IFNA(VLOOKUP(C50,Table1[],2,FALSE),"") -> #802AB7 | E50: Encuentra variedad de tallas | F50: 10
A51: Tracking | B51: Funcional | C51: Kantar Purple | D51: =_xlfn.IFNA(VLOOKUP(C51,Table1[],2,FALSE),"") -> #802AB7 | E51: Es una marca actual y vigente | F51: 18
A52: Tracking | B52: Funcional | C52: Kantar Purple | D52: =_xlfn.IFNA(VLOOKUP(C52,Table1[],2,FALSE),"") -> #802AB7 | E52: Su publicidad me dice algo relevante de la marca | F52: 19
A53: Tracking | B53: Funcional | C53: Kantar Purple | D53: =_xlfn.IFNA(VLOOKUP(C53,Table1[],2,FALSE),"") -> #802AB7 | E53: Cuenta con la mejor tarjeta de crédito | F53: 20
A54: Tracking | B54: Precios | C54: Kantar Red | D54: =_xlfn.IFNA(VLOOKUP(C54,Table1[],2,FALSE),"") -> #FA0028 | E54: Ropa/calzado y accesorios valen el precio que se paga | F54: 24
A55: Tracking | B55: Precios | C55: Kantar Red | D55: =_xlfn.IFNA(VLOOKUP(C55,Table1[],2,FALSE),"") -> #FA0028 | E55: Tiene los mejores precios | F55: 25
A56: Tracking | B56: Precios | C56: Kantar Red | D56: =_xlfn.IFNA(VLOOKUP(C56,Table1[],2,FALSE),"") -> #FA0028 | E56: Tiene las mejores promociones | F56: 26
... A63: Tracking | B63: Servicios | C63: Kantar Blue | D63: =_xlfn.IFNA(VLOOKUP(C63,Table1[],2,FALSE),"") -> #0060FF | E63: El personal me apoya a comparar en línea si el producto no está disponible en tienda | F63: 31

Sheet Empeños
A1: FactorType | B1: FactorName | C1: NodeColor | D1: =VLOOKUP(C1,CATA!A:B,2,FALSE) -> HexColor | E1: Attribute | H1: Path = Right
A2: Path | B2: Confianza y flexibilidad - 20.0% | C2: Kantar Blue | D2: =_xlfn.IFNA(VLOOKUP(C2,Table1[],2,FALSE),"") -> #0060FF | E2: Cuida mejor la prenda/ te la regresan en buen estado | H2: Tracking = Left | K2: Emo-Funcional 34.9%
A3: Tracking | B3: Cuidado al cliente - 22% | C3: Kantar Yellow | D3: =_xlfn.IFNA(VLOOKUP(C3,Table1[],2,FALSE),"") -> #FEDB00 | E3: Cuida mejor la prenda/ te la regresan en buen estado | K3: Emo-Funcional 34.9%
A4: Path | B4: Mejores condiciones y recompensas - 20.0% | C4: Kantar Blue | D4: =_xlfn.IFNA(VLOOKUP(C4,Table1[],2,FALSE),"") -> #0060FF | E4: Después de empeñar, brinda atención para ayudarme a recuperarla | K4: Emo-Funcional 34.9%
A5: Tracking | B5: Cuidado al cliente - 22% | C5: Kantar Yellow | D5: =_xlfn.IFNA(VLOOKUP(C5,Table1[],2,FALSE),"") -> #FEDB00 | E5: Después de empeñar, brinda atención para ayudarme a recuperarla | K5: Emo-Funcional 34.9%
A6: Path | B6: Confianza y flexibilidad - 20.0% | C6: Kantar Blue | D6: =_xlfn.IFNA(VLOOKUP(C6,Table1[],2,FALSE),"") -> #0060FF | E6: Entiende lo que necesito | K6: Emo-Funcional 34.9%
A7: Tracking | B7: Sensación de control - 19% | C7: Kantar Purple | D7: =_xlfn.IFNA(VLOOKUP(C7,Table1[],2,FALSE),"") -> #802AB7 | E7: Entiende lo que necesito | K7: Emo-Funcional 34.9%
A8: Path | B8: Expertos en oro - 4.9% | C8: Kantar Magenta | D8: =_xlfn.IFNA(VLOOKUP(C8,Table1[],2,FALSE),"") -> #C700D3 | E8: Es la marca experta en oro | K8: Experiencia 12%
A9: Tracking | B9: Expertos en oro y planes de pago - 20% | C9: Kantar Orange | D9: =_xlfn.IFNA(VLOOKUP(C9,Table1[],2,FALSE),"") -> #FF5000 | E9: Es la marca experta en oro | K9: Experiencia 12%
A10: Path | B10: Asesoría experta para la toma de decisiones - 41.3% | C10: Kantar Yellow | D10: =_xlfn.IFNA(VLOOKUP(C10,Table1[],2,FALSE),"") -> #FEDB00 | E10: Me brinda la mejor atención | K10: Expertise 21%
A11: Tracking | B11: Cuidado al cliente - 22% | C11: Kantar Yellow | D11: =_xlfn.IFNA(VLOOKUP(C11,Table1[],2,FALSE),"") -> #FEDB00 | E11: Me brinda la mejor atención | K11: Expertise 21%
A12: Path | B12: Cobro - 5.7% | C12: Kantar Green | D12: =_xlfn.IFNA(VLOOKUP(C12,Table1[],2,FALSE),"") -> #00B600 | E12: Me cobra menos al empeñar | K12: Presupuesto 15.7%
A13: Tracking | B13: Pagos y cobro - 11% | C13: Kantar Green | D13: =_xlfn.IFNA(VLOOKUP(C13,Table1[],2,FALSE),"") -> #00B600 | E13: Me cobra menos al empeñar | K13: Tendencia 16.4%
A14: Path | B14: Asesoría experta para la toma de decisiones - 41.3% | C14: Kantar Yellow | D14: =_xlfn.IFNA(VLOOKUP(C14,Table1[],2,FALSE),"") -> #FEDB00 | E14: Me da la mejor asesoría | K14: Tendencia 16.4%
... A16: Path | B16: Confianza y flexibilidad - 20.0% | C16: Kantar Blue | D16: =_xlfn.IFNA(VLOOKUP(C16,Table1[],2,FALSE),"") -> #0060FF | E16: Me genera más confianza | K16: Tendencia 16.4%
A17: Tracking | B17: Sensación de control - 19% | C17: Kantar Purple | D17: =_xlfn.IFNA(VLOOKUP(C17,Table1[],2,FALSE),"") -> #802AB7 | E17: Me genera más confianza
A18: Path | B18: Asesoría experta para la toma de decisiones - 41.3% | C18: Kantar Yellow | D18: =_xlfn.IFNA(VLOOKUP(C18,Table1[],2,FALSE),"") -> #FEDB00 | E18: Tengo el control porque decido cómo armar mi empeño
A19: Path
A20: Path | D20: =_xlfn.IFNA(VLOOKUP(C20,Table1[],2,FALSE),"")
A21: Tracking | B21: Sensación de control - 19% | C21: Kantar Purple | D21: =_xlfn.IFNA(VLOOKUP(C21,Table1[],2,FALSE),"") -> #802AB7 | E21: Tengo el control porque decido cómo armar mi empeño
A22: Path | B22: Mejores condiciones y recompensas - 20.0% | C22: Kantar Blue | D22: =_xlfn.IFNA(VLOOKUP(C22,Table1[],2,FALSE),"") -> #0060FF | E22: Me ofrece más refrendos al empeñar
A23: Tracking | B23: Planes de recompensas y lealtad - 16% | C23: Kantar Blue | D23: =_xlfn.IFNA(VLOOKUP(C23,Table1[],2,FALSE),"") -> #0060FF | E23: Me ofrece más refrendos al empeñar
A24: Path | B24: Comodidad y accesibilidad - 8.0% | C24: Kantar Orange | D24: =_xlfn.IFNA(VLOOKUP(C24,Table1[],2,FALSE),"") -> #FF5000 | E24: Me queda más cerca/ tiene muchas sucursales | K24: Calidad y experiencia en tienda 22.5% (4.9%)
A25: Tracking | B25: Conveniencia y Asesoría - 11% | C25: Kantar Magenta | D25: =_xlfn.IFNA(VLOOKUP(C25,Table1[],2,FALSE),"") -> #C700D3 | E25: Me queda más cerca/ tiene muchas sucursales | K25: Calidad y experiencia en tienda 22.5% (4.9%)
A26: Path | B26: Mejores condiciones y recompensas - 20.0% | C26: Kantar Blue | D26: =_xlfn.IFNA(VLOOKUP(C26,Table1[],2,FALSE),"") -> #0060FF | E26: Ofrece los mejores planes de lealtad | K26: Calidad y experiencia en tienda 22.5% (4.9%)
A27: Tracking | B27: Planes de recompensas y lealtad - 16% | C27: Kantar Blue | D27: =_xlfn.IFNA(VLOOKUP(C27,Table1[],2,FALSE),"") -> #0060FF | E27: Ofrece los mejores planes de lealtad | K27: Variedad y tendencia que encuentro en línea 23% (5%)
A28: Path | B28: Mejores condiciones y recompensas - 20.0% | C28: Kantar Blue | D28: =_xlfn.IFNA(VLOOKUP(C28,Table1[],2,FALSE),"") -> #0060FF | E28: Ofrece los mejores plazos para liquidar | K28: Variedad y tendencia que encuentro en línea 23% (5%)
A29: Tracking | B29: Cuidado al cliente - 22% | C29: Kantar Yellow | D29: =_xlfn.IFNA(VLOOKUP(C29,Table1[],2,FALSE),"") -> #FEDB00 | E29: Ofrece los mejores plazos para liquidar | K29: Variedad y tendencia que encuentro en línea 23% (5%)
A30: Path | B30: Asesoría experta para la toma de decisiones - 41.3% | C30: Kantar Yellow | D30: =_xlfn.IFNA(VLOOKUP(C30,Table1[],2,FALSE),"") -> #FEDB00 | E30: Ofrece más dinero por mi prenda | K30: Variedad y tendencia que encuentro en línea 23% (5%)
A31: Tracking | B31: Pagos y cobro - 11% | C31: Kantar Green | D31: =_xlfn.IFNA(VLOOKUP(C31,Table1[],2,FALSE),"") -> #00B600 | E31: Ofrece más dinero por mi prenda | K31: Para mi estilo y presupuesto 20.3% (4.4%)
A32: Path | B32: Confianza y flexibilidad - 20.0% | C32: Kantar Blue | D32: =_xlfn.IFNA(VLOOKUP(C32,Table1[],2,FALSE),"") -> #0060FF | E32: Ofrece una gran variedad de planes de pago | K32: Para mi estilo y presupuesto 20.3% (4.4%)
A33: Tracking | B33: Expertos en oro y planes de pago - 20% | C33: Kantar Orange | D33: =_xlfn.IFNA(VLOOKUP(C33,Table1[],2,FALSE),"") -> #FF5000 | E33: Ofrece una gran variedad de planes de pago | K33: Para mi estilo y presupuesto 20.3% (4.4%)
A34: Path | B34: Comodidad y accesibilidad - 8.0% | C34: Kantar Orange | D34: =_xlfn.IFNA(VLOOKUP(C34,Table1[],2,FALSE),"") -> #FF5000 | E34: Tiene requisitos fáciles de cumplir | K34: Productos innovadores y exclusivos 15.8% (3.4%)
A35: Tracking | B35: Conveniencia y Asesoría - 11% | C35: Kantar Magenta | D35: =_xlfn.IFNA(VLOOKUP(C35,Table1[],2,FALSE),"") -> #C700D3 | E35: Tiene requisitos fáciles de cumplir | K35: Productos innovadores y exclusivos 15.8% (3.4%)
... A37: Tracking | B37: Cuidado al cliente - 22% | C37: Kantar Yellow | D37: =_xlfn.IFNA(VLOOKUP(C37,Table1[],2,FALSE),"") -> #FEDB00 | E37: Tiene un amplio horario de servicio | K37: Expertise 3.8% (0.8%)
A38: Tracking | K38: Diseño original 14.6% (3.2%)
A39: Tracking | D39: =_xlfn.IFNA(VLOOKUP(C39,Table1[],2,FALSE),"")
A40: Tracking | D40: =_xlfn.IFNA(VLOOKUP(C40,Table1[],2,FALSE),"")
A41: Tracking | D41: =_xlfn.IFNA(VLOOKUP(C41,Table1[],2,FALSE),"")
A42: Tracking | D42: =_xlfn.IFNA(VLOOKUP(C42,Table1[],2,FALSE),"")

Sheet CATA
A1: NodeColor | B1: HexColor
A2: Kantar Purple | B2: #802AB7
A3: Kantar Blue | B3: #0060FF
A4: Kantar Sand | B4: #AEAE9F
A5: Kantar Teal | B5: #00E5BA
A6: Kantar Green | B6: #00B600
A7: Kantar Yellow | B7: #FEDB00
A8: Kantar Orange | B8: #FF5000
A9: Kantar Red | B9: #FA0028
A10: Kantar Magenta | B10: #C700D3
A11: Kantar Light Grey | B11: #D9D9D9

Sheet Template
A1: FactorType | B1: FactorName | C1: NodeColor | D1: =VLOOKUP(C1,CATA!A:B,2,FALSE) -> HexColor | E1: Attribute | H1: Path = Right
A2: Tracking | B2: Emo-Funcional 34.9% | C2: Kantar Green | D2: =_xlfn.IFNA(VLOOKUP(C2,Table1[],2,FALSE),"") -> #00B600 | E2: Buena atención a cliente en tienda física | H2: Tracking = Left | K2: Emo-Funcional 34.9%
A3: Tracking | B3: Emo-Funcional 34.9% | C3: Kantar Green | D3: =_xlfn.IFNA(VLOOKUP(C3,Table1[],2,FALSE),"") -> #00B600 | E3: Buena experiencia en tienda física | K3: Emo-Funcional 34.9%
A4: Tracking | B4: Emo-Funcional 34.9% | C4: Kantar Green | D4: =_xlfn.IFNA(VLOOKUP(C4,Table1[],2,FALSE),"") -> #00B600 | E4: Ofrece productos de buena calidad | K4: Emo-Funcional 34.9%
A5: Tracking | B5: Emo-Funcional 34.9% | C5: Kantar Green | D5: =_xlfn.IFNA(VLOOKUP(C5,Table1[],2,FALSE),"") -> #00B600 | E5: Es una marca con la que me identifico | K5: Emo-Funcional 34.9%
A6: Tracking | B6: Emo-Funcional 34.9% | C6: Kantar Green | D6: =_xlfn.IFNA(VLOOKUP(C6,Table1[],2,FALSE),"") -> #00B600 | E6: Me acompaña en el proceso de compra hasta la entrega | K6: Emo-Funcional 34.9%
A7: Tracking | B7: Emo-Funcional 34.9% | C7: Kantar Green | D7: =_xlfn.IFNA(VLOOKUP(C7,Table1[],2,FALSE),"") -> #00B600 | E7: Es una marca que se adecua a mi estilo | K7: Emo-Funcional 34.9%
A8: Tracking | B8: Experiencia 12% | C8: Kantar Blue | D8: =_xlfn.IFNA(VLOOKUP(C8,Table1[],2,FALSE),"") -> #0060FF | E8: Variedad de productos para decorar mi hogar | K8: Experiencia 12%
A9: Tracking | B9: Experiencia 12% | C9: Kantar Blue | D9: =_xlfn.IFNA(VLOOKUP(C9,Table1[],2,FALSE),"") -> #0060FF | E9: Buena experiencia en tienda en línea | K9: Experiencia 12%
A10: Tracking | B10: Expertise 21% | C10: Kantar Yellow | D10: =_xlfn.IFNA(VLOOKUP(C10,Table1[],2,FALSE),"") -> #FEDB00 | E10: Me inspira a decorar mi hogar | K10: Expertise 21%
A11: Tracking | B11: Expertise 21% | C11: Kantar Yellow | D11: =_xlfn.IFNA(VLOOKUP(C11,Table1[],2,FALSE),"") -> #FEDB00 | E11: Experta en decoración | K11: Expertise 21%
A12: Tracking | B12: Presupuesto 15.7% | C12: Kantar Teal | D12: =_xlfn.IFNA(VLOOKUP(C12,Table1[],2,FALSE),"") -> #00E5BA | E12: Opciones para todos los presupuestos | K12: Presupuesto 15.7%
A13: Tracking | B13: Tendencia 16.4% | C13: Kantar Magenta | D13: =_xlfn.IFNA(VLOOKUP(C13,Table1[],2,FALSE),"") -> #C700D3 | E13: Tiene artículos de moda | K13: Tendencia 16.4%
A14: Tracking | B14: Tendencia 16.4% | C14: Kantar Magenta | D14: =_xlfn.IFNA(VLOOKUP(C14,Table1[],2,FALSE),"") -> #C700D3 | E14: Esta innovando constantemente | K14: Tendencia 16.4%
... A16: Tracking | B16: Tendencia 16.4% | C16: Kantar Magenta | D16: =_xlfn.IFNA(VLOOKUP(C16,Table1[],2,FALSE),"") -> #C700D3 | E16: Vende artículos con diseño original | K16: Tendencia 16.4%
A17: Tracking | D17: =_xlfn.IFNA(VLOOKUP(C17,Table1[],2,FALSE),"")
A18: Tracking | D18: =_xlfn.IFNA(VLOOKUP(C18,Table1[],2,FALSE),"")
A19: Tracking | D19: =_xlfn.IFNA(VLOOKUP(C19,Table1[],2,FALSE),"")
A20: Tracking | D20: =_xlfn.IFNA(VLOOKUP(C20,Table1[],2,FALSE),"")
A21: Tracking | D21: =_xlfn.IFNA(VLOOKUP(C21,Table1[],2,FALSE),"")
A22: Tracking | D22: =_xlfn.IFNA(VLOOKUP(C22,Table1[],2,FALSE),"")
A23: Tracking | D23: =_xlfn.IFNA(VLOOKUP(C23,Table1[],2,FALSE),"")
A24: Path | B24: Calidad y experiencia en tienda 22.5% (4.9%) | C24: Kantar Green | D24: =_xlfn.IFNA(VLOOKUP(C24,Table1[],2,FALSE),"") -> #00B600 | E24: Buena experiencia en tienda física | K24: Calidad y experiencia en tienda 22.5% (4.9%)
A25: Path | B25: Calidad y experiencia en tienda 22.5% (4.9%) | C25: Kantar Green | D25: =_xlfn.IFNA(VLOOKUP(C25,Table1[],2,FALSE),"") -> #00B600 | E25: Buena atención a cliente en tienda física | K25: Calidad y experiencia en tienda 22.5% (4.9%)
A26: Path | B26: Calidad y experiencia en tienda 22.5% (4.9%) | C26: Kantar Green | D26: =_xlfn.IFNA(VLOOKUP(C26,Table1[],2,FALSE),"") -> #00B600 | E26: Ofrece productos de buena calidad | K26: Calidad y experiencia en tienda 22.5% (4.9%)
A27: Path | B27: Variedad y tendencia que encuentro en línea 23% (5%) | C27: Kantar Magenta | D27: =_xlfn.IFNA(VLOOKUP(C27,Table1[],2,FALSE),"") -> #C700D3 | E27: Variedad de productos para decorar mi hogar | K27: Variedad y tendencia que encuentro en línea 23% (5%)
A28: Path | B28: Variedad y tendencia que encuentro en línea 23% (5%) | C28: Kantar Magenta | D28: =_xlfn.IFNA(VLOOKUP(C28,Table1[],2,FALSE),"") -> #C700D3 | E28: Buena experiencia en tienda en línea | K28: Variedad y tendencia que encuentro en línea 23% (5%)
A29: Path | B29: Variedad y tendencia que encuentro en línea 23% (5%) | C29: Kantar Magenta | D29: =_xlfn.IFNA(VLOOKUP(C29,Table1[],2,FALSE),"") -> #C700D3 | E29: Me acompaña en el proceso de compra hasta la entrega | K29: Variedad y tendencia que encuentro en línea 23% (5%)
A30: Path | B30: Variedad y tendencia que encuentro en línea 23% (5%) | C30: Kantar Magenta | D30: =_xlfn.IFNA(VLOOKUP(C30,Table1[],2,FALSE),"") -> #C700D3 | E30: Tiene artículos de moda | K30: Variedad y tendencia que encuentro en línea 23% (5%)
A31: Path | B31: Para mi estilo y presupuesto 20.3% (4.4%) | C31: Kantar Red | D31: =_xlfn.IFNA(VLOOKUP(C31,Table1[],2,FALSE),"") -> #FA0028 | E31: Opciones para todos los presupuestos | K31: Para mi estilo y presupuesto 20.3% (4.4%)
A32: Path | B32: Para mi estilo y presupuesto 20.3% (4.4%) | C32: Kantar Red | D32: =_xlfn.IFNA(VLOOKUP(C32,Table1[],2,FALSE),"") -> #FA0028 | E32: Es una marca que se adecua a mi estilo | K32: Para mi estilo y presupuesto 20.3% (4.4%)
A33: Path | B33: Para mi estilo y presupuesto 20.3% (4.4%) | C33: Kantar Red | D33: =_xlfn.IFNA(VLOOKUP(C33,Table1[],2,FALSE),"") -> #FA0028 | E33: Es una marca con la que me identifico | K33: Para mi estilo y presupuesto 20.3% (4.4%)
A34: Path | B34: Productos innovadores y exclusivos 15.8% (3.4%) | C34: Kantar Blue | D34: =_xlfn.IFNA(VLOOKUP(C34,Table1[],2,FALSE),"") -> #0060FF | E34: Vende productos exclusivos | K34: Productos innovadores y exclusivos 15.8% (3.4%)
A35: Path | B35: Productos innovadores y exclusivos 15.8% (3.4%) | C35: Kantar Blue | D35: =_xlfn.IFNA(VLOOKUP(C35,Table1[],2,FALSE),"") -> #0060FF | E35: Esta innovando constantemente | K35: Productos innovadores y exclusivos 15.8% (3.4%)
... A38: Path | B38: Diseño original 14.6% (3.2%) | C38: Kantar Orange | D38: =_xlfn.IFNA(VLOOKUP(C38,Table1[],2,FALSE),"") -> #FF5000 | E38: Vende artículos con diseño original | K38: Diseño original 14.6% (3.2%)
A39: Path | D39: =_xlfn.IFNA(VLOOKUP(C39,Table1[],2,FALSE),"")
A40: Path | D40: =_xlfn.IFNA(VLOOKUP(C40,Table1[],2,FALSE),"")
A41: Path | D41: =_xlfn.IFNA(VLOOKUP(C41,Table1[],2,FALSE),"")
A42: Path | D42: =_xlfn.IFNA(VLOOKUP(C42,Table1[],2,FALSE),"")

Sheet BSA Protex IMG w Imp
A1: FactorType | B1: FactorName | C1: NodeColor | D1: =VLOOKUP(C1,CATA!A:B,2,FALSE) -> HexColor | E1: Attribute | H1: Path = Right
A2: Path | B2: Antibacterial - 7.5 | C2: Kantar Blue | D2: =_xlfn.IFNA(VLOOKUP(C2,Table1[],2,FALSE),"") -> #0060FF | E2: Provides long lasting antibacterial protection | H2: Tracking = Left
A3: Path | B3: Antibacterial - 7.5 | C3: Kantar Blue | D3: =_xlfn.IFNA(VLOOKUP(C3,Table1[],2,FALSE),"") -> #0060FF | E3: Kills germs provides antibacterial protection
A4: Path | B4: Attractive package that show the fragrance - 11.6 | C4: Kantar Magenta | D4: =_xlfn.IFNA(VLOOKUP(C4,Table1[],2,FALSE),"") -> #C700D3 | E4: Has a packaging that conveys an attractive fragrance
A5: Path | B5: Attractive package that show the fragrance - 11.6 | C5: Kantar Magenta | D5: =_xlfn.IFNA(VLOOKUP(C5,Table1[],2,FALSE),"") -> #C700D3 | E5: Has attractive packaging
A6: Path | B6: Expert in skin health - 1.8 | C6: Kantar Teal | D6: =_xlfn.IFNA(VLOOKUP(C6,Table1[],2,FALSE),"") -> #00E5BA | E6: Is expert in skin health
A7: Path | B7: Experts recommendation I follow - 19.7 | C7: Kantar Blue | D7: =_xlfn.IFNA(VLOOKUP(C7,Table1[],2,FALSE),"") -> #0060FF | E7: Is recommended by dermatologists
A8: Path | B8: Experts recommendation I follow - 19.7 | C8: Kantar Blue | D8: =_xlfn.IFNA(VLOOKUP(C8,Table1[],2,FALSE),"") -> #0060FF | E8: Makes me feel like an expert in skin care
A9: Path | B9: For my dry skin - 8.3 | C9: Kantar Orange | D9: =_xlfn.IFNA(VLOOKUP(C9,Table1[],2,FALSE),"") -> #FF5000 | E9: Does not dry out nor irritate the skin
A10: Path | B10: For my dry skin - 8.3 | C10: Kantar Orange | D10: =_xlfn.IFNA(VLOOKUP(C10,Table1[],2,FALSE),"") -> #FF5000 | E10: Provides the care my skin needs
A11: Path | B11: Fragrances for starting the day - 9.9 | C11: Kantar Yellow | D11: =_xlfn.IFNA(VLOOKUP(C11,Table1[],2,FALSE),"") -> #FEDB00 | E11: Has the scents that I like the most
A12: Path | B12: Fragrances for starting the day - 9.9 | C12: Kantar Yellow | D12: =_xlfn.IFNA(VLOOKUP(C12,Table1[],2,FALSE),"") -> #FEDB00 | E12: Fragrance that helps me start the day with energy
A13: Path | B13: Fragrances for starting the day - 9.9 | C13: Kantar Yellow | D13: =_xlfn.IFNA(VLOOKUP(C13,Table1[],2,FALSE),"") -> #FEDB00 | E13: Helps me feel more attractive
A14: Path | B14: Fragrances for starting the day - 9.9 | C14: Kantar Yellow | D14: =_xlfn.IFNA(VLOOKUP(C14,Table1[],2,FALSE),"") -> #FEDB00 | E14: Has aromas that improve my mood
... A65: Tracking | B65: Technology and recommendation - 11.5 | C65: Kantar Yellow | D65: =_xlfn.IFNA(VLOOKUP(C65,Table1[],2,FALSE),"") -> #FEDB00 | E65: Is recommended by dermatologists

Sheet BSA Protex IMG
A1: FactorType | B1: FactorName | C1: NodeColor | D1: =VLOOKUP(C1,CATA!A:B,2,FALSE) -> HexColor | E1: Attribute | H1: Path = Right
A2: Tracking | B2: Advanced skin defense | C2: Kantar Blue | D2: =_xlfn.IFNA(VLOOKUP(C2,Table1[],2,FALSE),"") -> #0060FF | E2: Helps me eliminate skin impurities | H2: Tracking = Left
A3: Tracking | B3: Advanced skin defense | C3: Kantar Blue | D3: =_xlfn.IFNA(VLOOKUP(C3,Table1[],2,FALSE),"") -> #0060FF | E3: Provides long lasting antibacterial protection
A4: Tracking | B4: Advanced skin defense | C4: Kantar Blue | D4: =_xlfn.IFNA(VLOOKUP(C4,Table1[],2,FALSE),"") -> #0060FF | E4: Kills germs provides antibacterial protection
A5: Tracking | B5: Advanced skin defense | C5: Kantar Blue | D5: =_xlfn.IFNA(VLOOKUP(C5,Table1[],2,FALSE),"") -> #0060FF | E5: Helps prevent skin problems
A6: Path | B6: Antibacterial | C6: Kantar Blue | D6: =_xlfn.IFNA(VLOOKUP(C6,Table1[],2,FALSE),"") -> #0060FF | E6: Provides long lasting antibacterial protection
A7: Path | B7: Antibacterial | C7: Kantar Blue | D7: =_xlfn.IFNA(VLOOKUP(C7,Table1[],2,FALSE),"") -> #0060FF | E7: Kills germs provides antibacterial protection
A8: Path | B8: Attractive package that show the fragrance | C8: Kantar Magenta | D8: =_xlfn.IFNA(VLOOKUP(C8,Table1[],2,FALSE),"") -> #C700D3 | E8: Has a packaging that conveys an attractive fragrance
A9: Path | B9: Attractive package that show the fragrance | C9: Kantar Magenta | D9: =_xlfn.IFNA(VLOOKUP(C9,Table1[],2,FALSE),"") -> #C700D3 | E9: Has attractive packaging
A10: Tracking | B10: Benefits and identification | C10: Kantar Purple | D10: =_xlfn.IFNA(VLOOKUP(C10,Table1[],2,FALSE),"") -> #802AB7 | E10: Is worth paying more for
A11: Tracking | B11: Benefits and identification | C11: Kantar Purple | D11: =_xlfn.IFNA(VLOOKUP(C11,Table1[],2,FALSE),"") -> #802AB7 | E11: Nourishes my skin
A12: Tracking | B12: Benefits and identification | C12: Kantar Purple | D12: =_xlfn.IFNA(VLOOKUP(C12,Table1[],2,FALSE),"") -> #802AB7 | E12: Moisturizes my skin
A13: Tracking | B13: Benefits and identification | C13: Kantar Purple | D13: =_xlfn.IFNA(VLOOKUP(C13,Table1[],2,FALSE),"") -> #802AB7 | E13: Does not dry out nor irritate the skin
A14: Tracking | B14: Benefits and identification | C14: Kantar Purple | D14: =_xlfn.IFNA(VLOOKUP(C14,Table1[],2,FALSE),"") -> #802AB7 | E14: Provides the care my skin needs
... A65: Path | B65: Trusted family care | C65: Kantar Purple | D65: =_xlfn.IFNA(VLOOKUP(C65,Table1[],2,FALSE),"") -> #802AB7 | E65: Makes me feel clean throughout the day

Sheet ACT Placer Ciudad Posadas
A1: FactorType | B1: FactorName | C1: NodeColor | D1: =VLOOKUP(C1,CATA!A:B,2,FALSE) -> HexColor | E1: Attribute | H1: Path = Right
A2: Path | B2: Availability (16.2%) | C2: Kantar Green | D2: =_xlfn.IFNA(VLOOKUP(C2,Table1[],2,FALSE),"") -> #00B600 | E2: Had availability for my travel dates | H2: Tracking = Left
A3: Path | B3: Experience and location I wanted (31.7%) | C3: Kantar Orange | D3: =_xlfn.IFNA(VLOOKUP(C3,Table1[],2,FALSE),"") -> #FF5000 | E3: It was on the location I was looking for
A4: Path | B4: Experience and location I wanted (31.7%) | C4: Kantar Orange | D4: =_xlfn.IFNA(VLOOKUP(C4,Table1[],2,FALSE),"") -> #FF5000 | E4: Offered the experience I was looking for
A5: Path | B5: Informative websites and reviews (14.8%) | C5: Kantar Blue | D5: =_xlfn.IFNA(VLOOKUP(C5,Table1[],2,FALSE),"") -> #0060FF | E5: It has good reviews from customers
A6: Path | B6: Informative websites and reviews (14.8%) | C6: Kantar Blue | D6: =_xlfn.IFNA(VLOOKUP(C6,Table1[],2,FALSE),"") -> #0060FF | E6: It has good reviews specifically on Tripadvisor
A7: Path | B7: Informative websites and reviews (14.8%) | C7: Kantar Blue | D7: =_xlfn.IFNA(VLOOKUP(C7,Table1[],2,FALSE),"") -> #0060FF | E7: The hotel website was informative and easy to use
A8: Path | B8: On promotion (7.9%) | C8: Kantar Yellow | D8: =_xlfn.IFNA(VLOOKUP(C8,Table1[],2,FALSE),"") -> #FEDB00 | E8: It was on promotion
A9: Path | B9: Tempting promotional package (29.4%) | C9: Kantar Purple | D9: =_xlfn.IFNA(VLOOKUP(C9,Table1[],2,FALSE),"") -> #802AB7 | E9: It had a good flight plus hotel offer
A10: Path | B10: Tempting promotional package (29.4%) | C10: Kantar Purple | D10: =_xlfn.IFNA(VLOOKUP(C10,Table1[],2,FALSE),"") -> #802AB7 | E10: It was within the price range I was looking for
A11: Path | B11: Tempting promotional package (29.4%) | C11: Kantar Purple | D11: =_xlfn.IFNA(VLOOKUP(C11,Table1[],2,FALSE),"") -> #802AB7 | E11: The photos looked tempting
A12: Path | D12: =_xlfn.IFNA(VLOOKUP(C12,Table1[],2,FALSE),"")
A13: Path | D13: =_xlfn.IFNA(VLOOKUP(C13,Table1[],2,FALSE),"")
A14: Path | D14: =_xlfn.IFNA(VLOOKUP(C14,Table1[],2,FALSE),"")
A15: Path | D15: =_xlfn.IFNA(VLOOKUP(C15,Table1[],2,FALSE),"")
A16: Path | D16: =_xlfn.IFNA(VLOOKUP(C16,Table1[],2,FALSE),"")
A17: Path | D17: =_xlfn.IFNA(VLOOKUP(C17,Table1[],2,FALSE),"")
A18: Path | D18: =_xlfn.IFNA(VLOOKUP(C18,Table1[],2,FALSE),"")
A19: Path | D19: =_xlfn.IFNA(VLOOKUP(C19,Table1[],2,FALSE),"")
A20: Path | D20: =_xlfn.IFNA(VLOOKUP(C20,Table1[],2,FALSE),"")
A21: Tracking | B21: Experience preview (23.0%) | C21: Kantar Red | D21: =_xlfn.IFNA(VLOOKUP(C21,Table1[],2,FALSE),"") -> #FA0028 | E21: Offered the experience I was looking for
A22: Tracking | B22: Experience preview (23.0%) | C22: Kantar Red | D22: =_xlfn.IFNA(VLOOKUP(C22,Table1[],2,FALSE),"") -> #FA0028 | E22: The hotel website was informative and easy to use
A23: Tracking | B23: Presence and accesibility (25.3%) | C23: Kantar Teal | D23: =_xlfn.IFNA(VLOOKUP(C23,Table1[],2,FALSE),"") -> #00E5BA | E23: Had availability for my travel dates
A24: Tracking | B24: Presence and accesibility (25.3%) | C24: Kantar Teal | D24: =_xlfn.IFNA(VLOOKUP(C24,Table1[],2,FALSE),"") -> #00E5BA | E24: It was on the location I was looking for
A25: Tracking | B25: Presence and accesibility (25.3%) | C25: Kantar Teal | D25: =_xlfn.IFNA(VLOOKUP(C25,Table1[],2,FALSE),"") -> #00E5BA | E25: It was within the price range I was looking for
A26: Tracking | B26: On promotion (5.5%) | C26: Kantar Yellow | D26: =_xlfn.IFNA(VLOOKUP(C26,Table1[],2,FALSE),"") -> #FEDB00 | E26: It was on promotion
A27: Tracking | B27: Options and visual stimulation (23.0%) | C27: Kantar Sand | D27: =_xlfn.IFNA(VLOOKUP(C27,Table1[],2,FALSE),"") -> #AEAE9F | E27: It has good reviews from customers
A28: Tracking | B28: Options and visual stimulation (23.0%) | C28: Kantar Sand | D28: =_xlfn.IFNA(VLOOKUP(C28,Table1[],2,FALSE),"") -> #AEAE9F | E28: The photos looked tempting
A29: Tracking | B29: Promotion and reliability (23.3%) | C29: Kantar Magenta | D29: =_xlfn.IFNA(VLOOKUP(C29,Table1[],2,FALSE),"") -> #C700D3 | E29: It had a good flight plus hotel offer
A30: Tracking | B30: Promotion and reliability (23.3%) | C30: Kantar Magenta | D30: =_xlfn.IFNA(VLOOKUP(C30,Table1[],2,FALSE),"") -> #C700D3 | E30: It has good reviews specifically on Tripadvisor
A31: Tracking | D31: =_xlfn.IFNA(VLOOKUP(C31,Table1[],2,FALSE),"")
A32: Tracking | D32: =_xlfn.IFNA(VLOOKUP(C32,Table1[],2,FALSE),"")
A33: Tracking | D33: =_xlfn.IFNA(VLOOKUP(C33,Table1[],2,FALSE),"")
A34: Tracking | D34: =_xlfn.IFNA(VLOOKUP(C34,Table1[],2,FALSE),"")
A35: Tracking | D35: =_xlfn.IFNA(VLOOKUP(C35,Table1[],2,FALSE),"")
A36: Tracking | D36: =_xlfn.IFNA(VLOOKUP(C36,Table1[],2,FALSE),"")
A37: Tracking | D37: =_xlfn.IFNA(VLOOKUP(C37,Table1[],2,FALSE),"")
A38: Tracking | D38: =_xlfn.IFNA(VLOOKUP(C38,Table1[],2,FALSE),"")
A39: Tracking | D39: =_xlfn.IFNA(VLOOKUP(C39,Table1[],2,FALSE),"")
A40: Tracking | D40: =_xlfn.IFNA(VLOOKUP(C40,Table1[],2,FALSE),"")
A41: Tracking | D41: =_xlfn.IFNA(VLOOKUP(C41,Table1[],2,FALSE),"")
A42: Tracking | D42: =_xlfn.IFNA(VLOOKUP(C42,Table1[],2,FALSE),"")

Sheet Placer Ciudad Posadas
A1: FactorType | B1: FactorName | C1: NodeColor | D1: =VLOOKUP(C1,CATA!A:B,2,FALSE) -> HexColor | E1: Attribute | F1: Comparación | H1: Path = Right
A2: Path | B2: Cares about me and the environment (22.8%) | C2: Kantar Green | D2: =_xlfn.IFNA(VLOOKUP(C2,Table1[],2,FALSE),"") -> #00B600 | E2: Provides experiences for my physical and mental wellbeing | F2: TOTAL | H2: Tracking = Left
A3: Path | B3: Cares about me and the environment (22.8%) | C3: Kantar Green | D3: =_xlfn.IFNA(VLOOKUP(C3,Table1[],2,FALSE),"") -> #00B600 | E3: Cares about the environment and takes action to protect it | F3: TOTAL
A4: Path | B4: Family escape from routine (7.3%) | C4: Kantar Purple | D4: =_xlfn.IFNA(VLOOKUP(C4,Table1[],2,FALSE),"") -> #802AB7 | E4: Allows you to disconnect from the routine | F4: TOTAL
A5: Path | B5: Family escape from routine (7.3%) | C5: Kantar Purple | D5: =_xlfn.IFNA(VLOOKUP(C5,Table1[],2,FALSE),"") -> #802AB7 | E5: Its hotels are ideal for the whole family | F5: TOTAL
A6: Path | B6: Infrastructure that suits my needs (17.8%) | C6: Kantar Blue | D6: =_xlfn.IFNA(VLOOKUP(C6,Table1[],2,FALSE),"") -> #0060FF | E6: Provides facilities to spend quality time with my companions | F6: TOTAL
A7: Path | B7: Infrastructure that suits my needs (17.8%) | C7: Kantar Blue | D7: =_xlfn.IFNA(VLOOKUP(C7,Table1[],2,FALSE),"") -> #0060FF | E7: Adapts to my lifestyle and needs | F7: TOTAL
A8: Path | B8: Infrastructure that suits my needs (17.8%) | C8: Kantar Blue | D8: =_xlfn.IFNA(VLOOKUP(C8,Table1[],2,FALSE),"") -> #0060FF | E8: Equipped with appropriate technology for my trip | F8: TOTAL
A9: Path | B9: Loyalty program (13.7%) | C9: Kantar Teal | D9: =_xlfn.IFNA(VLOOKUP(C9,Table1[],2,FALSE),"") -> #00E5BA | E9: Has the best loyalty frequent guest program | F9: TOTAL
A10: Path | B10: Memorable legacy and prestige (20.0%) | C10: Kantar Yellow | D10: =_xlfn.IFNA(VLOOKUP(C10,Table1[],2,FALSE),"") -> #FEDB00 | E10: It is a prestigious hotel chain | F10: TOTAL
A11: Path | B11: Memorable legacy and prestige (20.0%) | C11: Kantar Yellow | D11: =_xlfn.IFNA(VLOOKUP(C11,Table1[],2,FALSE),"") -> #FEDB00 | E11: Helps create experiences to always remember | F11: TOTAL
A12: Path | B12: Memorable legacy and prestige (20.0%) | C12: Kantar Yellow | D12: =_xlfn.IFNA(VLOOKUP(C12,Table1[],2,FALSE),"") -> #FEDB00 | E12: It is a brand with tradition | F12: TOTAL
A13: Path | B13: Hospitality and culinary experience (18.4%) | C13: Kantar Orange | D13: =_xlfn.IFNA(VLOOKUP(C13,Table1[],2,FALSE),"") -> #FF5000 | E13: Its hotels offer an adequate selection of food and beverages | F13: TOTAL
A14: Path | B14: Hospitality and culinary experience (18.4%) | C14: Kantar Orange | D14: =_xlfn.IFNA(VLOOKUP(C14,Table1[],2,FALSE),"") -> #FF5000 | E14: Its hotels have a pleasant atmosphere | F14: TOTAL
... A16: Path | B16: NA | C16: Kantar Light Grey | D16: =_xlfn.IFNA(VLOOKUP(C16,Table1[],2,FALSE),"") -> #D9D9D9 | E16: Offers good entertainment options | F16: PLAYA
A17: Path | D17: =_xlfn.IFNA(VLOOKUP(C17,Table1[],2,FALSE),"")
A18: Path | D18: =_xlfn.IFNA(VLOOKUP(C18,Table1[],2,FALSE),"")
A19: Path | D19: =_xlfn.IFNA(VLOOKUP(C19,Table1[],2,FALSE),"")
A20: Path | D20: =_xlfn.IFNA(VLOOKUP(C20,Table1[],2,FALSE),"")
A21: Tracking | B21: Environmental Care | C21: Kantar Green | D21: =_xlfn.IFNA(VLOOKUP(C21,Table1[],2,FALSE),"") -> #00B600 | E21: Cares about the environment and takes action to protect it | F21: CATEGORIA
A22: Tracking | B22: Holistic Stay Experience | C22: Kantar Red | D22: =_xlfn.IFNA(VLOOKUP(C22,Table1[],2,FALSE),"") -> #FA0028 | E22: Provides experiences for my physical and mental wellbeing | F22: CATEGORIA
A23: Tracking | B23: Holistic Stay Experience | C23: Kantar Red | D23: =_xlfn.IFNA(VLOOKUP(C23,Table1[],2,FALSE),"") -> #FA0028 | E23: Equipped with appropriate technology for my trip | F23: CATEGORIA
A24: Tracking | B24: Holistic Stay Experience | C24: Kantar Red | D24: =_xlfn.IFNA(VLOOKUP(C24,Table1[],2,FALSE),"") -> #FA0028 | E24: The hotel staff is friendly and attentive | F24: CATEGORIA
A25: Tracking | B25: Lifestyle Alignment | C25: Kantar Magenta | D25: =_xlfn.IFNA(VLOOKUP(C25,Table1[],2,FALSE),"") -> #C700D3 | E25: Its hotels are ideal for the whole family | F25: CATEGORIA
A26: Tracking | B26: Lifestyle Alignment | C26: Kantar Magenta | D26: =_xlfn.IFNA(VLOOKUP(C26,Table1[],2,FALSE),"") -> #C700D3 | E26: Adapts to my lifestyle and needs | F26: CATEGORIA
A27: Tracking | B27: Lifestyle Alignment | C27: Kantar Magenta | D27: =_xlfn.IFNA(VLOOKUP(C27,Table1[],2,FALSE),"") -> #C700D3 | E27: Its hotels have a pleasant atmosphere | F27: CATEGORIA
A28: Tracking | B28: Lifestyle Alignment | C28: Kantar Magenta | D28: =_xlfn.IFNA(VLOOKUP(C28,Table1[],2,FALSE),"") -> #C700D3 | E28: Helps create experiences to always remember | F28: CATEGORIA
A29: Tracking | B29: Loyalty Program | C29: Kantar Teal | D29: =_xlfn.IFNA(VLOOKUP(C29,Table1[],2,FALSE),"") -> #00E5BA | E29: Has the best loyalty frequent guest program | F29: CATEGORIA
A30: Tracking | B30: Shared Experience & Comfort | C30: Kantar Sand | D30: =_xlfn.IFNA(VLOOKUP(C30,Table1[],2,FALSE),"") -> #AEAE9F | E30: Provides facilities to spend quality time with my companions | F30: CATEGORIA
A31: Tracking | B31: Shared Experience & Comfort | C31: Kantar Sand | D31: =_xlfn.IFNA(VLOOKUP(C31,Table1[],2,FALSE),"") -> #AEAE9F | E31: Allows you to disconnect from the routine | F31: CATEGORIA
A32: Tracking | B32: Shared Experience & Comfort | C32: Kantar Sand | D32: =_xlfn.IFNA(VLOOKUP(C32,Table1[],2,FALSE),"") -> #AEAE9F | E32: It is a prestigious hotel chain | F32: CATEGORIA
... A49: Tracking | B49: All in one entertainment (25.9%) | C49: Kantar Orange | D49: =_xlfn.IFNA(VLOOKUP(C49,Table1[],2,FALSE),"") -> #FF5000 | E49: Its hotels offer an adequate selection of food and beverages | F49: PLAYA
A50: Tracking | D50: =_xlfn.IFNA(VLOOKUP(C50,Table1[],2,FALSE),"")
A51: Tracking | D51: =_xlfn.IFNA(VLOOKUP(C51,Table1[],2,FALSE),"")
A52: Tracking | D52: =_xlfn.IFNA(VLOOKUP(C52,Table1[],2,FALSE),"")
A53: Tracking | D53: =_xlfn.IFNA(VLOOKUP(C53,Table1[],2,FALSE),"")
A54: Tracking | D54: =_xlfn.IFNA(VLOOKUP(C54,Table1[],2,FALSE),"")
A55: Tracking | D55: =_xlfn.IFNA(VLOOKUP(C55,Table1[],2,FALSE),"")
A56: Tracking | D56: =_xlfn.IFNA(VLOOKUP(C56,Table1[],2,FALSE),"")
A57: Tracking | D57: =_xlfn.IFNA(VLOOKUP(C57,Table1[],2,FALSE),"")
A58: Tracking | D58: =_xlfn.IFNA(VLOOKUP(C58,Table1[],2,FALSE),"")
A59: Tracking | D59: =_xlfn.IFNA(VLOOKUP(C59,Table1[],2,FALSE),"")
A60: Tracking | D60: =_xlfn.IFNA(VLOOKUP(C60,Table1[],2,FALSE),"")
A61: Tracking | D61: =_xlfn.IFNA(VLOOKUP(C61,Table1[],2,FALSE),"")
... A67: Tracking | D67: =_xlfn.IFNA(VLOOKUP(C67,Table1[],2,FALSE),"")

Sheet Lipton BR vs H2OH BR
A1: FactorType | B1: FactorName | C1: NodeColor | D1: =VLOOKUP(C1,CATA!A:B,2,FALSE) -> HexColor | E1: Attribute | F1: Group | G1: Full ATT Label | H1: Path = Right
A2: Path | B2: Convenient And Attractive Package - 5.4% (60.7%) | C2: Kantar Teal | D2: =_xlfn.IFNA(VLOOKUP(C2,Table1[],2,FALSE),"") -> #00E5BA | E2: Attractive packaging | F2: Activador | H2: Tracking = Left | K2: Factor Label | L2: Factor Label w Imp | M2: Factor Label w Norm Imp
A3: Path | B3: Convenient And Attractive Package - 5.4% (60.7%) | C3: Kantar Teal | D3: =_xlfn.IFNA(VLOOKUP(C3,Table1[],2,FALSE),"") -> #00E5BA | E3: Convenient presentations | F3: Activador | K3: Accessible | L3: Accessible (3.5%) | M3: Accessible - 3.5% (39.3%)
A4: Path | B4: Accessible - 3.5% (39.3%) | C4: Kantar Purple | D4: =_xlfn.IFNA(VLOOKUP(C4,Table1[],2,FALSE),"") -> #802AB7 | E4: Easy to find | F4: Activador | K4: Balanced Recharge | L4: Balanced Recharge (3.3%) | M4: Balanced Recharge - 3.3% (23.5%)
A5: Path | B5: N/A | C5: Kantar Light Grey | D5: =_xlfn.IFNA(VLOOKUP(C5,Table1[],2,FALSE),"") -> #D9D9D9 | E5: Engaging advertising | F5: Activador | K5: Bright Side Of Life | L5: Bright Side Of Life (1.8%) | M5: Bright Side Of Life - 1.8% (13.5%)
A6: Path | B6: Accessible - 3.5% (39.3%) | C6: Kantar Purple | D6: =_xlfn.IFNA(VLOOKUP(C6,Table1[],2,FALSE),"") -> #802AB7 | E6: Fair value | F6: Activador | K6: Convenient And Attractive Package | L6: Convenient And Attractive Package (5.4%) | M6: Convenient And Attractive Package - 5.4% (60.7%)
A7: Path | B7: Flavor And Quality - 2.7% (19.1%) | C7: Kantar Blue | D7: =_xlfn.IFNA(VLOOKUP(C7,Table1[],2,FALSE),"") -> #0060FF | E7: Flavor | F7: Funcionales | K7: Different | L7: Different (13.3%) | M7: Different - 13.3% (27.2%)
A8: Path | B8: Enhancing My Journey - 3.5% (46.7%) | C8: Kantar Teal | D8: =_xlfn.IFNA(VLOOKUP(C8,Table1[],2,FALSE),"") -> #00E5BA | E8: For enjoying when I am alone | F8: Ocasiones | K8: Enhancing My Journey | L8: Enhancing My Journey (3.5%) | M8: Enhancing My Journey - 3.5% (46.7%)
A9: Path | B9: N/A | C9: Kantar Light Grey | D9: =_xlfn.IFNA(VLOOKUP(C9,Table1[],2,FALSE),"") -> #D9D9D9 | E9: For everyday | F9: Ocasiones | K9: Flavor And Quality | L9: Flavor And Quality (2.7%) | M9: Flavor And Quality - 2.7% (19.1%)
A10: Path | B10: For Me To Indulge - 5.1% (39.2%) | C10: Kantar Purple | D10: =_xlfn.IFNA(VLOOKUP(C10,Table1[],2,FALSE),"") -> #802AB7 | E10: For someone like me | F10: Posicionamiento | K10: For Me To Indulge | L10: For Me To Indulge (5.1%) | M10: For Me To Indulge - 5.1% (39.2%)
A11: Path | B11: Great Legacy - 0.8% (11.1%) | C11: Kantar Yellow | D11: =_xlfn.IFNA(VLOOKUP(C11,Table1[],2,FALSE),"") -> #FEDB00 | E11: Great career | F11: Emocional | K11: Good To Be Seen Drinking | L11: Good To Be Seen Drinking (1.8%) | M11: Good To Be Seen Drinking - 1.8% (13.7%)
A12: Path | B12: Distinguished Style - 2.4% (31.6%) | C12: Kantar Green | D12: =_xlfn.IFNA(VLOOKUP(C12,Table1[],2,FALSE),"") -> #00B600 | E12: It is sophisticated | F12: Emocional | K12: Great Career | L12: Great Career (0.8%) | M12: Great Career - 0.8% (11.1%)
A13: Path | B13: Relaxation - 2.3% (16.4%) | C13: Kantar Orange | D13: =_xlfn.IFNA(VLOOKUP(C13,Table1[],2,FALSE),"") -> #FF5000 | E13: Helps you relax your body and mind | F13: Funcionales | K13: Low Sugar Variety | L13: Low Sugar Variety (1.7%) | M13: Low Sugar Variety - 1.7% (12.1%)
A14: Path | B14: Bright Side Of Life - 1.8% (13.5%) | C14: Kantar Orange | D14: =_xlfn.IFNA(VLOOKUP(C14,Table1[],2,FALSE),"") -> #FF5000 | E14: Helps you see the good side of life | F14: Posicionamiento | K14: Meals | L14: Meals (2.2%) | M14: Meals - 2.2% (29.9%)
... A25: Path | B25: Pleasant Sensation - 1.6% (11.3%) | C25: Kantar Yellow | D25: =_xlfn.IFNA(VLOOKUP(C25,Table1[],2,FALSE),"") -> #FEDB00 | E25: Leaves a pleasant sensation | F25: Funcionales | K25: Worth | L25: Worth (14.3%) | M25: Worth - 14.3% (29.2%)
A26: Path | B26: Balanced Recharge - 3.3% (23.5%) | C26: Kantar Magenta | D26: =_xlfn.IFNA(VLOOKUP(C26,Table1[],2,FALSE),"") -> #C700D3 | E26: Light and balanced | F26: Funcionales
A27: Path | B27: N/A | C27: Kantar Light Grey | D27: =_xlfn.IFNA(VLOOKUP(C27,Table1[],2,FALSE),"") -> #D9D9D9 | E27: Mixer | F27: Funcionales
A28: Path | B28: Modern And Innovative - 4.4% (33.7%) | C28: Kantar Blue | D28: =_xlfn.IFNA(VLOOKUP(C28,Table1[],2,FALSE),"") -> #0060FF | E28: Modern | F28: Posicionamiento
A29: Path | B29: Natural Ingredients - 1.6% (11.8%) | C29: Kantar Green | D29: =_xlfn.IFNA(VLOOKUP(C29,Table1[],2,FALSE),"") -> #00B600 | E29: Natural flavor | F29: Funcionales
A30: Path | B30: Natural Ingredients - 1.6% (11.8%) | C30: Kantar Green | D30: =_xlfn.IFNA(VLOOKUP(C30,Table1[],2,FALSE),"") -> #00B600 | E30: Natural ingredients | F30: Funcionales
A31: Path | B31: N/A | C31: Kantar Light Grey | D31: =_xlfn.IFNA(VLOOKUP(C31,Table1[],2,FALSE),"") -> #D9D9D9 | E31: Remember your childhood | F31: Emocional
A32: Path | B32: Balanced Recharge - 3.3% (23.5%) | C32: Kantar Magenta | D32: =_xlfn.IFNA(VLOOKUP(C32,Table1[],2,FALSE),"") -> #C700D3 | E32: Quenches thirst | F32: Funcionales
A33: Path | B33: Trusted And Reliable - 2.3% (29.8%) | C33: Kantar Sand | D33: =_xlfn.IFNA(VLOOKUP(C33,Table1[],2,FALSE),"") -> #AEAE9F | E33: It is popular | F33: Emocional
A34: Path | B34: Balanced Recharge - 3.3% (23.5%) | C34: Kantar Magenta | D34: =_xlfn.IFNA(VLOOKUP(C34,Table1[],2,FALSE),"") -> #C700D3 | E34: Recharges you with energy | F34: Funcionales
A35: Path | B35: Refreshing - 0.8% (5.8%) | C35: Kantar Red | D35: =_xlfn.IFNA(VLOOKUP(C35,Table1[],2,FALSE),"") -> #FA0028 | E35: Refreshing | F35: Funcionales
A36: Path | B36: N/A | C36: Kantar Light Grey | D36: =_xlfn.IFNA(VLOOKUP(C36,Table1[],2,FALSE),"") -> #D9D9D9 | E36: Related to moments of entertainment | F36: Ocasiones
A37: Path | B37: Trusted And Reliable - 2.3% (29.8%) | C37: Kantar Sand | D37: =_xlfn.IFNA(VLOOKUP(C37,Table1[],2,FALSE),"") -> #AEAE9F | E37: Reliable | F37: Emocional
... A48: Path | B48: Unique Irresistible Sensation - 2.1% (27.5%) | C48: Kantar Red | D48: =_xlfn.IFNA(VLOOKUP(C48,Table1[],2,FALSE),"") -> #FA0028 | E48: Stimulates your senses | F48: Emocional
A49: Tracking | B49: Convenient and attractive package - 4.1% (42.7%) | C49: Kantar Teal | D49: =_xlfn.IFNA(VLOOKUP(C49,Table1[],2,FALSE),"") -> #00E5BA | E49: Attractive packaging | F49: Activador | G49: Attractive packaging - 1.3% (32.6%)
A50: Tracking | B50: Convenient and attractive package - 4.1% (42.7%) | C50: Kantar Teal | D50: =_xlfn.IFNA(VLOOKUP(C50,Table1[],2,FALSE),"") -> #00E5BA | E50: Convenient presentations | F50: Activador | G50: Convenient presentations - 1.4% (33.7%)
A51: Tracking | B51: Accessible - 2.4% (24.3%) | C51: Kantar Purple | D51: =_xlfn.IFNA(VLOOKUP(C51,Table1[],2,FALSE),"") -> #802AB7 | E51: Easy to find | F51: Activador | G51: Easy to find - 1.2% (49.5%)
A52: Tracking | B52: Attractive deals and marketing appeal - 3.2% (33.0%) | C52: Kantar Blue | D52: =_xlfn.IFNA(VLOOKUP(C52,Table1[],2,FALSE),"") -> #0060FF | E52: Engaging advertising | F52: Activador | G52: Engaging advertising - 1.6% (50.4%)
A53: Tracking | B53: Accessible - 2.4% (24.3%) | C53: Kantar Purple | D53: =_xlfn.IFNA(VLOOKUP(C53,Table1[],2,FALSE),"") -> #802AB7 | E53: Fair value | F53: Activador | G53: Fair value - 1.2% (50.5%)
A54: Tracking | B54: Delicious quality - 3.9% (42.1%) | C54: Kantar Blue | D54: =_xlfn.IFNA(VLOOKUP(C54,Table1[],2,FALSE),"") -> #0060FF | E54: Flavor | F54: Funcionales | G54: Flavor - 1.4% (35.0%)
A55: Tracking | B55: For my daily routine - 1.5% (15.6%) | C55: Kantar Teal | D55: =_xlfn.IFNA(VLOOKUP(C55,Table1[],2,FALSE),"") -> #00E5BA | E55: For enjoying when I am alone | F55: Ocasiones | G55: For enjoying when I am alone - 0.8% (50.2%)
A56: Tracking | B56: For my daily routine - 1.5% (15.6%) | C56: Kantar Teal | D56: =_xlfn.IFNA(VLOOKUP(C56,Table1[],2,FALSE),"") -> #00E5BA | E56: For everyday | F56: Ocasiones | G56: For everyday - 0.8% (49.8%)
A57: Tracking | B57: For me to indulge - 6.1% (52.4%) | C57: Kantar Purple | D57: =_xlfn.IFNA(VLOOKUP(C57,Table1[],2,FALSE),"") -> #802AB7 | E57: For someone like me | F57: Posicionamiento | G57: For someone like me - 3.1% (49.8%)
A58: Tracking | B58: My fun rebellious childhood - 3.0% (38.8%) | C58: Kantar Blue | D58: =_xlfn.IFNA(VLOOKUP(C58,Table1[],2,FALSE),"") -> #0060FF | E58: Fun | F58: Emocional | G58: Fun - 0.8% (26.0%)
A59: Tracking | B59: My fun rebellious childhood - 3.0% (38.8%) | C59: Kantar Blue | D59: =_xlfn.IFNA(VLOOKUP(C59,Table1[],2,FALSE),"") -> #0060FF | E59: Rebellious irreverent style | F59: Emocional | G59: Rebellious irreverent style - 0.7% (24.5%)
A60: Tracking | B60: Relaxation - 1.3% (13.7%) | C60: Kantar Orange | D60: =_xlfn.IFNA(VLOOKUP(C60,Table1[],2,FALSE),"") -> #FF5000 | E60: Helps you relax your body and mind | F60: Funcionales | G60: Helps you relax your body and mind - 1.3% (100.0%)
... A95: Tracking | B95: Unique irresistible sensation - 2.1% (27.9%) | C95: Kantar Red | D95: =_xlfn.IFNA(VLOOKUP(C95,Table1[],2,FALSE),"") -> #FA0028 | E95: Stimulates your senses | F95: Emocional | G95: Stimulates your senses - 0.7% (33.1%)

Sheet H2OH BR VS AR
A1: FactorType | B1: FactorName | C1: NodeColor | D1: =VLOOKUP(C1,CATA!A:B,2,FALSE) -> HexColor | E1: Attribute | F1: Group | G1: Full ATT Label | H1: Path = Right | Q1: Factor | R1: Factor Label
A2: Path | B2: Accessible - 2.4% (24.3%) | C2: Kantar Purple | D2: =_xlfn.IFNA(VLOOKUP(C2,Table1[],2,FALSE),"") -> #802AB7 | E2: =LEFT(G2,FIND(" - ",G2)) -> Easy to find | F2: Activador | G2: Easy to find - 1.2% (49.5%) | H2: Tracking = Left | L2: =LEFT(B2,FIND(" - ",B2)-1) -> Accessible | M2: =VLOOKUP(L2,Q:R,2,FALSE) -> Accessible - 2.4% (24.3%) | Q2: Convenient and attractive package | R2: Convenient and attractive package - 4.1% (42.7%)
A3: Path | B3: Accessible - 2.4% (24.3%) | C3: Kantar Purple | D3: =_xlfn.IFNA(VLOOKUP(C3,Table1[],2,FALSE),"") -> #802AB7 | E3: =LEFT(G3,FIND(" - ",G3)) -> Fair value | F3: Activador | G3: Fair value - 1.2% (50.5%) | L3: =LEFT(B3,FIND(" - ",B3)-1) -> Accessible | M3: =VLOOKUP(L3,Q:R,2,FALSE) -> Accessible - 2.4% (24.3%) | Q3: Convenient and attractive package | R3: Convenient and attractive package - 4.1% (42.7%)
A4: Path | B4: Attractive deals and marketing appeal - 3.2% (33.0%) | C4: Kantar Blue | D4: =_xlfn.IFNA(VLOOKUP(C4,Table1[],2,FALSE),"") -> #0060FF | E4: =LEFT(G4,FIND(" - ",G4)) -> Engaging advertising | F4: Activador | G4: Engaging advertising - 1.6% (50.4%) | L4: =LEFT(B4,FIND(" - ",B4)-1) -> Attractive deals and marketing appeal | M4: =VLOOKUP(L4,Q:R,2,FALSE) -> Attractive deals and marketing appeal - 3.2% (33.0%) | Q4: Convenient and attractive package | R4: Convenient and attractive package - 4.1% (42.7%)
A5: Path | B5: Attractive deals and marketing appeal - 3.2% (33.0%) | C5: Kantar Blue | D5: =_xlfn.IFNA(VLOOKUP(C5,Table1[],2,FALSE),"") -> #0060FF | E5: =LEFT(G5,FIND(" - ",G5)) -> It has offers or promotions | F5: Activador | G5: It has offers or promotions - 1.6% (49.6%) | L5: =LEFT(B5,FIND(" - ",B5)-1) -> Attractive deals and marketing appeal | M5: =VLOOKUP(L5,Q:R,2,FALSE) -> Attractive deals and marketing appeal - 3.2% (33.0%) | Q5: Attractive deals and marketing appeal | R5: Attractive deals and marketing appeal - 3.2% (33.0%)
A6: Path | B6: Convenient and attractive package - 4.1% (42.7%) | C6: Kantar Teal | D6: =_xlfn.IFNA(VLOOKUP(C6,Table1[],2,FALSE),"") -> #00E5BA | E6: =LEFT(G6,FIND(" - ",G6)) -> Attractive packaging | F6: Activador | G6: Attractive packaging - 1.3% (32.6%) | L6: =LEFT(B6,FIND(" - ",B6)-1) -> Convenient and attractive package | M6: =VLOOKUP(L6,Q:R,2,FALSE) -> Convenient and attractive package - 4.1% (42.7%) | Q6: Attractive deals and marketing appeal | R6: Attractive deals and marketing appeal - 3.2% (33.0%)
A7: Path | B7: Convenient and attractive package - 4.1% (42.7%) | C7: Kantar Teal | D7: =_xlfn.IFNA(VLOOKUP(C7,Table1[],2,FALSE),"") -> #00E5BA | E7: =LEFT(G7,FIND(" - ",G7)) -> Convenient presentations | F7: Activador | G7: Convenient presentations - 1.4% (33.7%) | L7: =LEFT(B7,FIND(" - ",B7)-1) -> Convenient and attractive package | M7: =VLOOKUP(L7,Q:R,2,FALSE) -> Convenient and attractive package - 4.1% (42.7%) | Q7: Accessible | R7: Accessible - 2.4% (24.3%)
A8: Path | B8: Convenient and attractive package - 4.1% (42.7%) | C8: Kantar Teal | D8: =_xlfn.IFNA(VLOOKUP(C8,Table1[],2,FALSE),"") -> #00E5BA | E8: =LEFT(G8,FIND(" - ",G8)) -> Ideal size | F8: Activador | G8: Ideal size - 1.4% (33.7%) | L8: =LEFT(B8,FIND(" - ",B8)-1) -> Convenient and attractive package | M8: =VLOOKUP(L8,Q:R,2,FALSE) -> Convenient and attractive package - 4.1% (42.7%) | Q8: Accessible | R8: Accessible - 2.4% (24.3%)
A9: Path | B9: Delicious quality - 3.9% (42.1%) | C9: Kantar Blue | D9: =_xlfn.IFNA(VLOOKUP(C9,Table1[],2,FALSE),"") -> #0060FF | E9: =LEFT(G9,FIND(" - ",G9)) -> Flavor | F9: Funcionales | G9: Flavor - 1.4% (35.0%) | L9: =LEFT(B9,FIND(" - ",B9)-1) -> Delicious quality | M9: =VLOOKUP(L9,Q:R,2,FALSE) -> Delicious quality - 3.9% (42.1%) | Q9: My fun rebellious childhood | R9: My fun rebellious childhood - 3.0% (38.8%)
A10: Path | B10: Delicious quality - 3.9% (42.1%) | C10: Kantar Blue | D10: =_xlfn.IFNA(VLOOKUP(C10,Table1[],2,FALSE),"") -> #0060FF | E10: =LEFT(G10,FIND(" - ",G10)) -> High quality | F10: Funcionales | G10: High quality - 1.3% (33.7%) | L10: =LEFT(B10,FIND(" - ",B10)-1) -> Delicious quality | M10: =VLOOKUP(L10,Q:R,2,FALSE) -> Delicious quality - 3.9% (42.1%) | Q10: My fun rebellious childhood | R10: My fun rebellious childhood - 3.0% (38.8%)
A11: Path | B11: Delicious quality - 3.9% (42.1%) | C11: Kantar Blue | D11: =_xlfn.IFNA(VLOOKUP(C11,Table1[],2,FALSE),"") -> #0060FF | E11: =LEFT(G11,FIND(" - ",G11)) -> Variety of flavors | F11: Funcionales | G11: Variety of flavors - 1.2% (31.2%) | L11: =LEFT(B11,FIND(" - ",B11)-1) -> Delicious quality | M11: =VLOOKUP(L11,Q:R,2,FALSE) -> Delicious quality - 3.9% (42.1%) | Q11: My fun rebellious childhood | R11: My fun rebellious childhood - 3.0% (38.8%)
A12: Path | B12: For commuting - 0.5% (4.6%) | C12: Kantar Blue | D12: =_xlfn.IFNA(VLOOKUP(C12,Table1[],2,FALSE),"") -> #0060FF | E12: =LEFT(G12,FIND(" - ",G12)) -> Is for when I go from one place to another | F12: Ocasiones | G12: Is for when I go from one place to another - 0.5% (100.0%) | L12: =LEFT(B12,FIND(" - ",B12)-1) -> For commuting | M12: =VLOOKUP(L12,Q:R,2,FALSE) -> For commuting - 0.5% (4.6%) | Q12: My fun rebellious childhood | R12: My fun rebellious childhood - 3.0% (38.8%)
A13: Path | B13: For entertainment - 0.6% (6.0%) | C13: Kantar Sand | D13: =_xlfn.IFNA(VLOOKUP(C13,Table1[],2,FALSE),"") -> #AEAE9F | E13: =LEFT(G13,FIND(" - ",G13)) -> Related to moments of entertainment | F13: Ocasiones | G13: Related to moments of entertainment - 0.6% (100.0%) | L13: =LEFT(B13,FIND(" - ",B13)-1) -> For entertainment | M13: =VLOOKUP(L13,Q:R,2,FALSE) -> For entertainment - 0.6% (6.0%) | Q13: Unique irresistible sensation | R13: Unique irresistible sensation - 2.1% (27.9%)
A14: Path | B14: For me to indulge - 6.1% (52.4%) | C14: Kantar Purple | D14: =_xlfn.IFNA(VLOOKUP(C14,Table1[],2,FALSE),"") -> #802AB7 | E14: =LEFT(G14,FIND(" - ",G14)) -> For someone like me | F14: Posicionamiento | G14: For someone like me - 3.1% (49.8%) | L14: =LEFT(B14,FIND(" - ",B14)-1) -> For me to indulge | M14: =VLOOKUP(L14,Q:R,2,FALSE) -> For me to indulge - 6.1% (52.4%) | Q14: Unique irresistible sensation | R14: Unique irresistible sensation - 2.1% (27.9%)
... A48: Path | B48: Worry-free refreshment - 0.3% (3.0%) | C48: Kantar Purple | D48: =_xlfn.IFNA(VLOOKUP(C48,Table1[],2,FALSE),"") -> #802AB7 | E48: =LEFT(G48,FIND(" - ",G48)) -> Sweetness options | F48: Funcionales | G48: Sweetness options - 0.1% (30.8%) | L48: =LEFT(B48,FIND(" - ",B48)-1) -> Worry-free refreshment | M48: =VLOOKUP(L48,Q:R,2,FALSE) -> Worry-free refreshment - 0.3% (3.0%) | Q48: For sharing at meals | R48: For sharing at meals - 4.7% (47.4%)
A49: Tracking | B49: Accessible - 1.9% (38.9%) | C49: Kantar Purple | D49: =_xlfn.IFNA(VLOOKUP(C49,Table1[],2,FALSE),"") -> #802AB7 | E49: =LEFT(G49,FIND(" - ",G49)) -> Easy to find | F49: Activador | G49: Easy to find - 1.2% (49.5%) | Q49: Special occasions | R49: Special occasions - 2.6% (26.3%)
A50: Tracking | B50: Accessible - 1.9% (38.9%) | C50: Kantar Purple | D50: =_xlfn.IFNA(VLOOKUP(C50,Table1[],2,FALSE),"") -> #802AB7 | E50: =LEFT(G50,FIND(" - ",G50)) -> Fair value | F50: Activador | G50: Fair value - 1.2% (50.5%) | Q50: Special occasions | R50: Special occasions - 2.6% (26.3%)
A51: Tracking | B51: Attractive deals and marketing appeal - 2.1% (42.9%) | C51: Kantar Blue | D51: =_xlfn.IFNA(VLOOKUP(C51,Table1[],2,FALSE),"") -> #0060FF | E51: =LEFT(G51,FIND(" - ",G51)) -> Engaging advertising | F51: Activador | G51: Engaging advertising - 1.6% (50.4%) | Q51: For my daily routine | R51: For my daily routine - 1.5% (15.6%)
A52: Tracking | B52: Attractive deals and marketing appeal - 2.1% (42.9%) | C52: Kantar Blue | D52: =_xlfn.IFNA(VLOOKUP(C52,Table1[],2,FALSE),"") -> #0060FF | E52: =LEFT(G52,FIND(" - ",G52)) -> It has offers or promotions | F52: Activador | G52: It has offers or promotions - 1.6% (49.6%) | Q52: For my daily routine | R52: For my daily routine - 1.5% (15.6%)
A53: Tracking | B53: Balanced and energizing refreshment - 2.7% (45.0%) | C53: Kantar Purple | D53: =_xlfn.IFNA(VLOOKUP(C53,Table1[],2,FALSE),"") -> #802AB7 | E53: =LEFT(G53,FIND(" - ",G53)) -> Flavor | F53: Funcionales | G53: Flavor - 1.4% (35.0%) | Q53: For entertainment | R53: For entertainment - 0.6% (6.0%)
A54: Tracking | B54: Balanced and energizing refreshment - 2.7% (45.0%) | C54: Kantar Purple | D54: =_xlfn.IFNA(VLOOKUP(C54,Table1[],2,FALSE),"") -> #802AB7 | E54: =LEFT(G54,FIND(" - ",G54)) -> High quality | F54: Funcionales | G54: High quality - 1.3% (33.7%) | Q54: For commuting | R54: For commuting - 0.5% (4.6%)
A55: Tracking | B55: Balanced and energizing refreshment - 2.7% (45.0%) | C55: Kantar Purple | D55: =_xlfn.IFNA(VLOOKUP(C55,Table1[],2,FALSE),"") -> #802AB7 | E55: =LEFT(G55,FIND(" - ",G55)) -> Leaves a pleasant sensation | F55: Funcionales | G55: Leaves a pleasant sensation - 0.8% (33.7%)
A56: Tracking | B56: Balanced and energizing refreshment - 2.7% (45.0%) | C56: Kantar Purple | D56: =_xlfn.IFNA(VLOOKUP(C56,Table1[],2,FALSE),"") -> #802AB7 | E56: =LEFT(G56,FIND(" - ",G56)) -> Light and balanced | F56: Funcionales | G56: Light and balanced - 0.8% (33.4%)
A57: Tracking | B57: Balanced and energizing refreshment - 2.7% (45.0%) | C57: Kantar Purple | D57: =_xlfn.IFNA(VLOOKUP(C57,Table1[],2,FALSE),"") -> #802AB7 | E57: =LEFT(G57,FIND(" - ",G57)) -> Quenches thirst | F57: Funcionales | G57: Quenches thirst - 0.1% (34.6%)
A58: Tracking | B58: Balanced and energizing refreshment - 2.7% (45.0%) | C58: Kantar Purple | D58: =_xlfn.IFNA(VLOOKUP(C58,Table1[],2,FALSE),"") -> #802AB7 | E58: =LEFT(G58,FIND(" - ",G58)) -> Refreshing | F58: Funcionales | G58: Refreshing - 0.1% (34.5%)
A59: Tracking | B59: Convenient and attractive package - 2.1% (38.9%) | C59: Kantar Teal | D59: =_xlfn.IFNA(VLOOKUP(C59,Table1[],2,FALSE),"") -> #00E5BA | E59: =LEFT(G59,FIND(" - ",G59)) -> Attractive packaging | F59: Activador | G59: Attractive packaging - 1.3% (32.6%)
A60: Tracking | B60: Convenient and attractive package - 2.1% (38.9%) | C60: Kantar Teal | D60: =_xlfn.IFNA(VLOOKUP(C60,Table1[],2,FALSE),"") -> #00E5BA | E60: =LEFT(G60,FIND(" - ",G60)) -> Ideal size | F60: Activador | G60: Ideal size - 1.4% (33.7%)
A61: Tracking | B61: Convenient and attractive package - 2.1% (38.9%) | C61: Kantar Teal | D61: =_xlfn.IFNA(VLOOKUP(C61,Table1[],2,FALSE),"") -> #00E5BA | E61: =LEFT(G61,FIND(" - ",G61)) -> Convenient presentations | F61: Activador | G61: Convenient presentations - 1.4% (33.7%)
A62: Tracking | B62: Daily commute - 3.6% (24.7%) | C62: Kantar Purple | D62: =_xlfn.IFNA(VLOOKUP(C62,Table1[],2,FALSE),"") -> #802AB7 | E62: =LEFT(G62,FIND(" - ",G62)) -> For everyday | F62: Ocasiones | G62: For everyday - 0.8% (49.8%)
A63: Tracking | B63: Daily commute - 3.6% (24.7%) | C63: Kantar Purple | D63: =_xlfn.IFNA(VLOOKUP(C63,Table1[],2,FALSE),"") -> #802AB7 | E63: =LEFT(G63,FIND(" - ",G63)) -> Is for when I go from one place to another | F63: Ocasiones | G63: Is for when I go from one place to another - 0.5% (100.0%)
A64: Tracking | B64: Distinguished - 2.2% (26.8%) | C64: Kantar Purple | D64: =_xlfn.IFNA(VLOOKUP(C64,Table1[],2,FALSE),"") -> #802AB7 | E64: =LEFT(G64,FIND(" - ",G64)) -> It is sophisticated | F64: Emocional | G64: It is sophisticated - 1.2% (100.0%)
A65: Tracking | B65: Distinguished - 2.2% (26.8%) | C65: Kantar Purple | D65: =_xlfn.IFNA(VLOOKUP(C65,Table1[],2,FALSE),"") -> #802AB7 | E65: =LEFT(G65,FIND(" - ",G65)) -> Offers something different | F65: Emocional | G65: Offers something different - 0.7% (32.5%)
A66: Tracking | B66: For entertainment - <1% (<1%) | C66: Kantar Sand | D66: =_xlfn.IFNA(VLOOKUP(C66,Table1[],2,FALSE),"") -> #AEAE9F | E66: =LEFT(G66,FIND(" - ",G66)) -> Related to moments of entertainment | F66: Ocasiones | G66: Related to moments of entertainment - 0.6% (100.0%)
... A95: Tracking | B95: Variety flavors - <1% (12.5%) | C95: Kantar Yellow | D95: =_xlfn.IFNA(VLOOKUP(C95,Table1[],2,FALSE),"") -> #FEDB00 | E95: =LEFT(G95,FIND(" - ",G95)) -> Variety of flavors | F95: Funcionales | G95: Variety of flavors - 1.2% (31.2%)

Sheet H2OH BR VS CO
A1: FactorType | B1: FactorName | C1: NodeColor | D1: =VLOOKUP(C1,CATA!A:B,2,FALSE) -> HexColor | E1: Attribute | F1: Group | H1: Path = Right
A2: Path | B2: Accessible | C2: Kantar Purple | D2: =_xlfn.IFNA(VLOOKUP(C2,Table1[],2,FALSE),"") -> #802AB7 | E2: Easy to find | F2: Activador | H2: Tracking = Left
A3: Path | B3: Accessible | C3: Kantar Purple | D3: =_xlfn.IFNA(VLOOKUP(C3,Table1[],2,FALSE),"") -> #802AB7 | E3: Fair value | F3: Activador
A4: Path | B4: Attractive deals and marketing appeal | C4: Kantar Blue | D4: =_xlfn.IFNA(VLOOKUP(C4,Table1[],2,FALSE),"") -> #0060FF | E4: Engaging advertising | F4: Activador
A5: Path | B5: Attractive deals and marketing appeal | C5: Kantar Blue | D5: =_xlfn.IFNA(VLOOKUP(C5,Table1[],2,FALSE),"") -> #0060FF | E5: It has offers or promotions | F5: Activador
A6: Path | B6: Convenient and attractive package | C6: Kantar Green | D6: =_xlfn.IFNA(VLOOKUP(C6,Table1[],2,FALSE),"") -> #00B600 | E6: Attractive packaging | F6: Activador
A7: Path | B7: Convenient and attractive package | C7: Kantar Green | D7: =_xlfn.IFNA(VLOOKUP(C7,Table1[],2,FALSE),"") -> #00B600 | E7: Convenient presentations | F7: Activador
A8: Path | B8: Convenient and attractive package | C8: Kantar Green | D8: =_xlfn.IFNA(VLOOKUP(C8,Table1[],2,FALSE),"") -> #00B600 | E8: Ideal size | F8: Activador
A9: Path | B9: My fun rebollious chilhood | C9: Kantar Sand | D9: =_xlfn.IFNA(VLOOKUP(C9,Table1[],2,FALSE),"") -> #AEAE9F | E9: Fun | F9: Emocional
A10: Path | B10: My fun rebollious chilhood | C10: Kantar Sand | D10: =_xlfn.IFNA(VLOOKUP(C10,Table1[],2,FALSE),"") -> #AEAE9F | E10: Rebellious/irreverent style | F10: Emocional
A11: Path | B11: My fun rebollious chilhood | C11: Kantar Sand | D11: =_xlfn.IFNA(VLOOKUP(C11,Table1[],2,FALSE),"") -> #AEAE9F | E11: Remember your childhood | F11: Emocional
A12: Path | B12: My fun rebollious chilhood | C12: Kantar Sand | D12: =_xlfn.IFNA(VLOOKUP(C12,Table1[],2,FALSE),"") -> #AEAE9F | E12: You identify | F12: Emocional
A13: Path | B13: Popular | C13: Kantar Teal | D13: =_xlfn.IFNA(VLOOKUP(C13,Table1[],2,FALSE),"") -> #00E5BA | E13: Great career | F13: Emocional
A14: Path | B14: Popular | C14: Kantar Teal | D14: =_xlfn.IFNA(VLOOKUP(C14,Table1[],2,FALSE),"") -> #00E5BA | E14: It is popular | F14: Emocional
... A95: Tracking | B95: Reflects my identity | C95: Kantar Green | D95: =_xlfn.IFNA(VLOOKUP(C95,Table1[],2,FALSE),"") -> #00B600 | E95: I like to be seen consuming it | F95: Posicionamiento

Sheet BSA Corona Capital
A1: FactorType | B1: FactorName | C1: NodeColor | D1: =VLOOKUP(C1,CATA!A:B,2,FALSE) -> HexColor | E1: Attribute | H1: Path = Right
A2: Path | B2: Balanced lifestyle | C2: Kantar Blue | D2: =_xlfn.IFNA(VLOOKUP(C2,Table1[],2,FALSE),"") -> #0060FF | E2: Represents a balanced lifestyle choice | H2: Tracking = Left
A3: Path | B3: Honest about their natural ingredients | C3: Kantar Green | D3: =_xlfn.IFNA(VLOOKUP(C3,Table1[],2,FALSE),"") -> #00B600 | E3: Is made from natural ingredients
A4: Path | B4: Honest about their natural ingredients | C4: Kantar Green | D4: =_xlfn.IFNA(VLOOKUP(C4,Table1[],2,FALSE),"") -> #00B600 | E4: It is open and honest about what it is made of
A5: Path | B5: Intrinsic and gathering | C5: Kantar Purple | D5: =_xlfn.IFNA(VLOOKUP(C5,Table1[],2,FALSE),"") -> #802AB7 | E5: You like to share with your friends
A6: Path | B6: Intrinsic and gathering | C6: Kantar Purple | D6: =_xlfn.IFNA(VLOOKUP(C6,Table1[],2,FALSE),"") -> #802AB7 | E6: Goes well with food meals
A7: Path | B7: Intrinsic and gathering | C7: Kantar Purple | D7: =_xlfn.IFNA(VLOOKUP(C7,Table1[],2,FALSE),"") -> #802AB7 | E7: You like to savour
A8: Path | B8: Intrinsic and gathering | C8: Kantar Purple | D8: =_xlfn.IFNA(VLOOKUP(C8,Table1[],2,FALSE),"") -> #802AB7 | E8: Adds energy to your social occasion
A9: Path | B9: Intrinsic and gathering | C9: Kantar Purple | D9: =_xlfn.IFNA(VLOOKUP(C9,Table1[],2,FALSE),"") -> #802AB7 | E9: Is good to drink when you want to relax
A10: Path | B10: Intrinsic and gathering | C10: Kantar Purple | D10: =_xlfn.IFNA(VLOOKUP(C10,Table1[],2,FALSE),"") -> #802AB7 | E10: Is more refreshing than others
A11: Path | B11: Smooth taste | C11: Kantar Teal | D11: =_xlfn.IFNA(VLOOKUP(C11,Table1[],2,FALSE),"") -> #00E5BA | E11: Has a smooth taste
A12: Path | B12: Socially responsible | C12: Kantar Magenta | D12: =_xlfn.IFNA(VLOOKUP(C12,Table1[],2,FALSE),"") -> #C700D3 | E12: It is a socially responsible brand
A13: Path | B13: Successful brand | C13: Kantar Yellow | D13: =_xlfn.IFNA(VLOOKUP(C13,Table1[],2,FALSE),"") -> #FEDB00 | E13: Is a successful international brand
A14: Path | B14: Superior standards | C14: Kantar Light Grey | D14: =_xlfn.IFNA(VLOOKUP(C14,Table1[],2,FALSE),"") -> #D9D9D9 | E14: Is a high quality brand
... A41: Tracking | B41: Traditions and national pride | C41: Kantar Red | D41: =_xlfn.IFNA(VLOOKUP(C41,Table1[],2,FALSE),"") -> #FA0028 | E41: Is the beer that combines the best with mexican flavors

Sheet Pacifico IMG vs Cat
A1: FactorType | B1: FactorName | C1: NodeColor | D1: =VLOOKUP(C1,CATA!A:B,2,FALSE) -> HexColor | E1: Attribute | K1: Path = Right
A2: Path | B2: Brewed with care | C2: Kantar Light Grey | D2: =_xlfn.IFNA(VLOOKUP(C2,Table1[],2,FALSE),"") -> #D9D9D9 | E2: Is brewed with care | G2: Brewed with care | H2: =VLOOKUP(G2,$L$46:$N$54,3,0) -> Brewed with care (11.2%) | K2: Tracking = Left
A3: Path | B3: High quality brand | C3: Kantar Light Grey | D3: =_xlfn.IFNA(VLOOKUP(C3,Table1[],2,FALSE),"") -> #D9D9D9 | E3: Is a high quality brand | G3: High quality brand | H3: =VLOOKUP(G3,$L$46:$N$54,3,0) -> High quality brand (0.0%)
A4: Path | B4: Refreshing and relaxing meals | C4: Kantar Sand | D4: =_xlfn.IFNA(VLOOKUP(C4,Table1[],2,FALSE),"") -> #AEAE9F | E4: Goes well with food/ meals | G4: Refreshing and relaxing meals | H4: =VLOOKUP(G4,$L$46:$N$54,3,0) -> Refreshing and relaxing meals (15.2%)
A5: Path | B5: Refreshing and relaxing meals | C5: Kantar Sand | D5: =_xlfn.IFNA(VLOOKUP(C5,Table1[],2,FALSE),"") -> #AEAE9F | E5: Is more refreshing than others | G5: Refreshing and relaxing meals | H5: =VLOOKUP(G5,$L$46:$N$54,3,0) -> Refreshing and relaxing meals (15.2%)
A6: Path | B6: Indulgent escape with friends | C6: Kantar Orange | D6: =_xlfn.IFNA(VLOOKUP(C6,Table1[],2,FALSE),"") -> #FF5000 | E6: You like to share with your friends | G6: Indulgent scape with friends | H6: =VLOOKUP(G6,$L$46:$N$54,3,0) -> Indulgent scape with friends (23.3%)
A7: Path | B7: Indulgent escape with friends | C7: Kantar Orange | D7: =_xlfn.IFNA(VLOOKUP(C7,Table1[],2,FALSE),"") -> #FF5000 | E7: Adds energy to your social occasion | G7: Indulgent scape with friends | H7: =VLOOKUP(G7,$L$46:$N$54,3,0) -> Indulgent scape with friends (23.3%)
A8: Path | B8: Indulgent escape with friends | C8: Kantar Orange | D8: =_xlfn.IFNA(VLOOKUP(C8,Table1[],2,FALSE),"") -> #FF5000 | E8: You like to savour | G8: Indulgent scape with friends | H8: =VLOOKUP(G8,$L$46:$N$54,3,0) -> Indulgent scape with friends (23.3%)
A9: Path | B9: Refreshing and relaxing meals | C9: Kantar Sand | D9: =_xlfn.IFNA(VLOOKUP(C9,Table1[],2,FALSE),"") -> #AEAE9F | E9: Is good to drink when you want to relax | G9: Refreshing and relaxing meals | H9: =VLOOKUP(G9,$L$46:$N$54,3,0) -> Refreshing and relaxing meals (15.2%)
A10: Path | B10: Smooth taste | C10: Kantar Teal | D10: =_xlfn.IFNA(VLOOKUP(C10,Table1[],2,FALSE),"") -> #00E5BA | E10: Has a smooth taste | G10: Smooth taste | H10: =VLOOKUP(G10,$L$46:$N$54,3,0) -> Smooth taste (4.6%)
A11: Path | B11: Social commitment | C11: Kantar Blue | D11: =_xlfn.IFNA(VLOOKUP(C11,Table1[],2,FALSE),"") -> #0060FF | E11: Is made from natural ingredients | G11: Social commitment | H11: =VLOOKUP(G11,$L$46:$N$54,3,0) -> Social commitment (9.0%)
A12: Path | B12: Social commitment | C12: Kantar Blue | D12: =_xlfn.IFNA(VLOOKUP(C12,Table1[],2,FALSE),"") -> #0060FF | E12: It is open and honest about what it is made of | G12: Social commitment | H12: =VLOOKUP(G12,$L$46:$N$54,3,0) -> Social commitment (9.0%) | L12: Intrinsic + Gathering | M12: Quality + Special occasions | N12: Traditions and national pride | O12: Social commitment | P12: Balanced lifestyle | Q12: Smooth | R12: International
A13: Path | B13: Social commitment | C13: Kantar Blue | D13: =_xlfn.IFNA(VLOOKUP(C13,Table1[],2,FALSE),"") -> #0060FF | E13: It is a socially responsible brand | G13: Social commitment | H13: =VLOOKUP(G13,$L$46:$N$54,3,0) -> Social commitment (9.0%) | J13: Importance weights to Meaningful | K13: 0.67589696 | L13: 0.24243947 | M13: 0.1269301 | N13: 0.097068766 | O13: 0.049972204 | P13: 0.043393756 | Q13: 0.083751712 | R13: 0.032340951
A14: Path | B14: Balanced special occasions | C14: Kantar Yellow | D14: =_xlfn.IFNA(VLOOKUP(C14,Table1[],2,FALSE),"") -> #FEDB00 | E14: Makes an occasion more special | G14: Balanced special occasions | H14: =VLOOKUP(G14,$L$46:$N$54,3,0) -> Balanced special occasions (21.6%) | J14: Importance weights to Different | K14: 0.59694002 | L14: 0.12337309 | M14: 0.15900972 | N14: 0.06722726 | O14: 0.068518512 | P14: 0.064925195 | Q14: 0.038784284 | R14: 0.075101952
A15: Path | B15: Balanced special occasions | C15: Kantar Yellow | D15: =_xlfn.IFNA(VLOOKUP(C15,Table1[],2,FALSE),"") -> #FEDB00 | E15: Is sophisticated | G15: Balanced special occasions | H15: =VLOOKUP(G15,$L$46:$N$54,3,0) -> Balanced special occasions (21.6%) | J15: Importance weights to Salient | K15: 1.0226284 | L15: 0.31417795 | M15: 0.1182202 | N15: 0.26691341 | O15: 0.089821019 | P15: 0.093990532 | Q15: 0.068606917 | R15: 0.070898375
A16: Path | B16: Balanced special occasions | C16: Kantar Yellow | D16: =_xlfn.IFNA(VLOOKUP(C16,Table1[],2,FALSE),"") -> #FEDB00 | E16: Is good to be seen drinking | G16: Balanced special occasions | H16: =VLOOKUP(G16,$L$46:$N$54,3,0) -> Balanced special occasions (21.6%) | J16: Importance weights to Demand Power | K16: 1.3446893 | L16: 0.41048277 | M16: 0.19241996 | N16: 0.30292417 | O16: 0.1171688 | P16: 0.11220056 | Q16: 0.10959803 | R16: 0.099895019
A17: Path | B17: Balanced special occasions | C17: Kantar Yellow | D17: =_xlfn.IFNA(VLOOKUP(C17,Table1[],2,FALSE),"") -> #FEDB00 | E17: Represents a balanced lifestyle choice | G17: Balanced special occasions | H17: =VLOOKUP(G17,$L$46:$N$54,3,0) -> Balanced special occasions (21.6%) | J17: Importance weights to Pricing Power | K17: 0.907267 | L17: 0.25529466 | M17: 0.18339554 | N17: 0.14215579 | O17: 0.092780126 | P17: 0.081675157 | Q17: 0.075539638 | R17: 0.076426089
A18: Path | B18: Successful international brand | C18: Kantar Magenta | D18: =_xlfn.IFNA(VLOOKUP(C18,Table1[],2,FALSE),"") -> #C700D3 | E18: Is a successful international brand | G18: Successful international brand | H18: =VLOOKUP(G18,$L$46:$N$54,3,0) -> Successful international brand (0.0%)
A19: Path | B19: Traditions and national pride | C19: Kantar Red | D19: =_xlfn.IFNA(VLOOKUP(C19,Table1[],2,FALSE),"") -> #FA0028 | E19: Is a brand that represents our traditions and heritage | G19: Traditions and national pride | H19: =VLOOKUP(G19,$L$46:$N$54,3,0) -> Traditions and national pride (15.1%) | J19: Importance weights to Meaningful % | L19: 0.35869294 | M19: 0.18779505 | N19: 0.14361474 | O19: 0.073934648 | P19: 0.064201732 | Q19: 0.12391195 | R19: 0.047848937
A20: Path | B20: Traditions and national pride | C20: Kantar Red | D20: =_xlfn.IFNA(VLOOKUP(C20,Table1[],2,FALSE),"") -> #FA0028 | E20: Represents my national pride | G20: Traditions and national pride | H20: =VLOOKUP(G20,$L$46:$N$54,3,0) -> Traditions and national pride (15.1%) | J20: Importance weights to Different % | L20: 0.20667587 | M20: 0.2663747 | N20: 0.11261979 | O20: 0.11478291 | P20: 0.10876335 | Q20: 0.064971827 | R20: 0.12581156
A21: Path | B21: Traditions and national pride | C21: Kantar Red | D21: =_xlfn.IFNA(VLOOKUP(C21,Table1[],2,FALSE),"") -> #FA0028 | E21: Is the beer that combines the best with mexican flavors | G21: Traditions and national pride | H21: =VLOOKUP(G21,$L$46:$N$54,3,0) -> Traditions and national pride (15.1%) | J21: Importance weights to Salient % | L21: 0.30722591 | M21: 0.11560426 | N21: 0.26100724 | O21: 0.087833487 | P21: 0.091910738 | Q21: 0.067088804 | R21: 0.069329558
A22: Tracking | B22: Balanced lifestyle | C22: Kantar Yellow | D22: =_xlfn.IFNA(VLOOKUP(C22,Table1[],2,FALSE),"") -> #FEDB00 | E22: Represents a balanced lifestyle choice | G22: Balanced lifestyle | H22: =VLOOKUP(G22,$K$30:$M$36,3,0) -> (8.3%) Balanced lifestyle | J22: Importance weights to Demand Power % | L22: 0.30526217 | M22: 0.14309622 | N22: 0.22527447 | O22: 0.087134476 | P22: 0.083439764 | Q22: 0.081504353 | R22: 0.07428855
A23: Tracking | B23: International | C23: Kantar Magenta | D23: =_xlfn.IFNA(VLOOKUP(C23,Table1[],2,FALSE),"") -> #C700D3 | E23: Is a successful international brand | G23: International | H23: =VLOOKUP(G23,$K$30:$M$36,3,0) -> (7.4%) International | J23: Importance weights to Pricing Power % | L23: 0.28138868 | M23: 0.20214064 | N23: 0.15668573 | O23: 0.10226331 | P23: 0.090023286 | Q23: 0.083260648 | R23: 0.084237704
A24: Tracking | B24: Intrinsic + Gathering | C24: Kantar Green | D24: =_xlfn.IFNA(VLOOKUP(C24,Table1[],2,FALSE),"") -> #00B600 | E24: You like to share with your friends | G24: Intrinsic + Gathering | H24: =VLOOKUP(G24,$K$30:$M$36,3,0) -> (30.5%) Intrinsic + Gathering
A25: Tracking | B25: Intrinsic + Gathering | C25: Kantar Green | D25: =_xlfn.IFNA(VLOOKUP(C25,Table1[],2,FALSE),"") -> #00B600 | E25: Adds energy to your social occasion | G25: Intrinsic + Gathering | H25: =VLOOKUP(G25,$K$30:$M$36,3,0) -> (30.5%) Intrinsic + Gathering
A26: Tracking | B26: Intrinsic + Gathering | C26: Kantar Green | D26: =_xlfn.IFNA(VLOOKUP(C26,Table1[],2,FALSE),"") -> #00B600 | E26: You like to savour | G26: Intrinsic + Gathering | H26: =VLOOKUP(G26,$K$30:$M$36,3,0) -> (30.5%) Intrinsic + Gathering
A27: Tracking | B27: Intrinsic + Gathering | C27: Kantar Green | D27: =_xlfn.IFNA(VLOOKUP(C27,Table1[],2,FALSE),"") -> #00B600 | E27: Is good to drink when you want to relax | G27: Intrinsic + Gathering | H27: =VLOOKUP(G27,$K$30:$M$36,3,0) -> (30.5%) Intrinsic + Gathering
A28: Tracking | B28: Intrinsic + Gathering | C28: Kantar Green | D28: =_xlfn.IFNA(VLOOKUP(C28,Table1[],2,FALSE),"") -> #00B600 | E28: Goes well with food/ meals | G28: Intrinsic + Gathering | H28: =VLOOKUP(G28,$K$30:$M$36,3,0) -> (30.5%) Intrinsic + Gathering
A29: Tracking | B29: Intrinsic + Gathering | C29: Kantar Green | D29: =_xlfn.IFNA(VLOOKUP(C29,Table1[],2,FALSE),"") -> #00B600 | E29: Is more refreshing than others | G29: Intrinsic + Gathering | H29: =VLOOKUP(G29,$K$30:$M$36,3,0) -> (30.5%) Intrinsic + Gathering | L29: Importance weights to Demand Power %
A30: Tracking | B30: Quality + Special occasions | C30: Kantar Yellow | D30: =_xlfn.IFNA(VLOOKUP(C30,Table1[],2,FALSE),"") -> #FEDB00 | E30: Is good to be seen drinking | G30: Quality + Special occasions | H30: =VLOOKUP(G30,$K$30:$M$36,3,0) -> (14.3%) Quality + Special occasions | K30: Intrinsic + Gathering | L30: 0.30526217 | M30: =_xlfn.TEXTJOIN(" ",1,TEXT(L30,"(0.0%)"),K30) -> (30.5%) Intrinsic + Gathering
A31: Tracking | B31: Quality + Special occasions | C31: Kantar Purple | D31: =_xlfn.IFNA(VLOOKUP(C31,Table1[],2,FALSE),"") -> #802AB7 | E31: Makes an occasion more special | G31: Quality + Special occasions | H31: =VLOOKUP(G31,$K$30:$M$36,3,0) -> (14.3%) Quality + Special occasions | K31: Quality + Special occasions | L31: 0.14309622 | M31: =_xlfn.TEXTJOIN(" ",1,TEXT(L31,"(0.0%)"),K31) -> (14.3%) Quality + Special occasions
A32: Tracking | B32: Quality + Special occasions | C32: Kantar Purple | D32: =_xlfn.IFNA(VLOOKUP(C32,Table1[],2,FALSE),"") -> #802AB7 | E32: Is sophisticated | G32: Quality + Special occasions | H32: =VLOOKUP(G32,$K$30:$M$36,3,0) -> (14.3%) Quality + Special occasions | K32: Traditions and national pride | L32: 0.22527447 | M32: =_xlfn.TEXTJOIN(" ",1,TEXT(L32,"(0.0%)"),K32) -> (22.5%) Traditions and national pride
A33: Tracking | B33: Quality + Special occasions | C33: Kantar Purple | D33: =_xlfn.IFNA(VLOOKUP(C33,Table1[],2,FALSE),"") -> #802AB7 | E33: Is brewed with care | G33: Quality + Special occasions | H33: =VLOOKUP(G33,$K$30:$M$36,3,0) -> (14.3%) Quality + Special occasions | K33: Social commitment | L33: 0.087134476 | M33: =_xlfn.TEXTJOIN(" ",1,TEXT(L33,"(0.0%)"),K33) -> (8.7%) Social commitment
A34: Tracking | B34: Quality + Special occasions | C34: Kantar Purple | D34: =_xlfn.IFNA(VLOOKUP(C34,Table1[],2,FALSE),"") -> #802AB7 | E34: Is a high quality brand | G34: Quality + Special occasions | H34: =VLOOKUP(G34,$K$30:$M$36,3,0) -> (14.3%) Quality + Special occasions | K34: Balanced lifestyle | L34: 0.083439764 | M34: =_xlfn.TEXTJOIN(" ",1,TEXT(L34,"(0.0%)"),K34) -> (8.3%) Balanced lifestyle
A35: Tracking | B35: Smooth | C35: Kantar Teal | D35: =_xlfn.IFNA(VLOOKUP(C35,Table1[],2,FALSE),"") -> #00E5BA | E35: Has a smooth taste | G35: Smooth | H35: =VLOOKUP(G35,$K$30:$M$36,3,0) -> (8.2%) Smooth | K35: Smooth | L35: 0.081504353 | M35: =_xlfn.TEXTJOIN(" ",1,TEXT(L35,"(0.0%)"),K35) -> (8.2%) Smooth
A36: Tracking | B36: Social commitment | C36: Kantar Blue | D36: =_xlfn.IFNA(VLOOKUP(C36,Table1[],2,FALSE),"") -> #0060FF | E36: Is made from natural ingredients | G36: Social commitment | H36: =VLOOKUP(G36,$K$30:$M$36,3,0) -> (8.7%) Social commitment | K36: International | L36: 0.07428855 | M36: =_xlfn.TEXTJOIN(" ",1,TEXT(L36,"(0.0%)"),K36) -> (7.4%) International
A37: Tracking | B37: Social commitment | C37: Kantar Blue | D37: =_xlfn.IFNA(VLOOKUP(C37,Table1[],2,FALSE),"") -> #0060FF | E37: It is open and honest about what it is made of | G37: Social commitment | H37: =VLOOKUP(G37,$K$30:$M$36,3,0) -> (8.7%) Social commitment
A38: Tracking | B38: Social commitment | C38: Kantar Blue | D38: =_xlfn.IFNA(VLOOKUP(C38,Table1[],2,FALSE),"") -> #0060FF | E38: It is a socially responsible brand | G38: Social commitment | H38: =VLOOKUP(G38,$K$30:$M$36,3,0) -> (8.7%) Social commitment
A39: Tracking | B39: Traditions and national pride | C39: Kantar Red | D39: =_xlfn.IFNA(VLOOKUP(C39,Table1[],2,FALSE),"") -> #FA0028 | E39: Is a brand that represents our traditions and heritage | G39: Traditions and national pride | H39: =VLOOKUP(G39,$K$30:$M$36,3,0) -> (22.5%) Traditions and national pride
A40: Tracking | B40: Traditions and national pride | C40: Kantar Red | D40: =_xlfn.IFNA(VLOOKUP(C40,Table1[],2,FALSE),"") -> #FA0028 | E40: Represents my national pride | G40: Traditions and national pride | H40: =VLOOKUP(G40,$K$30:$M$36,3,0) -> (22.5%) Traditions and national pride
A41: Tracking | B41: Traditions and national pride | C41: Kantar Red | D41: =_xlfn.IFNA(VLOOKUP(C41,Table1[],2,FALSE),"") -> #FA0028 | E41: Is the beer that combines the best with mexican flavors | G41: Traditions and national pride | H41: =VLOOKUP(G41,$K$30:$M$36,3,0) -> (22.5%) Traditions and national pride
L46: Brewed with care | M46: 0.11180446 | N46: =_xlfn.TEXTJOIN(" ",1,L46,TEXT(M46,"(0.0%)")) -> Brewed with care (11.2%)
L47: Balanced special occasions | M47: 0.21571841 | N47: =_xlfn.TEXTJOIN(" ",1,L47,TEXT(M47,"(0.0%)")) -> Balanced special occasions (21.6%)
L48: High quality brand | M48: 0.00014934378 | N48: =_xlfn.TEXTJOIN(" ",1,L48,TEXT(M48,"(0.0%)")) -> High quality brand (0.0%)
L49: Indulgent scape with friends | M49: 0.23267574 | N49: =_xlfn.TEXTJOIN(" ",1,L49,TEXT(M49,"(0.0%)")) -> Indulgent scape with friends (23.3%)
L50: Refreshing and relaxing meals | M50: 0.15181311 | N50: =_xlfn.TEXTJOIN(" ",1,L50,TEXT(M50,"(0.0%)")) -> Refreshing and relaxing meals (15.2%)
L51: Smooth taste | M51: 0.04626978 | N51: =_xlfn.TEXTJOIN(" ",1,L51,TEXT(M51,"(0.0%)")) -> Smooth taste (4.6%)
L52: Social commitment | M52: 0.09039298 | N52: =_xlfn.TEXTJOIN(" ",1,L52,TEXT(M52,"(0.0%)")) -> Social commitment (9.0%)
L53: Successful international brand | M53: 1.3276395e-05 | N53: =_xlfn.TEXTJOIN(" ",1,L53,TEXT(M53,"(0.0%)")) -> Successful international brand (0.0%)
L54: Traditions and national pride | M54: 0.1511629 | N54: =_xlfn.TEXTJOIN(" ",1,L54,TEXT(M54,"(0.0%)")) -> Traditions and national pride (15.1%)

Sheet Pacifico IMG vs Pac
A1: FactorType | B1: FactorName | C1: NodeColor | D1: =VLOOKUP(C1,CATA!A:B,2,FALSE) -> HexColor | E1: Attribute | H1: Path = Right
A2: Tracking | B2: High & cared quality | C2: Kantar Light Grey | D2: =_xlfn.IFNA(VLOOKUP(C2,Table1[],2,FALSE),"") -> #D9D9D9 | E2: Is a successful international brand | F2: High & cared quality | G2: =VLOOKUP(F2,$J$7:$M$12,4,0) -> (17.9%) High & cared quality | H2: Tracking = Left
A3: Tracking | B3: High & cared quality | C3: Kantar Light Grey | D3: =_xlfn.IFNA(VLOOKUP(C3,Table1[],2,FALSE),"") -> #D9D9D9 | E3: Is brewed with care | F3: High & cared quality | G3: =VLOOKUP(F3,$J$7:$M$12,4,0) -> (17.9%) High & cared quality
A4: Tracking | B4: High & cared quality | C4: Kantar Light Grey | D4: =_xlfn.IFNA(VLOOKUP(C4,Table1[],2,FALSE),"") -> #D9D9D9 | E4: Is a high quality brand | F4: High & cared quality | G4: =VLOOKUP(F4,$J$7:$M$12,4,0) -> (17.9%) High & cared quality
A5: Tracking | B5: Relax & social occasions | C5: Kantar Orange | D5: =_xlfn.IFNA(VLOOKUP(C5,Table1[],2,FALSE),"") -> #FF5000 | E5: Is good to be seen drinking | F5: Relax & social occasions | G5: =VLOOKUP(F5,$J$7:$M$12,4,0) -> (21.4%) Relax & social occasions
A6: Tracking | B6: Relax & social occasions | C6: Kantar Orange | D6: =_xlfn.IFNA(VLOOKUP(C6,Table1[],2,FALSE),"") -> #FF5000 | E6: You like to share with your friends | F6: Relax & social occasions | G6: =VLOOKUP(F6,$J$7:$M$12,4,0) -> (21.4%) Relax & social occasions
A7: Tracking | B7: Relax & social occasions | C7: Kantar Orange | D7: =_xlfn.IFNA(VLOOKUP(C7,Table1[],2,FALSE),"") -> #FF5000 | E7: Adds energy to your social occasion | F7: Relax & social occasions | G7: =VLOOKUP(F7,$J$7:$M$12,4,0) -> (21.4%) Relax & social occasions | J7: High & cared quality | K7: 0.047 | L7: =K7/SUM($K$7:$K$12) -> 0.17938931 | M7: =_xlfn.TEXTJOIN(" ",1,TEXT(L7,"(0.0%)"),J7) -> (17.9%) High & cared quality
A8: Tracking | B8: Relax & social occasions | C8: Kantar Orange | D8: =_xlfn.IFNA(VLOOKUP(C8,Table1[],2,FALSE),"") -> #FF5000 | E8: Is good to drink when you want to relax | F8: Relax & social occasions | G8: =VLOOKUP(F8,$J$7:$M$12,4,0) -> (21.4%) Relax & social occasions | J8: Relax & social occasions | K8: 0.056 | L8: =K8/SUM($K$7:$K$12) -> 0.21374046 | M8: =_xlfn.TEXTJOIN(" ",1,TEXT(L8,"(0.0%)"),J8) -> (21.4%) Relax & social occasions
A9: Tracking | B9: Relax & social occasions | C9: Kantar Orange | D9: =_xlfn.IFNA(VLOOKUP(C9,Table1[],2,FALSE),"") -> #FF5000 | E9: Makes an occasion more special | F9: Relax & social occasions | G9: =VLOOKUP(F9,$J$7:$M$12,4,0) -> (21.4%) Relax & social occasions | J9: Smooth + Intrinsics | K9: 0.06 | L9: =K9/SUM($K$7:$K$12) -> 0.22900763 | M9: =_xlfn.TEXTJOIN(" ",1,TEXT(L9,"(0.0%)"),J9) -> (22.9%) Smooth + Intrinsics
A10: Tracking | B10: Smooth + Intrinsics | C10: Kantar Teal | D10: =_xlfn.IFNA(VLOOKUP(C10,Table1[],2,FALSE),"") -> #00E5BA | E10: You like to savour | F10: Smooth + Intrinsics | G10: =VLOOKUP(F10,$J$7:$M$12,4,0) -> (22.9%) Smooth + Intrinsics | J10: Social commitment | K10: 0.037 | L10: =K10/SUM($K$7:$K$12) -> 0.14122137 | M10: =_xlfn.TEXTJOIN(" ",1,TEXT(L10,"(0.0%)"),J10) -> (14.1%) Social commitment
A11: Tracking | B11: Smooth + Intrinsics | C11: Kantar Teal | D11: =_xlfn.IFNA(VLOOKUP(C11,Table1[],2,FALSE),"") -> #00E5BA | E11: Goes well with food/ meals | F11: Smooth + Intrinsics | G11: =VLOOKUP(F11,$J$7:$M$12,4,0) -> (22.9%) Smooth + Intrinsics | J11: Sophisticated & balance | K11: 0.027 | L11: =K11/SUM($K$7:$K$12) -> 0.10305344 | M11: =_xlfn.TEXTJOIN(" ",1,TEXT(L11,"(0.0%)"),J11) -> (10.3%) Sophisticated & balance
A12: Tracking | B12: Smooth + Intrinsics | C12: Kantar Teal | D12: =_xlfn.IFNA(VLOOKUP(C12,Table1[],2,FALSE),"") -> #00E5BA | E12: Is more refreshing than others | F12: Smooth + Intrinsics | G12: =VLOOKUP(F12,$J$7:$M$12,4,0) -> (22.9%) Smooth + Intrinsics | J12: Traditions and national pride | K12: 0.035 | L12: =K12/SUM($K$7:$K$12) -> 0.13358779 | M12: =_xlfn.TEXTJOIN(" ",1,TEXT(L12,"(0.0%)"),J12) -> (13.4%) Traditions and national pride
A13: Tracking | B13: Smooth + Intrinsics | C13: Kantar Teal | D13: =_xlfn.IFNA(VLOOKUP(C13,Table1[],2,FALSE),"") -> #00E5BA | E13: Has a smooth taste | F13: Smooth + Intrinsics | G13: =VLOOKUP(F13,$J$7:$M$12,4,0) -> (22.9%) Smooth + Intrinsics
A14: Tracking | B14: Social commitment | C14: Kantar Blue | D14: =_xlfn.IFNA(VLOOKUP(C14,Table1[],2,FALSE),"") -> #0060FF | E14: Is made from natural ingredients | F14: Social commitment | G14: =VLOOKUP(F14,$J$7:$M$12,4,0) -> (14.1%) Social commitment
A15: Tracking | B15: Social commitment | C15: Kantar Blue | D15: =_xlfn.IFNA(VLOOKUP(C15,Table1[],2,FALSE),"") -> #0060FF | E15: It is open and honest about what it is made of | F15: Social commitment | G15: =VLOOKUP(F15,$J$7:$M$12,4,0) -> (14.1%) Social commitment
A16: Tracking | B16: Social commitment | C16: Kantar Blue | D16: =_xlfn.IFNA(VLOOKUP(C16,Table1[],2,FALSE),"") -> #0060FF | E16: It is a socially responsible brand | F16: Social commitment | G16: =VLOOKUP(F16,$J$7:$M$12,4,0) -> (14.1%) Social commitment
A17: Tracking | B17: Sophisticated & balance | C17: Kantar Yellow | D17: =_xlfn.IFNA(VLOOKUP(C17,Table1[],2,FALSE),"") -> #FEDB00 | E17: Represents a balanced lifestyle choice | F17: Sophisticated & balance | G17: =VLOOKUP(F17,$J$7:$M$12,4,0) -> (10.3%) Sophisticated & balance
A18: Tracking | B18: Sophisticated & balance | C18: Kantar Yellow | D18: =_xlfn.IFNA(VLOOKUP(C18,Table1[],2,FALSE),"") -> #FEDB00 | E18: Is sophisticated | F18: Sophisticated & balance | G18: =VLOOKUP(F18,$J$7:$M$12,4,0) -> (10.3%) Sophisticated & balance
A19: Tracking | B19: Traditions and national pride | C19: Kantar Red | D19: =_xlfn.IFNA(VLOOKUP(C19,Table1[],2,FALSE),"") -> #FA0028 | E19: Is a brand that represents our traditions and heritage | F19: Traditions and national pride | G19: =VLOOKUP(F19,$J$7:$M$12,4,0) -> (13.4%) Traditions and national pride
A20: Tracking | B20: Traditions and national pride | C20: Kantar Red | D20: =_xlfn.IFNA(VLOOKUP(C20,Table1[],2,FALSE),"") -> #FA0028 | E20: Represents my national pride | F20: Traditions and national pride | G20: =VLOOKUP(F20,$J$7:$M$12,4,0) -> (13.4%) Traditions and national pride
A21: Tracking | B21: Traditions and national pride | C21: Kantar Red | D21: =_xlfn.IFNA(VLOOKUP(C21,Table1[],2,FALSE),"") -> #FA0028 | E21: Is the beer that combines the best with mexican flavors | F21: Traditions and national pride | G21: =VLOOKUP(F21,$J$7:$M$12,4,0) -> (13.4%) Traditions and national pride
A22: Path | B22: Brewed with care | C22: Kantar Light Grey | D22: =_xlfn.IFNA(VLOOKUP(C22,Table1[],2,FALSE),"") -> #D9D9D9 | E22: Is brewed with care | G22: Brewed with care (11.2%)
A23: Path | B23: High quality brand | C23: Kantar Light Grey | D23: =_xlfn.IFNA(VLOOKUP(C23,Table1[],2,FALSE),"") -> #D9D9D9 | E23: Is a high quality brand | G23: High quality brand (0.0%)
A24: Path | B24: Refreshing and relaxing meals | C24: Kantar Sand | D24: =_xlfn.IFNA(VLOOKUP(C24,Table1[],2,FALSE),"") -> #AEAE9F | E24: Goes well with food/ meals | G24: Refreshing and relaxing meals (15.2%)
A25: Path | B25: Refreshing and relaxing meals | C25: Kantar Sand | D25: =_xlfn.IFNA(VLOOKUP(C25,Table1[],2,FALSE),"") -> #AEAE9F | E25: Is more refreshing than others | G25: Refreshing and relaxing meals (15.2%)
A26: Path | B26: Indulgent escape with friends | C26: Kantar Orange | D26: =_xlfn.IFNA(VLOOKUP(C26,Table1[],2,FALSE),"") -> #FF5000 | E26: You like to share with your friends | G26: Indulgent scape with friends (23.3%)
A27: Path | B27: Indulgent escape with friends | C27: Kantar Orange | D27: =_xlfn.IFNA(VLOOKUP(C27,Table1[],2,FALSE),"") -> #FF5000 | E27: Adds energy to your social occasion | G27: Indulgent scape with friends (23.3%)
A28: Path | B28: Indulgent escape with friends | C28: Kantar Orange | D28: =_xlfn.IFNA(VLOOKUP(C28,Table1[],2,FALSE),"") -> #FF5000 | E28: You like to savour | G28: Indulgent scape with friends (23.3%)
A29: Path | B29: Refreshing and relaxing meals | C29: Kantar Sand | D29: =_xlfn.IFNA(VLOOKUP(C29,Table1[],2,FALSE),"") -> #AEAE9F | E29: Is good to drink when you want to relax | G29: Refreshing and relaxing meals (15.2%)
A30: Path | B30: Smooth taste | C30: Kantar Teal | D30: =_xlfn.IFNA(VLOOKUP(C30,Table1[],2,FALSE),"") -> #00E5BA | E30: Has a smooth taste | G30: Smooth taste (4.6%)
A31: Path | B31: Social commitment | C31: Kantar Blue | D31: =_xlfn.IFNA(VLOOKUP(C31,Table1[],2,FALSE),"") -> #0060FF | E31: Is made from natural ingredients | G31: Social commitment (9.0%)
A32: Path | B32: Social commitment | C32: Kantar Blue | D32: =_xlfn.IFNA(VLOOKUP(C32,Table1[],2,FALSE),"") -> #0060FF | E32: It is open and honest about what it is made of | G32: Social commitment (9.0%)
A33: Path | B33: Social commitment | C33: Kantar Blue | D33: =_xlfn.IFNA(VLOOKUP(C33,Table1[],2,FALSE),"") -> #0060FF | E33: It is a socially responsible brand | G33: Social commitment (9.0%)
... A41: Path | B41: Traditions and national pride | C41: Kantar Red | D41: =_xlfn.IFNA(VLOOKUP(C41,Table1[],2,FALSE),"") -> #FA0028 | E41: Is the beer that combines the best with mexican flavors | G41: Traditions and national pride (15.1%)

Sheet Pacifico ACT vs Client
A1: FactorType | B1: FactorName | C1: NodeColor | D1: =VLOOKUP(C1,CATA!A:B,2,FALSE) -> HexColor | E1: Attribute | H1: Path = Right
A2: Path | B2: =VLOOKUP(F2,$J$5:$M$12,3,0) -> Easy to find (4.3%) | C2: Kantar Sand | D2: =_xlfn.IFNA(VLOOKUP(C2,Table1[],2,FALSE),"") -> #AEAE9F | E2: It was easy to find | F2: Easy to find | H2: Tracking = Left
A3: Path | B3: =VLOOKUP(F3,$J$5:$M$12,3,0) -> Pack availability (21.0%) | C3: Kantar Green | D3: =_xlfn.IFNA(VLOOKUP(C3,Table1[],2,FALSE),"") -> #00B600 | E3: It came in the pack size I wanted and others didn't | F3: Pack availability
A4: Path | B4: =VLOOKUP(F4,$J$5:$M$12,3,0) -> Pack availability (21.0%) | C4: Kantar Green | D4: =_xlfn.IFNA(VLOOKUP(C4,Table1[],2,FALSE),"") -> #00B600 | E4: It came in the presentation that I was looking for | F4: Pack availability
A5: Path | B5: =VLOOKUP(F5,$J$5:$M$12,3,0) -> POS Awareness (7.6%) | C5: Kantar Orange | D5: =_xlfn.IFNA(VLOOKUP(C5,Table1[],2,FALSE),"") -> #FF5000 | E5: It had promotional material displayed | F5: POS Awareness | J5: Easy to find | K5: 0.043456016 | L5: =_xlfn.TEXTJOIN(" ",1,J5,TEXT(K5,"(0.0%)")) -> Easy to find (4.3%)
A6: Path | B6: =VLOOKUP(F6,$J$5:$M$12,3,0) -> POS Awareness (7.6%) | C6: Kantar Orange | D6: =_xlfn.IFNA(VLOOKUP(C6,Table1[],2,FALSE),"") -> #FF5000 | E6: It was featured or listed on a menu | F6: POS Awareness | J6: POS Awareness | K6: 0.076110463 | L6: =_xlfn.TEXTJOIN(" ",1,J6,TEXT(K6,"(0.0%)")) -> POS Awareness (7.6%)
A7: Path | B7: =VLOOKUP(F7,$J$5:$M$12,3,0) -> POS Awareness (7.6%) | C7: Kantar Orange | D7: =_xlfn.IFNA(VLOOKUP(C7,Table1[],2,FALSE),"") -> #FF5000 | E7: It was in a different section of the store than usual | F7: POS Awareness | J7: Price perception | K7: 0.14054703 | L7: =_xlfn.TEXTJOIN(" ",1,J7,TEXT(K7,"(0.0%)")) -> Price perception (14.1%)
A8: Path | B8: =VLOOKUP(F8,$J$5:$M$12,3,0) -> Price perception (14.1%) | C8: Kantar Yellow | D8: =_xlfn.IFNA(VLOOKUP(C8,Table1[],2,FALSE),"") -> #FEDB00 | E8: It was at a good price | F8: Price perception | J8: Recommended | K8: 0.086959794 | L8: =_xlfn.TEXTJOIN(" ",1,J8,TEXT(K8,"(0.0%)")) -> Recommended (8.7%)
A9: Path | B9: =VLOOKUP(F9,$J$5:$M$12,3,0) -> Recommended (8.7%) | C9: Kantar Purple | D9: =_xlfn.IFNA(VLOOKUP(C9,Table1[],2,FALSE),"") -> #802AB7 | E9: It was recommended to me | F9: Recommended | J9: Refrigerated | K9: 0.2846651 | L9: =_xlfn.TEXTJOIN(" ",1,J9,TEXT(K9,"(0.0%)")) -> Refrigerated (28.5%)
A10: Path | B10: =VLOOKUP(F10,$J$5:$M$12,3,0) -> Refrigerated (28.5%) | C10: Kantar Teal | D10: =_xlfn.IFNA(VLOOKUP(C10,Table1[],2,FALSE),"") -> #00E5BA | E10: It was refrigerated | F10: Refrigerated | J10: Special activations | K10: 0.098667558 | L10: =_xlfn.TEXTJOIN(" ",1,J10,TEXT(K10,"(0.0%)")) -> Special activations (9.9%)
A11: Path | B11: =VLOOKUP(F11,$J$5:$M$12,3,0) -> Special activations (9.9%) | C11: Kantar Red | D11: =_xlfn.IFNA(VLOOKUP(C11,Table1[],2,FALSE),"") -> #FA0028 | E11: It included a gift or free sample | F11: Special activations | J11: Where I go | K11: 0.060008709 | L11: =_xlfn.TEXTJOIN(" ",1,J11,TEXT(K11,"(0.0%)")) -> Where I go (6.0%)
A12: Path | B12: =VLOOKUP(F12,$J$5:$M$12,3,0) -> Special activations (9.9%) | C12: Kantar Red | D12: =_xlfn.IFNA(VLOOKUP(C12,Table1[],2,FALSE),"") -> #FA0028 | E12: It was a new product | F12: Special activations | J12: Pack availability | K12: 0.20958533 | L12: =_xlfn.TEXTJOIN(" ",1,J12,TEXT(K12,"(0.0%)")) -> Pack availability (21.0%)
A13: Path | B13: =VLOOKUP(F13,$J$5:$M$12,3,0) -> Special activations (9.9%) | C13: Kantar Red | D13: =_xlfn.IFNA(VLOOKUP(C13,Table1[],2,FALSE),"") -> #FA0028 | E13: It was on sale, special, or promotion | F13: Special activations
A14: Path | B14: =VLOOKUP(F14,$J$5:$M$12,3,0) -> Special activations (9.9%) | C14: Kantar Red | D14: =_xlfn.IFNA(VLOOKUP(C14,Table1[],2,FALSE),"") -> #FA0028 | E14: Other brand (s) I usually buy were not available | F14: Special activations
A15: Path | B15: =VLOOKUP(F15,$J$5:$M$12,3,0) -> Special activations (9.9%) | C15: Kantar Red | D15: =_xlfn.IFNA(VLOOKUP(C15,Table1[],2,FALSE),"") -> #FA0028 | E15: Sponsors the sportsteam, festival, events that I like | F15: Special activations
A16: Path | B16: =VLOOKUP(F16,$J$5:$M$12,3,0) -> Where I go (6.0%) | C16: Kantar Blue | D16: =_xlfn.IFNA(VLOOKUP(C16,Table1[],2,FALSE),"") -> #0060FF | E16: It was easily available at the places I go to | F16: Where I go
A17: Tracking | B17: =VLOOKUP(F17,$J$17:$M$24,3,0) -> (49.7%) Others | C17: Kantar Light Grey | D17: =_xlfn.IFNA(VLOOKUP(C17,Table1[],2,FALSE),"") -> #D9D9D9 | E17: It had promotional material displayed | F17: Others | J17: Others | K17: 0.49667753 | L17: =_xlfn.TEXTJOIN(" ",1,TEXT(K17,"(0.0%)"),J17) -> (49.7%) Others
A18: Tracking | B18: =VLOOKUP(F18,$J$17:$M$24,3,0) -> (49.7%) Others | C18: Kantar Light Grey | D18: =_xlfn.IFNA(VLOOKUP(C18,Table1[],2,FALSE),"") -> #D9D9D9 | E18: It included a gift or free sample | F18: Others | J18: Pack availability | K18: 0.20958533 | L18: =_xlfn.TEXTJOIN(" ",1,TEXT(K18,"(0.0%)"),J18) -> (21.0%) Pack availability
A19: Tracking | B19: =VLOOKUP(F19,$J$17:$M$24,3,0) -> (49.7%) Others | C19: Kantar Light Grey | D19: =_xlfn.IFNA(VLOOKUP(C19,Table1[],2,FALSE),"") -> #D9D9D9 | E19: It was a new product | F19: Others | J19: Price perception | K19: 0.14054703 | L19: =_xlfn.TEXTJOIN(" ",1,TEXT(K19,"(0.0%)"),J19) -> (14.1%) Price perception
A20: Tracking | B20: =VLOOKUP(F20,$J$17:$M$24,3,0) -> (49.7%) Others | C20: Kantar Light Grey | D20: =_xlfn.IFNA(VLOOKUP(C20,Table1[],2,FALSE),"") -> #D9D9D9 | E20: It was on sale, special, or promotion | F20: Others | J20: Trade visibility | K20: 0.15319011 | L20: =_xlfn.TEXTJOIN(" ",1,TEXT(K20,"(0.0%)"),J20) -> (15.3%) Trade visibility
A21: Tracking | B21: =VLOOKUP(F21,$J$17:$M$24,3,0) -> (49.7%) Others | C21: Kantar Light Grey | D21: =_xlfn.IFNA(VLOOKUP(C21,Table1[],2,FALSE),"") -> #D9D9D9 | E21: It was recommended to me | F21: Others
A22: Tracking | B22: =VLOOKUP(F22,$J$17:$M$24,3,0) -> (49.7%) Others | C22: Kantar Light Grey | D22: =_xlfn.IFNA(VLOOKUP(C22,Table1[],2,FALSE),"") -> #D9D9D9 | E22: It was refrigerated | F22: Others
A23: Tracking | B23: =VLOOKUP(F23,$J$17:$M$24,3,0) -> (49.7%) Others | C23: Kantar Light Grey | D23: =_xlfn.IFNA(VLOOKUP(C23,Table1[],2,FALSE),"") -> #D9D9D9 | E23: Other brand (s) I usually buy were not available | F23: Others
A24: Tracking | B24: =VLOOKUP(F24,$J$17:$M$24,3,0) -> (49.7%) Others | C24: Kantar Light Grey | D24: =_xlfn.IFNA(VLOOKUP(C24,Table1[],2,FALSE),"") -> #D9D9D9 | E24: Sponsors the sportsteam, festival, events that I like | F24: Others
A25: Tracking | B25: =VLOOKUP(F25,$J$17:$M$24,3,0) -> (21.0%) Pack availability | C25: Kantar Green | D25: =_xlfn.IFNA(VLOOKUP(C25,Table1[],2,FALSE),"") -> #00B600 | E25: It came in the pack size I wanted and others didn't | F25: Pack availability
A26: Tracking | B26: =VLOOKUP(F26,$J$17:$M$24,3,0) -> (21.0%) Pack availability | C26: Kantar Green | D26: =_xlfn.IFNA(VLOOKUP(C26,Table1[],2,FALSE),"") -> #00B600 | E26: It came in the presentation that I was looking for | F26: Pack availability
A27: Tracking | B27: =VLOOKUP(F27,$J$17:$M$24,3,0) -> (14.1%) Price perception | C27: Kantar Yellow | D27: =_xlfn.IFNA(VLOOKUP(C27,Table1[],2,FALSE),"") -> #FEDB00 | E27: It was at a good price | F27: Price perception
A28: Tracking | B28: =VLOOKUP(F28,$J$17:$M$24,3,0) -> (15.3%) Trade visibility | C28: Kantar Blue | D28: =_xlfn.IFNA(VLOOKUP(C28,Table1[],2,FALSE),"") -> #0060FF | E28: It was easily available at the places I go to | F28: Trade visibility
A29: Tracking | B29: =VLOOKUP(F29,$J$17:$M$24,3,0) -> (15.3%) Trade visibility | C29: Kantar Blue | D29: =_xlfn.IFNA(VLOOKUP(C29,Table1[],2,FALSE),"") -> #0060FF | E29: It was easy to find | F29: Trade visibility
A30: Tracking | B30: =VLOOKUP(F30,$J$17:$M$24,3,0) -> (15.3%) Trade visibility | C30: Kantar Blue | D30: =_xlfn.IFNA(VLOOKUP(C30,Table1[],2,FALSE),"") -> #0060FF | E30: It was featured or listed on a menu | F30: Trade visibility
A31: Tracking | B31: =VLOOKUP(F31,$J$17:$M$24,3,0) -> (15.3%) Trade visibility | C31: Kantar Blue | D31: =_xlfn.IFNA(VLOOKUP(C31,Table1[],2,FALSE),"") -> #0060FF | E31: It was in a different section of the store than usual | F31: Trade visibility

Sheet Pacifico POS vs Client
A1: FactorType | B1: FactorName | C1: NodeColor | D1: HexColor | E1: Attribute
A2: Path | B2: =VLOOKUP(F2,$J$4:$M$12,3,0) -> Beverage Focused (29.1%) | C2: Kantar Blue | D2: =_xlfn.IFNA(VLOOKUP(C2,Table1[],2,FALSE),"") -> #0060FF | E2: Bar | F2: Beverage Focused
A3: Path | B3: =VLOOKUP(F3,$J$4:$M$12,3,0) -> Beverage Focused (29.1%) | C3: Kantar Blue | D3: =_xlfn.IFNA(VLOOKUP(C3,Table1[],2,FALSE),"") -> #0060FF | E3: Discotheque | F3: Beverage Focused
A4: Path | B4: =VLOOKUP(F4,$J$4:$M$12,3,0) -> Beverage Focused (29.1%) | C4: Kantar Blue | D4: =_xlfn.IFNA(VLOOKUP(C4,Table1[],2,FALSE),"") -> #0060FF | E4: Restaurant | F4: Beverage Focused | J4: Beverage Focused | K4: 0.29096941 | L4: =_xlfn.TEXTJOIN(" ",1,J4,TEXT(K4,"(0.0%)")) -> Beverage Focused (29.1%)
A5: Path | B5: =VLOOKUP(F5,$J$4:$M$12,3,0) -> Neighbourhood stores (30.2%) | C5: Kantar Orange | D5: =_xlfn.IFNA(VLOOKUP(C5,Table1[],2,FALSE),"") -> #FF5000 | E5: Convenience | F5: Neighbourhood stores | J5: Neighbourhood stores | K5: 0.30188628 | L5: =_xlfn.TEXTJOIN(" ",1,J5,TEXT(K5,"(0.0%)")) -> Neighbourhood stores (30.2%)
A6: Path | B6: =VLOOKUP(F6,$J$4:$M$12,3,0) -> Neighbourhood stores (30.2%) | C6: Kantar Orange | D6: =_xlfn.IFNA(VLOOKUP(C6,Table1[],2,FALSE),"") -> #FF5000 | E6: Modelorama or Tecate Six | F6: Neighbourhood stores | J6: Retailer | K6: 0.40714431 | L6: =_xlfn.TEXTJOIN(" ",1,J6,TEXT(K6,"(0.0%)")) -> Retailer (40.7%)
A7: Path | B7: =VLOOKUP(F7,$J$4:$M$12,3,0) -> Neighbourhood stores (30.2%) | C7: Kantar Orange | D7: =_xlfn.IFNA(VLOOKUP(C7,Table1[],2,FALSE),"") -> #FF5000 | E7: Mom & pop store | F7: Neighbourhood stores
A8: Path | B8: =VLOOKUP(F8,$J$4:$M$12,3,0) -> Retailer (40.7%) | C8: Kantar Green | D8: =_xlfn.IFNA(VLOOKUP(C8,Table1[],2,FALSE),"") -> #00B600 | E8: Online | F8: Retailer
A9: Path | B9: =VLOOKUP(F9,$J$4:$M$12,3,0) -> Retailer (40.7%) | C9: Kantar Green | D9: =_xlfn.IFNA(VLOOKUP(C9,Table1[],2,FALSE),"") -> #00B600 | E9: Supermarket | F9: Retailer | J9: Modern | K9: 0.34371204 | L9: =_xlfn.TEXTJOIN(" ",1,TEXT(K9,"(0.0%)"),J9) -> (34.4%) Modern
A10: Path | B10: =VLOOKUP(F10,$J$4:$M$12,3,0) -> Retailer (40.7%) | C10: Kantar Green | D10: =_xlfn.IFNA(VLOOKUP(C10,Table1[],2,FALSE),"") -> #00B600 | E10: Warehouse shop | F10: Retailer | J10: On premise | K10: 0.30062062 | L10: =_xlfn.TEXTJOIN(" ",1,TEXT(K10,"(0.0%)"),J10) -> (30.1%) On premise
A11: Tracking | B11: =VLOOKUP(F11,$J$4:$M$12,3,0) -> (34.4%) Modern | C11: Kantar Yellow | D11: =_xlfn.IFNA(VLOOKUP(C11,Table1[],2,FALSE),"") -> #FEDB00 | E11: Convenience | F11: Modern | J11: TT Off premise | K11: 0.25125647 | L11: =_xlfn.TEXTJOIN(" ",1,TEXT(K11,"(0.0%)"),J11) -> (25.1%) TT Off premise
A12: Tracking | B12: =VLOOKUP(F12,$J$4:$M$12,3,0) -> (10.4%) Modelorama or Tecate Six | C12: Kantar Yellow | D12: =_xlfn.IFNA(VLOOKUP(C12,Table1[],2,FALSE),"") -> #FEDB00 | E12: Modelorama or Tecate Six | F12: Modelorama or Tecate Six | J12: Modelorama or Tecate Six | K12: 0.10441087 | L12: =_xlfn.TEXTJOIN(" ",1,TEXT(K12,"(0.0%)"),J12) -> (10.4%) Modelorama or Tecate Six
A13: Tracking | B13: =VLOOKUP(F13,$J$4:$M$12,3,0) -> (34.4%) Modern | C13: Kantar Yellow | D13: =_xlfn.IFNA(VLOOKUP(C13,Table1[],2,FALSE),"") -> #FEDB00 | E13: Supermarket | F13: Modern
A14: Tracking | B14: =VLOOKUP(F14,$J$4:$M$12,3,0) -> (30.1%) On premise | C14: Kantar Blue | D14: =_xlfn.IFNA(VLOOKUP(C14,Table1[],2,FALSE),"") -> #0060FF | E14: Bar | F14: On premise
A15: Tracking | B15: =VLOOKUP(F15,$J$4:$M$12,3,0) -> (30.1%) On premise | C15: Kantar Blue | D15: =_xlfn.IFNA(VLOOKUP(C15,Table1[],2,FALSE),"") -> #0060FF | E15: Discotheque | F15: On premise
A16: Tracking | B16: =VLOOKUP(F16,$J$4:$M$12,3,0) -> (30.1%) On premise | C16: Kantar Blue | D16: =_xlfn.IFNA(VLOOKUP(C16,Table1[],2,FALSE),"") -> #0060FF | E16: Online | F16: On premise
A17: Tracking | B17: =VLOOKUP(F17,$J$4:$M$12,3,0) -> (30.1%) On premise | C17: Kantar Blue | D17: =_xlfn.IFNA(VLOOKUP(C17,Table1[],2,FALSE),"") -> #0060FF | E17: Restaurant | F17: On premise
A18: Tracking | B18: =VLOOKUP(F18,$J$4:$M$12,3,0) -> (25.1%) TT Off premise | C18: Kantar Magenta | D18: =_xlfn.IFNA(VLOOKUP(C18,Table1[],2,FALSE),"") -> #C700D3 | E18: Mom & pop store | F18: TT Off premise
A19: Tracking | B19: =VLOOKUP(F19,$J$4:$M$12,3,0) -> (25.1%) TT Off premise | C19: Kantar Magenta | D19: =_xlfn.IFNA(VLOOKUP(C19,Table1[],2,FALSE),"") -> #C700D3 | E19: Warehouse shop | F19: TT Off premise

Sheet Pacifico OCC vs Client
A1: FactorType | B1: FactorName | C1: NodeColor | D1: =VLOOKUP(C1,CATA!A:B,2,FALSE) -> HexColor | E1: Attribute | H1: Path = Right
A2: Path | B2: =VLOOKUP(F2,$J$4:$M$23,3,0) -> Celebrating (3.0%) | C2: Kantar Yellow | D2: =_xlfn.IFNA(VLOOKUP(C2,Table1[],2,FALSE),"") -> #FEDB00 | E2: Attending a party or special celebration outside of home | F2: Celebrating | H2: Tracking = Left
A3: Path | B3: =VLOOKUP(F3,$J$4:$M$23,3,0) -> Eating out with friends (8.6%) | C3: Kantar Teal | D3: =_xlfn.IFNA(VLOOKUP(C3,Table1[],2,FALSE),"") -> #00E5BA | E3: Eating a meal or a snack outside of home | F3: Eating out with friends
A4: Path | B4: =VLOOKUP(F4,$J$4:$M$23,3,0) -> Eating out with friends (8.6%) | C4: Kantar Teal | D4: =_xlfn.IFNA(VLOOKUP(C4,Table1[],2,FALSE),"") -> #00E5BA | E4: Socializing with mix of male and female friends/ family out of home | F4: Eating out with friends | J4: Celebrating | K4: 0.029749865 | L4: =_xlfn.TEXTJOIN(" ",1,J4,TEXT(K4,"(0.0%)")) -> Celebrating (3.0%)
A5: Path | B5: =VLOOKUP(F5,$J$4:$M$23,3,0) -> Everyday activities (22.2%) | C5: Kantar Magenta | D5: =_xlfn.IFNA(VLOOKUP(C5,Table1[],2,FALSE),"") -> #C700D3 | E5: Doing everyday activities like chores/ cooking/ studying | F5: Everyday activities | J5: Eating out with friends | K5: 0.085629698 | L5: =_xlfn.TEXTJOIN(" ",1,J5,TEXT(K5,"(0.0%)")) -> Eating out with friends (8.6%)
A6: Path | B6: =VLOOKUP(F6,$J$4:$M$23,3,0) -> Food at home (10.2%) | C6: Kantar Orange | D6: =_xlfn.IFNA(VLOOKUP(C6,Table1[],2,FALSE),"") -> #FF5000 | E6: Evening or pre-dinner drink before meal | F6: Food at home | J6: Everyday activities | K6: 0.22160211 | L6: =_xlfn.TEXTJOIN(" ",1,J6,TEXT(K6,"(0.0%)")) -> Everyday activities (22.2%)
A7: Path | B7: =VLOOKUP(F7,$J$4:$M$23,3,0) -> Food at home (10.2%) | C7: Kantar Orange | D7: =_xlfn.IFNA(VLOOKUP(C7,Table1[],2,FALSE),"") -> #FF5000 | E7: Meal or snack at home | F7: Food at home | J7: Food at home | K7: 0.10150648 | L7: =_xlfn.TEXTJOIN(" ",1,J7,TEXT(K7,"(0.0%)")) -> Food at home (10.2%)
A8: Path | B8: =VLOOKUP(F8,$J$4:$M$23,3,0) -> Men's socialization OOH (5.4%) | C8: Kantar Blue | D8: =_xlfn.IFNA(VLOOKUP(C8,Table1[],2,FALSE),"") -> #0060FF | E8: Socializing with male friends/ family out of home | F8: Men's socialization OOH | J8: Men's socialization OOH | K8: 0.054195052 | L8: =_xlfn.TEXTJOIN(" ",1,J8,TEXT(K8,"(0.0%)")) -> Men's socialization OOH (5.4%)
A9: Path | B9: =VLOOKUP(F9,$J$4:$M$23,3,0) -> Relaxing / Unwind (26.7%) | C9: Kantar Purple | D9: =_xlfn.IFNA(VLOOKUP(C9,Table1[],2,FALSE),"") -> #802AB7 | E9: Relaxing/ unwinding alone | F9: Relaxing / Unwind | J9: Relaxing / Unwind | K9: 0.26651528 | L9: =_xlfn.TEXTJOIN(" ",1,J9,TEXT(K9,"(0.0%)")) -> Relaxing / Unwind (26.7%)
A10: Path | B10: =VLOOKUP(F10,$J$4:$M$23,3,0) -> Relaxing / Unwind (26.7%) | C10: Kantar Purple | D10: =_xlfn.IFNA(VLOOKUP(C10,Table1[],2,FALSE),"") -> #802AB7 | E10: Relaxing/ unwinding with others | F10: Relaxing / Unwind | J10: Socializing at home | K10: 0.24080152 | L10: =_xlfn.TEXTJOIN(" ",1,J10,TEXT(K10,"(0.0%)")) -> Socializing at home (24.1%)
A11: Path | B11: =VLOOKUP(F11,$J$4:$M$23,3,0) -> Socializing at home (24.1%) | C11: Kantar Green | D11: =_xlfn.IFNA(VLOOKUP(C11,Table1[],2,FALSE),"") -> #00B600 | E11: Party or special celebration at home | F11: Socializing at home
A12: Path | B12: =VLOOKUP(F12,$J$4:$M$23,3,0) -> Socializing at home (24.1%) | C12: Kantar Green | D12: =_xlfn.IFNA(VLOOKUP(C12,Table1[],2,FALSE),"") -> #00B600 | E12: Socializing with male friends/ family at home | F12: Socializing at home
A13: Path | B13: =VLOOKUP(F13,$J$4:$M$23,3,0) -> Socializing at home (24.1%) | C13: Kantar Green | D13: =_xlfn.IFNA(VLOOKUP(C13,Table1[],2,FALSE),"") -> #00B600 | E13: Socializing with mix of male and female friends/ family at home | F13: Socializing at home
A14: Tracking | B14: =VLOOKUP(F14,$J$4:$M$23,3,0) -> (26.0%) Living | C14: Kantar Teal | D14: =_xlfn.IFNA(VLOOKUP(C14,Table1[],2,FALSE),"") -> #00E5BA | E14: Doing everyday activities like chores/ cooking/ studying | F14: Living
A15: Tracking | B15: =VLOOKUP(F15,$J$4:$M$23,3,0) -> (26.0%) Living | C15: Kantar Teal | D15: =_xlfn.IFNA(VLOOKUP(C15,Table1[],2,FALSE),"") -> #00E5BA | E15: Evening or pre-dinner drink before meal | F15: Living
A16: Tracking | B16: =VLOOKUP(F16,$J$4:$M$23,3,0) -> (10.1%) Meal | C16: Kantar Orange | D16: =_xlfn.IFNA(VLOOKUP(C16,Table1[],2,FALSE),"") -> #FF5000 | E16: Eating a meal or a snack outside of home | F16: Meal | J16: Living | K16: 0.25956725 | L16: =_xlfn.TEXTJOIN(" ",1,TEXT(K16,"(0.0%)"),J16) -> (26.0%) Living
A17: Tracking | B17: =VLOOKUP(F17,$J$4:$M$23,3,0) -> (10.1%) Meal | C17: Kantar Orange | D17: =_xlfn.IFNA(VLOOKUP(C17,Table1[],2,FALSE),"") -> #FF5000 | E17: Meal or snack at home | F17: Meal | J17: Meal | K17: 0.10075699 | L17: =_xlfn.TEXTJOIN(" ",1,TEXT(K17,"(0.0%)"),J17) -> (10.1%) Meal
A18: Tracking | B18: =VLOOKUP(F18,$J$4:$M$23,3,0) -> (12.1%) Party | C18: Kantar Yellow | D18: =_xlfn.IFNA(VLOOKUP(C18,Table1[],2,FALSE),"") -> #FEDB00 | E18: Attending a party or special celebration outside of home | F18: Party | J18: Party | K18: 0.12133991 | L18: =_xlfn.TEXTJOIN(" ",1,TEXT(K18,"(0.0%)"),J18) -> (12.1%) Party
A19: Tracking | B19: =VLOOKUP(F19,$J$4:$M$23,3,0) -> (12.1%) Party | C19: Kantar Yellow | D19: =_xlfn.IFNA(VLOOKUP(C19,Table1[],2,FALSE),"") -> #FEDB00 | E19: Party or special celebration at home | F19: Party | J19: Relax alone | K19: 0.14854519 | L19: =_xlfn.TEXTJOIN(" ",1,TEXT(K19,"(0.0%)"),J19) -> (14.9%) Relax alone
A20: Tracking | B20: =VLOOKUP(F20,$J$4:$M$23,3,0) -> (14.9%) Relax alone | C20: Kantar Magenta | D20: =_xlfn.IFNA(VLOOKUP(C20,Table1[],2,FALSE),"") -> #C700D3 | E20: Relaxing/ unwinding alone | F20: Relax alone | J20: Relax family | K20: 0.11797009 | L20: =_xlfn.TEXTJOIN(" ",1,TEXT(K20,"(0.0%)"),J20) -> (11.8%) Relax family
A21: Tracking | B21: =VLOOKUP(F21,$J$4:$M$23,3,0) -> (11.8%) Relax family | C21: Kantar Purple | D21: =_xlfn.IFNA(VLOOKUP(C21,Table1[],2,FALSE),"") -> #802AB7 | E21: Relaxing/ unwinding with others | F21: Relax family | J21: Social mixed gender | K21: 0.12129837 | L21: =_xlfn.TEXTJOIN(" ",1,TEXT(K21,"(0.0%)"),J21) -> (12.1%) Social mixed gender
A22: Tracking | B22: =VLOOKUP(F22,$J$4:$M$23,3,0) -> (12.1%) Social mixed gender | C22: Kantar Green | D22: =_xlfn.IFNA(VLOOKUP(C22,Table1[],2,FALSE),"") -> #00B600 | E22: Socializing with mix of male and female friends/ family at home | F22: Social mixed gender | J22: Social same gender | K22: 0.13052219 | L22: =_xlfn.TEXTJOIN(" ",1,TEXT(K22,"(0.0%)"),J22) -> (13.1%) Social same gender
A23: Tracking | B23: =VLOOKUP(F23,$J$4:$M$23,3,0) -> (12.1%) Social mixed gender | C23: Kantar Green | D23: =_xlfn.IFNA(VLOOKUP(C23,Table1[],2,FALSE),"") -> #00B600 | E23: Socializing with mix of male and female friends/ family out of home | F23: Social mixed gender
A24: Tracking | B24: =VLOOKUP(F24,$J$4:$M$23,3,0) -> (13.1%) Social same gender | C24: Kantar Blue | D24: =_xlfn.IFNA(VLOOKUP(C24,Table1[],2,FALSE),"") -> #0060FF | E24: Socializing with male friends/ family at home | F24: Social same gender
A25: Tracking | B25: =VLOOKUP(F25,$J$4:$M$23,3,0) -> (13.1%) Social same gender | C25: Kantar Blue | D25: =_xlfn.IFNA(VLOOKUP(C25,Table1[],2,FALSE),"") -> #0060FF | E25: Socializing with male friends/ family out of home | F25: Social same gender

Sheet Sheet1
B2: Group | C2: Pacifico Factors Labels | D2: Attribute Labels | E2: Sum of Imp to Power Att | F2: Factores | G2: Grupo | H2: Factores Normalizados | I2: Labels | J2: Att Label
B3: ACT | C3: Refrigerated | D3: It was refrigerated | E3: 0.017883828 | F3: =SUMIFS($E$3:$E$68,$C$3:$C$68,C3) -> 0.017883828 | G3: =SUMIFS($E$3:$E$68,$B$3:$B$68,B3) -> 0.062824097 | H3: =F3/G3 -> 0.2846651 | I3: =_xlfn.TEXTJOIN(" ",TRUE,C3,TEXT(H3,"(0.0%)")) -> Refrigerated (28.5%) | J3: It was refrigerated
B4: ACT | C4: Pack availability | D4: It came in the presentation that I was looking for | E4: 0.006610442 | F4: =SUMIFS($E$3:$E$68,$C$3:$C$68,C4) -> 0.013167009 | G4: =SUMIFS($E$3:$E$68,$B$3:$B$68,B4) -> 0.062824097 | H4: =F4/G4 -> 0.20958533 | I4: =_xlfn.TEXTJOIN(" ",TRUE,C4,TEXT(H4,"(0.0%)")) -> Pack availability (21.0%) | J4: It came in the presentation that I was looking for
B5: ACT | C5: Pack availability | D5: It came in the pack size I wanted and others didn't | E5: 0.0065565671 | F5: =SUMIFS($E$3:$E$68,$C$3:$C$68,C5) -> 0.013167009 | G5: =SUMIFS($E$3:$E$68,$B$3:$B$68,B5) -> 0.062824097 | H5: =F5/G5 -> 0.20958533 | I5: =_xlfn.TEXTJOIN(" ",TRUE,C5,TEXT(H5,"(0.0%)")) -> Pack availability (21.0%) | J5: It came in the pack size I wanted and others didn't
B6: ACT | C6: Price perception | D6: It was at a good price | E6: 0.0088297402 | F6: =SUMIFS($E$3:$E$68,$C$3:$C$68,C6) -> 0.0088297402 | G6: =SUMIFS($E$3:$E$68,$B$3:$B$68,B6) -> 0.062824097 | H6: =F6/G6 -> 0.14054703 | I6: =_xlfn.TEXTJOIN(" ",TRUE,C6,TEXT(H6,"(0.0%)")) -> Price perception (14.1%) | J6: It was at a good price
B7: ACT | C7: Special activations | D7: Sponsors the sportsteam, festival, events that I like | E7: 0.0013953227 | F7: =SUMIFS($E$3:$E$68,$C$3:$C$68,C7) -> 0.0061987002 | G7: =SUMIFS($E$3:$E$68,$B$3:$B$68,B7) -> 0.062824097 | H7: =F7/G7 -> 0.098667558 | I7: =_xlfn.TEXTJOIN(" ",TRUE,C7,TEXT(H7,"(0.0%)")) -> Special activations (9.9%) | J7: Sponsors the sportsteam, festival, events that I like
B8: ACT | C8: Special activations | D8: It was a new product | E8: 0.0012600665 | F8: =SUMIFS($E$3:$E$68,$C$3:$C$68,C8) -> 0.0061987002 | G8: =SUMIFS($E$3:$E$68,$B$3:$B$68,B8) -> 0.062824097 | H8: =F8/G8 -> 0.098667558 | I8: =_xlfn.TEXTJOIN(" ",TRUE,C8,TEXT(H8,"(0.0%)")) -> Special activations (9.9%) | J8: It was a new product
B9: ACT | C9: Special activations | D9: It included a gift or free sample | E9: 0.0011999522 | F9: =SUMIFS($E$3:$E$68,$C$3:$C$68,C9) -> 0.0061987002 | G9: =SUMIFS($E$3:$E$68,$B$3:$B$68,B9) -> 0.062824097 | H9: =F9/G9 -> 0.098667558 | I9: =_xlfn.TEXTJOIN(" ",TRUE,C9,TEXT(H9,"(0.0%)")) -> Special activations (9.9%) | J9: It included a gift or free sample
B10: ACT | C10: Special activations | D10: It was on sale, special, or promotion | E10: 0.0011914448 | F10: =SUMIFS($E$3:$E$68,$C$3:$C$68,C10) -> 0.0061987002 | G10: =SUMIFS($E$3:$E$68,$B$3:$B$68,B10) -> 0.062824097 | H10: =F10/G10 -> 0.098667558 | I10: =_xlfn.TEXTJOIN(" ",TRUE,C10,TEXT(H10,"(0.0%)")) -> Special activations (9.9%) | J10: It was on sale, special, or promotion
B11: ACT | C11: Special activations | D11: Other brand (s) I usually buy were not available | E11: 0.001151914 | F11: =SUMIFS($E$3:$E$68,$C$3:$C$68,C11) -> 0.0061987002 | G11: =SUMIFS($E$3:$E$68,$B$3:$B$68,B11) -> 0.062824097 | H11: =F11/G11 -> 0.098667558 | I11: =_xlfn.TEXTJOIN(" ",TRUE,C11,TEXT(H11,"(0.0%)")) -> Special activations (9.9%) | J11: Other brand (s) I usually buy were not available
B12: ACT | C12: Recommended | D12: It was recommended to me | E12: 0.0054631706 | F12: =SUMIFS($E$3:$E$68,$C$3:$C$68,C12) -> 0.0054631706 | G12: =SUMIFS($E$3:$E$68,$B$3:$B$68,B12) -> 0.062824097 | H12: =F12/G12 -> 0.086959794 | I12: =_xlfn.TEXTJOIN(" ",TRUE,C12,TEXT(H12,"(0.0%)")) -> Recommended (8.7%) | J12: It was recommended to me
B13: ACT | C13: POS Awareness | D13: It was in a different section of the store than usual | E13: 0.0016676746 | F13: =SUMIFS($E$3:$E$68,$C$3:$C$68,C13) -> 0.0047815711 | G13: =SUMIFS($E$3:$E$68,$B$3:$B$68,B13) -> 0.062824097 | H13: =F13/G13 -> 0.076110463 | I13: =_xlfn.TEXTJOIN(" ",TRUE,C13,TEXT(H13,"(0.0%)")) -> POS Awareness (7.6%) | J13: It was in a different section of the store than usual
B14: ACT | C14: POS Awareness | D14: It had promotional material displayed | E14: 0.0016576187 | F14: =SUMIFS($E$3:$E$68,$C$3:$C$68,C14) -> 0.0047815711 | G14: =SUMIFS($E$3:$E$68,$B$3:$B$68,B14) -> 0.062824097 | H14: =F14/G14 -> 0.076110463 | I14: =_xlfn.TEXTJOIN(" ",TRUE,C14,TEXT(H14,"(0.0%)")) -> POS Awareness (7.6%) | J14: It had promotional material displayed
... B68: TBCA | C68: Open TV | D68: TV | E68: 9.0512587e-05 | F68: =SUMIFS($E$3:$E$68,$C$3:$C$68,C68) -> 9.0512587e-05 | G68: =SUMIFS($E$3:$E$68,$B$3:$B$68,B68) -> 0.0041894685 | H68: =F68/G68 -> 0.02160479 | I68: =_xlfn.TEXTJOIN(" ",TRUE,C68,TEXT(H68,"(0.0%)")) -> Open TV (2.2%) | J68: TV
