Workbook

Sheet AVP
A1: g | B1: Period | C1: Observed | D1: Estimated | E1: Base | F1: Residual | G1: APE | I1: Model Stat | L1: Year | M1: Observed | N1: Estimated | O1: RSQ | P1: Total RSQ
A2: FY_2022 | B2: 44440 | C2: 3309.968 | D2: 3378.9217 | E2: 2486.3069 | F2: =C2-D2 -> -68.953714 | G2: =ABS(F2/C2) -> 0.020832139 | I2: RSQ | J2: 0.9055 | L2: FY_2021 | M2: =SUMIFS($C:$C,$A:$A,$L2) -> 0 | N2: =SUMIFS($D:$D,$A:$A,$L2) -> 0 | O2: =RSQ(C2:C38,D2:D38) -> 0.90549327 | P2: =RSQ(C2:C38,D2:D38) -> 0.90549327
A3: FY_2022 | B3: 44470 | C3: 3028.298 | D3: 2934.4873 | E3: 2472.805 | F3: =C3-D3 -> 93.810709 | G3: =ABS(F3/C3) -> 0.030978031 | I3: Adj Rsq | J3: 0.8209 | L3: FY_2022 | M3: =SUMIFS($C:$C,$A:$A,$L3) -> 33769.537 | N3: =SUMIFS($D:$D,$A:$A,$L3) -> 33568.271 | O3: =RSQ(C2:C13,D2:D13) -> 0.76986394
A4: FY_2022 | B4: 44501 | C4: 2525.561 | D4: 2703.1043 | E4: 2469.04 | F4: =C4-D4 -> -177.54328 | G4: =ABS(F4/C4) -> 0.070298552 | I4: Mape | J4: 0.0686 | L4: FY_2023 | M4: =SUMIFS($C:$C,$A:$A,$L4) -> 31283.97 | N4: =SUMIFS($D:$D,$A:$A,$L4) -> 31650.006 | O4: =RSQ(C14:C25,D14:D25) -> 0.90487683
A5: FY_2022 | B5: 44531 | C5: 2741.46 | D5: 2294.8618 | E5: 2447.4368 | F5: =C5-D5 -> 446.59825 | G5: =ABS(F5/C5) -> 0.16290526 | I5: DW | J5: 2.54 | L5: FY_2024 | M5: =SUMIFS($C:$C,$A:$A,$L5) -> 33662.95 | N5: =SUMIFS($D:$D,$A:$A,$L5) -> 33524.998 | O5: =RSQ(C26:C37,D26:D37) -> 0.93509263
A6: FY_2022 | B6: 44562 | C6: 2120.791 | D6: 2313.7008 | E6: 2469.8363 | F6: =C6-D6 -> -192.9098 | G6: =ABS(F6/C6) -> 0.090961251 | L6: Due to 23 vs 22 (12 Months) | M6: =M4/M3-1 -> -0.073603822 | N6: =N4/N3-1 -> -0.057145199
A7: FY_2022 | B7: 44593 | C7: 2025.474 | D7: 2423.8705 | E7: 2473.4603 | F7: =C7-D7 -> -398.39648 | G7: =ABS(F7/C7) -> 0.19669296 | L7: Due to 24 vs 23 (12 Months) | M7: =M5/M4-1 -> 0.076044696 | N7: =N5/N4-1 -> 0.059241462
A8: FY_2022 | B8: 44621 | C8: 2782.846 | D8: 2418.5679 | E8: 2439.2559 | F8: =C8-D8 -> 364.27812 | G8: =ABS(F8/C8) -> 0.13090128
A9: FY_2022 | B9: 44652 | C9: 2487.264 | D9: 2525.0552 | E9: 2438.6478 | F9: =C9-D9 -> -37.791168 | G9: =ABS(F9/C9) -> 0.015193871
A10: FY_2022 | B10: 44682 | C10: 3227.268 | D10: 3213.8703 | E10: 2434.8381 | F10: =C10-D10 -> 13.397744 | G10: =ABS(F10/C10) -> 0.0041514197
A11: FY_2022 | B11: 44713 | C11: 3720.315 | D11: 3627.6462 | E11: 2432.474 | F11: =C11-D11 -> 92.6688 | G11: =ABS(F11/C11) -> 0.024908859
A12: FY_2022 | B12: 44743 | C12: 2943.439 | D12: 2817.2819 | E12: 2437.3293 | F12: =C12-D12 -> 126.15708 | G12: =ABS(F12/C12) -> 0.042860436
A13: FY_2022 | B13: 44774 | C13: 2856.853 | D13: 2916.9034 | E13: 2451.2042 | F13: =C13-D13 -> -60.050363 | G13: =ABS(F13/C13) -> 0.02101976
A14: FY_2023 | B14: 44805 | C14: 3721.873 | D14: 3687.1325 | E14: 2460.6864 | F14: =C14-D14 -> 34.740544 | G14: =ABS(F14/C14) -> 0.0093341561
A15: FY_2023 | B15: 44835 | C15: 2659.504 | D15: 2840.6742 | E15: 2472.361 | F15: =C15-D15 -> -181.17022 | G15: =ABS(F15/C15) -> 0.068121809
A16: FY_2023 | B16: 44866 | C16: 2149.636 | D16: 2329.6368 | E16: 2471.2079 | F16: =C16-D16 -> -180.00079 | G16: =ABS(F16/C16) -> 0.083735474
A17: FY_2023 | B17: 44896 | C17: 2506.8 | D17: 2089.3193 | E17: 2458.2113 | F17: =C17-D17 -> 417.48072 | G17: =ABS(F17/C17) -> 0.1665393
A18: FY_2023 | B18: 44927 | C18: 1772.677 | D18: 1906.438 | E18: 2471.9961 | F18: =C18-D18 -> -133.76095 | G18: =ABS(F18/C18) -> 0.075457035
A19: FY_2023 | B19: 44958 | C19: 1399.56 | D19: 1650.4221 | E19: 2477.0791 | F19: =C19-D19 -> -250.86213 | G19: =ABS(F19/C19) -> 0.17924357
... A38: FY_2025 | B38: 45536 | C38: 4210.684 | D38: 4107.5456 | E38: 2444.9632 | F38: =C38-D38 -> 103.13841 | G38: =ABS(F38/C38) -> 0.024494454

Sheet Model Result
E1: Volume Contribution (in KG) | I1: Contribution % | M1: Due-to | O1: Revenue (in CLP) | S1: ROI | X1: Spends | AB1: Activity (Impressions, Clicks, GRPs, Search Index) | AF1: CPRP (Cost per Impressions/Click/GRP)
A2: Variable Name | B2: Spends | C2: Type | D2: Media Type | E2: Total | F2: FY_2022 | G2: FY_2023 | H2: FY_2024 | I2: Total | J2: FY_2022 | K2: FY_2023 | L2: FY_2024 | M2: FY23 vs FY22 (12 Months) | N2: FY24 vs FY23 (12 Months) | O2: Total | P2: FY_2022 | Q2: FY_2023 | R2: FY_2024 | S2: Total | T2: FY_2022 | U2: FY_2023 | V2: FY_2024 | W2: Change | X2: Total | Y2: FY_2022 | Z2: FY_2023 | AA2: FY_2024 | AB2: Total | AC2: FY_2022 | AD2: FY_2023 | AE2: FY_2024 | AF2: Total | AG2: FY_2022 | AH2: FY_2023 | AI2: FY_2024 | AJ2: Change
A3: Base | C3: Base | D3: Base | E3: {=IFERROR(HLOOKUP(A3,Decomposition!$G$1:$BB$43,{40,41,42,43},0),0)} -> 88765.075 | F3: 29452.635 | G3: 29748.318 | H3: 29564.123 | I3: =IFERROR(E3/SUM(E$3:E$22),0) -> 0.89894806 | J3: =IFERROR(F3/SUM(F$3:F$22),0) -> 0.87739504 | K3: =IFERROR(G3/SUM(G$3:G$22),0) -> 0.9399151 | L3: =IFERROR(H3/SUM(H$3:H$22),0) -> 0.88185307 | M3: =(G3-F3)/SUM(F$3:F$22) -> 0.0088084252 | N3: =(H3-G3)/SUM(G$3:G$22) -> -0.0058197644 | O3: {=IFERROR(HLOOKUP(A3,Decomposition!$BF$1:$BZ$43,{40,41,42,43},0),0)} -> 8.170997e+09 | P3: 2.5991958e+09 | Q3: 2.7541831e+09 | R3: 2.8176181e+09 | W3: =IFERROR(#REF!/T3-1,"") | AJ3: =IFERROR(AH3/AG3-1,"")
A4: Twinings_Price | C4: Twinings' Price | D4: Price | E4: {=IFERROR(HLOOKUP(A4,Decomposition!$G$1:$BB$43,{40,41,42,43},0),0)} -> -11484.703 | F4: -2409.3376 | G4: -6205.798 | H4: -2869.5675 | I4: =IFERROR(E4/SUM(E$3:E$22),0) -> -0.11630871 | J4: =IFERROR(F4/SUM(F$3:F$22),0) -> -0.071774255 | K4: =IFERROR(G4/SUM(G$3:G$22),0) -> -0.19607573 | L4: =IFERROR(H4/SUM(H$3:H$22),0) -> -0.085594858 | M4: =(G4-F4)/SUM(F$3:F$22) -> -0.11309669 | N4: =(H4-G4)/SUM(G$3:G$22) -> 0.10541011 | O4: {=IFERROR(HLOOKUP(A4,Decomposition!$BF$1:$BZ$43,{40,41,42,43},0),0)} -> -1.053808e+09 | P4: -2.0679123e+08 | Q4: -5.7441182e+08 | R4: -2.7260493e+08 | W4: =IFERROR(#REF!/T4-1,"") | AJ4: =IFERROR(AH4/AG4-1,"")
A5: Competitor_Price | C5: Competitors' Price | D5: Price | E5: {=IFERROR(HLOOKUP(A5,Decomposition!$G$1:$BB$43,{40,41,42,43},0),0)} -> 8556.7858 | F5: 1026.7715 | G5: 3222.3833 | H5: 4307.631 | I5: =IFERROR(E5/SUM(E$3:E$22),0) -> 0.086656897 | J5: =IFERROR(F5/SUM(F$3:F$22),0) -> 0.03058756 | K5: =IFERROR(G5/SUM(G$3:G$22),0) -> 0.10181304 | L5: =IFERROR(H5/SUM(H$3:H$22),0) -> 0.12849012 | M5: =(G5-F5)/SUM(F$3:F$22) -> 0.065407354 | N5: =(H5-G5)/SUM(G$3:G$22) -> 0.034289022 | O5: {=IFERROR(HLOOKUP(A5,Decomposition!$BF$1:$BZ$43,{40,41,42,43},0),0)} -> 8.0216579e+08 | P5: 92837964 | Q5: 2.9830993e+08 | R5: 4.110179e+08 | W5: =IFERROR(#REF!/T5-1,"") | AJ5: =IFERROR(AH5/AG5-1,"")
A6: Twinings_WD | C6: Twinings' Distribution | D6: Distribution | E6: {=IFERROR(HLOOKUP(A6,Decomposition!$G$1:$BB$43,{40,41,42,43},0),0)} -> 9366.052 | F6: 3370.9159 | G6: 1964.0368 | H6: 4031.0994 | I6: =IFERROR(E6/SUM(E$3:E$22),0) -> 0.094852556 | J6: =IFERROR(F6/SUM(F$3:F$22),0) -> 0.1004197 | K6: =IFERROR(G6/SUM(G$3:G$22),0) -> 0.062054863 | L6: =IFERROR(H6/SUM(H$3:H$22),0) -> 0.1202416 | M6: =(G6-F6)/SUM(F$3:F$22) -> -0.041910979 | N6: =(H6-G6)/SUM(G$3:G$22) -> 0.065310023 | O6: {=IFERROR(HLOOKUP(A6,Decomposition!$BF$1:$BZ$43,{40,41,42,43},0),0)} -> 8.6580008e+08 | P6: 2.9909529e+08 | Q6: 1.8114113e+08 | R6: 3.8556365e+08 | W6: =IFERROR(#REF!/T6-1,"") | AJ6: =IFERROR(AH6/AG6-1,"")
A7: Competitor_WD | C7: Competitors' Distribution | D7: Distribution | E7: {=IFERROR(HLOOKUP(A7,Decomposition!$G$1:$BB$43,{40,41,42,43},0),0)} -> -4392.7024 | F7: -948.99476 | G7: -911.16153 | H7: -2532.5461 | I7: =IFERROR(E7/SUM(E$3:E$22),0) -> -0.044486091 | J7: =IFERROR(F7/SUM(F$3:F$22),0) -> -0.028270588 | K7: =IFERROR(G7/SUM(G$3:G$22),0) -> -0.028788669 | L7: =IFERROR(H7/SUM(H$3:H$22),0) -> -0.07554202 | M7: =(G7-F7)/SUM(F$3:F$22) -> 0.0011270533 | N7: =(H7-G7)/SUM(G$3:G$22) -> -0.05122857 | O7: {=IFERROR(HLOOKUP(A7,Decomposition!$BF$1:$BZ$43,{40,41,42,43},0),0)} -> -4.1014827e+08 | P7: -84294846 | Q7: -84417543 | R7: -2.4143588e+08 | S7: =IFERROR(#REF!/P7-1,"") | T7: =IFERROR(#REF!/Q7-1,"") | U7: =IFERROR(#REF!/R7-1,"") | V7: =IFERROR(#REF!/S7-1,"") | W7: =IFERROR(#REF!/T7-1,"") | X7: {=IFERROR(HLOOKUP($B7,'Raw Data'!$F$1:$AI$43,{40,41,42,43},0),"")} | AM7: inversion | AR7: Contribucion
A8: Discounts_5%_Min | C8: Discount | D8: Discount | E8: {=IFERROR(HLOOKUP(A8,Decomposition!$G$1:$BB$43,{40,41,42,43},0),0)} -> 8683.6671 | F8: 3531.7831 | G8: 4071.3611 | H8: 1080.5228 | I8: =IFERROR(E8/SUM(E$3:E$22),0) -> 0.087941858 | J8: =IFERROR(F8/SUM(F$3:F$22),0) -> 0.10521195 | K8: =IFERROR(G8/SUM(G$3:G$22),0) -> 0.12863698 | L8: =IFERROR(H8/SUM(H$3:H$22),0) -> 0.032230362 | M8: =(G8-F8)/SUM(F$3:F$22) -> 0.016074048 | N8: =(H8-G8)/SUM(G$3:G$22) -> -0.094497244 | O8: {=IFERROR(HLOOKUP(A8,Decomposition!$BF$1:$BZ$43,{40,41,42,43},0),0)} -> 7.6799676e+08 | P8: 2.9993542e+08 | Q8: 3.6808757e+08 | R8: 99973766 | S8: =IFERROR(#REF!/P8-1,"") | T8: =IFERROR(#REF!/Q8-1,"") | U8: =IFERROR(#REF!/R8-1,"") | V8: =IFERROR(#REF!/S8-1,"") | W8: =IFERROR(#REF!/T8-1,"") | X8: {=IFERROR(HLOOKUP($B8,'Raw Data'!$F$1:$AI$43,{40,41,42,43},0),"")} | AM8: Total | AN8: FY_2022 | AO8: FY_2023 | AP8: FY_2024 | AR8: Total | AS8: FY_2022 | AT8: FY_2023 | AU8: FY_2024
A9: YouTube_FB_Impressions | B9: YouTube_FB_Spends | C9: Media | D9: Digital | E9: {=IFERROR(HLOOKUP(A9,Decomposition!$G$1:$BB$43,{40,41,42,43},0),0)} -> 3861.6138 | F9: 4.9790663e-07 | G9: 1179.903 | H9: 2681.7108 | I9: =IFERROR(E9/SUM(E$3:E$22),0) -> 0.039107613 | J9: =IFERROR(F9/SUM(F$3:F$22),0) -> 1.4832656e-11 | K9: =IFERROR(G9/SUM(G$3:G$22),0) -> 0.03727971 | L9: =IFERROR(H9/SUM(H$3:H$22),0) -> 0.079991377 | M9: =(G9-F9)/SUM(F$3:F$22) -> 0.035149353 | N9: =(H9-G9)/SUM(G$3:G$22) -> 0.047450473 | O9: {=IFERROR(HLOOKUP(A9,Decomposition!$BF$1:$BZ$43,{40,41,42,43},0),0)} -> 3.6464638e+08 | P9: 0.04387661 | Q9: 1.0779671e+08 | R9: 2.5684967e+08 | S9: =IFERROR(O9/X9,0) -> 1.9471255 | T9: =IFERROR(P9/Y9,0) -> 0 | U9: =IFERROR(Q9/Z9,0) -> 2.1526666 | V9: =IFERROR(R9/AA9,0) -> 1.8721053 | W9: =IFERROR(V9/U9,0) -> 0.86966798 | X9: {=IFERROR(HLOOKUP($B9,'Raw Data'!$F$1:$AX$43,{40,41,42,43},0),"")} -> 1.872742e+08 | Y9: 0 | Z9: 50075894 | AA9: 1.3719831e+08 | AB9: {=IFERROR(HLOOKUP($A9,'Raw Data'!$F$1:$AX$43,{40,41,42,43},0),"")} -> 269644723 | AC9: 0 | AD9: 78297126 | AE9: 191347597 | AF9: =IFERROR(X9/AB9,0) -> 0.69452204 | AG9: =IFERROR(Y9/AC9,0) -> 0 | AH9: =IFERROR(Z9/AD9,0) -> 0.63956235 | AI9: =IFERROR(AA9/AE9,0) -> 0.71701088 | AJ9: =IFERROR(AI9/AH9,0) -> 1.1210961 | AM9: =IFERROR(X9/SUM(X$9:X$13),0) -> 0.5930052 | AN9: =IFERROR(Y9/SUM(Y$9:Y$13),0) -> 0 | AO9: =IFERROR(Z9/SUM(Z$9:Z$13),0) -> 0.35880244 | AP9: =IFERROR(AA9/SUM(AA$9:AA$13),0) -> 0.77846831 | AR9: =IFERROR(I9/SUM(I$9:I$13),0) -> 0.48704591 | AS9: 0 | AT9: =IFERROR(K9/SUM(K$9:K$13),0) -> 0.36555662 | AU9: =IFERROR(L9/SUM(L$9:L$13),0) -> 0.57046078 | AW9: =IFERROR(AR9/AM9*100,"") -> 82.13181 | AX9: =IFERROR(AS9/AN9*100,"") | AY9: =IFERROR(AT9/AO9*100,"") -> 101.88243 | AZ9: =IFERROR(AU9/AP9*100,"") -> 73.279897
A10: Google_Search_Clicks | B10: Google_Search_Spends | C10: Media | D10: Digital | E10: {=IFERROR(HLOOKUP(A10,Decomposition!$G$1:$BB$43,{40,41,42,43},0),0)} -> 583.09361 | F10: 2.7099364e-07 | G10: 357.71739 | H10: 225.37621 | I10: =IFERROR(E10/SUM(E$3:E$22),0) -> 0.0059051476 | J10: =IFERROR(F10/SUM(F$3:F$22),0) -> 8.0729102e-12 | K10: =IFERROR(G10/SUM(G$3:G$22),0) -> 0.011302285 | L10: =IFERROR(H10/SUM(H$3:H$22),0) -> 0.0067226317 | M10: =(G10-F10)/SUM(F$3:F$22) -> 0.010656414 | N10: =(H10-G10)/SUM(G$3:G$22) -> -0.0041813951 | O10: {=IFERROR(HLOOKUP(A10,Decomposition!$BF$1:$BZ$43,{40,41,42,43},0),0)} -> 54442988 | P10: 0.023881322 | Q10: 32690641 | R10: 21752346 | S10: =IFERROR(O10/X10,0) -> 3.9220144 | T10: =IFERROR(P10/Y10,0) -> 0 | U10: =IFERROR(Q10/Z10,0) -> 4.6619312 | V10: =IFERROR(R10/AA10,0) -> 3.166681 | W10: =IFERROR(V10/U10,0) -> 0.67926376 | X10: {=IFERROR(HLOOKUP($B10,'Raw Data'!$F$1:$AX$43,{40,41,42,43},0),"")} -> 13881384 | Y10: 0 | Z10: 7012253 | AA10: 6869131 | AB10: {=IFERROR(HLOOKUP($A10,'Raw Data'!$F$1:$AX$43,{40,41,42,43},0),"")} -> 101654 | AC10: 0 | AD10: 60335 | AE10: 41319 | AF10: =IFERROR(X10/AB10,0) -> 136.55522 | AG10: =IFERROR(Y10/AC10,0) -> 0 | AH10: =IFERROR(Z10/AD10,0) -> 116.22198 | AI10: =IFERROR(AA10/AE10,0) -> 166.2463 | AJ10: =IFERROR(AI10/AH10,0) -> 1.4304205 | AM10: =IFERROR(X10/SUM(X$9:X$13),0) -> 0.043955509 | AN10: =IFERROR(Y10/SUM(Y$9:Y$13),0) -> 0 | AO10: =IFERROR(Z10/SUM(Z$9:Z$13),0) -> 0.050244005 | AP10: =IFERROR(AA10/SUM(AA$9:AA$13),0) -> 0.038975705 | AR10: =IFERROR(I10/SUM(I$9:I$13),0) -> 0.073542662 | AS10: 0 | AT10: =IFERROR(K10/SUM(K$9:K$13),0) -> 0.11082772 | AU10: =IFERROR(L10/SUM(L$9:L$13),0) -> 0.047942639 | AW10: =IFERROR(AR10/AM10*100,"") -> 167.31159 | AX10: =IFERROR(AS10/AN10*100,"") | AY10: =IFERROR(AT10/AO10*100,"") -> 220.579 | AZ10: =IFERROR(AU10/AP10*100,"") -> 123.00647
A11: Display_Impressions | B11: Display_Spends | C11: Media | D11: Digital | E11: {=IFERROR(HLOOKUP(A11,Decomposition!$G$1:$BB$43,{40,41,42,43},0),0)} -> 1054.2437 | F11: 4.1377384e-07 | G11: 801.47445 | H11: 252.76922 | I11: =IFERROR(E11/SUM(E$3:E$22),0) -> 0.010676612 | J11: =IFERROR(F11/SUM(F$3:F$22),0) -> 1.2326338e-11 | K11: =IFERROR(G11/SUM(G$3:G$22),0) -> 0.025323043 | L11: =IFERROR(H11/SUM(H$3:H$22),0) -> 0.0075397237 | M11: =(G11-F11)/SUM(F$3:F$22) -> 0.023875953 | N11: =(H11-G11)/SUM(G$3:G$22) -> -0.017336655 | O11: {=IFERROR(HLOOKUP(A11,Decomposition!$BF$1:$BZ$43,{40,41,42,43},0),0)} -> 96765547 | P11: 0.036507686 | Q11: 73223482 | R11: 23542064 | S11: =IFERROR(O11/X11,0) -> 5.2662044 | T11: =IFERROR(P11/Y11,0) -> 0 | U11: =IFERROR(Q11/Z11,0) -> 3.9849909 | V11: =IFERROR(R11/AA11,0) -> 0 | W11: =IFERROR(V11/U11,0) -> 0 | X11: {=IFERROR(HLOOKUP($B11,'Raw Data'!$F$1:$AX$43,{40,41,42,43},0),"")} -> 18374818 | Y11: 0 | Z11: 18374818 | AA11: 0 | AB11: {=IFERROR(HLOOKUP($A11,'Raw Data'!$F$1:$AX$43,{40,41,42,43},0),"")} -> 3532942 | AC11: 0 | AD11: 3532942 | AE11: 0 | AF11: =IFERROR(X11/AB11,0) -> 5.2009962 | AG11: =IFERROR(Y11/AC11,0) -> 0 | AH11: =IFERROR(Z11/AD11,0) -> 5.2009962 | AI11: =IFERROR(AA11/AE11,0) -> 0 | AJ11: =IFERROR(AI11/AH11,0) -> 0 | AM11: =IFERROR(X11/SUM(X$9:X$13),0) -> 0.058184003 | AN11: =IFERROR(Y11/SUM(Y$9:Y$13),0) -> 0 | AO11: =IFERROR(Z11/SUM(Z$9:Z$13),0) -> 0.13165875 | AP11: =IFERROR(AA11/SUM(AA$9:AA$13),0) -> 0 | AR11: =IFERROR(I11/SUM(I$9:I$13),0) -> 0.13296645 | AS11: 0 | AT11: =IFERROR(K11/SUM(K$9:K$13),0) -> 0.24831218 | AU11: =IFERROR(L11/SUM(L$9:L$13),0) -> 0.053769754 | AW11: =IFERROR(AR11/AM11*100,"") -> 228.5275 | AX11: =IFERROR(AS11/AN11*100,"") | AY11: =IFERROR(AT11/AO11*100,"") -> 188.60288 | AZ11: =IFERROR(AU11/AP11*100,"")
A12: OOH_Screen_GRPs | B12: OOH_Screen_Spends | C12: Media | D12: OOH | E12: {=IFERROR(HLOOKUP(A12,Decomposition!$G$1:$BB$43,{40,41,42,43},0),0)} -> 1227.3599 | F12: 3.002175e-07 | G12: 658.46213 | H12: 568.8978 | I12: =IFERROR(E12/SUM(E$3:E$22),0) -> 0.012429808 | J12: =IFERROR(F12/SUM(F$3:F$22),0) -> 8.9434902e-12 | K12: =IFERROR(G12/SUM(G$3:G$22),0) -> 0.020804487 | L12: =IFERROR(H12/SUM(H$3:H$22),0) -> 0.016969361 | M12: =(G12-F12)/SUM(F$3:F$22) -> 0.01961561 | N12: =(H12-G12)/SUM(G$3:G$22) -> -0.0028298362 | O12: {=IFERROR(HLOOKUP(A12,Decomposition!$BF$1:$BZ$43,{40,41,42,43},0),0)} -> 1.1363705e+08 | P12: 0.026589881 | Q12: 60149267 | R12: 53487786 | S12: =IFERROR(O12/X12,0) -> 2.4934118 | T12: =IFERROR(P12/Y12,0) -> 0 | U12: =IFERROR(Q12/Z12,0) -> 1.3197887 | V12: =IFERROR(R12/AA12,0) -> 0 | W12: =IFERROR(V12/U12,0) -> 0 | X12: {=IFERROR(HLOOKUP($B12,'Raw Data'!$F$1:$AX$43,{40,41,42,43},0),"")} -> 45574923 | Y12: 0 | Z12: 45574923 | AA12: 0 | AB12: {=IFERROR(HLOOKUP($A12,'Raw Data'!$F$1:$AX$43,{40,41,42,43},0),"")} -> 460.11573 | AC12: 0 | AD12: 460.11573 | AE12: 0 | AF12: =IFERROR(X12/AB12,0) -> 99050.999 | AG12: =IFERROR(Y12/AC12,0) -> 0 | AH12: =IFERROR(Z12/AD12,0) -> 99050.999 | AI12: =IFERROR(AA12/AE12,0) -> 0 | AJ12: =IFERROR(AI12/AH12,0) -> 0 | AM12: =IFERROR(X12/SUM(X$9:X$13),0) -> 0.14431334 | AN12: =IFERROR(Y12/SUM(Y$9:Y$13),0) -> 0 | AO12: =IFERROR(Z12/SUM(Z$9:Z$13),0) -> 0.3265522 | AP12: =IFERROR(AA12/SUM(AA$9:AA$13),0) -> 0 | AR12: =IFERROR(I12/SUM(I$9:I$13),0) -> 0.15480073 | AS12: 0 | AT12: =IFERROR(K12/SUM(K$9:K$13),0) -> 0.20400422 | AU12: =IFERROR(L12/SUM(L$9:L$13),0) -> 0.12101748 | AW12: =IFERROR(AR12/AM12*100,"") -> 107.26709 | AX12: =IFERROR(AS12/AN12*100,"") | AY12: =IFERROR(AT12/AO12*100,"") -> 62.472162 | AZ12: =IFERROR(AU12/AP12*100,"")
A13: OOH_Retail_GRPs | B13: OOH_Retail_Spends | C13: Media | D13: OOH | E13: {=IFERROR(HLOOKUP(A13,Decomposition!$G$1:$BB$43,{40,41,42,43},0),0)} -> 1202.3334 | F13: 5.5575132e-08 | G13: 230.1318 | H13: 972.20156 | I13: =IFERROR(E13/SUM(E$3:E$22),0) -> 0.012176357 | J13: =IFERROR(F13/SUM(F$3:F$22),0) -> 1.6555852e-12 | K13: =IFERROR(G13/SUM(G$3:G$22),0) -> 0.0072711457 | L13: =IFERROR(H13/SUM(H$3:H$22),0) -> 0.028999302 | M13: =(G13-F13)/SUM(F$3:F$22) -> 0.0068556346 | N13: =(H13-G13)/SUM(G$3:G$22) -> 0.023446118 | O13: {=IFERROR(HLOOKUP(A13,Decomposition!$BF$1:$BZ$43,{40,41,42,43},0),0)} -> 1.1363163e+08 | P13: 0.0049364765 | Q13: 21042717 | R13: 92588915 | S13: =IFERROR(O13/X13,0) -> 2.2412551 | T13: =IFERROR(P13/Y13,0) -> 0 | U13: =IFERROR(Q13/Z13,0) -> 1.1358425 | V13: =IFERROR(R13/AA13,0) -> 2.8777636 | W13: =IFERROR(V13/U13,0) -> 2.5335938 | X13: {=IFERROR(HLOOKUP($B13,'Raw Data'!$F$1:$AX$43,{40,41,42,43},0),"")} -> 50700000 | Y13: 0 | Z13: 18526087 | AA13: 32173913 | AB13: {=IFERROR(HLOOKUP($A13,'Raw Data'!$F$1:$AX$43,{40,41,42,43},0),"")} -> 287.88743 | AC13: 0 | AD13: 187.03583 | AE13: 100.8516 | AF13: =IFERROR(X13/AB13,0) -> 176110.5 | AG13: =IFERROR(Y13/AC13,0) -> 0 | AH13: =IFERROR(Z13/AD13,0) -> 99051.003 | AI13: =IFERROR(AA13/AE13,0) -> 319022.33 | AJ13: =IFERROR(AI13/AH13,0) -> 3.2207885 | AM13: =IFERROR(X13/SUM(X$9:X$13),0) -> 0.16054194 | AN13: =IFERROR(Y13/SUM(Y$9:Y$13),0) -> 0 | AO13: =IFERROR(Z13/SUM(Z$9:Z$13),0) -> 0.13274261 | AP13: =IFERROR(AA13/SUM(AA$9:AA$13),0) -> 0.18255598 | AR13: =IFERROR(I13/SUM(I$9:I$13),0) -> 0.15164425 | AS13: 0 | AT13: =IFERROR(K13/SUM(K$9:K$13),0) -> 0.071299253 | AU13: =IFERROR(L13/SUM(L$9:L$13),0) -> 0.20680935 | AW13: =IFERROR(AR13/AM13*100,"") -> 94.457719 | AX13: =IFERROR(AS13/AN13*100,"") | AY13: =IFERROR(AT13/AO13*100,"") -> 53.712408 | AZ13: =IFERROR(AU13/AP13*100,"") -> 113.28544
A14: Competitor_GRPs | B14: Competitor_Spends | C14: Competitors Media | D14: Comp TV | E14: {=IFERROR(HLOOKUP(A14,Decomposition!$G$1:$BB$43,{40,41,42,43},0),0)} -> -2484.2791 | F14: -552.81997 | G14: -760.90258 | H14: -1170.5565 | I14: =IFERROR(E14/SUM(E$3:E$22),0) -> -0.02515897 | J14: =IFERROR(F14/SUM(F$3:F$22),0) -> -0.016468527 | K14: =IFERROR(G14/SUM(G$3:G$22),0) -> -0.024041151 | L14: =IFERROR(H14/SUM(H$3:H$22),0) -> -0.034915932 | M14: =(G14-F14)/SUM(F$3:F$22) -> -0.0061987884 | N14: =(H14-G14)/SUM(G$3:G$22) -> -0.012943251 | O14: {=IFERROR(HLOOKUP(A14,Decomposition!$BF$1:$BZ$43,{40,41,42,43},0),0)} -> -2.2940367e+08 | P14: -48310261 | Q14: -69475883 | R14: -1.1161753e+08 | W14: =IFERROR(#REF!/T14-1,"") | AJ14: =IFERROR(AI14/AH14,0) -> 0
A15: Inflation | C15: External Factors | D15: External | E15: {=IFERROR(HLOOKUP(A15,Decomposition!$G$1:$BB$43,{40,41,42,43},0),0)} -> -2721.4789 | F15: -1564.8985 | G15: -597.69937 | H15: -558.88099 | I15: =IFERROR(E15/SUM(E$3:E$22),0) -> -0.027561157 | J15: =IFERROR(F15/SUM(F$3:F$22),0) -> -0.046618384 | K15: =IFERROR(G15/SUM(G$3:G$22),0) -> -0.018884653 | L15: =IFERROR(H15/SUM(H$3:H$22),0) -> -0.016670575 | M15: =(G15-F15)/SUM(F$3:F$22) -> 0.028812898 | N15: =(H15-G15)/SUM(G$3:G$22) -> 0.0012264889 | O15: {=IFERROR(HLOOKUP(A15,Decomposition!$BF$1:$BZ$43,{40,41,42,43},0),0)} -> -2.4686958e+08 | P15: -1.3836807e+08 | Q15: -54819984 | R15: -53681532 | W15: =IFERROR(#REF!/T15-1,"") | AJ15: =IFERROR(AH15/AG15-1,"")
A16: Temperature | C16: External Factors | D16: External | E16: {=IFERROR(HLOOKUP(A16,Decomposition!$G$1:$BB$43,{40,41,42,43},0),0)} -> -11897.195 | F16: -3749.1081 | G16: -4011.1989 | H16: -4136.8876 | I16: =IFERROR(E16/SUM(E$3:E$22),0) -> -0.12048613 | J16: =IFERROR(F16/SUM(F$3:F$22),0) -> -0.11168606 | K16: =IFERROR(G16/SUM(G$3:G$22),0) -> -0.12673612 | L16: =IFERROR(H16/SUM(H$3:H$22),0) -> -0.1233971 | M16: =(G16-F16)/SUM(F$3:F$22) -> -0.0078076955 | N16: =(H16-G16)/SUM(G$3:G$22) -> -0.0039712043 | O16: {=IFERROR(HLOOKUP(A16,Decomposition!$BF$1:$BZ$43,{40,41,42,43},0),0)} -> -1.0965518e+09 | P16: -3.2875377e+08 | Q16: -3.7524306e+08 | R16: -3.9255492e+08
A17: Covid_Index | C17: External Factors | D17: External | E17: {=IFERROR(HLOOKUP(A17,Decomposition!$G$1:$BB$43,{40,41,42,43},0),0)} -> 5102.9572 | F17: 4296.9998 | G17: 805.95741 | H17: 0 | I17: =IFERROR(E17/SUM(E$3:E$22),0) -> 0.051679035 | J17: =IFERROR(F17/SUM(F$3:F$22),0) -> 0.12800778 | K17: =IFERROR(G17/SUM(G$3:G$22),0) -> 0.025464685 | L17: =IFERROR(H17/SUM(H$3:H$22),0) -> 0 | M17: =(G17-F17)/SUM(F$3:F$22) -> -0.10399828 | N17: =(H17-G17)/SUM(G$3:G$22) -> -0.025464685 | O17: {=IFERROR(HLOOKUP(A17,Decomposition!$BF$1:$BZ$43,{40,41,42,43},0),0)} -> 4.5121725e+08 | P17: 3.786588e+08 | Q17: 72558453 | R17: 0
A18: Winter_Solstice | C18: External Factors | D18: External | E18: {=IFERROR(HLOOKUP(A18,Decomposition!$G$1:$BB$43,{40,41,42,43},0),0)} -> 1770.1362 | F18: 595.78993 | G18: 585.17521 | H18: 589.17107 | I18: =IFERROR(E18/SUM(E$3:E$22),0) -> 0.017926651 | J18: =IFERROR(F18/SUM(F$3:F$22),0) -> 0.017748603 | K18: =IFERROR(G18/SUM(G$3:G$22),0) -> 0.018488945 | L18: =IFERROR(H18/SUM(H$3:H$22),0) -> 0.017574082 | M18: =(G18-F18)/SUM(F$3:F$22) -> -0.00031621288 | N18: =(H18-G18)/SUM(G$3:G$22) -> 0.00012625155 | O18: {=IFERROR(HLOOKUP(A18,Decomposition!$BF$1:$BZ$43,{40,41,42,43},0),0)} -> 1.6597822e+08 | P18: 55836806 | Q18: 53203741 | R18: 56937673
A19: Independence_Month | C19: External Factors | D19: External | E19: {=IFERROR(HLOOKUP(A19,Decomposition!$G$1:$BB$43,{40,41,42,43},0),0)} -> 1550.3151 | F19: 518.53543 | G19: 511.84527 | H19: 519.93445 | I19: =IFERROR(E19/SUM(E$3:E$22),0) -> 0.015700463 | J19: =IFERROR(F19/SUM(F$3:F$22),0) -> 0.015447189 | K19: =IFERROR(G19/SUM(G$3:G$22),0) -> 0.016172044 | L19: =IFERROR(H19/SUM(H$3:H$22),0) -> 0.015508858 | M19: =(G19-F19)/SUM(F$3:F$22) -> -0.00019930016 | N19: =(H19-G19)/SUM(G$3:G$22) -> 0.00025558228 | O19: {=IFERROR(HLOOKUP(A19,Decomposition!$BF$1:$BZ$43,{40,41,42,43},0),0)} -> 1.3419586e+08 | P19: 42040638 | Q19: 43782135 | R19: 48373086
A23: *Consists of Dilmah, Lipton, Supremo, Te Club Prices | F23: =SUM(F3:F19) -> 33568.271 | G23: =SUM(G3:G19) -> 31650.006 | H23: =SUM(H3:H19) -> 33524.998
A24: **Consists of Dilmah and Te Club WD | G24: =G23/F23-1 -> -0.057145199 | H24: =H23/G23-1 -> 0.059241462 | I24: =MEDIAN(I9:I13) -> 0.012176357 | S24: =MEDIAN(S9:S13) -> 2.4934118
A25: ***Consists of TV GRPs of Supremo, Te Club, and Lipton | H25: =H23/F23 -> 0.9987109
E26: Volume Contribution (in KG) | I26: Contribution % | M26: Due-to | O26: Revenue (in CLP) | S26: ROI | X26: Spends | AB26: Activity (Impressions, Clicks, GRPs, Search Index) | AF26: CPRP (Cost per Impressions/Click/GRP)
C27: Type | D27: Media Type | E27: Total | F27: FY_2022 | G27: FY_2023 | H27: FY_2024 | I27: Total | J27: FY_2022 | K27: FY_2023 | L27: FY_2024 | M27: FY23 vs FY22 (12 Months) | N27: FY24 vs FY23 (12 Months) | O27: Total | P27: FY_2022 | Q27: FY_2023 | R27: FY_2024 | S27: Total | T27: FY_2022 | U27: FY_2023 | V27: FY_2024 | W27: Change | X27: Total | Y27: FY_2022 | Z27: FY_2023 | AA27: FY_2024 | AB27: Total | AC27: FY_2022 | AD27: FY_2023 | AE27: FY_2024 | AF27: Total | AG27: FY_2022 | AH27: FY_2023 | AI27: FY_2024 | AJ27: Change
C28: Base | D28: Base | E28: =SUMIFS(E$3:E$22,$C$3:$C$22,$C28,$D$3:$D$22,$D28) -> 88765.075 | F28: =SUMIFS(F$3:F$22,$C$3:$C$22,$C28,$D$3:$D$22,$D28) -> 29452.635 | G28: =SUMIFS(G$3:G$22,$C$3:$C$22,$C28,$D$3:$D$22,$D28) -> 29748.318 | H28: =SUMIFS(H$3:H$22,$C$3:$C$22,$C28,$D$3:$D$22,$D28) -> 29564.123 | I28: =E28/SUM(E$3:E$22) -> 0.89894806 | J28: =F28/SUM(F$3:F$22) -> 0.87739504 | K28: =G28/SUM(G$3:G$22) -> 0.9399151 | L28: =H28/SUM(H$3:H$22) -> 0.88185307 | M28: =(G28-F28)/SUM($F$3:$F$22) -> 0.0088084252 | N28: =(H28-G28)/SUM($G$3:$G$22) -> -0.0058197644 | O28: =SUMIFS(O$3:O$22,$C$3:$C$22,$C28,$D$3:$D$22,$D28) -> 8.170997e+09 | P28: =SUMIFS(P$3:P$22,$C$3:$C$22,$C28,$D$3:$D$22,$D28) -> 2.5991958e+09 | Q28: =SUMIFS(Q$3:Q$22,$C$3:$C$22,$C28,$D$3:$D$22,$D28) -> 2.7541831e+09 | R28: =SUMIFS(R$3:R$22,$C$3:$C$22,$C28,$D$3:$D$22,$D28) -> 2.8176181e+09 | X28: =SUMIFS(X$3:X$22,$C$3:$C$22,$C28,$D$3:$D$22,$D28) -> 0 | Y28: =SUMIFS(Y$3:Y$22,$C$3:$C$22,$C28,$D$3:$D$22,$D28) -> 0 | Z28: =SUMIFS(Z$3:Z$22,$C$3:$C$22,$C28,$D$3:$D$22,$D28) -> 0 | AA28: =SUMIFS(AA$3:AA$22,$C$3:$C$22,$C28,$D$3:$D$22,$D28) -> 0 | AB28: =SUMIFS(AB$3:AB$22,$C$3:$C$22,$C28,$D$3:$D$22,$D28) -> 0 | AC28: =SUMIFS(AC$3:AC$22,$C$3:$C$22,$C28,$D$3:$D$22,$D28) -> 0 | AD28: =SUMIFS(AD$3:AD$22,$C$3:$C$22,$C28,$D$3:$D$22,$D28) -> 0 | AE28: =SUMIFS(AE$3:AE$22,$C$3:$C$22,$C28,$D$3:$D$22,$D28) -> 0 | AF28: =IFERROR(X28/AB28,0) -> 0 | AG28: =IFERROR(Y28/AC28,0) -> 0 | AH28: =IFERROR(Z28/AD28,0) -> 0 | AI28: =IFERROR(AA28/AE28,0) -> 0 | AJ28: =IFERROR(AH28/AG28-1,"")
C29: Price | D29: Price | E29: =SUMIFS(E$3:E$22,$C$3:$C$22,$C29,$D$3:$D$22,$D29) -> 0 | F29: =SUMIFS(F$3:F$22,$C$3:$C$22,$C29,$D$3:$D$22,$D29) -> 0 | G29: =SUMIFS(G$3:G$22,$C$3:$C$22,$C29,$D$3:$D$22,$D29) -> 0 | H29: =SUMIFS(H$3:H$22,$C$3:$C$22,$C29,$D$3:$D$22,$D29) -> 0 | I29: =E29/SUM(E$3:E$22) -> 0 | J29: =F29/SUM(F$3:F$22) -> 0 | K29: =G29/SUM(G$3:G$22) -> 0 | L29: =H29/SUM(H$3:H$22) -> 0 | M29: =(G29-F29)/SUM($F$3:$F$22) -> 0 | N29: =(H29-G29)/SUM($G$3:$G$22) -> 0 | O29: =SUMIFS(O$3:O$22,$C$3:$C$22,$C29,$D$3:$D$22,$D29) -> 0 | P29: =SUMIFS(P$3:P$22,$C$3:$C$22,$C29,$D$3:$D$22,$D29) -> 0 | Q29: =SUMIFS(Q$3:Q$22,$C$3:$C$22,$C29,$D$3:$D$22,$D29) -> 0 | R29: =SUMIFS(R$3:R$22,$C$3:$C$22,$C29,$D$3:$D$22,$D29) -> 0 | X29: =SUMIFS(X$3:X$22,$C$3:$C$22,$C29,$D$3:$D$22,$D29) -> 0 | Y29: =SUMIFS(Y$3:Y$22,$C$3:$C$22,$C29,$D$3:$D$22,$D29) -> 0 | Z29: =SUMIFS(Z$3:Z$22,$C$3:$C$22,$C29,$D$3:$D$22,$D29) -> 0 | AA29: =SUMIFS(AA$3:AA$22,$C$3:$C$22,$C29,$D$3:$D$22,$D29) -> 0 | AB29: =SUMIFS(AB$3:AB$22,$C$3:$C$22,$C29,$D$3:$D$22,$D29) -> 0 | AC29: =SUMIFS(AC$3:AC$22,$C$3:$C$22,$C29,$D$3:$D$22,$D29) -> 0 | AD29: =SUMIFS(AD$3:AD$22,$C$3:$C$22,$C29,$D$3:$D$22,$D29) -> 0 | AE29: =SUMIFS(AE$3:AE$22,$C$3:$C$22,$C29,$D$3:$D$22,$D29) -> 0 | AF29: =IFERROR(X29/AB29,0) -> 0 | AG29: =IFERROR(Y29/AC29,0) -> 0 | AH29: =IFERROR(Z29/AD29,0) -> 0 | AI29: =IFERROR(AA29/AE29,0) -> 0 | AJ29: =IFERROR(AH29/AG29-1,"")
C30: Distribution | D30: Distribution | E30: =SUMIFS(E$3:E$22,$C$3:$C$22,$C30,$D$3:$D$22,$D30) -> 0 | F30: =SUMIFS(F$3:F$22,$C$3:$C$22,$C30,$D$3:$D$22,$D30) -> 0 | G30: =SUMIFS(G$3:G$22,$C$3:$C$22,$C30,$D$3:$D$22,$D30) -> 0 | H30: =SUMIFS(H$3:H$22,$C$3:$C$22,$C30,$D$3:$D$22,$D30) -> 0 | I30: =E30/SUM(E$3:E$22) -> 0 | J30: =F30/SUM(F$3:F$22) -> 0 | K30: =G30/SUM(G$3:G$22) -> 0 | L30: =H30/SUM(H$3:H$22) -> 0 | M30: =(G30-F30)/SUM($F$3:$F$22) -> 0 | N30: =(H30-G30)/SUM($G$3:$G$22) -> 0 | O30: =SUMIFS(O$3:O$22,$C$3:$C$22,$C30,$D$3:$D$22,$D30) -> 0 | P30: =SUMIFS(P$3:P$22,$C$3:$C$22,$C30,$D$3:$D$22,$D30) -> 0 | Q30: =SUMIFS(Q$3:Q$22,$C$3:$C$22,$C30,$D$3:$D$22,$D30) -> 0 | R30: =SUMIFS(R$3:R$22,$C$3:$C$22,$C30,$D$3:$D$22,$D30) -> 0 | X30: =SUMIFS(X$3:X$22,$C$3:$C$22,$C30,$D$3:$D$22,$D30) -> 0 | Y30: =SUMIFS(Y$3:Y$22,$C$3:$C$22,$C30,$D$3:$D$22,$D30) -> 0 | Z30: =SUMIFS(Z$3:Z$22,$C$3:$C$22,$C30,$D$3:$D$22,$D30) -> 0 | AA30: =SUMIFS(AA$3:AA$22,$C$3:$C$22,$C30,$D$3:$D$22,$D30) -> 0 | AB30: =SUMIFS(AB$3:AB$22,$C$3:$C$22,$C30,$D$3:$D$22,$D30) -> 0 | AC30: =SUMIFS(AC$3:AC$22,$C$3:$C$22,$C30,$D$3:$D$22,$D30) -> 0 | AD30: =SUMIFS(AD$3:AD$22,$C$3:$C$22,$C30,$D$3:$D$22,$D30) -> 0 | AE30: =SUMIFS(AE$3:AE$22,$C$3:$C$22,$C30,$D$3:$D$22,$D30) -> 0 | AF30: =IFERROR(X30/AB30,0) -> 0 | AG30: =IFERROR(Y30/AC30,0) -> 0 | AH30: =IFERROR(Z30/AD30,0) -> 0 | AI30: =IFERROR(AA30/AE30,0) -> 0 | AJ30: =IFERROR(AH30/AG30-1,"")
C31: Discount | D31: Discount | E31: =SUMIFS(E$3:E$22,$C$3:$C$22,$C31,$D$3:$D$22,$D31) -> 8683.6671 | F31: =SUMIFS(F$3:F$22,$C$3:$C$22,$C31,$D$3:$D$22,$D31) -> 3531.7831 | G31: =SUMIFS(G$3:G$22,$C$3:$C$22,$C31,$D$3:$D$22,$D31) -> 4071.3611 | H31: =SUMIFS(H$3:H$22,$C$3:$C$22,$C31,$D$3:$D$22,$D31) -> 1080.5228 | I31: =E31/SUM(E$3:E$22) -> 0.087941858 | J31: =F31/SUM(F$3:F$22) -> 0.10521195 | K31: =G31/SUM(G$3:G$22) -> 0.12863698 | L31: =H31/SUM(H$3:H$22) -> 0.032230362 | M31: =(G31-F31)/SUM($F$3:$F$22) -> 0.016074048 | N31: =(H31-G31)/SUM($G$3:$G$22) -> -0.094497244 | O31: =SUMIFS(O$3:O$22,$C$3:$C$22,$C31,$D$3:$D$22,$D31) -> 7.6799676e+08 | P31: =SUMIFS(P$3:P$22,$C$3:$C$22,$C31,$D$3:$D$22,$D31) -> 2.9993542e+08 | Q31: =SUMIFS(Q$3:Q$22,$C$3:$C$22,$C31,$D$3:$D$22,$D31) -> 3.6808757e+08 | R31: =SUMIFS(R$3:R$22,$C$3:$C$22,$C31,$D$3:$D$22,$D31) -> 99973766 | X31: =SUMIFS(X$3:X$22,$C$3:$C$22,$C31,$D$3:$D$22,$D31) -> 0 | Y31: =SUMIFS(Y$3:Y$22,$C$3:$C$22,$C31,$D$3:$D$22,$D31) -> 0 | Z31: =SUMIFS(Z$3:Z$22,$C$3:$C$22,$C31,$D$3:$D$22,$D31) -> 0 | AA31: =SUMIFS(AA$3:AA$22,$C$3:$C$22,$C31,$D$3:$D$22,$D31) -> 0 | AB31: =SUMIFS(AB$3:AB$22,$C$3:$C$22,$C31,$D$3:$D$22,$D31) -> 0 | AC31: =SUMIFS(AC$3:AC$22,$C$3:$C$22,$C31,$D$3:$D$22,$D31) -> 0 | AD31: =SUMIFS(AD$3:AD$22,$C$3:$C$22,$C31,$D$3:$D$22,$D31) -> 0 | AE31: =SUMIFS(AE$3:AE$22,$C$3:$C$22,$C31,$D$3:$D$22,$D31) -> 0 | AF31: =IFERROR(X31/AB31,0) -> 0 | AG31: =IFERROR(Y31/AC31,0) -> 0 | AH31: =IFERROR(Z31/AD31,0) -> 0 | AI31: =IFERROR(AA31/AE31,0) -> 0 | AJ31: =IFERROR(AH31/AG31-1,"")
C32: Media | D32: Digital | E32: =SUMIFS(E$3:E$22,$C$3:$C$22,$C32,$D$3:$D$22,$D32) -> 5498.9511 | F32: =SUMIFS(F$3:F$22,$C$3:$C$22,$C32,$D$3:$D$22,$D32) -> 1.1826741e-06 | G32: =SUMIFS(G$3:G$22,$C$3:$C$22,$C32,$D$3:$D$22,$D32) -> 2339.0949 | H32: =SUMIFS(H$3:H$22,$C$3:$C$22,$C32,$D$3:$D$22,$D32) -> 3159.8562 | I32: =E32/SUM(E$3:E$22) -> 0.055689373 | J32: =F32/SUM(F$3:F$22) -> 3.5231904e-11 | K32: =G32/SUM(G$3:G$22) -> 0.073905038 | L32: =H32/SUM(H$3:H$22) -> 0.094253732 | M32: =(G32-F32)/SUM($F$3:$F$22) -> 0.06968172 | N32: =(H32-G32)/SUM($G$3:$G$22) -> 0.025932423 | O32: =SUMIFS(O$3:O$22,$C$3:$C$22,$C32,$D$3:$D$22,$D32) -> 5.1585492e+08 | P32: =SUMIFS(P$3:P$22,$C$3:$C$22,$C32,$D$3:$D$22,$D32) -> 0.10426562 | Q32: =SUMIFS(Q$3:Q$22,$C$3:$C$22,$C32,$D$3:$D$22,$D32) -> 2.1371083e+08 | R32: =SUMIFS(R$3:R$22,$C$3:$C$22,$C32,$D$3:$D$22,$D32) -> 3.0214408e+08 | S32: =IFERROR(O32/X32,0) -> 2.3498108 | T32: =IFERROR(P32/Y32,0) -> 0 | U32: =IFERROR(Q32/Z32,0) -> 2.8319962 | V32: =IFERROR(R32/AA32,0) -> 2.0972406 | W32: =IFERROR(V32/U32-1,0) -> -0.25944794 | X32: =SUMIFS(X$3:X$22,$C$3:$C$22,$C32,$D$3:$D$22,$D32) -> 2.195304e+08 | Y32: =SUMIFS(Y$3:Y$22,$C$3:$C$22,$C32,$D$3:$D$22,$D32) -> 0 | Z32: =SUMIFS(Z$3:Z$22,$C$3:$C$22,$C32,$D$3:$D$22,$D32) -> 75462965 | AA32: =SUMIFS(AA$3:AA$22,$C$3:$C$22,$C32,$D$3:$D$22,$D32) -> 1.4406744e+08 | AB32: =SUMIFS(AB$3:AB$22,$C$3:$C$22,$C32,$D$3:$D$22,$D32) -> 273279319 | AC32: =SUMIFS(AC$3:AC$22,$C$3:$C$22,$C32,$D$3:$D$22,$D32) -> 0 | AD32: =SUMIFS(AD$3:AD$22,$C$3:$C$22,$C32,$D$3:$D$22,$D32) -> 81890403 | AE32: =SUMIFS(AE$3:AE$22,$C$3:$C$22,$C32,$D$3:$D$22,$D32) -> 191388916 | AF32: =IFERROR(X32/AB32,0) -> 0.80331876 | AG32: =IFERROR(Y32/AC32,0) -> 0 | AH32: =IFERROR(Z32/AD32,0) -> 0.92151171 | AI32: =IFERROR(AA32/AE32,0) -> 0.75274704 | AJ32: =IFERROR(AI32/AH32-1,0) -> -0.18313893
C33: Media | D33: OOH | E33: =SUMIFS(E$3:E$22,$C$3:$C$22,$C33,$D$3:$D$22,$D33) -> 2429.6933 | F33: =SUMIFS(F$3:F$22,$C$3:$C$22,$C33,$D$3:$D$22,$D33) -> 3.5579264e-07 | G33: =SUMIFS(G$3:G$22,$C$3:$C$22,$C33,$D$3:$D$22,$D33) -> 888.59393 | H33: =SUMIFS(H$3:H$22,$C$3:$C$22,$C33,$D$3:$D$22,$D33) -> 1541.0994 | I33: =E33/SUM(E$3:E$22) -> 0.024606165 | J33: =F33/SUM(F$3:F$22) -> 1.0599075e-11 | K33: =G33/SUM(G$3:G$22) -> 0.028075633 | L33: =H33/SUM(H$3:H$22) -> 0.045968664 | M33: =(G33-F33)/SUM($F$3:$F$22) -> 0.026471245 | N33: =(H33-G33)/SUM($G$3:$G$22) -> 0.020616282 | O33: =SUMIFS(O$3:O$22,$C$3:$C$22,$C33,$D$3:$D$22,$D33) -> 2.2726868e+08 | P33: =SUMIFS(P$3:P$22,$C$3:$C$22,$C33,$D$3:$D$22,$D33) -> 0.031526357 | Q33: =SUMIFS(Q$3:Q$22,$C$3:$C$22,$C33,$D$3:$D$22,$D33) -> 81191983 | R33: =SUMIFS(R$3:R$22,$C$3:$C$22,$C33,$D$3:$D$22,$D33) -> 1.460767e+08 | S33: =IFERROR(O33/X33,0) -> 2.3606218 | T33: =IFERROR(P33/Y33,0) -> 0 | U33: =IFERROR(Q33/Z33,0) -> 1.2666257 | V33: =IFERROR(R33/AA33,0) -> 4.5402218 | W33: =IFERROR(V33/U33-1,0) -> 2.5845016 | X33: =SUMIFS(X$3:X$22,$C$3:$C$22,$C33,$D$3:$D$22,$D33) -> 96274922 | Y33: =SUMIFS(Y$3:Y$22,$C$3:$C$22,$C33,$D$3:$D$22,$D33) -> 0 | Z33: =SUMIFS(Z$3:Z$22,$C$3:$C$22,$C33,$D$3:$D$22,$D33) -> 64101009 | AA33: =SUMIFS(AA$3:AA$22,$C$3:$C$22,$C33,$D$3:$D$22,$D33) -> 32173913 | AB33: =SUMIFS(AB$3:AB$22,$C$3:$C$22,$C33,$D$3:$D$22,$D33) -> 748.00316 | AC33: =SUMIFS(AC$3:AC$22,$C$3:$C$22,$C33,$D$3:$D$22,$D33) -> 0 | AD33: =SUMIFS(AD$3:AD$22,$C$3:$C$22,$C33,$D$3:$D$22,$D33) -> 647.15156 | AE33: =SUMIFS(AE$3:AE$22,$C$3:$C$22,$C33,$D$3:$D$22,$D33) -> 100.8516 | AF33: =IFERROR(X33/AB33,0) -> 128709.25 | AG33: =IFERROR(Y33/AC33,0) -> 0 | AH33: =IFERROR(Z33/AD33,0) -> 99051 | AI33: =IFERROR(AA33/AE33,0) -> 319022.33 | AJ33: =IFERROR(AI33/AH33-1,0) -> 2.2207886
C34: Comp Media | D34: Comp TV | E34: =SUMIFS(E$3:E$22,$C$3:$C$22,$C34,$D$3:$D$22,$D34) -> 0 | F34: =SUMIFS(F$3:F$22,$C$3:$C$22,$C34,$D$3:$D$22,$D34) -> 0 | G34: =SUMIFS(G$3:G$22,$C$3:$C$22,$C34,$D$3:$D$22,$D34) -> 0 | H34: =SUMIFS(H$3:H$22,$C$3:$C$22,$C34,$D$3:$D$22,$D34) -> 0 | I34: =E34/SUM(E$3:E$22) -> 0 | J34: =F34/SUM(F$3:F$22) -> 0 | K34: =G34/SUM(G$3:G$22) -> 0 | L34: =H34/SUM(H$3:H$22) -> 0 | M34: =(G34-F34)/SUM($F$3:$F$22) -> 0 | N34: =(H34-G34)/SUM($G$3:$G$22) -> 0 | O34: =SUMIFS(O$3:O$22,$C$3:$C$22,$C34,$D$3:$D$22,$D34) -> 0 | P34: =SUMIFS(P$3:P$22,$C$3:$C$22,$C34,$D$3:$D$22,$D34) -> 0 | Q34: =SUMIFS(Q$3:Q$22,$C$3:$C$22,$C34,$D$3:$D$22,$D34) -> 0 | R34: =SUMIFS(R$3:R$22,$C$3:$C$22,$C34,$D$3:$D$22,$D34) -> 0
C35: External | D35: External | E35: =SUMIFS(E$3:E$22,$C$3:$C$22,$C35,$D$3:$D$22,$D35) -> 0 | F35: =SUMIFS(F$3:F$22,$C$3:$C$22,$C35,$D$3:$D$22,$D35) -> 0 | G35: =SUMIFS(G$3:G$22,$C$3:$C$22,$C35,$D$3:$D$22,$D35) -> 0 | H35: =SUMIFS(H$3:H$22,$C$3:$C$22,$C35,$D$3:$D$22,$D35) -> 0 | I35: =E35/SUM(E$3:E$22) -> 0 | J35: =F35/SUM(F$3:F$22) -> 0 | K35: =G35/SUM(G$3:G$22) -> 0 | L35: =H35/SUM(H$3:H$22) -> 0 | M35: =(G35-F35)/SUM($F$3:$F$22) -> 0 | N35: =(H35-G35)/SUM($G$3:$G$22) -> 0 | O35: =SUMIFS(O$3:O$22,$C$3:$C$22,$C35,$D$3:$D$22,$D35) -> 0 | P35: =SUMIFS(P$3:P$22,$C$3:$C$22,$C35,$D$3:$D$22,$D35) -> 0 | Q35: =SUMIFS(Q$3:Q$22,$C$3:$C$22,$C35,$D$3:$D$22,$D35) -> 0 | R35: =SUMIFS(R$3:R$22,$C$3:$C$22,$C35,$D$3:$D$22,$D35) -> 0
E38: Volume Contribution (in KG) | I38: Contribution % | M38: Due-to | O38: Revenue (in CLP) | S38: ROI | X38: Spends | AB38: Activity (Impressions, Clicks, GRPs, Search Index) | AF38: CPRP (Cost per Impressions/Click/GRP)
C39: Type | E39: Total | F39: FY_2022 | G39: FY_2023 | H39: FY_2024 | I39: Total | J39: FY_2022 | K39: FY_2023 | L39: FY_2024 | M39: FY23 vs FY22 (12 Months) | N39: FY24 vs FY23 (12 Months) | O39: Total | P39: FY_2022 | Q39: FY_2023 | R39: FY_2024 | S39: Total | T39: FY_2022 | U39: FY_2023 | V39: FY_2024 | W39: Change | X39: Total | Y39: FY_2022 | Z39: FY_2023 | AA39: FY_2024 | AB39: Total | AC39: FY_2022 | AD39: FY_2023 | AE39: FY_2024 | AF39: Total | AG39: FY_2022 | AH39: FY_2023 | AI39: FY_2024 | AJ39: Change
C40: Base | E40: =SUMIFS(E$3:E$22,$C$3:$C$22,$C40) -> 88765.075 | F40: =SUMIFS(F$3:F$22,$C$3:$C$22,$C40) -> 29452.635 | G40: =SUMIFS(G$3:G$22,$C$3:$C$22,$C40) -> 29748.318 | H40: =SUMIFS(H$3:H$22,$C$3:$C$22,$C40) -> 29564.123 | I40: =E40/SUM(E$3:E$22) -> 0.89894806 | J40: =F40/SUM(F$3:F$22) -> 0.87739504 | K40: =G40/SUM(G$3:G$22) -> 0.9399151 | L40: =H40/SUM(H$3:H$22) -> 0.88185307 | M40: =(G40-F40)/SUM($F$3:$F$22) -> 0.0088084252 | N40: =(H40-G40)/SUM($G$3:$G$22) -> -0.0058197644 | O40: =SUMIFS(O$3:O$22,$C$3:$C$22,$C40) -> 8.170997e+09 | P40: =SUMIFS(P$3:P$22,$C$3:$C$22,$C40) -> 2.5991958e+09 | Q40: =SUMIFS(Q$3:Q$22,$C$3:$C$22,$C40) -> 2.7541831e+09 | R40: =SUMIFS(R$3:R$22,$C$3:$C$22,$C40) -> 2.8176181e+09
C41: Twinings' Price | E41: =SUMIFS(E$3:E$22,$C$3:$C$22,$C41) -> -11484.703 | F41: =SUMIFS(F$3:F$22,$C$3:$C$22,$C41) -> -2409.3376 | G41: =SUMIFS(G$3:G$22,$C$3:$C$22,$C41) -> -6205.798 | H41: =SUMIFS(H$3:H$22,$C$3:$C$22,$C41) -> -2869.5675 | I41: =E41/SUM(E$3:E$22) -> -0.11630871 | J41: =F41/SUM(F$3:F$22) -> -0.071774255 | K41: =G41/SUM(G$3:G$22) -> -0.19607573 | L41: =H41/SUM(H$3:H$22) -> -0.085594858 | M41: =(G41-F41)/SUM($F$3:$F$22) -> -0.11309669 | N41: =(H41-G41)/SUM($G$3:$G$22) -> 0.10541011 | O41: =SUMIFS(O$3:O$22,$C$3:$C$22,$C41) -> -1.053808e+09 | P41: =SUMIFS(P$3:P$22,$C$3:$C$22,$C41) -> -2.0679123e+08 | Q41: =SUMIFS(Q$3:Q$22,$C$3:$C$22,$C41) -> -5.7441182e+08 | R41: =SUMIFS(R$3:R$22,$C$3:$C$22,$C41) -> -2.7260493e+08
C42: Competitors' Price | E42: =SUMIFS(E$3:E$22,$C$3:$C$22,$C42) -> 8556.7858 | F42: =SUMIFS(F$3:F$22,$C$3:$C$22,$C42) -> 1026.7715 | G42: =SUMIFS(G$3:G$22,$C$3:$C$22,$C42) -> 3222.3833 | H42: =SUMIFS(H$3:H$22,$C$3:$C$22,$C42) -> 4307.631 | I42: =E42/SUM(E$3:E$22) -> 0.086656897 | J42: =F42/SUM(F$3:F$22) -> 0.03058756 | K42: =G42/SUM(G$3:G$22) -> 0.10181304 | L42: =H42/SUM(H$3:H$22) -> 0.12849012 | M42: =(G42-F42)/SUM($F$3:$F$22) -> 0.065407354 | N42: =(H42-G42)/SUM($G$3:$G$22) -> 0.034289022 | O42: =SUMIFS(O$3:O$22,$C$3:$C$22,$C42) -> 8.0216579e+08 | P42: =SUMIFS(P$3:P$22,$C$3:$C$22,$C42) -> 92837964 | Q42: =SUMIFS(Q$3:Q$22,$C$3:$C$22,$C42) -> 2.9830993e+08 | R42: =SUMIFS(R$3:R$22,$C$3:$C$22,$C42) -> 4.110179e+08
C43: Twinings' Distribution | E43: =SUMIFS(E$3:E$22,$C$3:$C$22,$C43) -> 9366.052 | F43: =SUMIFS(F$3:F$22,$C$3:$C$22,$C43) -> 3370.9159 | G43: =SUMIFS(G$3:G$22,$C$3:$C$22,$C43) -> 1964.0368 | H43: =SUMIFS(H$3:H$22,$C$3:$C$22,$C43) -> 4031.0994 | I43: =E43/SUM(E$3:E$22) -> 0.094852556 | J43: =F43/SUM(F$3:F$22) -> 0.1004197 | K43: =G43/SUM(G$3:G$22) -> 0.062054863 | L43: =H43/SUM(H$3:H$22) -> 0.1202416 | M43: =(G43-F43)/SUM($F$3:$F$22) -> -0.041910979 | N43: =(H43-G43)/SUM($G$3:$G$22) -> 0.065310023 | O43: =SUMIFS(O$3:O$22,$C$3:$C$22,$C43) -> 8.6580008e+08 | P43: =SUMIFS(P$3:P$22,$C$3:$C$22,$C43) -> 2.9909529e+08 | Q43: =SUMIFS(Q$3:Q$22,$C$3:$C$22,$C43) -> 1.8114113e+08 | R43: =SUMIFS(R$3:R$22,$C$3:$C$22,$C43) -> 3.8556365e+08
C44: Competitors' Distribution | E44: =SUMIFS(E$3:E$22,$C$3:$C$22,$C44) -> -4392.7024 | F44: =SUMIFS(F$3:F$22,$C$3:$C$22,$C44) -> -948.99476 | G44: =SUMIFS(G$3:G$22,$C$3:$C$22,$C44) -> -911.16153 | H44: =SUMIFS(H$3:H$22,$C$3:$C$22,$C44) -> -2532.5461 | I44: =E44/SUM(E$3:E$22) -> -0.044486091 | J44: =F44/SUM(F$3:F$22) -> -0.028270588 | K44: =G44/SUM(G$3:G$22) -> -0.028788669 | L44: =H44/SUM(H$3:H$22) -> -0.07554202 | M44: =(G44-F44)/SUM($F$3:$F$22) -> 0.0011270533 | N44: =(H44-G44)/SUM($G$3:$G$22) -> -0.05122857 | O44: =SUMIFS(O$3:O$22,$C$3:$C$22,$C44) -> -4.1014827e+08 | P44: =SUMIFS(P$3:P$22,$C$3:$C$22,$C44) -> -84294846 | Q44: =SUMIFS(Q$3:Q$22,$C$3:$C$22,$C44) -> -84417543 | R44: =SUMIFS(R$3:R$22,$C$3:$C$22,$C44) -> -2.4143588e+08
C45: Discount | E45: =SUMIFS(E$3:E$22,$C$3:$C$22,$C45) -> 8683.6671 | F45: =SUMIFS(F$3:F$22,$C$3:$C$22,$C45) -> 3531.7831 | G45: =SUMIFS(G$3:G$22,$C$3:$C$22,$C45) -> 4071.3611 | H45: =SUMIFS(H$3:H$22,$C$3:$C$22,$C45) -> 1080.5228 | I45: =E45/SUM(E$3:E$22) -> 0.087941858 | J45: =F45/SUM(F$3:F$22) -> 0.10521195 | K45: =G45/SUM(G$3:G$22) -> 0.12863698 | L45: =H45/SUM(H$3:H$22) -> 0.032230362 | M45: =(G45-F45)/SUM($F$3:$F$22) -> 0.016074048 | N45: =(H45-G45)/SUM($G$3:$G$22) -> -0.094497244 | O45: =SUMIFS(O$3:O$22,$C$3:$C$22,$C45) -> 7.6799676e+08 | P45: =SUMIFS(P$3:P$22,$C$3:$C$22,$C45) -> 2.9993542e+08 | Q45: =SUMIFS(Q$3:Q$22,$C$3:$C$22,$C45) -> 3.6808757e+08 | R45: =SUMIFS(R$3:R$22,$C$3:$C$22,$C45) -> 99973766
C46: Media | E46: =SUMIFS(E$3:E$22,$C$3:$C$22,$C46) -> 7928.6444 | F46: =SUMIFS(F$3:F$22,$C$3:$C$22,$C46) -> 1.5384667e-06 | G46: =SUMIFS(G$3:G$22,$C$3:$C$22,$C46) -> 3227.6888 | H46: =SUMIFS(H$3:H$22,$C$3:$C$22,$C46) -> 4700.9556 | I46: =E46/SUM(E$3:E$22) -> 0.080295538 | J46: =F46/SUM(F$3:F$22) -> 4.583098e-11 | K46: =G46/SUM(G$3:G$22) -> 0.10198067 | L46: =H46/SUM(H$3:H$22) -> 0.1402224 | M46: =(G46-F46)/SUM($F$3:$F$22) -> 0.096152965 | N46: =(H46-G46)/SUM($G$3:$G$22) -> 0.046548705 | O46: =SUMIFS(O$3:O$22,$C$3:$C$22,$C46) -> 7.431236e+08 | P46: =SUMIFS(P$3:P$22,$C$3:$C$22,$C46) -> 0.13579198 | Q46: =SUMIFS(Q$3:Q$22,$C$3:$C$22,$C46) -> 2.9490281e+08 | R46: =SUMIFS(R$3:R$22,$C$3:$C$22,$C46) -> 4.4822079e+08 | S46: =IFERROR(O46/X46,0) -> 2.3531066 | T46: =IFERROR(P46/Y46,0) -> 0 | U46: =IFERROR(Q46/Z46,0) -> 2.1130296 | V46: =IFERROR(R46/AA46,0) -> 2.5432214 | W46: =IFERROR(V46,U46-1) -> 2.5432214 | X46: =SUMIFS(X$3:X$22,$C$3:$C$22,$C46) -> 3.1580533e+08 | Y46: =SUMIFS(Y$3:Y$22,$C$3:$C$22,$C46) -> 0 | Z46: =SUMIFS(Z$3:Z$22,$C$3:$C$22,$C46) -> 1.3956397e+08 | AA46: =SUMIFS(AA$3:AA$22,$C$3:$C$22,$C46) -> 1.7624135e+08 | AB46: =SUMIFS(AB$3:AB$22,$C$3:$C$22,$C46) -> 2.7328007e+08 | AC46: =SUMIFS(AC$3:AC$22,$C$3:$C$22,$C46) -> 0 | AD46: =SUMIFS(AD$3:AD$22,$C$3:$C$22,$C46) -> 81891050 | AE46: =SUMIFS(AE$3:AE$22,$C$3:$C$22,$C46) -> 1.9138902e+08 | AF46: =IFERROR(X46/AB46,0) -> 1.1556105 | AG46: =IFERROR(Y46/AC46,0) -> 0 | AH46: =IFERROR(Z46/AD46,0) -> 1.7042641 | AI46: =IFERROR(AA46/AE46,0) -> 0.92085405 | AJ46: =IFERROR(AI46,AH46-1) -> 0.92085405
C47: Competitors Media | E47: =SUMIFS(E$3:E$22,$C$3:$C$22,$C47) -> -2484.2791 | F47: =SUMIFS(F$3:F$22,$C$3:$C$22,$C47) -> -552.81997 | G47: =SUMIFS(G$3:G$22,$C$3:$C$22,$C47) -> -760.90258 | H47: =SUMIFS(H$3:H$22,$C$3:$C$22,$C47) -> -1170.5565 | I47: =E47/SUM(E$3:E$22) -> -0.02515897 | J47: =F47/SUM(F$3:F$22) -> -0.016468527 | K47: =G47/SUM(G$3:G$22) -> -0.024041151 | L47: =H47/SUM(H$3:H$22) -> -0.034915932 | M47: =(G47-F47)/SUM($F$3:$F$22) -> -0.0061987884 | N47: =(H47-G47)/SUM($G$3:$G$22) -> -0.012943251 | O47: =SUMIFS(O$3:O$22,$C$3:$C$22,$C47) -> -2.2940367e+08 | P47: =SUMIFS(P$3:P$22,$C$3:$C$22,$C47) -> -48310261 | Q47: =SUMIFS(Q$3:Q$22,$C$3:$C$22,$C47) -> -69475883 | R47: =SUMIFS(R$3:R$22,$C$3:$C$22,$C47) -> -1.1161753e+08
C48: External Factors | E48: =SUMIFS(E$3:E$22,$C$3:$C$22,$C48) -> -6195.265 | F48: =SUMIFS(F$3:F$22,$C$3:$C$22,$C48) -> 97.318478 | G48: =SUMIFS(G$3:G$22,$C$3:$C$22,$C48) -> -2705.9204 | H48: =SUMIFS(H$3:H$22,$C$3:$C$22,$C48) -> -3586.663 | I48: =E48/SUM(E$3:E$22) -> -0.062741133 | J48: =F48/SUM(F$3:F$22) -> 0.002899121 | K48: =G48/SUM(G$3:G$22) -> -0.085495101 | L48: =H48/SUM(H$3:H$22) -> -0.10698473 | M48: =(G48-F48)/SUM($F$3:$F$22) -> -0.083508587 | N48: =(H48-G48)/SUM($G$3:$G$22) -> -0.027827566 | O48: =SUMIFS(O$3:O$22,$C$3:$C$22,$C48) -> -5.9203e+08 | P48: =SUMIFS(P$3:P$22,$C$3:$C$22,$C48) -> 9414413 | Q48: =SUMIFS(Q$3:Q$22,$C$3:$C$22,$C48) -> -2.6051872e+08 | R48: =SUMIFS(R$3:R$22,$C$3:$C$22,$C48) -> -3.409257e+08

Sheet Decomposition
A1: Year | D1: Period | E1: APE | F1: Residual | G1: Base | H1: Twinings_Price | I1: Competitor_Price | J1: Twinings_WD | K1: Competitor_WD | L1: Discounts_5%_Min | M1: YouTube_FB_Impressions | N1: Google_Search_Clicks | O1: Display_Impressions | P1: OOH_Screen_GRPs | Q1: OOH_Retail_GRPs | R1: Competitor_GRPs | S1: Inflation | T1: Temperature | U1: Covid_Index | V1: Winter_Solstice | W1: Independence_Month | BB1: Revenue Contribution | BD1: Twinings_Price | BF1: =G1 -> Base | BG1: =H1 -> Twinings_Price | BH1: =I1 -> Competitor_Price | BI1: =J1 -> Twinings_WD | BJ1: =K1 -> Competitor_WD | BK1: =L1 -> Discounts_5%_Min | BL1: =M1 -> YouTube_FB_Impressions | BM1: =N1 -> Google_Search_Clicks | ... BV1: =W1 -> Independence_Month
A2: FY_2022 | D2: 44440 | E2: =AVP!G2 -> 0.020832139 | F2: =AVP!F2 -> -68.953714 | G2: 2486.3069 | H2: -405.80771 | I2: 23.457837 | J2: 88.337517 | K2: -41.214992 | L2: 602.36364 | M2: 4.531819e-08 | N2: 2.4060811e-08 | O2: 3.5499081e-08 | P2: 2.0910124e-08 | Q2: 3.6233767e-09 | R2: -72.034822 | S2: -138.30448 | T2: -190.76284 | U2: 508.04528 | V2: 0 | W2: 518.53543 | BD2: 81075.729 | BF2: =$BD2*G2 -> 2.0157914e+08 | BG2: =$BD2*H2 -> -32901156 | BH2: =$BD2*I2 -> 1901861.3 | BI2: =$BD2*J2 -> 7162028.6 | BJ2: =$BD2*K2 -> -3341535.5 | BK2: =$BD2*L2 -> 48837071 | BL2: =$BD2*M2 -> 0.0036742053 | BM2: =$BD2*N2 -> 0.0019507478 | ... BV2: =$BD2*W2 -> 42040638
A3: FY_2022 | D3: 44470 | E3: =AVP!G3 -> 0.030978031 | F3: =AVP!F3 -> 93.810709 | G3: 2472.805 | H3: -300.40606 | I3: 3.2519825 | J3: 348.14223 | K3: -77.633851 | L3: 662.25311 | M3: 4.4237049e-08 | N3: 2.3685674e-08 | O3: 3.5473091e-08 | P3: 2.2251739e-08 | Q3: 3.9543283e-09 | R3: -72.448133 | S3: -156.9812 | T3: -312.01809 | U3: 367.52229 | V3: 0 | W3: 0 | BD3: 82223.331 | BF3: =$BD3*G3 -> 2.0332227e+08 | BG3: =$BD3*H3 -> -24700387 | BH3: =$BD3*I3 -> 267388.84 | BI3: =$BD3*J3 -> 28625414 | BJ3: =$BD3*K3 -> -6383313.8 | BK3: =$BD3*L3 -> 54452657 | BL3: =$BD3*M3 -> 0.0036373175 | BM3: =$BD3*N3 -> 0.001947515 | ... BV3: =$BD3*W3 -> 0
A4: FY_2022 | D4: 44501 | E4: =AVP!G4 -> 0.070298552 | F4: =AVP!F4 -> -177.54328 | G4: 2469.04 | H4: -296.87094 | I4: 0 | J4: 317.97258 | K4: -106.07662 | L4: 581.10768 | M4: 4.3414245e-08 | N4: 2.3657323e-08 | O4: 3.5278081e-08 | P4: 2.3129084e-08 | Q4: 3.9226535e-09 | R4: -79.62436 | S4: -58.628364 | T4: -450.0894 | U4: 326.27371 | V4: 0 | W4: 0 | BD4: 84167.764 | BF4: =$BD4*G4 -> 2.0781358e+08 | BG4: =$BD4*H4 -> -24986963 | BH4: =$BD4*I4 -> 0 | BI4: =$BD4*J4 -> 26763041 | BJ4: =$BD4*K4 -> -8928232.2 | BK4: =$BD4*L4 -> 48910534 | BL4: =$BD4*M4 -> 0.00365408 | BM4: =$BD4*N4 -> 0.001991184 | ... BV4: =$BD4*W4 -> 0
A5: FY_2022 | D5: 44531 | E5: =AVP!G5 -> 0.16290526 | F5: =AVP!F5 -> 446.59825 | G5: 2447.4368 | H5: -142.06705 | I5: 16.15853 | J5: 312.59825 | K5: -82.661178 | L5: 91.953482 | M5: 4.2091654e-08 | N5: 2.3005334e-08 | O5: 3.5404535e-08 | P5: 2.4873794e-08 | Q5: 4.5340986e-09 | R5: -86.216046 | S5: -91.119559 | T5: -540.29592 | U5: 369.07441 | V5: 0 | W5: 0 | BD5: 95099.893 | BF5: =$BD5*G5 -> 2.3275098e+08 | BG5: =$BD5*H5 -> -13510561 | BH5: =$BD5*I5 -> 1536674.5 | BI5: =$BD5*J5 -> 29728060 | BJ5: =$BD5*K5 -> -7861069.2 | BK5: =$BD5*L5 -> 8744766.3 | BL5: =$BD5*M5 -> 0.0040029118 | BM5: =$BD5*N5 -> 0.0021878048 | ... BV5: =$BD5*W5 -> 0
A6: FY_2022 | D6: 44562 | E6: =AVP!G6 -> 0.090961251 | F6: =AVP!F6 -> -192.9098 | G6: 2469.8363 | H6: -328.68596 | I6: 11.907814 | J6: 250.44131 | K6: -67.563189 | L6: 474.28451 | M6: 4.216859e-08 | N6: 2.3638541e-08 | O6: 3.4775597e-08 | P6: 2.4087149e-08 | Q6: 3.8383432e-09 | R6: -43.124682 | S6: -142.97646 | T6: -620.55192 | U6: 310.13311 | V6: 0 | W6: 0 | BD6: 84380.01 | BF6: =$BD6*G6 -> 2.0840481e+08 | BG6: =$BD6*H6 -> -27734524 | BH6: =$BD6*I6 -> 1004781.4 | BI6: =$BD6*J6 -> 21132240 | BJ6: =$BD6*K6 -> -5700982.6 | BK6: =$BD6*L6 -> 40020131 | BL6: =$BD6*M6 -> 0.0035581861 | BM6: =$BD6*N6 -> 0.0019946204 | ... BV6: =$BD6*W6 -> 0
A7: FY_2022 | D7: 44593 | E7: =AVP!G7 -> 0.19669296 | F7: =AVP!F7 -> -398.39648 | G7: 2473.4603 | H7: -401.39174 | I7: 32.352805 | J7: 312.15807 | K7: -73.834497 | L7: 407.44942 | M7: 4.1765391e-08 | N7: 2.3647195e-08 | O7: 3.4416747e-08 | P7: 2.4321727e-08 | Q7: 3.7176595e-09 | R7: -2.0469915 | S7: -34.694541 | T7: -591.38525 | U7: 301.80291 | V7: 0 | W7: 0 | BD7: 87097.274 | BF7: =$BD7*G7 -> 2.1543165e+08 | BG7: =$BD7*H7 -> -34960127 | BH7: =$BD7*I7 -> 2817841.2 | BI7: =$BD7*J7 -> 27188117 | BJ7: =$BD7*K7 -> -6430783.4 | BK7: =$BD7*L7 -> 35487734 | BL7: =$BD7*M7 -> 0.0036376517 | BM7: =$BD7*N7 -> 0.0020596062 | ... BV7: =$BD7*W7 -> 0
A8: FY_2022 | D8: 44621 | E8: =AVP!G8 -> 0.13090128 | F8: =AVP!F8 -> 364.27812 | G8: 2439.2559 | H8: -78.363982 | I8: 95.651762 | J8: 302.2904 | K8: -68.995241 | L8: 67.796035 | M8: 4.0555644e-08 | N8: 2.2296515e-08 | O8: 3.4657263e-08 | P8: 2.6368881e-08 | Q8: 4.9411717e-09 | R8: -0.0099414147 | S8: -217.05787 | T8: -486.65614 | U8: 364.65694 | V8: 0 | W8: 0 | BD8: 90924.408 | BF8: =$BD8*G8 -> 2.217879e+08 | BG8: =$BD8*H8 -> -7125198.7 | BH8: =$BD8*I8 -> 8697079.8 | BI8: =$BD8*J8 -> 27485576 | BJ8: =$BD8*K8 -> -6273351.5 | BK8: =$BD8*L8 -> 6164314.4 | BL8: =$BD8*M8 -> 0.0036874979 | BM8: =$BD8*N8 -> 0.0020272974 | ... BV8: =$BD8*W8 -> 0
A9: FY_2022 | D9: 44652 | E9: =AVP!G9 -> 0.015193871 | F9: =AVP!F9 -> -37.791168 | G9: 2438.6478 | H9: -75.960646 | I9: 117.77452 | J9: 192.71114 | K9: -28.260112 | L9: 10.168074 | M9: 4.0245759e-08 | N9: 2.1978655e-08 | O9: 3.4332068e-08 | P9: 2.6549414e-08 | Q9: 5.1215194e-09 | R9: -4.7360961e-05 | S9: -164.29248 | T9: -309.48337 | U9: 343.75031 | V9: 0 | W9: 0 | BD9: 90669.818 | BF9: =$BD9*G9 -> 2.2111175e+08 | BG9: =$BD9*H9 -> -6887337.9 | BH9: =$BD9*I9 -> 10678594 | BI9: =$BD9*J9 -> 17473084 | BJ9: =$BD9*K9 -> -2562339.2 | BK9: =$BD9*L9 -> 921937.44 | BL9: =$BD9*M9 -> 0.0036490757 | BM9: =$BD9*N9 -> 0.0019928006 | ... BV9: =$BD9*W9 -> 0
A10: FY_2022 | D10: 44682 | E10: =AVP!G10 -> 0.0041514197 | F10: =AVP!F10 -> 13.397744 | G10: 2434.8381 | H10: -36.49203 | I10: 171.79209 | J10: 376.43802 | K10: -54.308505 | L10: 256.57738 | M10: 3.9836385e-08 | N10: 2.1548683e-08 | O10: 3.4051022e-08 | P10: 2.6916924e-08 | Q10: 5.4112787e-09 | R10: -1.1326818e-06 | S10: -141.06156 | T10: -149.1075 | U10: 355.19429 | V10: 0 | W10: 0 | BD10: 89706.497 | BF10: =$BD10*G10 -> 2.1842079e+08 | BG10: =$BD10*H10 -> -3273572.2 | BH10: =$BD10*I10 -> 15410866 | BI10: =$BD10*J10 -> 33768936 | BJ10: =$BD10*K10 -> -4871825.8 | BK10: =$BD10*L10 -> 23016658 | BL10: =$BD10*M10 -> 0.0035735826 | BM10: =$BD10*N10 -> 0.0019330568 | ... BV10: =$BD10*W10 -> 0
A11: FY_2022 | D11: 44713 | E11: =AVP!G11 -> 0.024908859 | F11: =AVP!F11 -> 92.6688 | G11: 2432.474 | H11: -30.561234 | I11: 167.88313 | J11: 324.65844 | K11: -127.21848 | L11: 38.675634 | M11: 3.9499785e-08 | N11: 2.1176057e-08 | O11: 3.3759914e-08 | P11: 2.7183723e-08 | Q11: 5.6534115e-09 | R11: -0.018397855 | S11: -109.99467 | T11: -25.598204 | U11: 361.5561 | V11: 595.78993 | W11: 0 | BD11: 93718.949 | BF11: =$BD11*G11 -> 2.279689e+08 | BG11: =$BD11*H11 -> -2864166.8 | BH11: =$BD11*I11 -> 15733830 | BI11: =$BD11*J11 -> 30426648 | BJ11: =$BD11*K11 -> -11922783 | BK11: =$BD11*L11 -> 3624639.8 | BL11: =$BD11*M11 -> 0.0037018783 | BM11: =$BD11*N11 -> 0.0019845978 | ... BV11: =$BD11*W11 -> 0
A12: FY_2022 | D12: 44743 | E12: =AVP!G12 -> 0.042860436 | F12: =AVP!F12 -> 126.15708 | G12: 2437.3293 | H12: -87.756429 | I12: 182.68614 | J12: 313.23141 | K12: -126.241 | L12: 5.7017983 | M12: 3.9339584e-08 | N12: 2.1027383e-08 | O12: 3.3380169e-08 | P12: 2.706525e-08 | Q12: 5.6287082e-09 | R12: -100.3737 | S12: -163.51 | T12: 0 | U12: 356.21444 | V12: 0 | W12: 0 | BD12: 92625.097 | BF12: =$BD12*G12 -> 2.2575786e+08 | BG12: =$BD12*H12 -> -8128447.8 | BH12: =$BD12*I12 -> 16921321 | BI12: =$BD12*J12 -> 29013089 | BJ12: =$BD12*K12 -> -11693085 | BK12: =$BD12*L12 -> 528129.62 | BL12: =$BD12*M12 -> 0.0036438328 | BM12: =$BD12*N12 -> 0.0019476633 | ... BV12: =$BD12*W12 -> 0
A13: FY_2022 | D13: 44774 | E13: =AVP!G13 -> 0.02101976 | F13: =AVP!F13 -> -60.050363 | G13: 2451.2042 | H13: -224.97387 | I13: 203.8549 | J13: 231.93651 | K13: -94.987085 | L13: 333.45236 | M13: 3.9434355e-08 | N13: 2.1271468e-08 | O13: 3.2746273e-08 | P13: 2.6559694e-08 | Q13: 5.2285826e-09 | R13: -96.92285 | S13: -146.27735 | T13: -73.15946 | U13: 332.77597 | V13: 0 | W13: 0 | BD13: 87649.231 | BF13: =$BD13*G13 -> 2.1484617e+08 | BG13: =$BD13*H13 -> -19718786 | BH13: =$BD13*I13 -> 17867725 | BI13: =$BD13*J13 -> 20329057 | BJ13: =$BD13*K13 -> -8325545 | BK13: =$BD13*L13 -> 29226843 | BL13: =$BD13*M13 -> 0.0034563908 | BM13: =$BD13*N13 -> 0.0018644278 | ... BV13: =$BD13*W13 -> 0
... A22: FY_2023 | D22: 45047 | E22: =AVP!G22 -> 0.10315112 | F22: =AVP!F22 -> 281.60163 | G22: 2477.2815 | H22: -452.53099 | I22: 305.55373 | J22: 68.717994 | K22: -50.622441 | L22: 319.94457 | M22: 3.9197159e-08 | N22: 1.7443191e-08 | O22: 2.901106e-08 | P22: 2.2857843e-08 | Q22: 8.1988582e-09 | R22: -0.0047167484 | S22: -40.386887 | T22: -179.5634 | U22: 0 | V22: 0 | W22: 0 | BD22: 92943.709 | BF22: =$BD22*G22 -> 2.3024773e+08 | BG22: =$BD22*H22 -> -42059909 | BH22: =$BD22*I22 -> 28399297 | BI22: =$BD22*J22 -> 6386905.2 | BJ22: =$BD22*K22 -> -4705037.4 | BK22: =$BD22*L22 -> 29736835 | BL22: =$BD22*M22 -> 0.0036431294 | BM22: =$BD22*N22 -> 0.0016212348 | ... BV22: =$BD22*W22 -> 0
A23: FY_2023 | B23: 2023 Campaign | C23: 2023 | D23: 45078 | E23: =AVP!G23 -> 0.035653821 | F23: =AVP!F23 -> -137.10745 | G23: 2498.5346 | H23: -679.46175 | I23: 284.52755 | J23: 93.771502 | K23: -99.0875 | L23: 410.60916 | M23: 388.39792 | N23: 30.654477 | O23: 261.2774 | P23: 224.1308 | Q23: 73.835672 | R23: -91.053202 | S23: 55.313237 | T23: -53.998652 | U23: 0 | V23: 585.17521 | W23: 0 | BD23: 90919.335 | BF23: =$BD23*G23 -> 2.2716511e+08 | BG23: =$BD23*H23 -> -61776211 | BH23: =$BD23*I23 -> 25869055 | BI23: =$BD23*J23 -> 8525642.6 | BJ23: =$BD23*K23 -> -9008969.6 | BK23: =$BD23*L23 -> 37332312 | BL23: =$BD23*M23 -> 35312881 | BM23: =$BD23*N23 -> 2787084.7 | ... BV23: =$BD23*W23 -> 0
A24: FY_2023 | B24: 2023 Campaign | C24: 2023 | D24: 45108 | E24: =AVP!G24 -> 0.093820138 | F24: =AVP!F24 -> -294.8933 | G24: 2512.4215 | H24: -813.04055 | I24: 295.73714 | J24: 99.307273 | K24: -122.37396 | L24: 463.00458 | M24: 396.7406 | N24: 174.83294 | O24: 271.09594 | P24: 218.48179 | Q24: 74.603108 | R24: -89.735572 | S24: -15.500809 | T24: -27.503681 | U24: 0 | V24: 0 | W24: 0 | BD24: 89381.705 | BF24: =$BD24*G24 -> 2.2456452e+08 | BG24: =$BD24*H24 -> -72670951 | BH24: =$BD24*I24 -> 26433490 | BI24: =$BD24*J24 -> 8876253.4 | BJ24: =$BD24*K24 -> -10937994 | BK24: =$BD24*L24 -> 41384139 | BL24: =$BD24*M24 -> 35461351 | BM24: =$BD24*N24 -> 15626867 | ... BV24: =$BD24*W24 -> 0
A25: FY_2023 | B25: 2023 Campaign | C25: 2023 | D25: 45139 | E25: =AVP!G25 -> 0.070709761 | F25: =AVP!F25 -> -195.64161 | G25: 2510.2357 | H25: -827.935 | I25: 293.57268 | J25: 0 | K25: -239.63471 | L25: 319.59723 | M25: 394.7645 | N25: 152.22997 | O25: 269.10112 | P25: 215.84954 | Q25: 81.693021 | R25: -90.556003 | S25: -15.259075 | T25: -101.19136 | U25: 0 | V25: 0 | W25: 0 | BD25: 93783.699 | BF25: =$BD25*G25 -> 2.3541919e+08 | BG25: =$BD25*H25 -> -77646807 | BH25: =$BD25*I25 -> 27532332 | BI25: =$BD25*J25 -> 0 | BJ25: =$BD25*K25 -> -22473830 | BK25: =$BD25*L25 -> 29973010 | BL25: =$BD25*M25 -> 37022475 | BM25: =$BD25*N25 -> 14276690 | ... BV25: =$BD25*W25 -> 0
A26: FY_2024 | B26: 2023 Campaign | C26: 2023 | D26: 45170 | E26: =AVP!G26 -> 0.0095316656 | F26: =AVP!F26 -> -32.209404 | G26: 2497.7848 | H26: -657.94596 | I26: 331.1934 | J26: 71.937966 | K26: -165.74097 | L26: 264.16657 | M26: 388.26951 | N26: 25.14559 | O26: 221.07722 | P26: 213.14819 | Q26: 93.950802 | R26: -93.834404 | S26: -81.357619 | T26: -216.32015 | U26: 0 | V26: 0 | W26: 519.93445 | BD26: 93036.894 | BF26: =$BD26*G26 -> 2.3238614e+08 | BG26: =$BD26*H26 -> -61213248 | BH26: =$BD26*I26 -> 30813205 | BI26: =$BD26*J26 -> 6692884.9 | BJ26: =$BD26*K26 -> -15420025 | BK26: =$BD26*L26 -> 24577237 | BL26: =$BD26*M26 -> 36123389 | BM26: =$BD26*N26 -> 2339467.6 | ... BV26: =$BD26*W26 -> 48373086
A27: FY_2024 | B27: 2023 Campaign | C27: 2023 | D27: 45200 | E27: =AVP!G27 -> 0.00088521304 | F27: =AVP!F27 -> -2.2200222 | G27: 2483.6866 | H27: -483.23578 | I27: 288.00572 | J27: 229.78127 | K27: -248.43222 | L27: 42.010684 | M27: 348.10024 | N27: 0.21286901 | O27: 31.454488 | P27: 191.53098 | Q27: 107.09681 | R27: -98.676793 | S27: -37.033358 | T27: -344.38549 | U27: 0 | V27: 0 | W27: 0 | BD27: 93810.545 | BF27: =$BD27*G27 -> 2.3299599e+08 | BG27: =$BD27*H27 -> -45332612 | BH27: =$BD27*I27 -> 27017973 | BI27: =$BD27*J27 -> 21555906 | BJ27: =$BD27*K27 -> -23305562 | BK27: =$BD27*L27 -> 3941045.1 | BL27: =$BD27*M27 -> 32655473 | BM27: =$BD27*N27 -> 19969.358 | ... BV27: =$BD27*W27 -> 0
A28: FY_2024 | C28: 2023 | D28: 45231 | E28: =AVP!G28 -> 0.018570585 | F28: =AVP!F28 -> 41.297601 | G28: 2469.4882 | H28: -317.09604 | I28: 303.69198 | J28: 201.45044 | K28: -233.32727 | L28: 6.6611923 | M28: 192.64356 | N28: 0.00066468974 | O28: 0.23669973 | P28: 121.22939 | Q28: 118.42979 | R28: -102.51484 | S28: -93.037843 | T28: -485.33554 | U28: 0 | V28: 0 | W28: 0 | BD28: 96699.351 | BF28: =$BD28*G28 -> 2.3879791e+08 | BG28: =$BD28*H28 -> -30662982 | BH28: =$BD28*I28 -> 29366818 | BI28: =$BD28*J28 -> 19480127 | BJ28: =$BD28*K28 -> -22562596 | BK28: =$BD28*L28 -> 644132.98 | BL28: =$BD28*M28 -> 18628507 | BM28: =$BD28*N28 -> 64.275066 | ... BV28: =$BD28*W28 -> 0
A29: FY_2024 | C29: 2023 | D29: 45261 | E29: =AVP!G29 -> 0.14122528 | F29: =AVP!F29 -> 414.69928 | G29: 2457.5901 | H29: -143.34458 | I29: 358.70944 | J29: 206.3175 | K29: -232.89211 | L29: 306.15348 | M29: 36.542491 | N29: 7.0487086e-06 | O29: 0.00080167269 | P29: 37.81912 | Q29: 111.21874 | R29: -93.874296 | S29: 65.043704 | T29: -587.54571 | U29: 0 | V29: 0 | W29: 0 | BD29: 91848.106 | BF29: =$BD29*G29 -> 2.25725e+08 | BG29: =$BD29*H29 -> -13165928 | BH29: =$BD29*I29 -> 32946782 | BI29: =$BD29*J29 -> 18949872 | BJ29: =$BD29*K29 -> -21390699 | BK29: =$BD29*L29 -> 28119618 | BL29: =$BD29*M29 -> 3356358.6 | BM29: =$BD29*N29 -> 0.64741054 | ... BV29: =$BD29*W29 -> 0
A30: FY_2024 | C30: 2023 | D30: 45292 | E30: =AVP!G30 -> 0.11969613 | F30: =AVP!F30 -> -197.52745 | G30: 2466.5158 | H30: -262.80847 | I30: 366.80436 | J30: 173.30839 | K30: -182.00252 | L30: 44.718573 | M30: 2.0851824 | N30: 4.2544307e-07 | O30: 9.8430011e-06 | P30: 4.8345857 | Q30: 64.572101 | R30: -86.148307 | S30: -83.308111 | T30: -660.80319 | U30: 0 | V30: 0 | W30: 0 | BD30: 95254.808 | BF30: =$BD30*G30 -> 2.3494749e+08 | BG30: =$BD30*H30 -> -25033770 | BH30: =$BD30*I30 -> 34939879 | BI30: =$BD30*J30 -> 16508458 | BJ30: =$BD30*K30 -> -17336615 | BK30: =$BD30*L30 -> 4259659 | BL30: =$BD30*M30 -> 198623.65 | BM30: =$BD30*N30 -> 0.040525498 | ... BV30: =$BD30*W30 -> 0
A31: FY_2024 | C31: 2023 | D31: 45323 | E31: =AVP!G31 -> 0.15898315 | F31: =AVP!F31 -> -239.73197 | G31: 2465.5534 | H31: -265.43209 | I31: 300.38691 | J31: 178.0944 | K31: -176.09808 | L31: 6.7279409 | M31: 0.059535282 | N31: 8.6703063e-08 | O31: 6.3899061e-07 | P31: 0.31827315 | Q31: 18.434886 | R31: -80.361086 | S31: -73.196175 | T31: -626.84791 | U31: 0 | V31: 0 | W31: 0 | BD31: 97401.97 | BF31: =$BD31*G31 -> 2.4014976e+08 | BG31: =$BD31*H31 -> -25853609 | BH31: =$BD31*I31 -> 29258277 | BI31: =$BD31*J31 -> 17346745 | BJ31: =$BD31*K31 -> -17152300 | BK31: =$BD31*L31 -> 655314.7 | BL31: =$BD31*M31 -> 5798.8538 | BM31: =$BD31*N31 -> 0.0084450491 | ... BV31: =$BD31*W31 -> 0
A32: FY_2024 | C32: 2023 | D32: 45352 | E32: =AVP!G32 -> 0.1205951 | F32: =AVP!F32 -> 343.81181 | G32: 2452.5354 | H32: -88.889636 | I32: 335.72503 | J32: 330.4026 | K32: -203.49607 | L32: 349.29427 | M32: 0.0017366023 | N32: 3.6148983e-08 | O32: 1.3983778e-07 | P32: 0.016276671 | Q32: 2.2716044 | R32: -90.405011 | S32: -46.660467 | T32: -533.64757 | U32: 0 | V32: 0 | W32: 0 | BD32: 91043.974 | BF32: =$BD32*G32 -> 2.2328857e+08 | BG32: =$BD32*H32 -> -8092865.7 | BH32: =$BD32*I32 -> 30565741 | BI32: =$BD32*J32 -> 30081166 | BJ32: =$BD32*K32 -> -18527091 | BK32: =$BD32*L32 -> 31801138 | BL32: =$BD32*M32 -> 158.10718 | BM32: =$BD32*N32 -> 0.0032911471 | ... BV32: =$BD32*W32 -> 0
A33: FY_2024 | B33: 2024 Campaign | C33: 2024 | D33: 45383 | E33: =AVP!G33 -> 0.054921557 | F33: =AVP!F33 -> -133.5237 | G33: 2457.0878 | H33: -175.31489 | I33: 403.41198 | J33: 337.21028 | K33: -217.04544 | L33: 51.634841 | M33: 212.743 | N33: 2.3880435e-08 | O33: 6.2159987e-08 | P33: 0.00090118799 | Q33: 0.1415737 | R33: -92.347599 | S33: -65.287895 | T33: -347.53987 | U33: 0 | V33: 0 | W33: 0 | BD33: 98408.435 | BF33: =$BD33*G33 -> 2.4179817e+08 | BG33: =$BD33*H33 -> -17252464 | BH33: =$BD33*I33 -> 39699141 | BI33: =$BD33*J33 -> 33184335 | BJ33: =$BD33*K33 -> -21359102 | BK33: =$BD33*L33 -> 5081303.9 | BL33: =$BD33*M33 -> 20935706 | BM33: =$BD33*N33 -> 0.0023500363 | ... BV33: =$BD33*W33 -> 0
A34: FY_2024 | B34: 2024 Campaign | C34: 2024 | D34: 45413 | E34: =AVP!G34 -> 0.0080035982 | F34: =AVP!F34 -> 24.560618 | G34: 2455.1185 | H34: -147.25453 | I34: 423.44366 | J34: 313.68342 | K34: -217.80848 | L34: 7.7925402 | M34: 375.13119 | N34: 73.117875 | O34: 4.1061125e-08 | P34: 7.2052681e-05 | Q34: 77.838029 | R34: -106.26174 | S34: -32.568116 | T34: -178.09604 | U34: 0 | V34: 0 | W34: 0 | BD34: 97880.884 | BF34: =$BD34*G34 -> 2.4030917e+08 | BG34: =$BD34*H34 -> -14413404 | BH34: =$BD34*I34 -> 41447040 | BI34: =$BD34*J34 -> 30703611 | BJ34: =$BD34*K34 -> -21319287 | BK34: =$BD34*L34 -> 762740.72 | BL34: =$BD34*M34 -> 36718173 | BM34: =$BD34*N34 -> 7156842.3 | ... BV34: =$BD34*W34 -> 0
A35: FY_2024 | B35: 2024 Campaign | C35: 2024 | D35: 45444 | E35: =AVP!G35 -> 0.0099044476 | F35: =AVP!F35 -> 40.218594 | G35: 2454.2686 | H35: -130.51414 | I35: 386.58614 | J35: 533.49589 | K35: -243.65024 | L35: 1.1687171 | M35: 375.12123 | N35: 77.45752 | O35: 3.326942e-08 | P35: 9.097344e-06 | Q35: 122.29204 | R35: -108.22723 | S35: 11.04837 | T35: -47.776533 | U35: 0 | V35: 589.17107 | W35: 0 | BD35: 96640.306 | BF35: =$BD35*G35 -> 2.3718127e+08 | BG35: =$BD35*H35 -> -12612927 | BH35: =$BD35*I35 -> 37359803 | BI35: =$BD35*J35 -> 51557206 | BJ35: =$BD35*K35 -> -23546434 | BK35: =$BD35*L35 -> 112945.17 | BL35: =$BD35*M35 -> 36251830 | BM35: =$BD35*N35 -> 7485518.4 | ... BV35: =$BD35*W35 -> 0
A36: FY_2024 | B36: 2024 Campaign | C36: 2024 | D36: 45474 | E36: =AVP!G36 -> 0.047482288 | F36: =AVP!F36 -> -161.93317 | G36: 2455.24 | H36: -140.13616 | I36: 416.27711 | J36: 765.1333 | K36: -256.99128 | L36: 0.17124917 | M36: 375.5408 | N36: 48.559183 | O36: 2.993724e-08 | P36: 1.8031148e-06 | Q36: 126.61589 | R36: -108.04891 | S36: -91.078063 | T36: -18.958915 | U36: 0 | V36: 0 | W36: 0 | BD36: 96091.605 | BF36: =$BD36*G36 -> 2.3592795e+08 | BG36: =$BD36*H36 -> -13465908 | BH36: =$BD36*I36 -> 40000735 | BI36: =$BD36*J36 -> 73522887 | BJ36: =$BD36*K36 -> -24694705 | BK36: =$BD36*L36 -> 16455.607 | BL36: =$BD36*M36 -> 36086319 | BM36: =$BD36*N36 -> 4666129.8 | ... BV36: =$BD36*W36 -> 0
A37: FY_2024 | B37: 2024 Campaign | C37: 2024 | D37: 45505 | E37: =AVP!G37 -> 0.011142576 | F37: =AVP!F37 -> 40.509614 | G37: 2449.2533 | H37: -57.595195 | I37: 393.39531 | J37: 690.2839 | K37: -155.06138 | L37: 0.022772859 | M37: 375.47228 | N37: 0.88250619 | O37: 2.8395308e-08 | P37: 5.315418e-07 | Q37: 129.3393 | R37: -109.85632 | S37: -31.445418 | T37: -89.630655 | U37: 0 | V37: 0 | W37: 0 | BD37: 95584.521 | BF37: =$BD37*G37 -> 2.341107e+08 | BG37: =$BD37*H37 -> -5505209.2 | BH37: =$BD37*I37 -> 37602503 | BI37: =$BD37*J37 -> 65980456 | BJ37: =$BD37*K37 -> -14821468 | BK37: =$BD37*L37 -> 2176.7328 | BL37: =$BD37*M37 -> 35889338 | BM37: =$BD37*N37 -> 84353.932 | ... BV37: =$BD37*W37 -> 0
A38: FY_2025 | B38: 2024 Campaign | C38: 2024 | D38: 45536 | E38: =AVP!G38 -> 0.024494454 | F38: =AVP!F38 -> 103.13841 | G38: 2444.9632 | H38: 0 | I38: 436.14917 | J38: 640.40914 | K38: -95.872775 | L38: 0 | M38: 375.34962 | N38: 0.0028087807 | O38: 2.7641688e-08 | P38: 2.1569365e-07 | Q38: 115.59984 | R38: -111.0964 | S38: -10.765847 | T38: -203.37505 | U38: 0 | V38: 0 | W38: 516.18183 | BD38: 95547.008 | BF38: =$BD38*G38 -> 2.3360892e+08 | BG38: =$BD38*H38 -> 0 | BH38: =$BD38*I38 -> 41672749 | BI38: =$BD38*J38 -> 61189178 | BJ38: =$BD38*K38 -> -9160356.8 | BK38: =$BD38*L38 -> 0 | BL38: =$BD38*M38 -> 35863533 | BM38: =$BD38*N38 -> 268.3706 | ... BV38: =$BD38*W38 -> 49319630
A40: Total | D40: =COUNT($G$2:$G$38) -> 37 | G40: =SUM(G2:G37) -> 88765.075 | H40: =SUM(H2:H37) -> -11484.703 | I40: =SUM(I2:I37) -> 8556.7858 | J40: =SUM(J2:J37) -> 9366.052 | K40: =SUM(K2:K37) -> -4392.7024 | L40: =SUM(L2:L37) -> 8683.6671 | M40: =SUM(M2:M37) -> 3861.6138 | N40: =SUM(N2:N37) -> 583.09361 | ... W40: =SUM(W2:W37) -> 1550.3151 | BD40: =SUM(BD2:BD37) -> 3314070.7 | BF40: =SUM(BF2:BF37) -> 8.170997e+09 | BG40: =SUM(BG2:BG37) -> -1.053808e+09 | BH40: =SUM(BH2:BH37) -> 8.0216579e+08 | BI40: =SUM(BI2:BI37) -> 8.6580008e+08 | BJ40: =SUM(BJ2:BJ37) -> -4.1014827e+08 | BK40: =SUM(BK2:BK37) -> 7.6799676e+08 | BL40: =SUM(BL2:BL37) -> 3.6464638e+08 | BM40: =SUM(BM2:BM37) -> 54442988 | ... BV40: =SUM(BV2:BV37) -> 1.3419586e+08
A41: FY_2022 | D41: =COUNTIF($A$2:$A$38,A41) -> 12 | G41: =SUM(G2:G13) -> 29452.635 | H41: =SUM(H2:H13) -> -2409.3376 | I41: =SUM(I2:I13) -> 1026.7715 | J41: =SUM(J2:J13) -> 3370.9159 | K41: =SUM(K2:K13) -> -948.99476 | L41: =SUM(L2:L13) -> 3531.7831 | M41: =SUM(M2:M13) -> 4.9790663e-07 | N41: =SUM(N2:N13) -> 2.7099364e-07 | ... W41: =SUM(W2:W13) -> 518.53543 | BD41: =SUM(BD2:BD13) -> 1059338 | BF41: =SUM(BF2:BF13) -> 2.5991958e+09 | BG41: =SUM(BG2:BG13) -> -2.0679123e+08 | BH41: =SUM(BH2:BH13) -> 92837964 | BI41: =SUM(BI2:BI13) -> 2.9909529e+08 | BJ41: =SUM(BJ2:BJ13) -> -84294846 | BK41: =SUM(BK2:BK13) -> 2.9993542e+08 | BL41: =SUM(BL2:BL13) -> 0.04387661 | BM41: =SUM(BM2:BM13) -> 0.023881322 | ... BV41: =SUM(BV2:BV13) -> 42040638
A42: FY_2023 | D42: =COUNTIF($A$2:$A$38,A42) -> 12 | G42: =SUM(G14:G25) -> 29748.318 | H42: =SUM(H14:H25) -> -6205.798 | I42: =SUM(I14:I25) -> 3222.3833 | J42: =SUM(J14:J25) -> 1964.0368 | K42: =SUM(K14:K25) -> -911.16153 | L42: =SUM(L14:L25) -> 4071.3611 | M42: =SUM(M14:M25) -> 1179.903 | N42: =SUM(N14:N25) -> 357.71739 | ... W42: =SUM(W14:W25) -> 511.84527 | BD42: =SUM(BD14:BD25) -> 1111031.3 | BF42: =SUM(BF14:BF25) -> 2.7541831e+09 | BG42: =SUM(BG14:BG25) -> -5.7441182e+08 | BH42: =SUM(BH14:BH25) -> 2.9830993e+08 | BI42: =SUM(BI14:BI25) -> 1.8114113e+08 | BJ42: =SUM(BJ14:BJ25) -> -84417543 | BK42: =SUM(BK14:BK25) -> 3.6808757e+08 | BL42: =SUM(BL14:BL25) -> 1.0779671e+08 | BM42: =SUM(BM14:BM25) -> 32690641 | ... BV42: =SUM(BV14:BV25) -> 43782135
A43: FY_2024 | D43: =COUNTIF($A$2:$A$38,A43) -> 12 | G43: =SUM(G26:G37) -> 29564.123 | H43: =SUM(H26:H37) -> -2869.5675 | I43: =SUM(I26:I37) -> 4307.631 | J43: =SUM(J26:J37) -> 4031.0994 | K43: =SUM(K26:K37) -> -2532.5461 | L43: =SUM(L26:L37) -> 1080.5228 | M43: =SUM(M26:M37) -> 2681.7108 | N43: =SUM(N26:N37) -> 225.37621 | ... W43: =SUM(W26:W37) -> 519.93445 | BD43: =SUM(BD26:BD37) -> 1143701.4 | BF43: =SUM(BF26:BF37) -> 2.8176181e+09 | BG43: =SUM(BG26:BG37) -> -2.7260493e+08 | BH43: =SUM(BH26:BH37) -> 4.110179e+08 | BI43: =SUM(BI26:BI37) -> 3.8556365e+08 | BJ43: =SUM(BJ26:BJ37) -> -2.4143588e+08 | BK43: =SUM(BK26:BK37) -> 99973766 | BL43: =SUM(BL26:BL37) -> 2.5684967e+08 | BM43: =SUM(BM26:BM37) -> 21752346 | ... BV43: =SUM(BV26:BV37) -> 48373086
G45: Base | H45: Twinings_Price | I45: Competitor_Price | J45: Twinings_WD | K45: Competitor_WD | L45: Discounts_5%_Min | M45: YouTube_FB_Impressions | N45: Google_Search_Clicks | O45: Display_Impressions | P45: OOH_Screen_GRPs | Q45: OOH_Retail_GRPs | R45: Competitor_GRPs | S45: Inflation | T45: Temperature | U45: Covid_Index | V45: Winter_Solstice | W45: Independence_Month | BF45: =G45 -> Base | BG45: =H45 -> Twinings_Price | BH45: =I45 -> Competitor_Price | BI45: =J45 -> Twinings_WD | BJ45: =K45 -> Competitor_WD | BK45: =L45 -> Discounts_5%_Min | BL45: =M45 -> YouTube_FB_Impressions | BM45: =N45 -> Google_Search_Clicks | ... BV45: =W45 -> Independence_Month
F46: 2023 Campaign | G46: =SUMIFS(G$2:G$38,$B$2:$B$38,$F46) -> 12502.663 | H46: =SUMIFS(H$2:H$38,$B$2:$B$38,$F46) -> -3461.619 | I46: =SUMIFS(I$2:I$38,$B$2:$B$38,$F46) -> 1493.0365 | J46: =SUMIFS(J$2:J$38,$B$2:$B$38,$F46) -> 494.79801 | K46: =SUMIFS(K$2:K$38,$B$2:$B$38,$F46) -> -875.26937 | L46: =SUMIFS(L$2:L$38,$B$2:$B$38,$F46) -> 1499.3882 | M46: =SUMIFS(M$2:M$38,$B$2:$B$38,$F46) -> 1916.2728 | N46: =SUMIFS(N$2:N$38,$B$2:$B$38,$F46) -> 383.07585 | ... W46: =SUMIFS(W$2:W$38,$B$2:$B$38,$F46) -> 519.93445 | BF46: =SUMIFS(BF$2:BF$38,$B$2:$B$38,$F46) -> 1.1525309e+09 | BG46: =SUMIFS(BG$2:BG$38,$B$2:$B$38,$F46) -> -3.1863983e+08 | BH46: =SUMIFS(BH$2:BH$38,$B$2:$B$38,$F46) -> 1.3766606e+08 | BI46: =SUMIFS(BI$2:BI$38,$B$2:$B$38,$F46) -> 45650687 | BJ46: =SUMIFS(BJ$2:BJ$38,$B$2:$B$38,$F46) -> -81146380 | BK46: =SUMIFS(BK$2:BK$38,$B$2:$B$38,$F46) -> 1.3720774e+08 | BL46: =SUMIFS(BL$2:BL$38,$B$2:$B$38,$F46) -> 1.7657557e+08 | BM46: =SUMIFS(BM$2:BM$38,$B$2:$B$38,$F46) -> 35050078 | ... BV46: =SUMIFS(BV$2:BV$38,$B$2:$B$38,$F46) -> 48373086
F47: 2024 Campaign | G47: =SUMIFS(G$2:G$38,$B$2:$B$38,$F47) -> 14715.931 | H47: =SUMIFS(H$2:H$38,$B$2:$B$38,$F47) -> -650.81492 | I47: =SUMIFS(I$2:I$38,$B$2:$B$38,$F47) -> 2459.2634 | J47: =SUMIFS(J$2:J$38,$B$2:$B$38,$F47) -> 3280.2159 | K47: =SUMIFS(K$2:K$38,$B$2:$B$38,$F47) -> -1186.4296 | L47: =SUMIFS(L$2:L$38,$B$2:$B$38,$F47) -> 60.79012 | M47: =SUMIFS(M$2:M$38,$B$2:$B$38,$F47) -> 2089.3581 | N47: =SUMIFS(N$2:N$38,$B$2:$B$38,$F47) -> 200.01989 | ... W47: =SUMIFS(W$2:W$38,$B$2:$B$38,$F47) -> 516.18183 | BF47: =SUMIFS(BF$2:BF$38,$B$2:$B$38,$F47) -> 1.4229362e+09 | BG47: =SUMIFS(BG$2:BG$38,$B$2:$B$38,$F47) -> -63249912 | BH47: =SUMIFS(BH$2:BH$38,$B$2:$B$38,$F47) -> 2.3778197e+08 | BI47: =SUMIFS(BI$2:BI$38,$B$2:$B$38,$F47) -> 3.1613767e+08 | BJ47: =SUMIFS(BJ$2:BJ$38,$B$2:$B$38,$F47) -> -1.1490135e+08 | BK47: =SUMIFS(BK$2:BK$38,$B$2:$B$38,$F47) -> 5975622.1 | BL47: =SUMIFS(BL$2:BL$38,$B$2:$B$38,$F47) -> 2.017449e+08 | BM47: =SUMIFS(BM$2:BM$38,$B$2:$B$38,$F47) -> 19393113 | ... BV47: =SUMIFS(BV$2:BV$38,$B$2:$B$38,$F47) -> 49319630
F49: 2023 | G49: =SUMIFS(G$2:G$38,$C$2:$C$38,$F49) -> 24814.346 | H49: =SUMIFS(H$2:H$38,$C$2:$C$38,$F49) -> -4539.1899 | I49: =SUMIFS(I$2:I$38,$C$2:$C$38,$F49) -> 3158.3542 | J49: =SUMIFS(J$2:J$38,$C$2:$C$38,$F49) -> 1584.3714 | K49: =SUMIFS(K$2:K$38,$C$2:$C$38,$F49) -> -1903.0854 | L49: =SUMIFS(L$2:L$38,$C$2:$C$38,$F49) -> 2212.9437 | M49: =SUMIFS(M$2:M$38,$C$2:$C$38,$F49) -> 2147.6053 | N49: =SUMIFS(N$2:N$38,$C$2:$C$38,$F49) -> 383.07653 | ... W49: =SUMIFS(W$2:W$38,$C$2:$C$38,$F49) -> 519.93445 | BE49: 2023 | BF49: =SUMIFS(BF$2:BF$38,$C$2:$C$38,$F49) -> 2.3154397e+09 | BG49: =SUMIFS(BG$2:BG$38,$C$2:$C$38,$F49) -> -4.2144898e+08 | BH49: =SUMIFS(BH$2:BH$38,$C$2:$C$38,$F49) -> 2.9474355e+08 | BI49: =SUMIFS(BI$2:BI$38,$C$2:$C$38,$F49) -> 1.4801706e+08 | BJ49: =SUMIFS(BJ$2:BJ$38,$C$2:$C$38,$F49) -> -1.7811568e+08 | BK49: =SUMIFS(BK$2:BK$38,$C$2:$C$38,$F49) -> 2.0268761e+08 | BL49: =SUMIFS(BL$2:BL$38,$C$2:$C$38,$F49) -> 1.9876502e+08 | BM49: =SUMIFS(BM$2:BM$38,$C$2:$C$38,$F49) -> 35050143 | ... BV49: =SUMIFS(BV$2:BV$38,$C$2:$C$38,$F49) -> 48373086
F50: 2024 | G50: =SUMIFS(G$2:G$38,$C$2:$C$38,$F50) -> 14715.931 | H50: =SUMIFS(H$2:H$38,$C$2:$C$38,$F50) -> -650.81492 | I50: =SUMIFS(I$2:I$38,$C$2:$C$38,$F50) -> 2459.2634 | J50: =SUMIFS(J$2:J$38,$C$2:$C$38,$F50) -> 3280.2159 | K50: =SUMIFS(K$2:K$38,$C$2:$C$38,$F50) -> -1186.4296 | L50: =SUMIFS(L$2:L$38,$C$2:$C$38,$F50) -> 60.79012 | M50: =SUMIFS(M$2:M$38,$C$2:$C$38,$F50) -> 2089.3581 | N50: =SUMIFS(N$2:N$38,$C$2:$C$38,$F50) -> 200.01989 | ... W50: =SUMIFS(W$2:W$38,$C$2:$C$38,$F50) -> 516.18183 | BE50: 2024 | BF50: =SUMIFS(BF$2:BF$38,$C$2:$C$38,$F50) -> 1.4229362e+09 | BG50: =SUMIFS(BG$2:BG$38,$C$2:$C$38,$F50) -> -63249912 | BH50: =SUMIFS(BH$2:BH$38,$C$2:$C$38,$F50) -> 2.3778197e+08 | BI50: =SUMIFS(BI$2:BI$38,$C$2:$C$38,$F50) -> 3.1613767e+08 | BJ50: =SUMIFS(BJ$2:BJ$38,$C$2:$C$38,$F50) -> -1.1490135e+08 | BK50: =SUMIFS(BK$2:BK$38,$C$2:$C$38,$F50) -> 5975622.1 | BL50: =SUMIFS(BL$2:BL$38,$C$2:$C$38,$F50) -> 2.017449e+08 | BM50: =SUMIFS(BM$2:BM$38,$C$2:$C$38,$F50) -> 19393113 | ... BV50: =SUMIFS(BV$2:BV$38,$C$2:$C$38,$F50) -> 49319630
BJ54: Contribution $ | BK54: =SUM(BL49:BP49) -> 5.1386861e+08
L55: 2023 contribution | M55: =SUM(M49:Q49) -> 5558.3909 | N55: 5558.3909 | BJ55: Spend | BK55: =BL55-BM55 -> 139563974 | BL55: 167673039 | BM55: 28109065
L56: Total volume | M56: =SUM(G42:W42) -> 31650.006 | N56: 28422 | BJ56: ROI | BK56: =BK54/BK55 -> 3.6819574
M57: =M55/M56 -> 0.17562054 | N57: =N55/N56 -> 0.1955665
M60: 5558.3909 | N60: =M60*N61/M61 -> 0.084601562
M61: 4848 | N61: 0.073789047 | O61: =N60-N61 -> 0.010812515

Sheet Comparison
A1: Modelo | B1: 1 | C1: 2 | D1: 3 | E1: 4
B2: 45695 | C2: 45698 | D2: 45700 | E2: 45702 | F2: Change
A3: Base | B3: 0.96085031 | C3: 0.86567843 | D3: 0.92532531 | E3: ='Model Result'!I3 -> 0.89894806 | F3: =E3-D3 -> -0.02637725
A4: Price Own | B4: -0.11532086 | C4: -0.082742587 | D4: -0.15527882 | E4: ='Model Result'!I4 -> -0.11630871 | F4: =E4-D4 -> 0.038970106
A5: Price Competitors | B5: 0.11754513 | C5: 0.06166677 | D5: 0.11727927 | E5: ='Model Result'!I5 -> 0.086656897 | F5: =E5-D5 -> -0.030622374
A6: Distribution | B6: 0.1078211 | C6: 0.1292178 | D6: 0.099791832 | E6: ='Model Result'!I6 -> 0.094852556 | F6: =E6-D6 -> -0.004939276
A7: Distribution Comp | B7: -0.049059353 | C7: -0.024055111 | D7: -0.056203142 | E7: ='Model Result'!I7 -> -0.044486091 | F7: =E7-D7 -> 0.011717051
A8: Discounts | B8: 0.0083805355 | C8: 0.0017213552 | D8: 0.01436971 | E8: ='Model Result'!I8 -> 0.087941858 | F8: =E8-D8 -> 0.073572148
A9: Media YouTube FB | B9: 0.03390979 | C9: 0.026375333 | D9: 0.03843749 | E9: ='Model Result'!I9 -> 0.039107613 | F9: =E9-D9 -> 0.0006701231
A10: Media Search | B10: 0.015073446 | C10: 0.010883651 | D10: 0.022280076 | E10: ='Model Result'!I10 -> 0.0059051476 | F10: =E10-D10 -> -0.016374928
A11: Media OOH Screen | B11: 0.011455089 | C11: 0.0070443113 | D11: 0.0058327295 | E11: ='Model Result'!I12 -> 0.012429808 | F11: =E11-D11 -> 0.0065970783
A12: Media OOH Retail | B12: 0 | C12: 0.013676391 | D12: 0.016733445 | E12: ='Model Result'!I13 -> 0.012176357 | F12: =E12-D12 -> -0.0045570882
A13: Media Display | B13: NA | C13: NA | D13: 0.011027657 | E13: ='Model Result'!I11 -> 0.010676612 | F13: =E13-D13 -> -0.00035104484
A14: Comp Media Competitor | B14: -0.023737773 | C14: -0.012609588 | D14: -0.0097235142 | E14: ='Model Result'!I14 -> -0.02515897 | F14: =E14-D14 -> -0.015435456
A15: External Organic Search | B15: 0.018913389 | C15: 0.0051790477 | D15: 0.0049102398 | F15: =E15-D15 -> -0.0049102398
A16: External Others | B16: -0.085830804 | C16: -0.0020357944 | D16: -0.034782284 | E16: =SUM('Model Result'!I16:I22) -> -0.035179976 | F16: =E16-D16 -> -0.00039769268
A18: Modelo | B18: 1 | C18: 2 | D18: 3 | E18: 4
A19: RSQ | B19: 0.81695805 | C19: 0.8124 | D19: 0.6114 | E19: 0.9055
A20: Adj Rsq | B20: 0.6532 | C20: 0.6027 | D20: 0.2227 | E20: 0.8209
A21: Mape | B21: 0.10604729 | C21: 0.0929 | D21: 0.1771 | E21: 0.0686
A22: DW | B22: 1.5322584 | C22: 1.57 | D22: 1.05 | E22: 2.54

Sheet Graficos
A1: Variable | B1: Variable 2 | C1: Variable 3 | D1: Total | E1: FY'22 | F1: FY'23 | G1: FY'24 | H1: FY_2022 | I1: FY_2023 | J1: FY_2024 | K1: FY23 vs FY22 (12 Months) | L1: FY24 vs FY23 (12 Months)
A2: Base | B2: Base | C2: Base | D2: 0.89894806 | E2: 0.87739504 | F2: 0.9399151 | G2: 0.88185307 | H2: 29452.635 | I2: 29748.318 | J2: 29564.123 | K2: 0.0088084252 | L2: -0.0058197644
A3: Twinings Price | B3: Twinings Price | C3: Price | D3: -0.11630871 | E3: -0.071774255 | F3: -0.19607573 | G3: -0.085594858 | H3: -2409.3376 | I3: -6205.798 | J3: -2869.5675 | K3: -0.11309669 | L3: 0.10541011 | P3: Row Labels | Q3: Sum of Total
A4: Competitor Price | B4: Competitor Price | C4: Competitors | D4: 0.086656897 | E4: 0.03058756 | F4: 0.10181304 | G4: 0.12849012 | H4: 1026.7715 | I4: 3222.3833 | J4: 4307.631 | K4: 0.065407354 | L4: 0.034289022 | P4: Base | Q4: 0.89894806
A5: Twinings WD | B5: Twinings WD | C5: Distribution | D5: 0.094852556 | E5: 0.1004197 | F5: 0.062054863 | G5: 0.1202416 | H5: 3370.9159 | I5: 1964.0368 | J5: 4031.0994 | K5: -0.041910979 | L5: 0.065310023 | P5: Competitors | Q5: 0.017011836
A6: Competitor WD | B6: Competitor WD | C6: Competitors | D6: -0.044486091 | E6: -0.028270588 | F6: -0.028788669 | G6: -0.07554202 | H6: -948.99476 | I6: -911.16153 | J6: -2532.5461 | K6: 0.0011270533 | L6: -0.05122857 | P6: Discount | Q6: 0.087941858
A7: Discounts | B7: Discounts | C7: Discount | D7: 0.087941858 | E7: 0.10521195 | F7: 0.12863698 | G7: 0.032230362 | H7: 3531.7831 | I7: 4071.3611 | J7: 1080.5228 | K7: 0.016074048 | L7: -0.094497244 | P7: Distribution | Q7: 0.094852556
A8: YouTube + Facebook | B8: YouTube + Facebook | C8: Media | D8: 0.039107613 | E8: 1.4832656e-11 | F8: 0.03727971 | G8: 0.079991377 | H8: 4.9790663e-07 | I8: 1179.903 | J8: 2681.7108 | K8: 0.035149353 | L8: 0.047450473 | P8: External Factors | Q8: -0.062741133
A9: Paid Search | B9: Paid Search | C9: Media | D9: 0.0059051476 | E9: 8.0729102e-12 | F9: 0.011302285 | G9: 0.0067226317 | H9: 2.7099364e-07 | I9: 357.71739 | J9: 225.37621 | K9: 0.010656414 | L9: -0.0041813951 | P9: Media | Q9: 0.080295538
A10: Online Banners | B10: Online Banners | C10: Media | D10: 0.010676612 | E10: 1.2326338e-11 | F10: 0.025323043 | G10: 0.0075397237 | H10: 4.1377384e-07 | I10: 801.47445 | J10: 252.76922 | K10: 0.023875953 | L10: -0.017336655 | P10: Price | Q10: -0.11630871
A11: OOH Large Format | B11: OOH Large Format | C11: Media | D11: 0.012429808 | E11: 8.9434902e-12 | F11: 0.020804487 | G11: 0.016969361 | H11: 3.002175e-07 | I11: 658.46213 | J11: 568.8978 | K11: 0.01961561 | L11: -0.0028298362 | P11: Grand Total | Q11: 1
A12: OOH Retail Media | B12: OOH Retail Media | C12: Media | D12: 0.012176357 | E12: 1.6555852e-12 | F12: 0.0072711457 | G12: 0.028999302 | H12: 5.5575132e-08 | I12: 230.1318 | J12: 972.20156 | K12: 0.0068556346 | L12: 0.023446118
A13: Competitor Media | B13: Competitor Media | C13: Competitors | D13: -0.02515897 | E13: -0.016468527 | F13: -0.024041151 | G13: -0.034915932 | H13: -552.81997 | I13: -760.90258 | J13: -1170.5565 | K13: -0.0061987884 | L13: -0.012943251
A14: Inflation | B14: Other EF | C14: External Factors | D14: -0.027561157 | E14: -0.046618384 | F14: -0.018884653 | G14: -0.016670575 | H14: -1564.8985 | I14: -597.69937 | J14: -558.88099 | K14: 0.028812898 | L14: 0.0012264889
A15: Temperature | B15: Temperature | C15: External Factors | D15: -0.12048613 | E15: -0.11168606 | F15: -0.12673612 | G15: -0.1233971 | H15: -3749.1081 | I15: -4011.1989 | J15: -4136.8876 | K15: -0.0078076955 | L15: -0.0039712043
A16: Covid Index | B16: Covid Index | C16: External Factors | D16: 0.051679035 | E16: 0.12800778 | F16: 0.025464685 | G16: 0 | H16: 4296.9998 | I16: 805.95741 | J16: 0 | K16: -0.10399828 | L16: -0.025464685
A17: Winter Solstice | B17: Other EF | C17: External Factors | D17: 0.017926651 | E17: 0.017748603 | F17: 0.018488945 | G17: 0.017574082 | H17: 595.78993 | I17: 585.17521 | J17: 589.17107 | K17: -0.00031621288 | L17: 0.00012625155
A18: Independence Month | B18: Other EF | C18: External Factors | D18: 0.015700463 | E18: 0.015447189 | F18: 0.016172044 | G18: 0.015508858 | H18: 518.53543 | I18: 511.84527 | J18: 519.93445 | K18: -0.00019930016 | L18: 0.00025558228
G22: Base | H22: Competitors | I22: Discount | J22: Distribution | K22: External Factors | L22: Media | M22: Price
G23: 0.89894806 | H23: 0.017011836 | I23: 0.087941858 | J23: 0.094852556 | K23: -0.062741133 | L23: 0.080295538 | M23: -0.11630871
G25: Base | H25: Competitor Price | I25: Competitor WD | J25: Covid Index | K25: Discounts | L25: Other EF | M25: Temperature | N25: Twinings Price | O25: Twinings WD | P25: YouTube + Facebook | Q25: Paid Search | R25: Online Banners | S25: OOH Large Format | T25: OOH Retail Media | U25: Competitor Media
G26: 0.89894806 | H26: 0.086656897 | I26: -0.044486091 | J26: 0.051679035 | K26: 0.087941858 | L26: 0.0060659569 | M26: -0.12048613 | N26: -0.11630871 | O26: 0.094852556 | P26: 0.039107613 | Q26: 0.0059051476 | R26: 0.010676612 | S26: 0.012429808 | T26: 0.012176357 | U26: -0.02515897
D31: Base | E31: Twinings Price | F31: Competitor Price | G31: Twinings WD | H31: Competitor WD | I31: Discounts | J31: YouTube + Facebook | K31: Paid Search | L31: Online Banners | M31: OOH Large Format | N31: OOH Retail Media | O31: Competitor Media | P31: Inflation | Q31: Temperature | R31: Covid Index | S31: Winter Solstice | T31: Independence Month
A32: Period | B32: APE | C32: Residual | D32: Base | E32: Twinings_Price | F32: Competitor_Price | G32: Twinings_WD | H32: Competitor_WD | I32: Discounts_5%_Min | J32: YouTube_FB_Impressions | K32: Google_Search_Clicks | L32: Display_Impressions | M32: OOH_Screen_GRPs | N32: OOH_Retail_GRPs | O32: Competitor_GRPs | P32: Inflation | Q32: Temperature | R32: Covid_Index | S32: Winter_Solstice | T32: Independence_Month | V32: Base | W32: Competitors | X32: Discount | Y32: Distribution | Z32: External Factors | AA32: Media | AB32: Price | AD32: Total estimated
A33: 44440 | B33: 0.020832139 | C33: -68.953714 | D33: 2486.3069 | E33: -405.80771 | F33: 23.457837 | G33: 88.337517 | H33: -41.214992 | I33: 602.36364 | J33: 4.531819e-08 | K33: 2.4060811e-08 | L33: 3.5499081e-08 | M33: 2.0910124e-08 | N33: 3.6233767e-09 | O33: -72.034822 | P33: -138.30448 | Q33: -190.76284 | R33: 508.04528 | S33: 0 | T33: 518.53543 | V33: =D33 -> 2486.3069 | W33: =SUM(F33,H33,O33) -> -89.791977 | X33: =I33 -> 602.36364 | Y33: =G33 -> 88.337517 | Z33: =SUM(P33:T33) -> 697.51338 | AA33: =SUM(J33:N33) -> 1.2941158e-07 | AB33: =E33 -> -405.80771 | AD33: =SUM(V33:AB33) -> 3378.9217
A34: 44470 | B34: 0.030978031 | C34: 93.810709 | D34: 2472.805 | E34: -300.40606 | F34: 3.2519825 | G34: 348.14223 | H34: -77.633851 | I34: 662.25311 | J34: 4.4237049e-08 | K34: 2.3685674e-08 | L34: 3.5473091e-08 | M34: 2.2251739e-08 | N34: 3.9543283e-09 | O34: -72.448133 | P34: -156.9812 | Q34: -312.01809 | R34: 367.52229 | S34: 0 | T34: 0 | V34: =D34 -> 2472.805 | W34: =SUM(F34,H34,O34) -> -146.83 | X34: =I34 -> 662.25311 | Y34: =G34 -> 348.14223 | Z34: =SUM(P34:T34) -> -101.477 | AA34: =SUM(J34:N34) -> 1.2960188e-07 | AB34: =E34 -> -300.40606 | AD34: =SUM(V34:AB34) -> 2934.4873
A35: 44501 | B35: 0.070298552 | C35: -177.54328 | D35: 2469.04 | E35: -296.87094 | F35: 0 | G35: 317.97258 | H35: -106.07662 | I35: 581.10768 | J35: 4.3414245e-08 | K35: 2.3657323e-08 | L35: 3.5278081e-08 | M35: 2.3129084e-08 | N35: 3.9226535e-09 | O35: -79.62436 | P35: -58.628364 | Q35: -450.0894 | R35: 326.27371 | S35: 0 | T35: 0 | V35: =D35 -> 2469.04 | W35: =SUM(F35,H35,O35) -> -185.70098 | X35: =I35 -> 581.10768 | Y35: =G35 -> 317.97258 | Z35: =SUM(P35:T35) -> -182.44405 | AA35: =SUM(J35:N35) -> 1.2940139e-07 | AB35: =E35 -> -296.87094 | AD35: =SUM(V35:AB35) -> 2703.1043
A36: 44531 | B36: 0.16290526 | C36: 446.59825 | D36: 2447.4368 | E36: -142.06705 | F36: 16.15853 | G36: 312.59825 | H36: -82.661178 | I36: 91.953482 | J36: 4.2091654e-08 | K36: 2.3005334e-08 | L36: 3.5404535e-08 | M36: 2.4873794e-08 | N36: 4.5340986e-09 | O36: -86.216046 | P36: -91.119559 | Q36: -540.29592 | R36: 369.07441 | S36: 0 | T36: 0 | V36: =D36 -> 2447.4368 | W36: =SUM(F36,H36,O36) -> -152.71869 | X36: =I36 -> 91.953482 | Y36: =G36 -> 312.59825 | Z36: =SUM(P36:T36) -> -262.34107 | AA36: =SUM(J36:N36) -> 1.2990942e-07 | AB36: =E36 -> -142.06705 | AD36: =SUM(V36:AB36) -> 2294.8618
A37: 44562 | B37: 0.090961251 | C37: -192.9098 | D37: 2469.8363 | E37: -328.68596 | F37: 11.907814 | G37: 250.44131 | H37: -67.563189 | I37: 474.28451 | J37: 4.216859e-08 | K37: 2.3638541e-08 | L37: 3.4775597e-08 | M37: 2.4087149e-08 | N37: 3.8383432e-09 | O37: -43.124682 | P37: -142.97646 | Q37: -620.55192 | R37: 310.13311 | S37: 0 | T37: 0 | V37: =D37 -> 2469.8363 | W37: =SUM(F37,H37,O37) -> -98.780057 | X37: =I37 -> 474.28451 | Y37: =G37 -> 250.44131 | Z37: =SUM(P37:T37) -> -453.39527 | AA37: =SUM(J37:N37) -> 1.2850822e-07 | AB37: =E37 -> -328.68596 | AD37: =SUM(V37:AB37) -> 2313.7008
A38: 44593 | B38: 0.19669296 | C38: -398.39648 | D38: 2473.4603 | E38: -401.39174 | F38: 32.352805 | G38: 312.15807 | H38: -73.834497 | I38: 407.44942 | J38: 4.1765391e-08 | K38: 2.3647195e-08 | L38: 3.4416747e-08 | M38: 2.4321727e-08 | N38: 3.7176595e-09 | O38: -2.0469915 | P38: -34.694541 | Q38: -591.38525 | R38: 301.80291 | S38: 0 | T38: 0 | V38: =D38 -> 2473.4603 | W38: =SUM(F38,H38,O38) -> -43.528683 | X38: =I38 -> 407.44942 | Y38: =G38 -> 312.15807 | Z38: =SUM(P38:T38) -> -324.27688 | AA38: =SUM(J38:N38) -> 1.2786872e-07 | AB38: =E38 -> -401.39174 | AD38: =SUM(V38:AB38) -> 2423.8705
A39: 44621 | B39: 0.13090128 | C39: 364.27812 | D39: 2439.2559 | E39: -78.363982 | F39: 95.651762 | G39: 302.2904 | H39: -68.995241 | I39: 67.796035 | J39: 4.0555644e-08 | K39: 2.2296515e-08 | L39: 3.4657263e-08 | M39: 2.6368881e-08 | N39: 4.9411717e-09 | O39: -0.0099414147 | P39: -217.05787 | Q39: -486.65614 | R39: 364.65694 | S39: 0 | T39: 0 | V39: =D39 -> 2439.2559 | W39: =SUM(F39,H39,O39) -> 26.646579 | X39: =I39 -> 67.796035 | Y39: =G39 -> 302.2904 | Z39: =SUM(P39:T39) -> -339.05708 | AA39: =SUM(J39:N39) -> 1.2881947e-07 | AB39: =E39 -> -78.363982 | AD39: =SUM(V39:AB39) -> 2418.5679
A40: 44652 | B40: 0.015193871 | C40: -37.791168 | D40: 2438.6478 | E40: -75.960646 | F40: 117.77452 | G40: 192.71114 | H40: -28.260112 | I40: 10.168074 | J40: 4.0245759e-08 | K40: 2.1978655e-08 | L40: 3.4332068e-08 | M40: 2.6549414e-08 | N40: 5.1215194e-09 | O40: -4.7360961e-05 | P40: -164.29248 | Q40: -309.48337 | R40: 343.75031 | S40: 0 | T40: 0 | V40: =D40 -> 2438.6478 | W40: =SUM(F40,H40,O40) -> 89.514362 | X40: =I40 -> 10.168074 | Y40: =G40 -> 192.71114 | Z40: =SUM(P40:T40) -> -130.02554 | AA40: =SUM(J40:N40) -> 1.2822742e-07 | AB40: =E40 -> -75.960646 | AD40: =SUM(V40:AB40) -> 2525.0552
A41: 44682 | B41: 0.0041514197 | C41: 13.397744 | D41: 2434.8381 | E41: -36.49203 | F41: 171.79209 | G41: 376.43802 | H41: -54.308505 | I41: 256.57738 | J41: 3.9836385e-08 | K41: 2.1548683e-08 | L41: 3.4051022e-08 | M41: 2.6916924e-08 | N41: 5.4112787e-09 | O41: -1.1326818e-06 | P41: -141.06156 | Q41: -149.1075 | R41: 355.19429 | S41: 0 | T41: 0 | V41: =D41 -> 2434.8381 | W41: =SUM(F41,H41,O41) -> 117.48358 | X41: =I41 -> 256.57738 | Y41: =G41 -> 376.43802 | Z41: =SUM(P41:T41) -> 65.025239 | AA41: =SUM(J41:N41) -> 1.2776429e-07 | AB41: =E41 -> -36.49203 | AD41: =SUM(V41:AB41) -> 3213.8703
A42: 44713 | B42: 0.024908859 | C42: 92.6688 | D42: 2432.474 | E42: -30.561234 | F42: 167.88313 | G42: 324.65844 | H42: -127.21848 | I42: 38.675634 | J42: 3.9499785e-08 | K42: 2.1176057e-08 | L42: 3.3759914e-08 | M42: 2.7183723e-08 | N42: 5.6534115e-09 | O42: -0.018397855 | P42: -109.99467 | Q42: -25.598204 | R42: 361.5561 | S42: 595.78993 | T42: 0 | V42: =D42 -> 2432.474 | W42: =SUM(F42,H42,O42) -> 40.646243 | X42: =I42 -> 38.675634 | Y42: =G42 -> 324.65844 | Z42: =SUM(P42:T42) -> 821.75315 | AA42: =SUM(J42:N42) -> 1.2727289e-07 | AB42: =E42 -> -30.561234 | AD42: =SUM(V42:AB42) -> 3627.6462
A43: 44743 | B43: 0.042860436 | C43: 126.15708 | D43: 2437.3293 | E43: -87.756429 | F43: 182.68614 | G43: 313.23141 | H43: -126.241 | I43: 5.7017983 | J43: 3.9339584e-08 | K43: 2.1027383e-08 | L43: 3.3380169e-08 | M43: 2.706525e-08 | N43: 5.6287082e-09 | O43: -100.3737 | P43: -163.51 | Q43: 0 | R43: 356.21444 | S43: 0 | T43: 0 | V43: =D43 -> 2437.3293 | W43: =SUM(F43,H43,O43) -> -43.928556 | X43: =I43 -> 5.7017983 | Y43: =G43 -> 313.23141 | Z43: =SUM(P43:T43) -> 192.70444 | AA43: =SUM(J43:N43) -> 1.2644109e-07 | AB43: =E43 -> -87.756429 | AD43: =SUM(V43:AB43) -> 2817.2819
A44: 44774 | B44: 0.02101976 | C44: -60.050363 | D44: 2451.2042 | E44: -224.97387 | F44: 203.8549 | G44: 231.93651 | H44: -94.987085 | I44: 333.45236 | J44: 3.9434355e-08 | K44: 2.1271468e-08 | L44: 3.2746273e-08 | M44: 2.6559694e-08 | N44: 5.2285826e-09 | O44: -96.92285 | P44: -146.27735 | Q44: -73.15946 | R44: 332.77597 | S44: 0 | T44: 0 | V44: =D44 -> 2451.2042 | W44: =SUM(F44,H44,O44) -> 11.944963 | X44: =I44 -> 333.45236 | Y44: =G44 -> 231.93651 | Z44: =SUM(P44:T44) -> 113.33916 | AA44: =SUM(J44:N44) -> 1.2524037e-07 | AB44: =E44 -> -224.97387 | AD44: =SUM(V44:AB44) -> 2916.9034
... A69: 45536 | B69: 0.024494454 | C69: 103.13841 | D69: 2444.9632 | E69: 0 | F69: 436.14917 | G69: 640.40914 | H69: -95.872775 | I69: 0 | J69: 375.34962 | K69: 0.0028087807 | L69: 2.7641688e-08 | M69: 2.1569365e-07 | N69: 115.59984 | O69: -111.0964 | P69: -10.765847 | Q69: -203.37505 | R69: 0 | S69: 0 | T69: 516.18183 | V69: =D69 -> 2444.9632 | W69: =SUM(F69,H69,O69) -> 229.18 | X69: =I69 -> 0 | Y69: =G69 -> 640.40914 | Z69: =SUM(P69:T69) -> 302.04093 | AA69: =SUM(J69:N69) -> 490.95227 | AB69: =E69 -> 0 | AD69: =SUM(V69:AB69) -> 4107.5456
V71: =SUM(V33:V69) -> 91210.038 | W71: =SUM(W33:W69) -> 1908.9844 | X71: =SUM(X33:X69) -> 8683.6671 | Y71: =SUM(Y33:Y69) -> 10006.461 | Z71: =SUM(Z33:Z69) -> -5893.2241 | AA71: =SUM(AA33:AA69) -> 8419.5966 | AB71: =SUM(AB33:AB69) -> -11484.703
A80: Row Labels | B80: Sum of FY_2022 | C80: Sum of FY_2023 | D80: Sum of FY_2024
A81: Base | B81: 29452.635 | C81: 29748.318 | D81: 29564.123 | G81: Base | H81: 29452.635 | I81: 29748.318 | J81: 29564.123 | L81: Base | M81: YouTube + Facebook | N81: Paid Search | O81: Online Banners | P81: OOH Large Format | Q81: OOH Retail Media | R81: Other Factors | T81: Total | V81: Media
A82: Competitor Media | B82: -552.81997 | C82: -760.90258 | D82: -1170.5565 | G82: YouTube + Facebook | H82: 4.9790663e-07 | I82: 1179.903 | J82: 2681.7108 | L82: 29452.635 | M82: 4.9790663e-07 | N82: 2.7099364e-07 | O82: 4.1377384e-07 | P82: 3.002175e-07 | Q82: 5.5575132e-08 | R82: 4115.6366 | T82: =SUM(L82:R82) -> 33568.271 | V82: =SUM(M82:Q82) -> 1.5384667e-06
A83: Competitor Price | B83: 1026.7715 | C83: 3222.3833 | D83: 4307.631 | G83: Paid Search | H83: 2.7099364e-07 | I83: 357.71739 | J83: 225.37621 | L83: 29748.318 | M83: 1179.903 | N83: 357.71739 | O83: 801.47445 | P83: 658.46213 | Q83: 230.1318 | R83: -1326.0013 | T83: =SUM(L83:R83) -> 31650.006 | U83: =T83/T82-1 -> -0.057145199 | V83: =SUM(M83:Q83) -> 3227.6888
A84: Competitor WD | B84: -948.99476 | C84: -911.16153 | D84: -2532.5461 | G84: Online Banners | H84: 4.1377384e-07 | I84: 801.47445 | J84: 252.76922 | L84: 29564.123 | M84: 2681.7108 | N84: 225.37621 | O84: 252.76922 | P84: 568.8978 | Q84: 972.20156 | R84: -740.07991 | T84: =SUM(L84:R84) -> 33524.998 | U84: =T84/T83-1 -> 0.059241462 | V84: =SUM(M84:Q84) -> 4700.9556 | W84: =V84/V83-1 -> 0.45644635
A85: Covid Index | B85: 4296.9998 | C85: 805.95741 | D85: 0 | G85: OOH Large Format | H85: 3.002175e-07 | I85: 658.46213 | J85: 568.8978
A86: Discounts | B86: 3531.7831 | C86: 4071.3611 | D86: 1080.5228 | G86: OOH Retail Media | H86: 5.5575132e-08 | I86: 230.1318 | J86: 972.20156
A87: Independence Month | B87: 518.53543 | C87: 511.84527 | D87: 519.93445 | G87: Other Factors | H87: 4115.6366 | I87: -1326.0013 | J87: -740.07991
A88: Inflation | B88: -1564.8985 | C88: -597.69937 | D88: -558.88099
A89: Online Banners | B89: 4.1377384e-07 | C89: 801.47445 | D89: 252.76922
A90: OOH Large Format | B90: 3.002175e-07 | C90: 658.46213 | D90: 568.8978
A91: OOH Retail Media | B91: 5.5575132e-08 | C91: 230.1318 | D91: 972.20156
A92: Paid Search | B92: 2.7099364e-07 | C92: 357.71739 | D92: 225.37621
A93: Temperature | B93: -3749.1081 | C93: -4011.1989 | D93: -4136.8876
A94: Twinings Price | B94: -2409.3376 | C94: -6205.798 | D94: -2869.5675
A95: Twinings WD | B95: 3370.9159 | C95: 1964.0368 | D95: 4031.0994
A96: Winter Solstice | B96: 595.78993 | C96: 585.17521 | D96: 589.17107
A97: YouTube + Facebook | B97: 4.9790663e-07 | C97: 1179.903 | D97: 2681.7108
A98: Grand Total | B98: 33568.271 | C98: 31650.006 | D98: 33524.998
G99: Competitor Media | H99: -552.81997 | I99: -760.90258 | J99: -1170.5565
G100: Competitor Price | H100: 1026.7715 | I100: 3222.3833 | J100: 4307.631
G101: Competitor WD | H101: -948.99476 | I101: -911.16153 | J101: -2532.5461
G102: Covid Index | H102: 4296.9998 | I102: 805.95741 | J102: 0
G103: Discounts | H103: 3531.7831 | I103: 4071.3611 | J103: 1080.5228
G104: Independence Month | H104: 518.53543 | I104: 511.84527 | J104: 519.93445
G105: Inflation | H105: -1564.8985 | I105: -597.69937 | J105: -558.88099
G106: Temperature | H106: -3749.1081 | I106: -4011.1989 | J106: -4136.8876
G107: Twinings Price | H107: -2409.3376 | I107: -6205.798 | J107: -2869.5675
G108: Twinings WD | H108: 3370.9159 | I108: 1964.0368 | J108: 4031.0994
G109: Winter Solstice | H109: 595.78993 | I109: 585.17521 | J109: 589.17107
C130: Row Labels | D130: Sum of FY24 vs FY23 (12 Months) | E130: Sum of FY23 vs FY22 (12 Months) | G130: Row Labels | H130: Sum of FY_2022 | I130: Sum of FY_2023 | J130: Sum of FY_2024 | L130: FY'23 vs FY'22 | M130: FY'24 vs FY'23
C131: Base | D131: -0.0058197644 | E131: 0.0088084252 | G131: Base | H131: 29452.635 | I131: 29748.318 | J131: 29564.123 | L131: =(I131-H131)/$H$138 -> 0.0088084252 | M131: =(J131-I131)/$H$138 -> -0.0054871928
C132: Competitors | D132: -0.0298828 | E132: 0.060335619 | G132: Competitors | H132: -475.04322 | I132: 1550.3192 | J132: 604.52841 | L132: =(I132-H132)/$H$138 -> 0.060335619 | M132: =(J132-I132)/$H$138 -> -0.028175141
C133: Discount | D133: -0.094497244 | E133: 0.016074048 | G133: Discount | H133: 3531.7831 | I133: 4071.3611 | J133: 1080.5228 | L133: =(I133-H133)/$H$138 -> 0.016074048 | M133: =(J133-I133)/$H$138 -> -0.089097181
C134: Distribution | D134: 0.065310023 | E134: -0.041910979 | G134: Distribution | H134: 3370.9159 | I134: 1964.0368 | J134: 4031.0994 | L134: =(I134-H134)/$H$138 -> -0.041910979 | M134: =(J134-I134)/$H$138 -> 0.061577869
C135: External Factors | D135: -0.027827566 | E135: -0.083508587 | G135: External Factors | H135: 97.318478 | I135: -2705.9204 | J135: -3586.663 | L135: =(I135-H135)/$H$138 -> -0.083508587 | M135: =(J135-I135)/$H$138 -> -0.026237354
C136: Media | D136: 0.046548705 | E136: 0.096152965 | G136: Media | H136: 1.5384667e-06 | I136: 3227.6888 | J136: 4700.9556 | L136: =(I136-H136)/$H$138 -> 0.096152965 | M136: =(J136-I136)/$H$138 -> 0.04388867
C137: Price | D137: 0.10541011 | E137: -0.11309669 | G137: Price | H137: -2409.3376 | I137: -6205.798 | J137: -2869.5675 | L137: =(I137-H137)/$H$138 -> -0.11309669 | M137: =(J137-I137)/$H$138 -> 0.099386428
C138: Grand Total | D138: 0.059241462 | E138: -0.057145199 | G138: Grand Total | H138: 33568.271 | I138: 31650.006 | J138: 33524.998
B159: Total | C159: FY_2023 | D159: FY_2024 | E159: Total | F159: FY_2023 | G159: FY_2024 | H159: Total | I159: FY_2023 | J159: FY_2024 | K159: Total | L159: FY_2023 | M159: FY_2024 | N159: Total | O159: FY_2023 | P159: FY_2024
B160: Spend | C160: Spend | D160: Spend | E160: Contribution | F160: Contribution | G160: Contribution | H160: % of Media Spend | I160: % of Media Spend | J160: % of Media Spend | K160: % Media contribution | N160: Index of contribution / spend
A161: YouTube + Facebook + Instagram | B161: 1.872742e+08 | C161: 50075894 | D161: 1.3719831e+08 | E161: 3861.6138 | F161: 1179.903 | G161: 2681.7108 | H161: =B161/SUM(B$161:B$165) -> 0.5930052 | I161: =C161/SUM(C$161:C$165) -> 0.35880244 | J161: =D161/SUM(D$161:D$165) -> 0.77846831 | K161: =E161/SUM(E$161:E$165) -> 0.48704591 | L161: =F161/SUM(F$161:F$165) -> 0.36555662 | M161: =G161/SUM(G$161:G$165) -> 0.57046078 | N161: =K161/H161 -> 0.8213181 | O161: =L161/I161 -> 1.0188243 | P161: =M161/J161 -> 0.73279897
A162: Paid Search | B162: 13881384 | C162: 7012253 | D162: 6869131 | E162: 583.09361 | F162: 357.71739 | G162: 225.37621 | H162: =B162/SUM(B$161:B$165) -> 0.043955509 | I162: =C162/SUM(C$161:C$165) -> 0.050244005 | J162: =D162/SUM(D$161:D$165) -> 0.038975705 | K162: =E162/SUM(E$161:E$165) -> 0.073542662 | L162: =F162/SUM(F$161:F$165) -> 0.11082772 | M162: =G162/SUM(G$161:G$165) -> 0.047942639 | N162: =K162/H162 -> 1.6731159 | O162: =L162/I162 -> 2.20579 | P162: =M162/J162 -> 1.2300647
A163: Online Banners | B163: 18374818 | C163: 18374818 | D163: 0 | E163: 1054.2437 | F163: 801.47445 | G163: 252.76922 | H163: =B163/SUM(B$161:B$165) -> 0.058184003 | I163: =C163/SUM(C$161:C$165) -> 0.13165875 | J163: =D163/SUM(D$161:D$165) -> 0 | K163: =E163/SUM(E$161:E$165) -> 0.13296645 | L163: =F163/SUM(F$161:F$165) -> 0.24831218 | M163: =G163/SUM(G$161:G$165) -> 0.053769754 | N163: =K163/H163 -> 2.285275 | O163: =L163/I163 -> 1.8860288 | P163: =M163/J163 -> #DIV/0!
A164: OOH Large format | B164: 45574923 | C164: 45574923 | D164: 0 | E164: 1227.3599 | F164: 658.46213 | G164: 568.8978 | H164: =B164/SUM(B$161:B$165) -> 0.14431334 | I164: =C164/SUM(C$161:C$165) -> 0.3265522 | J164: =D164/SUM(D$161:D$165) -> 0 | K164: =E164/SUM(E$161:E$165) -> 0.15480073 | L164: =F164/SUM(F$161:F$165) -> 0.20400422 | M164: =G164/SUM(G$161:G$165) -> 0.12101748 | N164: =K164/H164 -> 1.0726709 | O164: =L164/I164 -> 0.62472162 | P164: =M164/J164 -> #DIV/0!
A165: OOH Retail Media | B165: 50700000 | C165: 18526087 | D165: 32173913 | E165: 1202.3334 | F165: 230.1318 | G165: 972.20156 | H165: =B165/SUM(B$161:B$165) -> 0.16054194 | I165: =C165/SUM(C$161:C$165) -> 0.13274261 | J165: =D165/SUM(D$161:D$165) -> 0.18255598 | K165: =E165/SUM(E$161:E$165) -> 0.15164425 | L165: =F165/SUM(F$161:F$165) -> 0.071299253 | M165: =G165/SUM(G$161:G$165) -> 0.20680935 | N165: =K165/H165 -> 0.94457719 | O165: =L165/I165 -> 0.53712408 | P165: =M165/J165 -> 1.1328544
B169: Total | C169: FY_2023 | D169: FY_2024 | E169: Total | F169: FY_2023 | G169: FY_2024 | H169: Total | I169: FY_2023 | J169: FY_2024 | K169: Total | L169: FY_2023 | M169: FY_2024 | N169: Total | O169: FY_2023 | P169: FY_2024
B170: Spend | E170: Contribution | H170: % of Media Spend | K170: % Media contribution | N170: Index of contribution / spend
A171: YouTube + Facebook + Instagram | B171: 1.872742e+08 | C171: 50075894 | D171: 1.3719831e+08 | E171: 3861.6138 | F171: 1179.903 | G171: 2681.7108 | H171: =B171/SUM(B$171:B$173) -> 0.74357772 | I171: =C171/SUM(C$171:C$173) -> 0.66225486 | J171: =D171/SUM(D$171:D$173) -> 0.77846831 | K171: =E171/SUM(E$171:E$173) -> 0.68382963 | L171: =F171/SUM(F$171:F$173) -> 0.66745951 | M171: =G171/SUM(G$171:G$173) -> 0.69128933 | N171: =K171/H171 -> 0.91964782 | O171: =L171/I171 -> 1.007859 | P171: =M171/J171 -> 0.88801216
A172: Paid Search | B172: 13881384 | C172: 7012253 | D172: 6869131 | E172: 583.09361 | F172: 357.71739 | G172: 225.37621 | H172: =B172/SUM(B$171:B$173) -> 0.055116443 | I172: =C172/SUM(C$171:C$173) -> 0.092737209 | J172: =D172/SUM(D$171:D$173) -> 0.038975705 | K172: =E172/SUM(E$171:E$173) -> 0.10325649 | L172: =F172/SUM(F$171:F$173) -> 0.2023572 | M172: =G172/SUM(G$171:G$173) -> 0.058097306 | N172: =K172/H172 -> 1.8734244 | O172: =L172/I172 -> 2.1820497 | P172: =M172/J172 -> 1.4906031
A173: OOH Retail Media | B173: 50700000 | C173: 18526087 | D173: 32173913 | E173: 1202.3334 | F173: 230.1318 | G173: 972.20156 | H173: =B173/SUM(B$171:B$173) -> 0.20130584 | I173: =C173/SUM(C$171:C$173) -> 0.24500793 | J173: =D173/SUM(D$171:D$173) -> 0.18255598 | K173: =E173/SUM(E$171:E$173) -> 0.21291388 | L173: =F173/SUM(F$171:F$173) -> 0.13018329 | M173: =G173/SUM(G$171:G$173) -> 0.25061337 | N173: =K173/H173 -> 1.0576637 | O173: =L173/I173 -> 0.53134318 | P173: =M173/J173 -> 1.3728028

Sheet Raw Data
A1: Geography | D1: Period | E1: Twinings_Volume | F1: Twinings_Value | G1: Twinings_Price | H1: Competitor_Price | I1: Twinings_WD | J1: Dilmah_WD | K1: Te_Club_WD | L1: Competitor_WD | M1: Discounts_7%_Min | N1: Discounts_Price_Differential_vs_Year_Max | O1: Discounts_5%_Min | P1: Discounts_6%_Min | Q1: Facebook_Instagram_Impressions | R1: Facebook_Instagram_Spends | S1: YouTube_Impressions | T1: YouTube_Spends | U1: YouTube_FB_Impressions | V1: YouTube_FB_Spends | W1: Google_Search_Clicks | X1: Google_Search_Spends | Y1: Google_Organic_Search | Z1: Display_Impressions | AA1: Display_Spends | AB1: OOH_Screen_Spends | AC1: OOH_Screen_GRPs | AD1: OOH_Retail_Spends | AE1: OOH_Retail_GRPs | AF1: OOH_Cinema_Spends | AG1: OOH_Cinema_GRPs | AH1: Supremo_GRPs | AI1: Te_Club_GRPs | AJ1: Lipton_GRPs | AK1: Competitor_GRPs | AL1: Supremo_Spends | AM1: Te_Club_Spends | AN1: Lipton_Spends | AO1: Competitor_Spends | AP1: Inflation | AQ1: Temperature | AR1: Unployement_Index | AS1: GDP | AT1: Concumer_Trust_Index | AU1: Covid_Index | AV1: Winter_Solstice | AW1: Independence_Month | AX1: Christmas
A2: Chile | B2: FY_2022 | D2: 44440 | E2: 3309.968 | F2: 268358070 | G2: 81075.729 | H2: 15727.388 | I2: 75.557 | J2: 89.316 | K2: 57.873329 | L2: 77.15525 | M2: 0.14746772 | N2: 0.14746772 | O2: 0.14746772 | P2: 0.14746772 | Q2: 0 | R2: 0 | S2: 0 | T2: 0 | U2: 0 | V2: 0 | W2: 0 | X2: 0 | Y2: 0 | Z2: 0 | AA2: 0 | AB2: 0 | AC2: 0 | AD2: 0 | AE2: 0 | AF2: 0 | AG2: 0 | AH2: 468.2082 | AI2: 268.21275 | AJ2: 39.402786 | AK2: 775.82373 | AL2: 0 | AM2: 0 | AN2: 0 | AO2: 0 | AP2: 1.1778775 | AQ2: 12.1 | AR2: 8.4056112 | AS2: 16026.595 | AT2: 38.602875 | AU2: 58.1 | AV2: 0 | AW2: 1 | AX2: 0
A3: Chile | B3: FY_2022 | D3: 44470 | E3: 3028.298 | F3: 2.4899675e+08 | G3: 82223.331 | H3: 15195.163 | I3: 78.862 | J3: 91.333 | K3: 59.345455 | L3: 79.372791 | M3: 0.13540038 | N3: 0.13540038 | O3: 0.13540038 | P3: 0.13540038 | Q3: 0 | R3: 0 | S3: 0 | T3: 0 | U3: 0 | V3: 0 | W3: 0 | X3: 0 | Y3: 56 | Z3: 0 | AA3: 0 | AB3: 0 | AC3: 0 | AD3: 0 | AE3: 0 | AF3: 0 | AG3: 0 | AH3: 3.3770262 | AI3: 170.11277 | AJ3: 60.24991 | AK3: 233.7397 | AL3: 0 | AM3: 0 | AN3: 0 | AO3: 0 | AP3: 1.3410165 | AQ3: 14.8 | AR3: 8.0766005 | AS3: 16026.595 | AT3: 38.294675 | AU3: 37.7 | AV3: 0 | AW3: 0 | AX3: 0
A4: Chile | B4: FY_2022 | D4: 44501 | E4: 2525.561 | F4: 212570823 | G4: 84167.764 | H4: 15021.65 | I4: 78.118 | J4: 91.82 | K4: 59.635036 | L4: 80.879468 | M4: 0.11495417 | N4: 0.11495417 | O4: 0.11495417 | P4: 0.11495417 | Q4: 0 | R4: 0 | S4: 0 | T4: 0 | U4: 0 | V4: 0 | W4: 0 | X4: 0 | Y4: 96 | Z4: 0 | AA4: 0 | AB4: 0 | AC4: 0 | AD4: 0 | AE4: 0 | AF4: 0 | AG4: 0 | AH4: 581.69393 | AI4: 174.69948 | AJ4: 5.5167764 | AK4: 761.91019 | AL4: 0 | AM4: 0 | AN4: 0 | AO4: 0 | AP4: 0.49877719 | AQ4: 17.8 | AR4: 7.5276491 | AS4: 16026.595 | AT4: 34.230895 | AU4: 32.2 | AV4: 0 | AW4: 0 | AX4: 0
A5: Chile | B5: FY_2022 | D5: 44531 | E5: 2741.46 | F5: 260712553 | G5: 95099.893 | H5: 14951.082 | I5: 77.146 | J5: 91.677 | K5: 59.45317 | L5: 80.035332 | M5: 0 | N5: 0 | O5: 0 | P5: 0 | Q5: 0 | R5: 0 | S5: 0 | T5: 0 | U5: 0 | V5: 0 | W5: 0 | X5: 0 | Y5: 107 | Z5: 0 | AA5: 0 | AB5: 0 | AC5: 0 | AD5: 0 | AE5: 0 | AF5: 0 | AG5: 0 | AH5: 43.972823 | AI5: 179.24994 | AJ5: 10.022854 | AK5: 233.24562 | AL5: 0 | AM5: 0 | AN5: 0 | AO5: 0 | AP5: 0.78140216 | AQ5: 20 | AR5: 7.1898934 | AS5: 16026.595 | AT5: 33.701885 | AU5: 31.6 | AV5: 0 | AW5: 0 | AX5: 1
A6: Chile | B6: FY_2022 | D6: 44562 | E6: 2120.791 | F6: 178952366 | G6: 84380.01 | H6: 15075.673 | I6: 76.95 | J6: 89.609 | K6: 59.753445 | L6: 78.478416 | M6: 0.11272235 | N6: 0.11272235 | O6: 0.11272235 | P6: 0.11272235 | Q6: 0 | R6: 0 | S6: 0 | T6: 0 | U6: 0 | V6: 0 | W6: 0 | X6: 0 | Y6: 104 | Z6: 0 | AA6: 0 | AB6: 0 | AC6: 0 | AD6: 0 | AE6: 0 | AF6: 0 | AG6: 0 | AH6: 16.11189 | AI6: 0 | AJ6: 0 | AK6: 16.11189 | AL6: 4270269.5 | AM6: 0 | AN6: 0 | AO6: 4270269.5 | AP6: 1.2011129 | AQ6: 21.4 | AR6: 7.2714648 | AS6: 15268.746 | AT6: 34.95089 | AU6: 29.9 | AV6: 0 | AW6: 0 | AX6: 0
A7: Chile | B7: FY_2022 | D7: 44593 | E7: 2025.474 | F7: 176413263 | G7: 87097.274 | H7: 15329.93 | I7: 77.934 | J7: 89.951 | K7: 58.502907 | L7: 78.67244 | M7: 0.084149611 | N7: 0.084149611 | O7: 0.084149611 | P7: 0.084149611 | Q7: 0 | R7: 0 | S7: 0 | T7: 0 | U7: 0 | V7: 0 | W7: 0 | X7: 0 | Y7: 110 | Z7: 0 | AA7: 0 | AB7: 0 | AC7: 0 | AD7: 0 | AE7: 0 | AF7: 0 | AG7: 0 | AH7: 2.624368 | AI7: 0 | AJ7: 0 | AK7: 2.624368 | AL7: 33047.972 | AM7: 0 | AN7: 0 | AO7: 33047.972 | AP7: 0.28933382 | AQ7: 20.7 | AR7: 7.4985219 | AS7: 15268.746 | AT7: 35.472745 | AU7: 29.4 | AV7: 0 | AW7: 0 | AX7: 0
A8: Chile | B8: FY_2022 | D8: 44621 | E8: 2782.846 | F8: 253028625 | G8: 90924.408 | H8: 15728.361 | I8: 76.572 | J8: 90.073 | K8: 60 | L8: 79.395653 | M8: 0 | N8: 0.043906306 | O8: 0 | P8: 0 | Q8: 0 | R8: 0 | S8: 0 | T8: 0 | U8: 0 | V8: 0 | W8: 0 | X8: 0 | Y8: 122 | Z8: 0 | AA8: 0 | AB8: 0 | AC8: 0 | AD8: 0 | AE8: 0 | AF8: 0 | AG8: 0 | AH8: 0 | AI8: 0 | AJ8: 0 | AK8: 0 | AL8: 0 | AM8: 0 | AN8: 0 | AO8: 0 | AP8: 1.8545071 | AQ8: 18.9 | AR8: 7.7978652 | AS8: 15268.746 | AT8: 33.09346 | AU8: 29 | AV8: 0 | AW8: 0 | AX8: 0
A9: Chile | B9: FY_2022 | D9: 44652 | E9: 2487.264 | F9: 225519775 | G9: 90669.818 | H9: 15970.924 | I9: 74.961 | J9: 89.114 | K9: 61.594203 | L9: 77.175024 | M9: 0 | N9: 0.046583386 | O9: 0 | P9: 0 | Q9: 0 | R9: 0 | S9: 0 | T9: 0 | U9: 0 | V9: 0 | W9: 0 | X9: 0 | Y9: 141 | Z9: 0 | AA9: 0 | AB9: 0 | AC9: 0 | AD9: 0 | AE9: 0 | AF9: 0 | AG9: 0 | AH9: 0 | AI9: 0 | AJ9: 0 | AK9: 0 | AL9: 0 | AM9: 0 | AN9: 0 | AO9: 0 | AP9: 1.3982786 | AQ9: 15 | AR9: 7.7474932 | AS9: 15268.746 | AT9: 31.40742 | AU9: 27 | AV9: 0 | AW9: 0 | AX9: 0
A10: Chile | B10: FY_2022 | D10: 44682 | E10: 3227.268 | F10: 289506908 | G10: 89706.497 | H10: 16601.22 | I10: 77.554 | J10: 91.267 | K10: 62.807525 | L10: 78.787091 | M10: 0 | N10: 0.056712956 | O10: 0.056712956 | P10: 0 | Q10: 0 | R10: 0 | S10: 0 | T10: 0 | U10: 0 | V10: 0 | W10: 0 | X10: 0 | Y10: 222 | Z10: 0 | AA10: 0 | AB10: 0 | AC10: 0 | AD10: 0 | AE10: 0 | AF10: 0 | AG10: 0 | AH10: 0 | AI10: 0 | AJ10: 0 | AK10: 0 | AL10: 0 | AM10: 0 | AN10: 0 | AO10: 0 | AP10: 1.1988546 | AQ10: 11.5 | AR10: 7.8039798 | AS10: 15268.746 | AT10: 29.804635 | AU10: 27.1 | AV10: 0 | AW10: 0 | AX10: 0
A11: Chile | B11: FY_2022 | D11: 44713 | E11: 3720.315 | F11: 348664012 | G11: 93718.949 | H11: 16463.369 | I11: 76.74 | J11: 90.72 | K11: 70.404624 | L11: 82.993615 | M11: 0 | N11: 0.014520984 | O11: 0 | P11: 0 | Q11: 0 | R11: 0 | S11: 0 | T11: 0 | U11: 0 | V11: 0 | W11: 0 | X11: 0 | Y11: 187 | Z11: 0 | AA11: 0 | AB11: 0 | AC11: 0 | AD11: 0 | AE11: 0 | AF11: 0 | AG11: 0 | AH11: 0 | AI11: 95.603473 | AJ11: 0 | AK11: 95.603473 | AL11: 0 | AM11: 0 | AN11: 0 | AO11: 0 | AP11: 0.9326304 | AQ11: 8.8 | AR11: 7.8114738 | AS11: 15268.746 | AT11: 29.377175 | AU11: 27 | AV11: 1 | AW11: 0 | AX11: 0
A12: Chile | B12: FY_2022 | D12: 44743 | E12: 2943.439 | F12: 272636324 | G12: 92625.097 | H12: 16669.438 | I12: 76.757 | J12: 89.425 | K12: 72.170151 | L12: 82.864963 | M12: 0 | N12: 0.026023121 | O12: 0 | P12: 0 | Q12: 0 | R12: 0 | S12: 0 | T12: 0 | U12: 0 | V12: 0 | W12: 0 | X12: 0 | Y12: 189 | Z12: 0 | AA12: 0 | AB12: 0 | AC12: 0 | AD12: 0 | AE12: 0 | AF12: 0 | AG12: 0 | AH12: 812.98696 | AI12: 143.05752 | AJ12: 0 | AK12: 956.04448 | AL12: 1.1708773e+08 | AM12: 0 | AN12: 0 | AO12: 1.1708773e+08 | AP12: 1.3747565 | AQ12: 8.2 | AR12: 7.9188115 | AS12: 15268.746 | AT12: 26.919255 | AU12: 27 | AV12: 0 | AW12: 0 | AX12: 0
A13: Chile | B13: FY_2022 | D13: 44774 | E13: 2856.853 | F13: 250400968 | G13: 87649.231 | H13: 17071.247 | I13: 76.034 | J13: 89.675 | K13: 71.305595 | L13: 80.801766 | M13: 0.07834564 | N13: 0.07834564 | O13: 0.07834564 | P13: 0.07834564 | Q13: 0 | R13: 0 | S13: 0 | T13: 0 | U13: 0 | V13: 0 | W13: 0 | X13: 0 | Y13: 169 | Z13: 0 | AA13: 0 | AB13: 0 | AC13: 0 | AD13: 0 | AE13: 0 | AF13: 0 | AG13: 0 | AH13: 584.78638 | AI13: 151.19719 | AJ13: 44.969406 | AK13: 780.95297 | AL13: 1.0962042e+08 | AM13: 0 | AN13: 0 | AO13: 1.0962042e+08 | AP13: 1.2109226 | AQ13: 9.7 | AR13: 7.9293998 | AS13: 15268.746 | AT13: 26.222545 | AU13: 26.9 | AV13: 0 | AW13: 0 | AX13: 0
... A22: Chile | B22: FY_2023 | D22: 45047 | E22: 2729.991 | F22: 253735489 | G22: 92943.709 | H22: 18840.959 | I22: 75.503 | J22: 88.625 | K22: 71.685879 | L22: 78.929354 | M22: 0.075631959 | N22: 0.075631959 | O22: 0.075631959 | P22: 0.075631959 | Q22: 0 | R22: 0 | S22: 0 | T22: 0 | U22: 0 | V22: 0 | W22: 0 | X22: 0 | Y22: 225 | Z22: 0 | AA22: 0 | AB22: 0 | AC22: 0 | AD22: 0 | AE22: 0 | AF22: 0 | AG22: 0 | AH22: 1.6524268 | AI22: 52.323665 | AJ22: 0 | AK22: 53.976092 | AL22: 318745.27 | AM22: 911880 | AN22: 0 | AO22: 1230625.3 | AP22: 0.32152854 | AQ22: 11.5 | AR22: 8.5247377 | AS22: 16832.888 | AT22: 29.283433 | AU22: 0 | AV22: 0 | AW22: 0 | AX22: 0
A23: Chile | B23: FY_2023 | C23: 2023 Campaign | D23: 45078 | E23: 3845.519 | F23: 349632031 | G23: 90919.335 | H23: 18679.786 | I23: 76.621 | J23: 87.597 | K23: 74.425287 | L23: 80.69032 | M23: 0.095765292 | N23: 0.095765292 | O23: 0.095765292 | P23: 0.095765292 | Q23: 22690032 | R23: 9834237 | S23: 6130482 | T23: 10478488 | U23: 28820514 | V23: 20312725 | W23: 16340 | X23: 2420275 | Y23: 222 | Z23: 1194909 | AA23: 7700000 | AB23: 26962828 | AC23: 272.21157 | AD23: 5052632 | AE23: 51.010409 | AF23: 0 | AG23: 0 | AH23: 435.1711 | AI23: 164.08155 | AJ23: 72.71106 | AK23: 671.96371 | AL23: 82233589 | AM23: 14458294 | AN23: 14112405 | AO23: 1.1080429e+08 | AP23: -0.43174433 | AQ23: 8.8 | AR23: 8.5275847 | AS23: 16832.888 | AT23: 29.414292 | AU23: 0 | AV23: 1 | AW23: 0 | AX23: 0
A24: Chile | B24: FY_2023 | C24: 2023 Campaign | D24: 45108 | E24: 3143.177 | F24: 280942518 | G24: 89381.705 | H24: 18925.095 | I24: 77.26 | J24: 88.472 | K24: 77.992831 | L24: 81.382939 | M24: 0.11105773 | N24: 0.11105773 | O24: 0.11105773 | P24: 0.11105773 | Q24: 27844032 | R24: 7815954 | S24: 4602267 | T24: 8528999 | U24: 32446299 | V24: 16344953 | W24: 32735 | X24: 2257577 | Y24: 323 | Z24: 1460318 | AA24: 5765930 | AB24: 14661064 | AC24: 148.01531 | AD24: 5518796.1 | AE24: 55.716712 | AF24: 28109065 | AG24: 80 | AH24: 370.38775 | AI24: 369.0422 | AJ24: 132.59826 | AK24: 872.02821 | AL24: 50374619 | AM24: 37212824 | AN24: 30330317 | AO24: 1.1791776e+08 | AP24: 0.11949614 | AQ24: 8.2 | AR24: 8.772214 | AS24: 16832.888 | AT24: 29.911715 | AU24: 0 | AV24: 0 | AW24: 0 | AX24: 0
A25: Chile | B25: FY_2023 | C25: 2023 Campaign | D25: 45139 | E25: 2766.826 | F25: 259483176 | G25: 93783.699 | H25: 18915.858 | I25: 75.728 | J25: 86.072 | K25: 89.008621 | L25: 88.029149 | M25: 0 | N25: 0.067277872 | O25: 0.067277872 | P25: 0.067277872 | Q25: 13093405 | R25: 4838705 | S25: 3936908 | T25: 8579511 | U25: 17030313 | V25: 13418216 | W25: 11260 | X25: 2334401 | Y25: 204 | Z25: 877715 | AA25: 4908888 | AB25: 3951030.7 | AC25: 39.888855 | AD25: 7954658.4 | AE25: 80.30871 | AF25: 0 | AG25: 0 | AH25: 14.811962 | AI25: 688.49309 | AJ25: 12.527611 | AK25: 715.83267 | AL25: 775072.6 | AM25: 90192422 | AN25: 642561.35 | AO25: 91610056 | AP25: 0.11787766 | AQ25: 9.7 | AR25: 8.9956513 | AS25: 16832.888 | AT25: 29.701405 | AU25: 0 | AV25: 0 | AW25: 0 | AX25: 0
A26: Chile | B26: FY_2024 | C26: 2023 Campaign | D26: 45170 | E26: 3379.2 | F26: 314390273 | G26: 93036.894 | H26: 19391.709 | I26: 76.478 | J26: 85.097 | K26: 84.147042 | L26: 84.447313 | M26: 0 | N26: 0.054584152 | O26: 0.054584152 | P26: 0 | Q26: 0 | R26: 0 | S26: 0 | T26: 0 | U26: 0 | V26: 0 | W26: 0 | X26: 0 | Y26: 211 | Z26: 0 | AA26: 0 | AB26: 0 | AC26: 0 | AD26: 1173913 | AE26: 11.851602 | AF26: 0 | AG26: 0 | AH26: 18.559029 | AI26: 183.50756 | AJ26: 1.5644068 | AK26: 203.63099 | AL26: 685153.26 | AM26: 14082944 | AN26: 0 | AO26: 14768097 | AP26: 0.63557056 | AQ26: 12.1 | AR26: 8.9130086 | AS26: 16832.888 | AT26: 30.16597 | AU26: 0 | AV26: 0 | AW26: 1 | AX26: 0
A27: Chile | B27: FY_2024 | C27: 2023 Campaign | D27: 45200 | E27: 2507.896 | F27: 2.3526709e+08 | G27: 93810.545 | H27: 18725.549 | I27: 78.486 | J27: 86.551 | K27: 90.732759 | L27: 89.673684 | M27: 0 | N27: 0.046722519 | O27: 0 | P27: 0 | Q27: 0 | R27: 0 | S27: 0 | T27: 0 | U27: 0 | V27: 0 | W27: 0 | X27: 0 | Y27: 222 | Z27: 0 | AA27: 0 | AB27: 0 | AC27: 0 | AD27: 0 | AE27: 0 | AF27: 0 | AG27: 0 | AH27: 231.12174 | AI27: 244.59652 | AJ27: 0 | AK27: 475.71825 | AL27: 95017350 | AM27: 26099958 | AN27: 0 | AO27: 1.2111731e+08 | AP27: 0.29292643 | AQ27: 14.8 | AR27: 8.8864691 | AS27: 16832.888 | AT27: 31.556535 | AU27: 0 | AV27: 0 | AW27: 0 | AX27: 0
A28: Chile | B28: FY_2024 | D28: 45231 | E28: 2223.818 | F28: 2.1504176e+08 | G28: 96699.351 | H28: 18875.669 | I28: 77.63 | J28: 86.32 | K28: 90.45911 | L28: 89.434417 | M28: 0 | N28: 0.017367251 | O28: 0 | P28: 0 | Q28: 0 | R28: 0 | S28: 0 | T28: 0 | U28: 0 | V28: 0 | W28: 0 | X28: 0 | Y28: 173 | Z28: 0 | AA28: 0 | AB28: 0 | AC28: 0 | AD28: 0 | AE28: 0 | AF28: 0 | AG28: 0 | AH28: 108.97724 | AI28: 253.36196 | AJ28: 0 | AK28: 362.3392 | AL28: 34672576 | AM28: 34127658 | AN28: 0 | AO28: 68800234 | AP28: 0.74525502 | AQ28: 17.8 | AR28: 8.7324121 | AS28: 16832.888 | AT28: 33.022065 | AU28: 0 | AV28: 0 | AW28: 0 | AX28: 0
A29: Chile | B29: FY_2024 | D29: 45261 | E29: 2936.438 | F29: 2.6970627e+08 | G29: 91848.106 | H29: 19578.523 | I29: 77.312 | J29: 88.424 | K29: 90.598291 | L29: 89.962712 | M29: 0 | N29: 0.066664296 | O29: 0.066664296 | P29: 0.066664296 | Q29: 0 | R29: 0 | S29: 0 | T29: 0 | U29: 0 | V29: 0 | W29: 0 | X29: 0 | Y29: 191 | Z29: 0 | AA29: 0 | AB29: 0 | AC29: 0 | AD29: 0 | AE29: 0 | AF29: 0 | AG29: 0 | AH29: 0 | AI29: 153.07651 | AJ29: 0 | AK29: 153.07651 | AL29: 0 | AM29: 24482274 | AN29: 0 | AO29: 24482274 | AP29: -0.52574812 | AQ29: 20 | AR29: 8.4756393 | AS29: 16832.888 | AT29: 31.835285 | AU29: 0 | AV29: 0 | AW29: 0 | AX29: 1
A30: Chile | B30: FY_2024 | D30: 45292 | E30: 1650.241 | F30: 157193389 | G30: 95254.808 | H30: 19794.411 | I30: 77.138 | J30: 88.563 | K30: 85.724432 | L30: 86.771129 | M30: 0 | N30: 0.032046308 | O30: 0 | P30: 0 | Q30: 0 | R30: 0 | S30: 0 | T30: 0 | U30: 0 | V30: 0 | W30: 0 | X30: 0 | Y30: 143 | Z30: 0 | AA30: 0 | AB30: 0 | AC30: 0 | AD30: 0 | AE30: 0 | AF30: 0 | AG30: 0 | AH30: 183.29923 | AI30: 59.288106 | AJ30: 0 | AK30: 242.58733 | AL30: 13930063 | AM30: 0 | AN30: 0 | AO30: 13930063 | AP30: 0.66854217 | AQ30: 21.4 | AR30: 8.4356311 | AS30: 0 | AT30: 32.58169 | AU30: 0 | AV30: 0 | AW30: 0 | AX30: 0
A31: Chile | B31: FY_2024 | D31: 45323 | E31: 1507.908 | F31: 1.4687321e+08 | G31: 97401.97 | H31: 18880.053 | I31: 77.153 | J31: 88.054 | K31: 85.653409 | L31: 86.506584 | M31: 0 | N31: 0.010227426 | O31: 0 | P31: 0 | Q31: 0 | R31: 0 | S31: 0 | T31: 0 | U31: 0 | V31: 0 | W31: 0 | X31: 0 | Y31: 182 | Z31: 0 | AA31: 0 | AB31: 0 | AC31: 0 | AD31: 0 | AE31: 0 | AF31: 0 | AG31: 0 | AH31: 186.68655 | AI31: 41.287169 | AJ31: 0 | AK31: 227.97372 | AL31: 18086456 | AM31: 0 | AN31: 0 | AO31: 18086456 | AP31: 0.58775 | AQ31: 20.7 | AR31: 8.5042567 | AS31: 0 | AT31: 33.31309 | AU31: 0 | AV31: 0 | AW31: 0 | AX31: 0
A32: Chile | B32: FY_2024 | D32: 45352 | E32: 2850.96 | F32: 2.5956273e+08 | G32: 91043.974 | H32: 19268.877 | I32: 78.924 | J32: 89.37 | K32: 88.125 | L32: 88.620528 | M32: 0.074835668 | N32: 0.074835668 | O32: 0.074835668 | P32: 0.074835668 | Q32: 0 | R32: 0 | S32: 0 | T32: 0 | U32: 0 | V32: 0 | W32: 0 | X32: 0 | Y32: 220 | Z32: 0 | AA32: 0 | AB32: 0 | AC32: 0 | AD32: 0 | AE32: 0 | AF32: 0 | AG32: 0 | AH32: 131.4637 | AI32: 152.35423 | AJ32: 0 | AK32: 283.81794 | AL32: 13837747 | AM32: 25101847 | AN32: 0 | AO32: 38939594 | AP32: 0.37822707 | AQ32: 18.9 | AR32: 8.677778 | AS32: 0 | AT32: 33.54474 | AU32: 0 | AV32: 0 | AW32: 0 | AX32: 0
A33: Chile | B33: FY_2024 | C33: 2024 Campaign | D33: 45383 | E33: 2431.171 | F33: 2.3924773e+08 | G33: 98408.435 | H33: 20256.024 | I33: 79.179 | J33: 89.558 | K33: 88.896797 | L33: 89.187412 | M33: 0 | N33: 0 | O33: 0 | P33: 0 | Q33: 9853942.3 | R33: 4856684.9 | S33: 3076005 | T33: 5955932 | U33: 12929947 | V33: 10812617 | W33: 0 | X33: 0 | Y33: 227 | Z33: 0 | AA33: 0 | AB33: 0 | AC33: 0 | AD33: 0 | AE33: 0 | AF33: 0 | AG33: 0 | AH33: 165.98282 | AI33: 121.59797 | AJ33: 0 | AK33: 287.58079 | AL33: 13897411 | AM33: 18676023 | AN33: 0 | AO33: 32573434 | AP33: 0.52741101 | AQ33: 15 | AR33: 8.5237837 | AS33: 0 | AT33: 33.17006 | AU33: 0 | AV33: 0 | AW33: 0 | AX33: 0
A34: Chile | B34: FY_2024 | C34: 2024 Campaign | D34: 45413 | E34: 3068.697 | F34: 3.0036678e+08 | G34: 97880.884 | H34: 20531.041 | I34: 78.751 | J34: 89.748 | K34: 88.888889 | L34: 89.314672 | M34: 0 | N34: 0.0053608311 | O34: 0 | P34: 0 | Q34: 51393559 | R34: 19430727 | S34: 12391156 | T34: 25129055 | U34: 63784715 | V34: 44559782 | W34: 21903 | X34: 3417594 | Y34: 296 | Z34: 0 | AA34: 0 | AB34: 0 | AC34: 0 | AD34: 5391304.3 | AE34: 22.686275 | AF34: 0 | AG34: 0 | AH34: 317.17378 | AI34: 193.64375 | AJ34: 0 | AK34: 510.81753 | AL34: 45659048 | AM34: 23334329 | AN34: 0 | AO34: 68993377 | AP34: 0.26348546 | AQ34: 11.5 | AR34: 8.3128804 | AS34: 0 | AT34: 31.339375 | AU34: 0 | AV34: 0 | AW34: 0 | AX34: 0
A35: Chile | B35: FY_2024 | C35: 2024 Campaign | D35: 45444 | E35: 4060.66 | F35: 392423423 | G35: 96640.306 | H35: 20024.545 | I35: 82.038 | J35: 89.674 | K35: 91.628702 | L35: 90.828237 | M35: 0 | N35: 0.01796725 | O35: 0 | P35: 0 | Q35: 47341557 | R35: 19099018 | S35: 10039021 | T35: 20699998 | U35: 57380577 | V35: 39799015 | W35: 11517 | X35: 1946017.9 | Y35: 319 | Z35: 0 | AA35: 0 | AB35: 0 | AC35: 0 | AD35: 10108696 | AE35: 26.176471 | AF35: 0 | AG35: 0 | AH35: 599.95514 | AI35: 53.497099 | AJ35: 0 | AK35: 653.45224 | AL35: 1.0071255e+08 | AM35: 0 | AN35: 0 | AO35: 1.0071255e+08 | AP35: -0.089436455 | AQ35: 8.8 | AR35: 8.348178 | AS35: 0 | AT35: 32.144585 | AU35: 0 | AV35: 1 | AW35: 0 | AX35: 0
A36: Chile | B36: FY_2024 | C36: 2024 Campaign | D36: 45474 | E36: 3410.391 | F36: 3.2770994e+08 | G36: 96091.605 | H36: 20448.668 | I36: 85.571 | J36: 90.383 | K36: 92.258523 | L36: 91.559227 | M36: 0 | N36: 0.023543002 | O36: 0 | P36: 0 | Q36: 50246461 | R36: 27612878 | S36: 7005896 | T36: 14414016 | U36: 57252357 | V36: 42026894 | W36: 7899 | X36: 1505519 | Y36: 358 | Z36: 0 | AA36: 0 | AB36: 0 | AC36: 0 | AD36: 10445652 | AE36: 27.04902 | AF36: 0 | AG36: 0 | AH36: 325.56935 | AI36: 405.56192 | AJ36: 0 | AK36: 731.13127 | AL36: 30760088 | AM36: 84491927 | AN36: 0 | AO36: 1.1525201e+08 | AP36: 0.73651447 | AQ36: 8.2 | AR36: 8.6841758 | AS36: 0 | AT36: 32.18748 | AU36: 0 | AV36: 0 | AW36: 0 | AX36: 0
A37: Chile | B37: FY_2024 | C37: 2024 Campaign | D37: 45505 | E37: 3635.57 | F37: 3.4750422e+08 | G37: 95584.521 | H37: 20112.215 | I37: 84.265 | J37: 92.957 | K37: 80.836237 | L37: 86.002013 | M37: 0 | N37: 0.028695853 | O37: 0 | P37: 0 | Q37: 0 | R37: 0 | S37: 0 | T37: 0 | U37: 0 | V37: 0 | W37: 0 | X37: 0 | Y37: 287 | Z37: 0 | AA37: 0 | AB37: 0 | AC37: 0 | AD37: 5054347.8 | AE37: 13.088235 | AF37: 0 | AG37: 0 | AH37: 283.37272 | AI37: 329.5796 | AJ37: 0 | AK37: 612.95232 | AL37: 22479018 | AM37: 63161317 | AN37: 0 | AO37: 85640335 | AP37: 0.25549723 | AQ37: 9.7 | AR37: 8.9013223 | AS37: 0 | AT37: 32.76822 | AU37: 0 | AV37: 0 | AW37: 0 | AX37: 0
A38: Chile | B38: FY_2025 | C38: 2024 Campaign | D38: 45536 | E38: 4210.684 | F38: 402318259 | G38: 95547.008 | H38: 20692.397 | I38: 83.384 | J38: 92.72 | K38: 74.986103 | L38: 82.794983 | M38: 0 | N38: 0 | O38: 0 | P38: 0 | Q38: 0 | R38: 0 | S38: 0 | T38: 0 | U38: 0 | V38: 0 | W38: 0 | X38: 0 | Y38: 308 | Z38: 0 | AA38: 0 | AB38: 0 | AC38: 0 | AD38: 0 | AE38: 0 | AF38: 0 | AG38: 0 | AH38: 378.41224 | AI38: 151.70855 | AJ38: 0 | AK38: 530.12079 | AL38: 71858077 | AM38: 25948334 | AN38: 0 | AO38: 97806411 | AP38: 0.087768664 | AQ38: 12.1 | AR38: 8.7423149 | AS38: 0 | AT38: 31.836135 | AU38: 0 | AV38: 0 | AW38: 1 | AX38: 0
D40: Total | E40: =SUM(E2:E37) -> 98716.457 | F40: =SUM(F2:F37) -> 9.0676918e+09 | G40: =SUM(G2:G37) -> 3314070.7 | H40: =SUM(H2:H37) -> 644444.2 | I40: =SUM(I2:I37) -> 2795.395 | J40: =SUM(J2:J37) -> 3219.217 | K40: =SUM(K2:K37) -> 2682.5314 | L40: =SUM(L2:L37) -> 2975.0569 | ... AX40: =SUM(AX2:AX37) -> 3
D41: FY_2022 | E41: =SUMIFS(E$2:E$38,$B$2:$B$38,$D41) -> 33769.537 | F41: =SUMIFS(F$2:F$38,$B$2:$B$38,$D41) -> 2.9857604e+09 | G41: =AVERAGEIFS(G$2:G$38,$B$2:$B$38,$D41) -> 88278.167 | H41: =SUMIFS(H$2:H$38,$B$2:$B$38,$D41) -> 189805.44 | I41: =SUMIFS(I$2:I$38,$B$2:$B$38,$D41) -> 923.185 | J41: =SUMIFS(J$2:J$38,$B$2:$B$38,$D41) -> 1083.98 | K41: =SUMIFS(K$2:K$38,$B$2:$B$38,$D41) -> 752.84544 | L41: =SUMIFS(L$2:L$38,$B$2:$B$38,$D41) -> 956.61181 | M41: =SUMIFS(M$2:M$38,$B$2:$B$38,$D41) -> 0.67303986 | N41: =SUMIFS(N$2:N$38,$B$2:$B$38,$D41) -> 0.86078662 | O41: =SUMIFS(O$2:O$38,$B$2:$B$38,$D41) -> 0.72975282 | ... AX41: =SUMIFS(AX$2:AX$38,$B$2:$B$38,$D41) -> 1
D42: FY_2023 | E42: =SUMIFS(E$2:E$38,$B$2:$B$38,$D42) -> 31283.97 | F42: =SUMIFS(F$2:F$38,$B$2:$B$38,$D42) -> 2876644521 | G42: =AVERAGEIFS(G$2:G$38,$B$2:$B$38,$D42) -> 92585.942 | H42: =SUMIFS(H$2:H$38,$B$2:$B$38,$D42) -> 218751.47 | I42: =SUMIFS(I$2:I$38,$B$2:$B$38,$D42) -> 919.285 | J42: =SUMIFS(J$2:J$38,$B$2:$B$38,$D42) -> 1070.538 | K42: =SUMIFS(K$2:K$38,$B$2:$B$38,$D42) -> 871.73677 | L42: =SUMIFS(L$2:L$38,$B$2:$B$38,$D42) -> 956.13713 | M42: =SUMIFS(M$2:M$38,$B$2:$B$38,$D42) -> 0.74388444 | N42: =SUMIFS(N$2:N$38,$B$2:$B$38,$D42) -> 0.95028145 | O42: =SUMIFS(O$2:O$38,$B$2:$B$38,$D42) -> 0.87619135 | ... AX42: =SUMIFS(AX$2:AX$38,$B$2:$B$38,$D42) -> 1
D43: FY_2024 | E43: =SUMIFS(E$2:E$38,$B$2:$B$38,$D43) -> 33662.95 | F43: =SUMIFS(F$2:F$38,$B$2:$B$38,$D43) -> 3.2052868e+09 | G43: =AVERAGEIFS(G$2:G$38,$B$2:$B$38,$D43) -> 95308.45 | H43: =SUMIFS(H$2:H$38,$B$2:$B$38,$D43) -> 235887.28 | I43: =SUMIFS(I$2:I$38,$B$2:$B$38,$D43) -> 952.925 | J43: =SUMIFS(J$2:J$38,$B$2:$B$38,$D43) -> 1064.699 | K43: =SUMIFS(K$2:K$38,$B$2:$B$38,$D43) -> 1057.9492 | L43: =SUMIFS(L$2:L$38,$B$2:$B$38,$D43) -> 1062.3079 | M43: =SUMIFS(M$2:M$38,$B$2:$B$38,$D43) -> 0.074835668 | N43: =SUMIFS(N$2:N$38,$B$2:$B$38,$D43) -> 0.37801456 | O43: =SUMIFS(O$2:O$38,$B$2:$B$38,$D43) -> 0.19608412 | ... AX43: =SUMIFS(AX$2:AX$38,$B$2:$B$38,$D43) -> 1
Q46: Facebook_Instagram_Impressions | R46: Facebook_Instagram_Spends | S46: YouTube_Impressions | T46: YouTube_Spends | U46: YouTube_FB_Impressions | V46: YouTube_FB_Spends | W46: Google_Search_Clicks | X46: Google_Search_Spends | Y46: Google_Organic_Search | Z46: Display_Impressions | AA46: Display_Spends | AB46: OOH_Screen_Spends | AC46: OOH_Screen_GRPs | AD46: OOH_Retail_Spends | AE46: OOH_Retail_GRPs
E47: 2023 Campaign | F47: =SUMIFS(F$2:F$38,$C$2:$C$38,$E47) -> 1.4397151e+09 | G47: =SUMIFS(G$2:G$38,$C$2:$C$38,$E47) -> 460932.18 | H47: =SUMIFS(H$2:H$38,$C$2:$C$38,$E47) -> 94637.996 | I47: =SUMIFS(I$2:I$38,$C$2:$C$38,$E47) -> 384.573 | J47: =SUMIFS(J$2:J$38,$C$2:$C$38,$E47) -> 433.789 | K47: =SUMIFS(K$2:K$38,$C$2:$C$38,$E47) -> 416.30654 | L47: =SUMIFS(L$2:L$38,$C$2:$C$38,$E47) -> 424.2234 | M47: =SUMIFS(M$2:M$38,$C$2:$C$38,$E47) -> 0.20682302 | ... AX47: =SUMIFS(AX$2:AX$38,$C$2:$C$38,$E47) -> 0
E48: 2024 Campaign | F48: =SUMIFS(F$2:F$38,$C$2:$C$38,$E48) -> 2.0095704e+09 | G48: =SUMIFS(G$2:G$38,$C$2:$C$38,$E48) -> 580152.76 | H48: =SUMIFS(H$2:H$38,$C$2:$C$38,$E48) -> 122064.89 | I48: =SUMIFS(I$2:I$38,$C$2:$C$38,$E48) -> 493.188 | J48: =SUMIFS(J$2:J$38,$C$2:$C$38,$E48) -> 545.04 | K48: =SUMIFS(K$2:K$38,$C$2:$C$38,$E48) -> 517.49525 | L48: =SUMIFS(L$2:L$38,$C$2:$C$38,$E48) -> 529.68654 | M48: =SUMIFS(M$2:M$38,$C$2:$C$38,$E48) -> 0 | ... AX48: =SUMIFS(AX$2:AX$38,$C$2:$C$38,$E48) -> 0
P52: 2023 AVG Spend | Q52: =AVERAGE(Q23:Q25) -> 21209156 | R52: =AVERAGE(R23:R25) -> 7496298.7 | S52: =AVERAGE(S23:S25) -> 4889885.7 | T52: =AVERAGE(T23:T25) -> 9195666 | U52: =AVERAGE(U23:U25) -> 26099042 | V52: =AVERAGE(V23:V25) -> 16691965 | W52: =AVERAGE(W23:W25) -> 20111.667 | X52: =AVERAGE(X23:X25) -> 2337417.7 | Z52: =AVERAGE(Z23:Z25) -> 1177647.3 | AA52: =AVERAGE(AA23:AA25) -> 6124939.3 | AB52: =AVERAGE(AB23:AB25) -> 15191641 | AC52: =AVERAGE(AC23:AC25) -> 153.37191 | AD52: =AVERAGE(AD23:AD26) -> 4924999.9 | AE52: =AVERAGE(AE23:AE25) -> 62.345277 | AF52: =AVERAGE(AF23:AF25) -> 9369688.3 | AG52: =AVERAGE(AG23:AG25) -> 26.666667
P53: 2024 AVG Spend | Q53: =AVERAGE(Q33:Q36) -> 39708880 | R53: =AVERAGE(R33:R36) -> 17749827 | S53: =AVERAGE(S33:S36) -> 8128019.5 | T53: =AVERAGE(T33:T36) -> 16549750 | U53: =AVERAGE(U33:U36) -> 47836899 | V53: =AVERAGE(V33:V36) -> 34299577 | W53: =AVERAGE(W34:W36) -> 13773 | X53: =AVERAGE(X34:X36) -> 2289710.3 | Z53: =AVERAGE(Z33:Z36) -> 0 | AA53: =AVERAGE(AA33:AA36) -> 0 | AB53: =AVERAGE(AB33:AB36) -> 0 | AC53: =AVERAGE(AC33:AC36) -> 0 | AD53: =AVERAGE(AD34:AD37) -> 7750000 | AE53: =AVERAGE(AE34:AE37) -> 22.25

Sheet SPLIT ADSTOCK
L1: 0.65 | M1: 0.5 | N1: 0.5 | O1: 0.7 | P1: 0.7 | Q1: 0.65 | R1: 0.65 | AU1: Direct Contribution | BB1: Lagged Contribution
D2: Period | E2: YouTube_FB_Impressions | F2: Google_Search_Clicks | G2: Display_Impressions | H2: OOH_Screen_GRPs | I2: OOH_Retail_GRPs | J2: Facebook_Instagram_Impressions | K2: YouTube_Impressions | L2: YT+FB Adstocked Activity | M2: Paid Search Adstocked Act | N2: Online Banner Adstocked Act | O2: OOH Large Format Adstocked Act | P2: OOH Retail Adstocked Act | Q2: FB Adstocked Act | R2: YT Adstocked Act | S2: YT+FB Adstocked Effect | T2: Paid Search Adstocked Effect | U2: Online Banner Adstocked Effect | V2: OOH Large Format Adstocked Effect | W2: OOH Retail Adstocked Effect | X2: FB Adstocked Effect | Y2: YT Adstocked Effect | Z2: YT+FB Adstocked Direct Contrib % | AA2: Paid Search Adstocked Direct Contrib % | AB2: Online Banner Adstocked Direct Contrib % | AC2: OOH Large Format Adstocked Direct Contrib % | AD2: OOH Retail Adstocked Direct Contrib % | AE2: FB Adstocked Direct Contrib % | AF2: YT Adstocked Direct Contrib % | AG2: YT+FB Adstocked Laged Contrib % | AH2: Paid Search Adstocked Laged Contrib % | AI2: Online Banner Adstocked Laged Contrib % | AJ2: OOH Large Format Adstocked Laged Contrib % | AK2: OOH Retail Adstocked Laged Contrib % | AL2: FB Adstocked Laged Contrib % | AM2: YT Adstocked Laged Contrib % | AN2: YouTube_FB_Impressions | AO2: Google_Search_Clicks | AP2: Display_Impressions | AQ2: OOH_Screen_GRPs | AR2: OOH_Retail_GRPs | AS2: Facebook_Instagram_Impressions | AT2: Youtube_Impressions | AU2: YouTube + Facebook + Instagram | AV2: Paid Search | AW2: Online Banners | AX2: OOH Large Format | AY2: OOH Retail | AZ2: Facebook + Instagram | BA2: YouTube | BB2: YouTube + Facebook + Instagram | BC2: Paid Search | BD2: Online Banners | BE2: OOH Large Format | BF2: OOH Retail | BG2: Facebook + Instagram | BH2: YouTube
AU3: =_xlfn.TEXTJOIN(" - ",TRUE,AU2,$AU$1) -> YouTube + Facebook + Instagram - Direct Contribution | AV3: =_xlfn.TEXTJOIN(" - ",TRUE,AV2,$AU$1) -> Paid Search - Direct Contribution | AW3: =_xlfn.TEXTJOIN(" - ",TRUE,AW2,$AU$1) -> Online Banners - Direct Contribution | AX3: =_xlfn.TEXTJOIN(" - ",TRUE,AX2,$AU$1) -> OOH Large Format - Direct Contribution | AY3: =_xlfn.TEXTJOIN(" - ",TRUE,AY2,$AU$1) -> OOH Retail - Direct Contribution | AZ3: =_xlfn.TEXTJOIN(" - ",TRUE,AZ2,$AU$1) -> Facebook + Instagram - Direct Contribution | BA3: =_xlfn.TEXTJOIN(" - ",TRUE,BA2,$AU$1) -> YouTube - Direct Contribution | BB3: =_xlfn.TEXTJOIN(" - ",TRUE,BB2,$BB$1) -> YouTube + Facebook + Instagram - Lagged Contribution | BC3: =_xlfn.TEXTJOIN(" - ",TRUE,BC2,$BB$1) -> Paid Search - Lagged Contribution | BD3: =_xlfn.TEXTJOIN(" - ",TRUE,BD2,$BB$1) -> Online Banners - Lagged Contribution | BE3: =_xlfn.TEXTJOIN(" - ",TRUE,BE2,$BB$1) -> OOH Large Format - Lagged Contribution | BF3: =_xlfn.TEXTJOIN(" - ",TRUE,BF2,$BB$1) -> OOH Retail - Lagged Contribution | BG3: =_xlfn.TEXTJOIN(" - ",TRUE,BG2,$BB$1) -> Facebook + Instagram - Lagged Contribution | BH3: =_xlfn.TEXTJOIN(" - ",TRUE,BH2,$BB$1) -> YouTube - Lagged Contribution
A4: FY_2022 | D4: 44440 | E4: 0 | F4: 0 | G4: 0 | H4: 0 | I4: 0 | J4: 0 | K4: 0 | L4: =L3*L$1+E4 -> 0 | M4: =M3*M$1+F4 -> 0 | N4: =N3*N$1+G4 -> 0 | O4: =O3*O$1+H4 -> 0 | P4: =P3*P$1+I4 -> 0 | Q4: =Q3*Q$1+J4 -> 0 | R4: =R3*R$1+K4 -> 0 | S4: =L4-E4 -> 0 | T4: =M4-F4 -> 0 | U4: =N4-G4 -> 0 | V4: =O4-H4 -> 0 | W4: =P4-I4 -> 0 | X4: =Q4-J4 -> 0 | Y4: =R4-K4 -> 0 | Z4: =IFERROR(E4/L4,0) -> 0 | AA4: =IFERROR(F4/M4,0) -> 0 | AB4: =IFERROR(G4/N4,0) -> 0 | AC4: =IFERROR(H4/O4,0) -> 0 | AD4: =IFERROR(I4/P4,0) -> 0 | AE4: =IFERROR(J4/Q4,0) -> 0 | AF4: =IFERROR(K4/R4,0) -> 0 | AG4: =IFERROR(S4/L4,0) -> 0 | AH4: =IFERROR(T4/M4,0) -> 0 | AI4: =IFERROR(U4/N4,0) -> 0 | AJ4: =IFERROR(V4/O4,0) -> 0 | AK4: =IFERROR(W4/P4,0) -> 0 | AL4: =IFERROR(X4/Q4,0) -> 0 | AM4: =IFERROR(Y4/R4,0) -> 0 | AN4: 4.531819e-08 | AO4: 2.4060811e-08 | AP4: 3.5499081e-08 | AQ4: 2.0910124e-08 | AR4: 3.6233767e-09 | AS4: 2.220931e-08 | AT4: 2.310888e-08 | AU4: =AN4*Z4 -> 0 | AV4: =AO4*AA4 -> 0 | AW4: =AP4*AB4 -> 0 | AX4: =AQ4*AC4 -> 0 | AY4: =AR4*AD4 -> 0 | AZ4: =AS4*AE4 -> 0 | BA4: =AT4*AF4 -> 0 | BB4: =AN4*AG4 -> 0 | BC4: =AO4*AH4 -> 0 | BD4: =AP4*AI4 -> 0 | BE4: =AQ4*AJ4 -> 0 | BF4: =AR4*AK4 -> 0 | BG4: =AS4*AL4 -> 0 | BH4: =AT4*AM4 -> 0
A5: FY_2022 | D5: 44470 | E5: 0 | F5: 0 | G5: 0 | H5: 0 | I5: 0 | J5: 0 | K5: 0 | L5: =L4*L$1+E5 -> 0 | M5: =M4*M$1+F5 -> 0 | N5: =N4*N$1+G5 -> 0 | O5: =O4*O$1+H5 -> 0 | P5: =P4*P$1+I5 -> 0 | Q5: =Q4*Q$1+J5 -> 0 | R5: =R4*R$1+K5 -> 0 | S5: =L5-E5 -> 0 | T5: =M5-F5 -> 0 | U5: =N5-G5 -> 0 | V5: =O5-H5 -> 0 | W5: =P5-I5 -> 0 | X5: =Q5-J5 -> 0 | Y5: =R5-K5 -> 0 | Z5: =IFERROR(E5/L5,0) -> 0 | AA5: =IFERROR(F5/M5,0) -> 0 | AB5: =IFERROR(G5/N5,0) -> 0 | AC5: =IFERROR(H5/O5,0) -> 0 | AD5: =IFERROR(I5/P5,0) -> 0 | AE5: =IFERROR(J5/Q5,0) -> 0 | AF5: =IFERROR(K5/R5,0) -> 0 | AG5: =IFERROR(S5/L5,0) -> 0 | AH5: =IFERROR(T5/M5,0) -> 0 | AI5: =IFERROR(U5/N5,0) -> 0 | AJ5: =IFERROR(V5/O5,0) -> 0 | AK5: =IFERROR(W5/P5,0) -> 0 | AL5: =IFERROR(X5/Q5,0) -> 0 | AM5: =IFERROR(Y5/R5,0) -> 0 | AN5: 4.4237049e-08 | AO5: 2.3685674e-08 | AP5: 3.5473091e-08 | AQ5: 2.2251739e-08 | AR5: 3.9543283e-09 | AS5: 2.176848e-08 | AT5: 2.2468569e-08 | AU5: =AN5*Z5 -> 0 | AV5: =AO5*AA5 -> 0 | AW5: =AP5*AB5 -> 0 | AX5: =AQ5*AC5 -> 0 | AY5: =AR5*AD5 -> 0 | AZ5: =AS5*AE5 -> 0 | BA5: =AT5*AF5 -> 0 | BB5: =AN5*AG5 -> 0 | BC5: =AO5*AH5 -> 0 | BD5: =AP5*AI5 -> 0 | BE5: =AQ5*AJ5 -> 0 | BF5: =AR5*AK5 -> 0 | BG5: =AS5*AL5 -> 0 | BH5: =AT5*AM5 -> 0
A6: FY_2022 | D6: 44501 | E6: 0 | F6: 0 | G6: 0 | H6: 0 | I6: 0 | J6: 0 | K6: 0 | L6: =L5*L$1+E6 -> 0 | M6: =M5*M$1+F6 -> 0 | N6: =N5*N$1+G6 -> 0 | O6: =O5*O$1+H6 -> 0 | P6: =P5*P$1+I6 -> 0 | Q6: =Q5*Q$1+J6 -> 0 | R6: =R5*R$1+K6 -> 0 | S6: =L6-E6 -> 0 | T6: =M6-F6 -> 0 | U6: =N6-G6 -> 0 | V6: =O6-H6 -> 0 | W6: =P6-I6 -> 0 | X6: =Q6-J6 -> 0 | Y6: =R6-K6 -> 0 | Z6: =IFERROR(E6/L6,0) -> 0 | AA6: =IFERROR(F6/M6,0) -> 0 | AB6: =IFERROR(G6/N6,0) -> 0 | AC6: =IFERROR(H6/O6,0) -> 0 | AD6: =IFERROR(I6/P6,0) -> 0 | AE6: =IFERROR(J6/Q6,0) -> 0 | AF6: =IFERROR(K6/R6,0) -> 0 | AG6: =IFERROR(S6/L6,0) -> 0 | AH6: =IFERROR(T6/M6,0) -> 0 | AI6: =IFERROR(U6/N6,0) -> 0 | AJ6: =IFERROR(V6/O6,0) -> 0 | AK6: =IFERROR(W6/P6,0) -> 0 | AL6: =IFERROR(X6/Q6,0) -> 0 | AM6: =IFERROR(Y6/R6,0) -> 0 | AN6: 4.3414245e-08 | AO6: 2.3657323e-08 | AP6: 3.5278081e-08 | AQ6: 2.3129084e-08 | AR6: 3.9226535e-09 | AS6: 2.145167e-08 | AT6: 2.1962576e-08 | AU6: =AN6*Z6 -> 0 | AV6: =AO6*AA6 -> 0 | AW6: =AP6*AB6 -> 0 | AX6: =AQ6*AC6 -> 0 | AY6: =AR6*AD6 -> 0 | AZ6: =AS6*AE6 -> 0 | BA6: =AT6*AF6 -> 0 | BB6: =AN6*AG6 -> 0 | BC6: =AO6*AH6 -> 0 | BD6: =AP6*AI6 -> 0 | BE6: =AQ6*AJ6 -> 0 | BF6: =AR6*AK6 -> 0 | BG6: =AS6*AL6 -> 0 | BH6: =AT6*AM6 -> 0
A7: FY_2022 | D7: 44531 | E7: 0 | F7: 0 | G7: 0 | H7: 0 | I7: 0 | J7: 0 | K7: 0 | L7: =L6*L$1+E7 -> 0 | M7: =M6*M$1+F7 -> 0 | N7: =N6*N$1+G7 -> 0 | O7: =O6*O$1+H7 -> 0 | P7: =P6*P$1+I7 -> 0 | Q7: =Q6*Q$1+J7 -> 0 | R7: =R6*R$1+K7 -> 0 | S7: =L7-E7 -> 0 | T7: =M7-F7 -> 0 | U7: =N7-G7 -> 0 | V7: =O7-H7 -> 0 | W7: =P7-I7 -> 0 | X7: =Q7-J7 -> 0 | Y7: =R7-K7 -> 0 | Z7: =IFERROR(E7/L7,0) -> 0 | AA7: =IFERROR(F7/M7,0) -> 0 | AB7: =IFERROR(G7/N7,0) -> 0 | AC7: =IFERROR(H7/O7,0) -> 0 | AD7: =IFERROR(I7/P7,0) -> 0 | AE7: =IFERROR(J7/Q7,0) -> 0 | AF7: =IFERROR(K7/R7,0) -> 0 | AG7: =IFERROR(S7/L7,0) -> 0 | AH7: =IFERROR(T7/M7,0) -> 0 | AI7: =IFERROR(U7/N7,0) -> 0 | AJ7: =IFERROR(V7/O7,0) -> 0 | AK7: =IFERROR(W7/P7,0) -> 0 | AL7: =IFERROR(X7/Q7,0) -> 0 | AM7: =IFERROR(Y7/R7,0) -> 0 | AN7: 4.2091654e-08 | AO7: 2.3005334e-08 | AP7: 3.5404535e-08 | AQ7: 2.4873794e-08 | AR7: 4.5340986e-09 | AS7: 2.0884306e-08 | AT7: 2.1207349e-08 | AU7: =AN7*Z7 -> 0 | AV7: =AO7*AA7 -> 0 | AW7: =AP7*AB7 -> 0 | AX7: =AQ7*AC7 -> 0 | AY7: =AR7*AD7 -> 0 | AZ7: =AS7*AE7 -> 0 | BA7: =AT7*AF7 -> 0 | BB7: =AN7*AG7 -> 0 | BC7: =AO7*AH7 -> 0 | BD7: =AP7*AI7 -> 0 | BE7: =AQ7*AJ7 -> 0 | BF7: =AR7*AK7 -> 0 | BG7: =AS7*AL7 -> 0 | BH7: =AT7*AM7 -> 0
A8: FY_2022 | D8: 44562 | E8: 0 | F8: 0 | G8: 0 | H8: 0 | I8: 0 | J8: 0 | K8: 0 | L8: =L7*L$1+E8 -> 0 | M8: =M7*M$1+F8 -> 0 | N8: =N7*N$1+G8 -> 0 | O8: =O7*O$1+H8 -> 0 | P8: =P7*P$1+I8 -> 0 | Q8: =Q7*Q$1+J8 -> 0 | R8: =R7*R$1+K8 -> 0 | S8: =L8-E8 -> 0 | T8: =M8-F8 -> 0 | U8: =N8-G8 -> 0 | V8: =O8-H8 -> 0 | W8: =P8-I8 -> 0 | X8: =Q8-J8 -> 0 | Y8: =R8-K8 -> 0 | Z8: =IFERROR(E8/L8,0) -> 0 | AA8: =IFERROR(F8/M8,0) -> 0 | AB8: =IFERROR(G8/N8,0) -> 0 | AC8: =IFERROR(H8/O8,0) -> 0 | AD8: =IFERROR(I8/P8,0) -> 0 | AE8: =IFERROR(J8/Q8,0) -> 0 | AF8: =IFERROR(K8/R8,0) -> 0 | AG8: =IFERROR(S8/L8,0) -> 0 | AH8: =IFERROR(T8/M8,0) -> 0 | AI8: =IFERROR(U8/N8,0) -> 0 | AJ8: =IFERROR(V8/O8,0) -> 0 | AK8: =IFERROR(W8/P8,0) -> 0 | AL8: =IFERROR(X8/Q8,0) -> 0 | AM8: =IFERROR(Y8/R8,0) -> 0 | AN8: 4.216859e-08 | AO8: 2.3638541e-08 | AP8: 3.4775597e-08 | AQ8: 2.4087149e-08 | AR8: 3.8383432e-09 | AS8: 2.1009584e-08 | AT8: 2.1159006e-08 | AU8: =AN8*Z8 -> 0 | AV8: =AO8*AA8 -> 0 | AW8: =AP8*AB8 -> 0 | AX8: =AQ8*AC8 -> 0 | AY8: =AR8*AD8 -> 0 | AZ8: =AS8*AE8 -> 0 | BA8: =AT8*AF8 -> 0 | BB8: =AN8*AG8 -> 0 | BC8: =AO8*AH8 -> 0 | BD8: =AP8*AI8 -> 0 | BE8: =AQ8*AJ8 -> 0 | BF8: =AR8*AK8 -> 0 | BG8: =AS8*AL8 -> 0 | BH8: =AT8*AM8 -> 0
A9: FY_2022 | D9: 44593 | E9: 0 | F9: 0 | G9: 0 | H9: 0 | I9: 0 | J9: 0 | K9: 0 | L9: =L8*L$1+E9 -> 0 | M9: =M8*M$1+F9 -> 0 | N9: =N8*N$1+G9 -> 0 | O9: =O8*O$1+H9 -> 0 | P9: =P8*P$1+I9 -> 0 | Q9: =Q8*Q$1+J9 -> 0 | R9: =R8*R$1+K9 -> 0 | S9: =L9-E9 -> 0 | T9: =M9-F9 -> 0 | U9: =N9-G9 -> 0 | V9: =O9-H9 -> 0 | W9: =P9-I9 -> 0 | X9: =Q9-J9 -> 0 | Y9: =R9-K9 -> 0 | Z9: =IFERROR(E9/L9,0) -> 0 | AA9: =IFERROR(F9/M9,0) -> 0 | AB9: =IFERROR(G9/N9,0) -> 0 | AC9: =IFERROR(H9/O9,0) -> 0 | AD9: =IFERROR(I9/P9,0) -> 0 | AE9: =IFERROR(J9/Q9,0) -> 0 | AF9: =IFERROR(K9/R9,0) -> 0 | AG9: =IFERROR(S9/L9,0) -> 0 | AH9: =IFERROR(T9/M9,0) -> 0 | AI9: =IFERROR(U9/N9,0) -> 0 | AJ9: =IFERROR(V9/O9,0) -> 0 | AK9: =IFERROR(W9/P9,0) -> 0 | AL9: =IFERROR(X9/Q9,0) -> 0 | AM9: =IFERROR(Y9/R9,0) -> 0 | AN9: 4.1765391e-08 | AO9: 2.3647195e-08 | AP9: 3.4416747e-08 | AQ9: 2.4321727e-08 | AR9: 3.7176595e-09 | AS9: 2.0895805e-08 | AT9: 2.0869586e-08 | AU9: =AN9*Z9 -> 0 | AV9: =AO9*AA9 -> 0 | AW9: =AP9*AB9 -> 0 | AX9: =AQ9*AC9 -> 0 | AY9: =AR9*AD9 -> 0 | AZ9: =AS9*AE9 -> 0 | BA9: =AT9*AF9 -> 0 | BB9: =AN9*AG9 -> 0 | BC9: =AO9*AH9 -> 0 | BD9: =AP9*AI9 -> 0 | BE9: =AQ9*AJ9 -> 0 | BF9: =AR9*AK9 -> 0 | BG9: =AS9*AL9 -> 0 | BH9: =AT9*AM9 -> 0
A10: FY_2022 | D10: 44621 | E10: 0 | F10: 0 | G10: 0 | H10: 0 | I10: 0 | J10: 0 | K10: 0 | L10: =L9*L$1+E10 -> 0 | M10: =M9*M$1+F10 -> 0 | N10: =N9*N$1+G10 -> 0 | O10: =O9*O$1+H10 -> 0 | P10: =P9*P$1+I10 -> 0 | Q10: =Q9*Q$1+J10 -> 0 | R10: =R9*R$1+K10 -> 0 | S10: =L10-E10 -> 0 | T10: =M10-F10 -> 0 | U10: =N10-G10 -> 0 | V10: =O10-H10 -> 0 | W10: =P10-I10 -> 0 | X10: =Q10-J10 -> 0 | Y10: =R10-K10 -> 0 | Z10: =IFERROR(E10/L10,0) -> 0 | AA10: =IFERROR(F10/M10,0) -> 0 | AB10: =IFERROR(G10/N10,0) -> 0 | AC10: =IFERROR(H10/O10,0) -> 0 | AD10: =IFERROR(I10/P10,0) -> 0 | AE10: =IFERROR(J10/Q10,0) -> 0 | AF10: =IFERROR(K10/R10,0) -> 0 | AG10: =IFERROR(S10/L10,0) -> 0 | AH10: =IFERROR(T10/M10,0) -> 0 | AI10: =IFERROR(U10/N10,0) -> 0 | AJ10: =IFERROR(V10/O10,0) -> 0 | AK10: =IFERROR(W10/P10,0) -> 0 | AL10: =IFERROR(X10/Q10,0) -> 0 | AM10: =IFERROR(Y10/R10,0) -> 0 | AN10: 4.0555644e-08 | AO10: 2.2296515e-08 | AP10: 3.4657263e-08 | AQ10: 2.6368881e-08 | AR10: 4.9411717e-09 | AS10: 2.0375985e-08 | AT10: 2.0179659e-08 | AU10: =AN10*Z10 -> 0 | AV10: =AO10*AA10 -> 0 | AW10: =AP10*AB10 -> 0 | AX10: =AQ10*AC10 -> 0 | AY10: =AR10*AD10 -> 0 | AZ10: =AS10*AE10 -> 0 | BA10: =AT10*AF10 -> 0 | BB10: =AN10*AG10 -> 0 | BC10: =AO10*AH10 -> 0 | BD10: =AP10*AI10 -> 0 | BE10: =AQ10*AJ10 -> 0 | BF10: =AR10*AK10 -> 0 | BG10: =AS10*AL10 -> 0 | BH10: =AT10*AM10 -> 0
A11: FY_2022 | D11: 44652 | E11: 0 | F11: 0 | G11: 0 | H11: 0 | I11: 0 | J11: 0 | K11: 0 | L11: =L10*L$1+E11 -> 0 | M11: =M10*M$1+F11 -> 0 | N11: =N10*N$1+G11 -> 0 | O11: =O10*O$1+H11 -> 0 | P11: =P10*P$1+I11 -> 0 | Q11: =Q10*Q$1+J11 -> 0 | R11: =R10*R$1+K11 -> 0 | S11: =L11-E11 -> 0 | T11: =M11-F11 -> 0 | U11: =N11-G11 -> 0 | V11: =O11-H11 -> 0 | W11: =P11-I11 -> 0 | X11: =Q11-J11 -> 0 | Y11: =R11-K11 -> 0 | Z11: =IFERROR(E11/L11,0) -> 0 | AA11: =IFERROR(F11/M11,0) -> 0 | AB11: =IFERROR(G11/N11,0) -> 0 | AC11: =IFERROR(H11/O11,0) -> 0 | AD11: =IFERROR(I11/P11,0) -> 0 | AE11: =IFERROR(J11/Q11,0) -> 0 | AF11: =IFERROR(K11/R11,0) -> 0 | AG11: =IFERROR(S11/L11,0) -> 0 | AH11: =IFERROR(T11/M11,0) -> 0 | AI11: =IFERROR(U11/N11,0) -> 0 | AJ11: =IFERROR(V11/O11,0) -> 0 | AK11: =IFERROR(W11/P11,0) -> 0 | AL11: =IFERROR(X11/Q11,0) -> 0 | AM11: =IFERROR(Y11/R11,0) -> 0 | AN11: 4.0245759e-08 | AO11: 2.1978655e-08 | AP11: 3.4332068e-08 | AQ11: 2.6549414e-08 | AR11: 5.1215194e-09 | AS11: 2.0305953e-08 | AT11: 1.9939807e-08 | AU11: =AN11*Z11 -> 0 | AV11: =AO11*AA11 -> 0 | AW11: =AP11*AB11 -> 0 | AX11: =AQ11*AC11 -> 0 | AY11: =AR11*AD11 -> 0 | AZ11: =AS11*AE11 -> 0 | BA11: =AT11*AF11 -> 0 | BB11: =AN11*AG11 -> 0 | BC11: =AO11*AH11 -> 0 | BD11: =AP11*AI11 -> 0 | BE11: =AQ11*AJ11 -> 0 | BF11: =AR11*AK11 -> 0 | BG11: =AS11*AL11 -> 0 | BH11: =AT11*AM11 -> 0
A12: FY_2022 | D12: 44682 | E12: 0 | F12: 0 | G12: 0 | H12: 0 | I12: 0 | J12: 0 | K12: 0 | L12: =L11*L$1+E12 -> 0 | M12: =M11*M$1+F12 -> 0 | N12: =N11*N$1+G12 -> 0 | O12: =O11*O$1+H12 -> 0 | P12: =P11*P$1+I12 -> 0 | Q12: =Q11*Q$1+J12 -> 0 | R12: =R11*R$1+K12 -> 0 | S12: =L12-E12 -> 0 | T12: =M12-F12 -> 0 | U12: =N12-G12 -> 0 | V12: =O12-H12 -> 0 | W12: =P12-I12 -> 0 | X12: =Q12-J12 -> 0 | Y12: =R12-K12 -> 0 | Z12: =IFERROR(E12/L12,0) -> 0 | AA12: =IFERROR(F12/M12,0) -> 0 | AB12: =IFERROR(G12/N12,0) -> 0 | AC12: =IFERROR(H12/O12,0) -> 0 | AD12: =IFERROR(I12/P12,0) -> 0 | AE12: =IFERROR(J12/Q12,0) -> 0 | AF12: =IFERROR(K12/R12,0) -> 0 | AG12: =IFERROR(S12/L12,0) -> 0 | AH12: =IFERROR(T12/M12,0) -> 0 | AI12: =IFERROR(U12/N12,0) -> 0 | AJ12: =IFERROR(V12/O12,0) -> 0 | AK12: =IFERROR(W12/P12,0) -> 0 | AL12: =IFERROR(X12/Q12,0) -> 0 | AM12: =IFERROR(Y12/R12,0) -> 0 | AN12: 3.9836385e-08 | AO12: 2.1548683e-08 | AP12: 3.4051022e-08 | AQ12: 2.6916924e-08 | AR12: 5.4112787e-09 | AS12: 2.0185099e-08 | AT12: 1.9651286e-08 | AU12: =AN12*Z12 -> 0 | AV12: =AO12*AA12 -> 0 | AW12: =AP12*AB12 -> 0 | AX12: =AQ12*AC12 -> 0 | AY12: =AR12*AD12 -> 0 | AZ12: =AS12*AE12 -> 0 | BA12: =AT12*AF12 -> 0 | BB12: =AN12*AG12 -> 0 | BC12: =AO12*AH12 -> 0 | BD12: =AP12*AI12 -> 0 | BE12: =AQ12*AJ12 -> 0 | BF12: =AR12*AK12 -> 0 | BG12: =AS12*AL12 -> 0 | BH12: =AT12*AM12 -> 0
A13: FY_2022 | D13: 44713 | E13: 0 | F13: 0 | G13: 0 | H13: 0 | I13: 0 | J13: 0 | K13: 0 | L13: =L12*L$1+E13 -> 0 | M13: =M12*M$1+F13 -> 0 | N13: =N12*N$1+G13 -> 0 | O13: =O12*O$1+H13 -> 0 | P13: =P12*P$1+I13 -> 0 | Q13: =Q12*Q$1+J13 -> 0 | R13: =R12*R$1+K13 -> 0 | S13: =L13-E13 -> 0 | T13: =M13-F13 -> 0 | U13: =N13-G13 -> 0 | V13: =O13-H13 -> 0 | W13: =P13-I13 -> 0 | X13: =Q13-J13 -> 0 | Y13: =R13-K13 -> 0 | Z13: =IFERROR(E13/L13,0) -> 0 | AA13: =IFERROR(F13/M13,0) -> 0 | AB13: =IFERROR(G13/N13,0) -> 0 | AC13: =IFERROR(H13/O13,0) -> 0 | AD13: =IFERROR(I13/P13,0) -> 0 | AE13: =IFERROR(J13/Q13,0) -> 0 | AF13: =IFERROR(K13/R13,0) -> 0 | AG13: =IFERROR(S13/L13,0) -> 0 | AH13: =IFERROR(T13/M13,0) -> 0 | AI13: =IFERROR(U13/N13,0) -> 0 | AJ13: =IFERROR(V13/O13,0) -> 0 | AK13: =IFERROR(W13/P13,0) -> 0 | AL13: =IFERROR(X13/Q13,0) -> 0 | AM13: =IFERROR(Y13/R13,0) -> 0 | AN13: 3.9499785e-08 | AO13: 2.1176057e-08 | AP13: 3.3759914e-08 | AQ13: 2.7183723e-08 | AR13: 5.6534115e-09 | AS13: 2.010045e-08 | AT13: 1.9399335e-08 | AU13: =AN13*Z13 -> 0 | AV13: =AO13*AA13 -> 0 | AW13: =AP13*AB13 -> 0 | AX13: =AQ13*AC13 -> 0 | AY13: =AR13*AD13 -> 0 | AZ13: =AS13*AE13 -> 0 | BA13: =AT13*AF13 -> 0 | BB13: =AN13*AG13 -> 0 | BC13: =AO13*AH13 -> 0 | BD13: =AP13*AI13 -> 0 | BE13: =AQ13*AJ13 -> 0 | BF13: =AR13*AK13 -> 0 | BG13: =AS13*AL13 -> 0 | BH13: =AT13*AM13 -> 0
A14: FY_2022 | D14: 44743 | E14: 0 | F14: 0 | G14: 0 | H14: 0 | I14: 0 | J14: 0 | K14: 0 | L14: =L13*L$1+E14 -> 0 | M14: =M13*M$1+F14 -> 0 | N14: =N13*N$1+G14 -> 0 | O14: =O13*O$1+H14 -> 0 | P14: =P13*P$1+I14 -> 0 | Q14: =Q13*Q$1+J14 -> 0 | R14: =R13*R$1+K14 -> 0 | S14: =L14-E14 -> 0 | T14: =M14-F14 -> 0 | U14: =N14-G14 -> 0 | V14: =O14-H14 -> 0 | W14: =P14-I14 -> 0 | X14: =Q14-J14 -> 0 | Y14: =R14-K14 -> 0 | Z14: =IFERROR(E14/L14,0) -> 0 | AA14: =IFERROR(F14/M14,0) -> 0 | AB14: =IFERROR(G14/N14,0) -> 0 | AC14: =IFERROR(H14/O14,0) -> 0 | AD14: =IFERROR(I14/P14,0) -> 0 | AE14: =IFERROR(J14/Q14,0) -> 0 | AF14: =IFERROR(K14/R14,0) -> 0 | AG14: =IFERROR(S14/L14,0) -> 0 | AH14: =IFERROR(T14/M14,0) -> 0 | AI14: =IFERROR(U14/N14,0) -> 0 | AJ14: =IFERROR(V14/O14,0) -> 0 | AK14: =IFERROR(W14/P14,0) -> 0 | AL14: =IFERROR(X14/Q14,0) -> 0 | AM14: =IFERROR(Y14/R14,0) -> 0 | AN14: 3.9339584e-08 | AO14: 2.1027383e-08 | AP14: 3.3380169e-08 | AQ14: 2.706525e-08 | AR14: 5.6287082e-09 | AS14: 2.010545e-08 | AT14: 1.9234134e-08 | AU14: =AN14*Z14 -> 0 | AV14: =AO14*AA14 -> 0 | AW14: =AP14*AB14 -> 0 | AX14: =AQ14*AC14 -> 0 | AY14: =AR14*AD14 -> 0 | AZ14: =AS14*AE14 -> 0 | BA14: =AT14*AF14 -> 0 | BB14: =AN14*AG14 -> 0 | BC14: =AO14*AH14 -> 0 | BD14: =AP14*AI14 -> 0 | BE14: =AQ14*AJ14 -> 0 | BF14: =AR14*AK14 -> 0 | BG14: =AS14*AL14 -> 0 | BH14: =AT14*AM14 -> 0
A15: FY_2022 | D15: 44774 | E15: 0 | F15: 0 | G15: 0 | H15: 0 | I15: 0 | J15: 0 | K15: 0 | L15: =L14*L$1+E15 -> 0 | M15: =M14*M$1+F15 -> 0 | N15: =N14*N$1+G15 -> 0 | O15: =O14*O$1+H15 -> 0 | P15: =P14*P$1+I15 -> 0 | Q15: =Q14*Q$1+J15 -> 0 | R15: =R14*R$1+K15 -> 0 | S15: =L15-E15 -> 0 | T15: =M15-F15 -> 0 | U15: =N15-G15 -> 0 | V15: =O15-H15 -> 0 | W15: =P15-I15 -> 0 | X15: =Q15-J15 -> 0 | Y15: =R15-K15 -> 0 | Z15: =IFERROR(E15/L15,0) -> 0 | AA15: =IFERROR(F15/M15,0) -> 0 | AB15: =IFERROR(G15/N15,0) -> 0 | AC15: =IFERROR(H15/O15,0) -> 0 | AD15: =IFERROR(I15/P15,0) -> 0 | AE15: =IFERROR(J15/Q15,0) -> 0 | AF15: =IFERROR(K15/R15,0) -> 0 | AG15: =IFERROR(S15/L15,0) -> 0 | AH15: =IFERROR(T15/M15,0) -> 0 | AI15: =IFERROR(U15/N15,0) -> 0 | AJ15: =IFERROR(V15/O15,0) -> 0 | AK15: =IFERROR(W15/P15,0) -> 0 | AL15: =IFERROR(X15/Q15,0) -> 0 | AM15: =IFERROR(Y15/R15,0) -> 0 | AN15: 3.9434355e-08 | AO15: 2.1271468e-08 | AP15: 3.2746273e-08 | AQ15: 2.6559694e-08 | AR15: 5.2285826e-09 | AS15: 2.0241614e-08 | AT15: 1.919274e-08 | AU15: =AN15*Z15 -> 0 | AV15: =AO15*AA15 -> 0 | AW15: =AP15*AB15 -> 0 | AX15: =AQ15*AC15 -> 0 | AY15: =AR15*AD15 -> 0 | AZ15: =AS15*AE15 -> 0 | BA15: =AT15*AF15 -> 0 | BB15: =AN15*AG15 -> 0 | BC15: =AO15*AH15 -> 0 | BD15: =AP15*AI15 -> 0 | BE15: =AQ15*AJ15 -> 0 | BF15: =AR15*AK15 -> 0 | BG15: =AS15*AL15 -> 0 | BH15: =AT15*AM15 -> 0
... A24: FY_2023 | D24: 45047 | E24: 0 | F24: 0 | G24: 0 | H24: 0 | I24: 0 | J24: 0 | K24: 0 | L24: =L23*L$1+E24 -> 0 | M24: =M23*M$1+F24 -> 0 | N24: =N23*N$1+G24 -> 0 | O24: =O23*O$1+H24 -> 0 | P24: =P23*P$1+I24 -> 0 | Q24: =Q23*Q$1+J24 -> 0 | R24: =R23*R$1+K24 -> 0 | S24: =L24-E24 -> 0 | T24: =M24-F24 -> 0 | U24: =N24-G24 -> 0 | V24: =O24-H24 -> 0 | W24: =P24-I24 -> 0 | X24: =Q24-J24 -> 0 | Y24: =R24-K24 -> 0 | Z24: =IFERROR(E24/L24,0) -> 0 | AA24: =IFERROR(F24/M24,0) -> 0 | AB24: =IFERROR(G24/N24,0) -> 0 | AC24: =IFERROR(H24/O24,0) -> 0 | AD24: =IFERROR(I24/P24,0) -> 0 | AE24: =IFERROR(J24/Q24,0) -> 0 | AF24: =IFERROR(K24/R24,0) -> 0 | AG24: =IFERROR(S24/L24,0) -> 0 | AH24: =IFERROR(T24/M24,0) -> 0 | AI24: =IFERROR(U24/N24,0) -> 0 | AJ24: =IFERROR(V24/O24,0) -> 0 | AK24: =IFERROR(W24/P24,0) -> 0 | AL24: =IFERROR(X24/Q24,0) -> 0 | AM24: =IFERROR(Y24/R24,0) -> 0 | AN24: 3.9197159e-08 | AO24: 1.7443191e-08 | AP24: 2.901106e-08 | AQ24: 2.2857843e-08 | AR24: 8.1988582e-09 | AS24: 2.0954624e-08 | AT24: 1.8242535e-08 | AU24: =AN24*Z24 -> 0 | AV24: =AO24*AA24 -> 0 | AW24: =AP24*AB24 -> 0 | AX24: =AQ24*AC24 -> 0 | AY24: =AR24*AD24 -> 0 | AZ24: =AS24*AE24 -> 0 | BA24: =AT24*AF24 -> 0 | BB24: =AN24*AG24 -> 0 | BC24: =AO24*AH24 -> 0 | BD24: =AP24*AI24 -> 0 | BE24: =AQ24*AJ24 -> 0 | BF24: =AR24*AK24 -> 0 | BG24: =AS24*AL24 -> 0 | BH24: =AT24*AM24 -> 0
A25: FY_2023 | B25: 2023 Campaign | C25: 2023 | D25: 45078 | E25: 28820514 | F25: 16340 | G25: 1194909 | H25: 272.21157 | I25: 51.010409 | J25: 22690032 | K25: 6130482 | L25: =L24*L$1+E25 -> 28820514 | M25: =M24*M$1+F25 -> 16340 | N25: =N24*N$1+G25 -> 1194909 | O25: =O24*O$1+H25 -> 272.21157 | P25: =P24*P$1+I25 -> 51.010409 | Q25: =Q24*Q$1+J25 -> 22690032 | R25: =R24*R$1+K25 -> 6130482 | S25: =L25-E25 -> 0 | T25: =M25-F25 -> 0 | U25: =N25-G25 -> 0 | V25: =O25-H25 -> 0 | W25: =P25-I25 -> 0 | X25: =Q25-J25 -> 0 | Y25: =R25-K25 -> 0 | Z25: =IFERROR(E25/L25,0) -> 1 | AA25: =IFERROR(F25/M25,0) -> 1 | AB25: =IFERROR(G25/N25,0) -> 1 | AC25: =IFERROR(H25/O25,0) -> 1 | AD25: =IFERROR(I25/P25,0) -> 1 | AE25: =IFERROR(J25/Q25,0) -> 1 | AF25: =IFERROR(K25/R25,0) -> 1 | AG25: =IFERROR(S25/L25,0) -> 0 | AH25: =IFERROR(T25/M25,0) -> 0 | AI25: =IFERROR(U25/N25,0) -> 0 | AJ25: =IFERROR(V25/O25,0) -> 0 | AK25: =IFERROR(W25/P25,0) -> 0 | AL25: =IFERROR(X25/Q25,0) -> 0 | AM25: =IFERROR(Y25/R25,0) -> 0 | AN25: 388.39792 | AO25: 30.654477 | AP25: 261.2774 | AQ25: 224.1308 | AR25: 73.835672 | AS25: 207.6296 | AT25: 180.76832 | AU25: =AN25*Z25 -> 388.39792 | AV25: =AO25*AA25 -> 30.654477 | AW25: =AP25*AB25 -> 261.2774 | AX25: =AQ25*AC25 -> 224.1308 | AY25: =AR25*AD25 -> 73.835672 | AZ25: =AS25*AE25 -> 207.6296 | BA25: =AT25*AF25 -> 180.76832 | BB25: =AN25*AG25 -> 0 | BC25: =AO25*AH25 -> 0 | BD25: =AP25*AI25 -> 0 | BE25: =AQ25*AJ25 -> 0 | BF25: =AR25*AK25 -> 0 | BG25: =AS25*AL25 -> 0 | BH25: =AT25*AM25 -> 0
A26: FY_2023 | B26: 2023 Campaign | C26: 2023 | D26: 45108 | E26: 32446299 | F26: 32735 | G26: 1460318 | H26: 148.01531 | I26: 55.716712 | J26: 27844032 | K26: 4602267 | L26: =L25*L$1+E26 -> 51179633 | M26: =M25*M$1+F26 -> 40905 | N26: =N25*N$1+G26 -> 2057772.5 | O26: =O25*O$1+H26 -> 338.5634 | P26: =P25*P$1+I26 -> 91.423998 | Q26: =Q25*Q$1+J26 -> 42592553 | R26: =R25*R$1+K26 -> 8587080.3 | S26: =L26-E26 -> 18733334 | T26: =M26-F26 -> 8170 | U26: =N26-G26 -> 597454.5 | V26: =O26-H26 -> 190.5481 | W26: =P26-I26 -> 35.707286 | X26: =Q26-J26 -> 14748521 | Y26: =R26-K26 -> 3984813.3 | Z26: =IFERROR(E26/L26,0) -> 0.63396896 | AA26: =IFERROR(F26/M26,0) -> 0.80026892 | AB26: =IFERROR(G26/N26,0) -> 0.7096596 | AC26: =IFERROR(H26/O26,0) -> 0.43718637 | AD26: =IFERROR(I26/P26,0) -> 0.60943202 | AE26: =IFERROR(J26/Q26,0) -> 0.65373006 | AF26: =IFERROR(K26/R26,0) -> 0.53595248 | AG26: =IFERROR(S26/L26,0) -> 0.36603104 | AH26: =IFERROR(T26/M26,0) -> 0.19973108 | AI26: =IFERROR(U26/N26,0) -> 0.2903404 | AJ26: =IFERROR(V26/O26,0) -> 0.56281363 | AK26: =IFERROR(W26/P26,0) -> 0.39056798 | AL26: =IFERROR(X26/Q26,0) -> 0.34626994 | AM26: =IFERROR(Y26/R26,0) -> 0.46404752 | AN26: 396.7406 | AO26: 174.83294 | AP26: 271.09594 | AQ26: 218.48179 | AR26: 74.603108 | AS26: 214.18533 | AT26: 182.55526 | AU26: =AN26*Z26 -> 251.52123 | AV26: =AO26*AA26 -> 139.91337 | AW26: =AP26*AB26 -> 192.38584 | AX26: =AQ26*AC26 -> 95.517259 | AY26: =AR26*AD26 -> 45.465523 | AZ26: =AS26*AE26 -> 140.01939 | BA26: =AT26*AF26 -> 97.840946 | BB26: =AN26*AG26 -> 145.21937 | BC26: =AO26*AH26 -> 34.919574 | BD26: =AP26*AI26 -> 78.710105 | BE26: =AQ26*AJ26 -> 122.96453 | BF26: =AR26*AK26 -> 29.137585 | BG26: =AS26*AL26 -> 74.165943 | BH26: =AT26*AM26 -> 84.714316
A27: FY_2023 | B27: 2023 Campaign | C27: 2023 | D27: 45139 | E27: 17030313 | F27: 11260 | G27: 877715 | H27: 39.888855 | I27: 80.30871 | J27: 13093405 | K27: 3936908 | L27: =L26*L$1+E27 -> 50297075 | M27: =M26*M$1+F27 -> 31712.5 | N27: =N26*N$1+G27 -> 1906601.2 | O27: =O26*O$1+H27 -> 276.88324 | P27: =P26*P$1+I27 -> 144.30551 | Q27: =Q26*Q$1+J27 -> 40778564 | R27: =R26*R$1+K27 -> 9518510.2 | S27: =L27-E27 -> 33266762 | T27: =M27-F27 -> 20452.5 | U27: =N27-G27 -> 1028886.2 | V27: =O27-H27 -> 236.99438 | W27: =P27-I27 -> 63.996798 | X27: =Q27-J27 -> 27685159 | Y27: =R27-K27 -> 5581602.2 | Z27: =IFERROR(E27/L27,0) -> 0.3385945 | AA27: =IFERROR(F27/M27,0) -> 0.35506504 | AB27: =IFERROR(G27/N27,0) -> 0.46035583 | AC27: =IFERROR(H27/O27,0) -> 0.14406381 | AD27: =IFERROR(I27/P27,0) -> 0.55651867 | AE27: =IFERROR(J27/Q27,0) -> 0.32108548 | AF27: =IFERROR(K27/R27,0) -> 0.41360548 | AG27: =IFERROR(S27/L27,0) -> 0.6614055 | AH27: =IFERROR(T27/M27,0) -> 0.64493496 | AI27: =IFERROR(U27/N27,0) -> 0.53964417 | AJ27: =IFERROR(V27/O27,0) -> 0.85593619 | AK27: =IFERROR(W27/P27,0) -> 0.44348133 | AL27: =IFERROR(X27/Q27,0) -> 0.67891452 | AM27: =IFERROR(Y27/R27,0) -> 0.58639452 | AN27: 394.7645 | AO27: 152.22997 | AP27: 269.10112 | AQ27: 215.84954 | AR27: 81.693021 | AS27: 214.46276 | AT27: 180.30175 | AU27: =AN27*Z27 -> 133.66509 | AV27: =AO27*AA27 -> 54.051541 | AW27: =AP27*AB27 -> 123.88227 | AX27: =AQ27*AC27 -> 31.096108 | AY27: =AR27*AD27 -> 45.463691 | AZ27: =AS27*AE27 -> 68.860877 | BA27: =AT27*AF27 -> 74.573791 | BB27: =AN27*AG27 -> 261.09941 | BC27: =AO27*AH27 -> 98.178432 | BD27: =AP27*AI27 -> 145.21885 | BE27: =AQ27*AJ27 -> 184.75343 | BF27: =AR27*AK27 -> 36.229329 | BG27: =AS27*AL27 -> 145.60188 | BH27: =AT27*AM27 -> 105.72796
A28: FY_2024 | B28: 2023 Campaign | C28: 2023 | D28: 45170 | E28: 0 | F28: 0 | G28: 0 | H28: 0 | I28: 11.851602 | J28: 0 | K28: 0 | L28: =L27*L$1+E28 -> 32693098 | M28: =M27*M$1+F28 -> 15856.25 | N28: =N27*N$1+G28 -> 953300.62 | O28: =O27*O$1+H28 -> 193.81827 | P28: =P27*P$1+I28 -> 112.86546 | Q28: =Q27*Q$1+J28 -> 26506067 | R28: =R27*R$1+K28 -> 6187031.6 | S28: =L28-E28 -> 32693098 | T28: =M28-F28 -> 15856.25 | U28: =N28-G28 -> 953300.62 | V28: =O28-H28 -> 193.81827 | W28: =P28-I28 -> 101.01386 | X28: =Q28-J28 -> 26506067 | Y28: =R28-K28 -> 6187031.6 | Z28: =IFERROR(E28/L28,0) -> 0 | AA28: =IFERROR(F28/M28,0) -> 0 | AB28: =IFERROR(G28/N28,0) -> 0 | AC28: =IFERROR(H28/O28,0) -> 0 | AD28: =IFERROR(I28/P28,0) -> 0.10500646 | AE28: =IFERROR(J28/Q28,0) -> 0 | AF28: =IFERROR(K28/R28,0) -> 0 | AG28: =IFERROR(S28/L28,0) -> 1 | AH28: =IFERROR(T28/M28,0) -> 1 | AI28: =IFERROR(U28/N28,0) -> 1 | AJ28: =IFERROR(V28/O28,0) -> 1 | AK28: =IFERROR(W28/P28,0) -> 0.89499354 | AL28: =IFERROR(X28/Q28,0) -> 1 | AM28: =IFERROR(Y28/R28,0) -> 1 | AN28: 388.26951 | AO28: 25.14559 | AP28: 221.07722 | AQ28: 213.14819 | AR28: 93.950802 | AS28: 212.6813 | AT28: 175.58821 | AU28: =AN28*Z28 -> 0 | AV28: =AO28*AA28 -> 0 | AW28: =AP28*AB28 -> 0 | AX28: =AQ28*AC28 -> 0 | AY28: =AR28*AD28 -> 9.8654407 | AZ28: =AS28*AE28 -> 0 | BA28: =AT28*AF28 -> 0 | BB28: =AN28*AG28 -> 388.26951 | BC28: =AO28*AH28 -> 25.14559 | BD28: =AP28*AI28 -> 221.07722 | BE28: =AQ28*AJ28 -> 213.14819 | BF28: =AR28*AK28 -> 84.085361 | BG28: =AS28*AL28 -> 212.6813 | BH28: =AT28*AM28 -> 175.58821
A29: FY_2024 | B29: 2023 Campaign | C29: 2023 | D29: 45200 | E29: 0 | F29: 0 | G29: 0 | H29: 0 | I29: 0 | J29: 0 | K29: 0 | L29: =L28*L$1+E29 -> 21250514 | M29: =M28*M$1+F29 -> 7928.125 | N29: =N28*N$1+G29 -> 476650.31 | O29: =O28*O$1+H29 -> 135.67279 | P29: =P28*P$1+I29 -> 79.00582 | Q29: =Q28*Q$1+J29 -> 17228943 | R29: =R28*R$1+K29 -> 4021570.6 | S29: =L29-E29 -> 21250514 | T29: =M29-F29 -> 7928.125 | U29: =N29-G29 -> 476650.31 | V29: =O29-H29 -> 135.67279 | W29: =P29-I29 -> 79.00582 | X29: =Q29-J29 -> 17228943 | Y29: =R29-K29 -> 4021570.6 | Z29: =IFERROR(E29/L29,0) -> 0 | AA29: =IFERROR(F29/M29,0) -> 0 | AB29: =IFERROR(G29/N29,0) -> 0 | AC29: =IFERROR(H29/O29,0) -> 0 | AD29: =IFERROR(I29/P29,0) -> 0 | AE29: =IFERROR(J29/Q29,0) -> 0 | AF29: =IFERROR(K29/R29,0) -> 0 | AG29: =IFERROR(S29/L29,0) -> 1 | AH29: =IFERROR(T29/M29,0) -> 1 | AI29: =IFERROR(U29/N29,0) -> 1 | AJ29: =IFERROR(V29/O29,0) -> 1 | AK29: =IFERROR(W29/P29,0) -> 1 | AL29: =IFERROR(X29/Q29,0) -> 1 | AM29: =IFERROR(Y29/R29,0) -> 1 | AN29: 348.10024 | AO29: 0.21286901 | AP29: 31.454488 | AQ29: 191.53098 | AR29: 107.09681 | AS29: 193.80607 | AT29: 154.29417 | AU29: =AN29*Z29 -> 0 | AV29: =AO29*AA29 -> 0 | AW29: =AP29*AB29 -> 0 | AX29: =AQ29*AC29 -> 0 | AY29: =AR29*AD29 -> 0 | AZ29: =AS29*AE29 -> 0 | BA29: =AT29*AF29 -> 0 | BB29: =AN29*AG29 -> 348.10024 | BC29: =AO29*AH29 -> 0.21286901 | BD29: =AP29*AI29 -> 31.454488 | BE29: =AQ29*AJ29 -> 191.53098 | BF29: =AR29*AK29 -> 107.09681 | BG29: =AS29*AL29 -> 193.80607 | BH29: =AT29*AM29 -> 154.29417
A30: FY_2024 | B30: 2023 Campaign | D30: 45231 | E30: 0 | F30: 0 | G30: 0 | H30: 0 | I30: 0 | J30: 0 | K30: 0 | L30: =L29*L$1+E30 -> 13812834 | M30: =M29*M$1+F30 -> 3964.0625 | N30: =N29*N$1+G30 -> 238325.16 | O30: =O29*O$1+H30 -> 94.97095 | P30: =P29*P$1+I30 -> 55.304074 | Q30: =Q29*Q$1+J30 -> 11198813 | R30: =R29*R$1+K30 -> 2614020.9 | S30: =L30-E30 -> 13812834 | T30: =M30-F30 -> 3964.0625 | U30: =N30-G30 -> 238325.16 | V30: =O30-H30 -> 94.97095 | W30: =P30-I30 -> 55.304074 | X30: =Q30-J30 -> 11198813 | Y30: =R30-K30 -> 2614020.9 | Z30: =IFERROR(E30/L30,0) -> 0 | AA30: =IFERROR(F30/M30,0) -> 0 | AB30: =IFERROR(G30/N30,0) -> 0 | AC30: =IFERROR(H30/O30,0) -> 0 | AD30: =IFERROR(I30/P30,0) -> 0 | AE30: =IFERROR(J30/Q30,0) -> 0 | AF30: =IFERROR(K30/R30,0) -> 0 | AG30: =IFERROR(S30/L30,0) -> 1 | AH30: =IFERROR(T30/M30,0) -> 1 | AI30: =IFERROR(U30/N30,0) -> 1 | AJ30: =IFERROR(V30/O30,0) -> 1 | AK30: =IFERROR(W30/P30,0) -> 1 | AL30: =IFERROR(X30/Q30,0) -> 1 | AM30: =IFERROR(Y30/R30,0) -> 1 | AN30: 192.64356 | AO30: 0.00066468974 | AP30: 0.23669973 | AQ30: 121.22939 | AR30: 118.42979 | AS30: 111.2641 | AT30: 81.379462 | AU30: =AN30*Z30 -> 0 | AV30: =AO30*AA30 -> 0 | AW30: =AP30*AB30 -> 0 | AX30: =AQ30*AC30 -> 0 | AY30: =AR30*AD30 -> 0 | AZ30: =AS30*AE30 -> 0 | BA30: =AT30*AF30 -> 0 | BB30: =AN30*AG30 -> 192.64356 | BC30: =AO30*AH30 -> 0.00066468974 | BD30: =AP30*AI30 -> 0.23669973 | BE30: =AQ30*AJ30 -> 121.22939 | BF30: =AR30*AK30 -> 118.42979 | BG30: =AS30*AL30 -> 111.2641 | BH30: =AT30*AM30 -> 81.379462
A31: FY_2024 | B31: 2023 Campaign | D31: 45261 | E31: 0 | F31: 0 | G31: 0 | H31: 0 | I31: 0 | J31: 0 | K31: 0 | L31: =L30*L$1+E31 -> 8978342.2 | M31: =M30*M$1+F31 -> 1982.0312 | N31: =N30*N$1+G31 -> 119162.58 | O31: =O30*O$1+H31 -> 66.479665 | P31: =P30*P$1+I31 -> 38.712852 | Q31: =Q30*Q$1+J31 -> 7279228.6 | R31: =R30*R$1+K31 -> 1699113.6 | S31: =L31-E31 -> 8978342.2 | T31: =M31-F31 -> 1982.0312 | U31: =N31-G31 -> 119162.58 | V31: =O31-H31 -> 66.479665 | W31: =P31-I31 -> 38.712852 | X31: =Q31-J31 -> 7279228.6 | Y31: =R31-K31 -> 1699113.6 | Z31: =IFERROR(E31/L31,0) -> 0 | AA31: =IFERROR(F31/M31,0) -> 0 | AB31: =IFERROR(G31/N31,0) -> 0 | AC31: =IFERROR(H31/O31,0) -> 0 | AD31: =IFERROR(I31/P31,0) -> 0 | AE31: =IFERROR(J31/Q31,0) -> 0 | AF31: =IFERROR(K31/R31,0) -> 0 | AG31: =IFERROR(S31/L31,0) -> 1 | AH31: =IFERROR(T31/M31,0) -> 1 | AI31: =IFERROR(U31/N31,0) -> 1 | AJ31: =IFERROR(V31/O31,0) -> 1 | AK31: =IFERROR(W31/P31,0) -> 1 | AL31: =IFERROR(X31/Q31,0) -> 1 | AM31: =IFERROR(Y31/R31,0) -> 1 | AN31: 36.542491 | AO31: 7.0487086e-06 | AP31: 0.00080167269 | AQ31: 37.81912 | AR31: 111.21874 | AS31: 22.191279 | AT31: 14.351213 | AU31: =AN31*Z31 -> 0 | AV31: =AO31*AA31 -> 0 | AW31: =AP31*AB31 -> 0 | AX31: =AQ31*AC31 -> 0 | AY31: =AR31*AD31 -> 0 | AZ31: =AS31*AE31 -> 0 | BA31: =AT31*AF31 -> 0 | BB31: =AN31*AG31 -> 36.542491 | BC31: =AO31*AH31 -> 7.0487086e-06 | BD31: =AP31*AI31 -> 0.00080167269 | BE31: =AQ31*AJ31 -> 37.81912 | BF31: =AR31*AK31 -> 111.21874 | BG31: =AS31*AL31 -> 22.191279 | BH31: =AT31*AM31 -> 14.351213
A32: FY_2024 | B32: 2023 Campaign | D32: 45292 | E32: 0 | F32: 0 | G32: 0 | H32: 0 | I32: 0 | J32: 0 | K32: 0 | L32: =L31*L$1+E32 -> 5835922.4 | M32: =M31*M$1+F32 -> 991.01562 | N32: =N31*N$1+G32 -> 59581.289 | O32: =O31*O$1+H32 -> 46.535766 | P32: =P31*P$1+I32 -> 27.098996 | Q32: =Q31*Q$1+J32 -> 4731498.6 | R32: =R31*R$1+K32 -> 1104423.8 | S32: =L32-E32 -> 5835922.4 | T32: =M32-F32 -> 991.01562 | U32: =N32-G32 -> 59581.289 | V32: =O32-H32 -> 46.535766 | W32: =P32-I32 -> 27.098996 | X32: =Q32-J32 -> 4731498.6 | Y32: =R32-K32 -> 1104423.8 | Z32: =IFERROR(E32/L32,0) -> 0 | AA32: =IFERROR(F32/M32,0) -> 0 | AB32: =IFERROR(G32/N32,0) -> 0 | AC32: =IFERROR(H32/O32,0) -> 0 | AD32: =IFERROR(I32/P32,0) -> 0 | AE32: =IFERROR(J32/Q32,0) -> 0 | AF32: =IFERROR(K32/R32,0) -> 0 | AG32: =IFERROR(S32/L32,0) -> 1 | AH32: =IFERROR(T32/M32,0) -> 1 | AI32: =IFERROR(U32/N32,0) -> 1 | AJ32: =IFERROR(V32/O32,0) -> 1 | AK32: =IFERROR(W32/P32,0) -> 1 | AL32: =IFERROR(X32/Q32,0) -> 1 | AM32: =IFERROR(Y32/R32,0) -> 1 | AN32: 2.0851824 | AO32: 4.2544307e-07 | AP32: 9.8430011e-06 | AQ32: 4.8345857 | AR32: 64.572101 | AS32: 1.3175103 | AT32: 0.76767216 | AU32: =AN32*Z32 -> 0 | AV32: =AO32*AA32 -> 0 | AW32: =AP32*AB32 -> 0 | AX32: =AQ32*AC32 -> 0 | AY32: =AR32*AD32 -> 0 | AZ32: =AS32*AE32 -> 0 | BA32: =AT32*AF32 -> 0 | BB32: =AN32*AG32 -> 2.0851824 | BC32: =AO32*AH32 -> 4.2544307e-07 | BD32: =AP32*AI32 -> 9.8430011e-06 | BE32: =AQ32*AJ32 -> 4.8345857 | BF32: =AR32*AK32 -> 64.572101 | BG32: =AS32*AL32 -> 1.3175103 | BH32: =AT32*AM32 -> 0.76767216
A33: FY_2024 | B33: 2023 Campaign | D33: 45323 | E33: 0 | F33: 0 | G33: 0 | H33: 0 | I33: 0 | J33: 0 | K33: 0 | L33: =L32*L$1+E33 -> 3793349.6 | M33: =M32*M$1+F33 -> 495.50781 | N33: =N32*N$1+G33 -> 29790.645 | O33: =O32*O$1+H33 -> 32.575036 | P33: =P32*P$1+I33 -> 18.969297 | Q33: =Q32*Q$1+J33 -> 3075474.1 | R33: =R32*R$1+K33 -> 717875.48 | S33: =L33-E33 -> 3793349.6 | T33: =M33-F33 -> 495.50781 | U33: =N33-G33 -> 29790.645 | V33: =O33-H33 -> 32.575036 | W33: =P33-I33 -> 18.969297 | X33: =Q33-J33 -> 3075474.1 | Y33: =R33-K33 -> 717875.48 | Z33: =IFERROR(E33/L33,0) -> 0 | AA33: =IFERROR(F33/M33,0) -> 0 | AB33: =IFERROR(G33/N33,0) -> 0 | AC33: =IFERROR(H33/O33,0) -> 0 | AD33: =IFERROR(I33/P33,0) -> 0 | AE33: =IFERROR(J33/Q33,0) -> 0 | AF33: =IFERROR(K33/R33,0) -> 0 | AG33: =IFERROR(S33/L33,0) -> 1 | AH33: =IFERROR(T33/M33,0) -> 1 | AI33: =IFERROR(U33/N33,0) -> 1 | AJ33: =IFERROR(V33/O33,0) -> 1 | AK33: =IFERROR(W33/P33,0) -> 1 | AL33: =IFERROR(X33/Q33,0) -> 1 | AM33: =IFERROR(Y33/R33,0) -> 1 | AN33: 0.059535282 | AO33: 8.6703063e-08 | AP33: 6.3899061e-07 | AQ33: 0.31827315 | AR33: 18.434886 | AS33: 0.038310656 | AT33: 0.021224626 | AU33: =AN33*Z33 -> 0 | AV33: =AO33*AA33 -> 0 | AW33: =AP33*AB33 -> 0 | AX33: =AQ33*AC33 -> 0 | AY33: =AR33*AD33 -> 0 | AZ33: =AS33*AE33 -> 0 | BA33: =AT33*AF33 -> 0 | BB33: =AN33*AG33 -> 0.059535282 | BC33: =AO33*AH33 -> 8.6703063e-08 | BD33: =AP33*AI33 -> 6.3899061e-07 | BE33: =AQ33*AJ33 -> 0.31827315 | BF33: =AR33*AK33 -> 18.434886 | BG33: =AS33*AL33 -> 0.038310656 | BH33: =AT33*AM33 -> 0.021224626
A34: FY_2024 | B34: 2023 Campaign | D34: 45352 | E34: 0 | F34: 0 | G34: 0 | H34: 0 | I34: 0 | J34: 0 | K34: 0 | L34: =L33*L$1+E34 -> 2465677.2 | M34: =M33*M$1+F34 -> 247.75391 | N34: =N33*N$1+G34 -> 14895.322 | O34: =O33*O$1+H34 -> 22.802525 | P34: =P33*P$1+I34 -> 13.278508 | Q34: =Q33*Q$1+J34 -> 1999058.2 | R34: =R33*R$1+K34 -> 466619.06 | S34: =L34-E34 -> 2465677.2 | T34: =M34-F34 -> 247.75391 | U34: =N34-G34 -> 14895.322 | V34: =O34-H34 -> 22.802525 | W34: =P34-I34 -> 13.278508 | X34: =Q34-J34 -> 1999058.2 | Y34: =R34-K34 -> 466619.06 | Z34: =IFERROR(E34/L34,0) -> 0 | AA34: =IFERROR(F34/M34,0) -> 0 | AB34: =IFERROR(G34/N34,0) -> 0 | AC34: =IFERROR(H34/O34,0) -> 0 | AD34: =IFERROR(I34/P34,0) -> 0 | AE34: =IFERROR(J34/Q34,0) -> 0 | AF34: =IFERROR(K34/R34,0) -> 0 | AG34: =IFERROR(S34/L34,0) -> 1 | AH34: =IFERROR(T34/M34,0) -> 1 | AI34: =IFERROR(U34/N34,0) -> 1 | AJ34: =IFERROR(V34/O34,0) -> 1 | AK34: =IFERROR(W34/P34,0) -> 1 | AL34: =IFERROR(X34/Q34,0) -> 1 | AM34: =IFERROR(Y34/R34,0) -> 1 | AN34: 0.0017366023 | AO34: 3.6148983e-08 | AP34: 1.3983778e-07 | AQ34: 0.016276671 | AR34: 2.2716044 | AS34: 0.0011189458 | AT34: 0.00061765652 | AU34: =AN34*Z34 -> 0 | AV34: =AO34*AA34 -> 0 | AW34: =AP34*AB34 -> 0 | AX34: =AQ34*AC34 -> 0 | AY34: =AR34*AD34 -> 0 | AZ34: =AS34*AE34 -> 0 | BA34: =AT34*AF34 -> 0 | BB34: =AN34*AG34 -> 0.0017366023 | BC34: =AO34*AH34 -> 3.6148983e-08 | BD34: =AP34*AI34 -> 1.3983778e-07 | BE34: =AQ34*AJ34 -> 0.016276671 | BF34: =AR34*AK34 -> 2.2716044 | BG34: =AS34*AL34 -> 0.0011189458 | BH34: =AT34*AM34 -> 0.00061765652
A35: FY_2024 | B35: 2024 Campaign | C35: 2024 | D35: 45383 | E35: 12929947 | F35: 0 | G35: 0 | H35: 0 | I35: 0 | J35: 9853942.3 | K35: 3076005 | L35: =L34*L$1+E35 -> 14532637 | M35: =M34*M$1+F35 -> 123.87695 | N35: =N34*N$1+G35 -> 7447.6611 | O35: =O34*O$1+H35 -> 15.961768 | P35: =P34*P$1+I35 -> 9.2949557 | Q35: =Q34*Q$1+J35 -> 11153330 | R35: =R34*R$1+K35 -> 3379307.4 | S35: =L35-E35 -> 1602690.2 | T35: =M35-F35 -> 123.87695 | U35: =N35-G35 -> 7447.6611 | V35: =O35-H35 -> 15.961768 | W35: =P35-I35 -> 9.2949557 | X35: =Q35-J35 -> 1299387.8 | Y35: =R35-K35 -> 303302.39 | Z35: =IFERROR(E35/L35,0) -> 0.88971787 | AA35: =IFERROR(F35/M35,0) -> 0 | AB35: =IFERROR(G35/N35,0) -> 0 | AC35: =IFERROR(H35/O35,0) -> 0 | AD35: =IFERROR(I35/P35,0) -> 0 | AE35: =IFERROR(J35/Q35,0) -> 0.88349777 | AF35: =IFERROR(K35/R35,0) -> 0.91024717 | AG35: =IFERROR(S35/L35,0) -> 0.11028213 | AH35: =IFERROR(T35/M35,0) -> 1 | AI35: =IFERROR(U35/N35,0) -> 1 | AJ35: =IFERROR(V35/O35,0) -> 1 | AK35: =IFERROR(W35/P35,0) -> 1 | AL35: =IFERROR(X35/Q35,0) -> 0.11650223 | AM35: =IFERROR(Y35/R35,0) -> 0.089752827 | AN35: 212.743 | AO35: 2.3880435e-08 | AP35: 6.2159987e-08 | AQ35: 0.00090118799 | AR35: 0.1415737 | AS35: 104.84363 | AT35: 107.89938 | AU35: =AN35*Z35 -> 189.28125 | AV35: =AO35*AA35 -> 0 | AW35: =AP35*AB35 -> 0 | AX35: =AQ35*AC35 -> 0 | AY35: =AR35*AD35 -> 0 | AZ35: =AS35*AE35 -> 92.629109 | BA35: =AT35*AF35 -> 98.215104 | BB35: =AN35*AG35 -> 23.461751 | BC35: =AO35*AH35 -> 2.3880435e-08 | BD35: =AP35*AI35 -> 6.2159987e-08 | BE35: =AQ35*AJ35 -> 0.00090118799 | BF35: =AR35*AK35 -> 0.1415737 | BG35: =AS35*AL35 -> 12.214516 | BH35: =AT35*AM35 -> 9.6842742
A36: FY_2024 | B36: 2024 Campaign | C36: 2024 | D36: 45413 | E36: 63784715 | F36: 21903 | G36: 0 | H36: 0 | I36: 22.686275 | J36: 51393559 | K36: 12391156 | L36: =L35*L$1+E36 -> 73230930 | M36: =M35*M$1+F36 -> 21964.938 | N36: =N35*N$1+G36 -> 3723.8306 | O36: =O35*O$1+H36 -> 11.173237 | P36: =P35*P$1+I36 -> 29.192744 | Q36: =Q35*Q$1+J36 -> 58643224 | R36: =R35*R$1+K36 -> 14587706 | S36: =L36-E36 -> 9446214.4 | T36: =M36-F36 -> 61.938477 | U36: =N36-G36 -> 3723.8306 | V36: =O36-H36 -> 11.173237 | W36: =P36-I36 -> 6.506469 | X36: =Q36-J36 -> 7249664.6 | Y36: =R36-K36 -> 2196549.8 | Z36: =IFERROR(E36/L36,0) -> 0.87100786 | AA36: =IFERROR(F36/M36,0) -> 0.99718012 | AB36: =IFERROR(G36/N36,0) -> 0 | AC36: =IFERROR(H36/O36,0) -> 0 | AD36: =IFERROR(I36/P36,0) -> 0.77712033 | AE36: =IFERROR(J36/Q36,0) -> 0.87637677 | AF36: =IFERROR(K36/R36,0) -> 0.84942459 | AG36: =IFERROR(S36/L36,0) -> 0.12899214 | AH36: =IFERROR(T36/M36,0) -> 0.0028198794 | AI36: =IFERROR(U36/N36,0) -> 1 | AJ36: =IFERROR(V36/O36,0) -> 1 | AK36: =IFERROR(W36/P36,0) -> 0.22287967 | AL36: =IFERROR(X36/Q36,0) -> 0.12362323 | AM36: =IFERROR(Y36/R36,0) -> 0.15057541 | AN36: 375.13119 | AO36: 73.117875 | AP36: 4.1061125e-08 | AQ36: 7.2052681e-05 | AR36: 77.838029 | AS36: 221.74281 | AT36: 153.38838 | AU36: =AN36*Z36 -> 326.74222 | AV36: =AO36*AA36 -> 72.911692 | AW36: =AP36*AB36 -> 0 | AX36: =AQ36*AC36 -> 0 | AY36: =AR36*AD36 -> 60.489515 | AZ36: =AS36*AE36 -> 194.33025 | BA36: =AT36*AF36 -> 130.29186 | BB36: =AN36*AG36 -> 48.388975 | BC36: =AO36*AH36 -> 0.20618359 | BD36: =AP36*AI36 -> 4.1061125e-08 | BE36: =AQ36*AJ36 -> 7.2052681e-05 | BF36: =AR36*AK36 -> 17.348514 | BG36: =AS36*AL36 -> 27.412562 | BH36: =AT36*AM36 -> 23.096517
A37: FY_2024 | B37: 2024 Campaign | C37: 2024 | D37: 45444 | E37: 57380577 | F37: 11517 | G37: 0 | H37: 0 | I37: 26.176471 | J37: 47341557 | K37: 10039021 | L37: =L36*L$1+E37 -> 1.0498068e+08 | M37: =M36*M$1+F37 -> 22499.469 | N37: =N36*N$1+G37 -> 1861.9153 | O37: =O36*O$1+H37 -> 7.8212661 | P37: =P36*P$1+I37 -> 46.611391 | Q37: =Q36*Q$1+J37 -> 85459652 | R37: =R36*R$1+K37 -> 19521030 | S37: =L37-E37 -> 47600104 | T37: =M37-F37 -> 10982.469 | U37: =N37-G37 -> 1861.9153 | V37: =O37-H37 -> 7.8212661 | W37: =P37-I37 -> 20.43492 | X37: =Q37-J37 -> 38118095 | Y37: =R37-K37 -> 9482009.1 | Z37: =IFERROR(E37/L37,0) -> 0.54658225 | AA37: =IFERROR(F37/M37,0) -> 0.51187874 | AB37: =IFERROR(G37/N37,0) -> 0 | AC37: =IFERROR(H37/O37,0) -> 0 | AD37: =IFERROR(I37/P37,0) -> 0.56158956 | AE37: =IFERROR(J37/Q37,0) -> 0.55396384 | AF37: =IFERROR(K37/R37,0) -> 0.51426696 | AG37: =IFERROR(S37/L37,0) -> 0.45341775 | AH37: =IFERROR(T37/M37,0) -> 0.48812126 | AI37: =IFERROR(U37/N37,0) -> 1 | AJ37: =IFERROR(V37/O37,0) -> 1 | AK37: =IFERROR(W37/P37,0) -> 0.43841044 | AL37: =IFERROR(X37/Q37,0) -> 0.44603616 | AM37: =IFERROR(Y37/R37,0) -> 0.48573304 | AN37: 375.12123 | AO37: 77.45752 | AP37: 3.326942e-08 | AQ37: 9.097344e-06 | AR37: 122.29204 | AS37: 221.34869 | AT37: 153.77253 | AU37: =AN37*Z37 -> 205.0346 | AV37: =AO37*AA37 -> 39.648858 | AW37: =AP37*AB37 -> 0 | AX37: =AQ37*AC37 -> 0 | AY37: =AR37*AD37 -> 68.677933 | AZ37: =AS37*AE37 -> 122.61917 | BA37: =AT37*AF37 -> 79.080133 | BB37: =AN37*AG37 -> 170.08662 | BC37: =AO37*AH37 -> 37.808662 | BD37: =AP37*AI37 -> 3.326942e-08 | BE37: =AQ37*AJ37 -> 9.097344e-06 | BF37: =AR37*AK37 -> 53.614107 | BG37: =AS37*AL37 -> 98.729522 | BH37: =AT37*AM37 -> 74.6924
A38: FY_2024 | B38: 2024 Campaign | C38: 2024 | D38: 45474 | E38: 57252357 | F38: 7899 | G38: 0 | H38: 0 | I38: 27.04902 | J38: 50246461 | K38: 7005896 | L38: =L37*L$1+E38 -> 1.254898e+08 | M38: =M37*M$1+F38 -> 19148.735 | N38: =N37*N$1+G38 -> 930.95764 | O38: =O37*O$1+H38 -> 5.4748863 | P38: =P37*P$1+I38 -> 59.676993 | Q38: =Q37*Q$1+J38 -> 1.0579523e+08 | R38: =R37*R$1+K38 -> 19694565 | S38: =L38-E38 -> 68237443 | T38: =M38-F38 -> 11249.735 | U38: =N38-G38 -> 930.95764 | V38: =O38-H38 -> 5.4748863 | W38: =P38-I38 -> 32.627974 | X38: =Q38-J38 -> 55548774 | Y38: =R38-K38 -> 12688669 | Z38: =IFERROR(E38/L38,0) -> 0.45623116 | AA38: =IFERROR(F38/M38,0) -> 0.41250768 | AB38: =IFERROR(G38/N38,0) -> 0 | AC38: =IFERROR(H38/O38,0) -> 0 | AD38: =IFERROR(I38/P38,0) -> 0.45325708 | AE38: =IFERROR(J38/Q38,0) -> 0.47494068 | AF38: =IFERROR(K38/R38,0) -> 0.35572738 | AG38: =IFERROR(S38/L38,0) -> 0.54376884 | AH38: =IFERROR(T38/M38,0) -> 0.58749232 | AI38: =IFERROR(U38/N38,0) -> 1 | AJ38: =IFERROR(V38/O38,0) -> 1 | AK38: =IFERROR(W38/P38,0) -> 0.54674292 | AL38: =IFERROR(X38/Q38,0) -> 0.52505932 | AM38: =IFERROR(Y38/R38,0) -> 0.64427262 | AN38: 375.5408 | AO38: 48.559183 | AP38: 2.993724e-08 | AQ38: 1.8031148e-06 | AR38: 126.61589 | AS38: 221.32622 | AT38: 154.21459 | AU38: =AN38*Z38 -> 171.33342 | AV38: =AO38*AA38 -> 20.031036 | AW38: =AP38*AB38 -> 0 | AX38: =AQ38*AC38 -> 0 | AY38: =AR38*AD38 -> 57.38955 | AZ38: =AS38*AE38 -> 105.11682 | BA38: =AT38*AF38 -> 54.85835 | BB38: =AN38*AG38 -> 204.20739 | BC38: =AO38*AH38 -> 28.528147 | BD38: =AP38*AI38 -> 2.993724e-08 | BE38: =AQ38*AJ38 -> 1.8031148e-06 | BF38: =AR38*AK38 -> 69.226343 | BG38: =AS38*AL38 -> 116.20939 | BH38: =AT38*AM38 -> 99.356237
A39: FY_2024 | B39: 2024 Campaign | C39: 2024 | D39: 45505 | E39: 0 | F39: 0 | G39: 0 | H39: 0 | I39: 13.088235 | J39: 0 | K39: 0 | L39: =L38*L$1+E39 -> 81568370 | M39: =M38*M$1+F39 -> 9574.3673 | N39: =N38*N$1+G39 -> 465.47882 | O39: =O38*O$1+H39 -> 3.8324204 | P39: =P38*P$1+I39 -> 54.862131 | Q39: =Q38*Q$1+J39 -> 68766903 | R39: =R38*R$1+K39 -> 12801467 | S39: =L39-E39 -> 81568370 | T39: =M39-F39 -> 9574.3673 | U39: =N39-G39 -> 465.47882 | V39: =O39-H39 -> 3.8324204 | W39: =P39-I39 -> 41.773895 | X39: =Q39-J39 -> 68766903 | Y39: =R39-K39 -> 12801467 | Z39: =IFERROR(E39/L39,0) -> 0 | AA39: =IFERROR(F39/M39,0) -> 0 | AB39: =IFERROR(G39/N39,0) -> 0 | AC39: =IFERROR(H39/O39,0) -> 0 | AD39: =IFERROR(I39/P39,0) -> 0.23856593 | AE39: =IFERROR(J39/Q39,0) -> 0 | AF39: =IFERROR(K39/R39,0) -> 0 | AG39: =IFERROR(S39/L39,0) -> 1 | AH39: =IFERROR(T39/M39,0) -> 1 | AI39: =IFERROR(U39/N39,0) -> 1 | AJ39: =IFERROR(V39/O39,0) -> 1 | AK39: =IFERROR(W39/P39,0) -> 0.76143407 | AL39: =IFERROR(X39/Q39,0) -> 1 | AM39: =IFERROR(Y39/R39,0) -> 1 | AN39: 375.47228 | AO39: 0.88250619 | AP39: 2.8395308e-08 | AQ39: 5.315418e-07 | AR39: 129.3393 | AS39: 221.11762 | AT39: 154.35466 | AU39: =AN39*Z39 -> 0 | AV39: =AO39*AA39 -> 0 | AW39: =AP39*AB39 -> 0 | AX39: =AQ39*AC39 -> 0 | AY39: =AR39*AD39 -> 30.855952 | AZ39: =AS39*AE39 -> 0 | BA39: =AT39*AF39 -> 0 | BB39: =AN39*AG39 -> 375.47228 | BC39: =AO39*AH39 -> 0.88250619 | BD39: =AP39*AI39 -> 2.8395308e-08 | BE39: =AQ39*AJ39 -> 5.315418e-07 | BF39: =AR39*AK39 -> 98.483353 | BG39: =AS39*AL39 -> 221.11762 | BH39: =AT39*AM39 -> 154.35466
A40: FY_2025 | B40: 2024 Campaign | C40: 2024 | D40: 45536 | E40: 0 | F40: 0 | G40: 0 | H40: 0 | I40: 0 | J40: 0 | K40: 0 | L40: =L39*L$1+E40 -> 53019441 | M40: =M39*M$1+F40 -> 4787.1837 | N40: =N39*N$1+G40 -> 232.73941 | O40: =O39*O$1+H40 -> 2.6826943 | P40: =P39*P$1+I40 -> 38.403491 | Q40: =Q39*Q$1+J40 -> 44698487 | R40: =R39*R$1+K40 -> 8320953.8 | S40: =L40-E40 -> 53019441 | T40: =M40-F40 -> 4787.1837 | U40: =N40-G40 -> 232.73941 | V40: =O40-H40 -> 2.6826943 | W40: =P40-I40 -> 38.403491 | X40: =Q40-J40 -> 44698487 | Y40: =R40-K40 -> 8320953.8 | Z40: =IFERROR(E40/L40,0) -> 0 | AA40: =IFERROR(F40/M40,0) -> 0 | AB40: =IFERROR(G40/N40,0) -> 0 | AC40: =IFERROR(H40/O40,0) -> 0 | AD40: =IFERROR(I40/P40,0) -> 0 | AE40: =IFERROR(J40/Q40,0) -> 0 | AF40: =IFERROR(K40/R40,0) -> 0 | AG40: =IFERROR(S40/L40,0) -> 1 | AH40: =IFERROR(T40/M40,0) -> 1 | AI40: =IFERROR(U40/N40,0) -> 1 | AJ40: =IFERROR(V40/O40,0) -> 1 | AK40: =IFERROR(W40/P40,0) -> 1 | AL40: =IFERROR(X40/Q40,0) -> 1 | AM40: =IFERROR(Y40/R40,0) -> 1 | AN40: 375.34962 | AO40: 0.0028087807 | AP40: 2.7641688e-08 | AQ40: 2.1569365e-07 | AR40: 115.59984 | AS40: 221.00193 | AT40: 154.34769 | AU40: =AN40*Z40 -> 0 | AV40: =AO40*AA40 -> 0 | AW40: =AP40*AB40 -> 0 | AX40: =AQ40*AC40 -> 0 | AY40: =AR40*AD40 -> 0 | AZ40: =AS40*AE40 -> 0 | BA40: =AT40*AF40 -> 0 | BB40: =AN40*AG40 -> 375.34962 | BC40: =AO40*AH40 -> 0.0028087807 | BD40: =AP40*AI40 -> 2.7641688e-08 | BE40: =AQ40*AJ40 -> 2.1569365e-07 | BF40: =AR40*AK40 -> 115.59984 | BG40: =AS40*AL40 -> 221.00193 | BH40: =AT40*AM40 -> 154.34769
AU41: YouTube + Facebook + Instagram - Direct Contribution | AV41: Paid Search - Direct Contribution | AW41: Online Banners - Direct Contribution | AX41: OOH Large Format - Direct Contribution | AY41: OOH Retail - Direct Contribution | AZ41: Facebook + Instagram - Direct Contribution | BA41: YouTube - Direct Contribution | BB41: YouTube + Facebook + Instagram - Lagged Contribution | BC41: Paid Search - Lagged Contribution | BD41: Online Banners - Lagged Contribution | BE41: OOH Large Format - Lagged Contribution | BF41: OOH Retail - Lagged Contribution | BG41: Facebook + Instagram - Lagged Contribution | BH41: YouTube - Lagged Contribution
AR42: FY_2023 | AU42: =SUMIFS(AU$4:AU$40,$A$4:$A$40,$AR42) -> 773.58424 | AV42: =SUMIFS(AV$4:AV$40,$A$4:$A$40,$AR42) -> 224.61939 | AW42: =SUMIFS(AW$4:AW$40,$A$4:$A$40,$AR42) -> 577.5455 | AX42: =SUMIFS(AX$4:AX$40,$A$4:$A$40,$AR42) -> 350.74417 | AY42: =SUMIFS(AY$4:AY$40,$A$4:$A$40,$AR42) -> 164.76489 | AZ42: =SUMIFS(AZ$4:AZ$40,$A$4:$A$40,$AR42) -> 416.50987 | BA42: =SUMIFS(BA$4:BA$40,$A$4:$A$40,$AR42) -> 353.18306 | BB42: =SUMIFS(BB$4:BB$40,$A$4:$A$40,$AR42) -> 406.31878 | ... BH42: =SUMIFS(BH$4:BH$40,$A$4:$A$40,$AR42) -> 190.44227
AR43: FY_2024 | AU43: =SUMIFS(AU$4:AU$40,$A$4:$A$40,$AR43) -> 892.39149 | AV43: =SUMIFS(AV$4:AV$40,$A$4:$A$40,$AR43) -> 132.59158 | AW43: =SUMIFS(AW$4:AW$40,$A$4:$A$40,$AR43) -> 0 | AX43: =SUMIFS(AX$4:AX$40,$A$4:$A$40,$AR43) -> 0 | AY43: =SUMIFS(AY$4:AY$40,$A$4:$A$40,$AR43) -> 227.27839 | AZ43: =SUMIFS(AZ$4:AZ$40,$A$4:$A$40,$AR43) -> 514.69536 | BA43: =SUMIFS(BA$4:BA$40,$A$4:$A$40,$AR43) -> 362.44545 | BB43: =SUMIFS(BB$4:BB$40,$A$4:$A$40,$AR43) -> 1789.3193 | ... BH43: =SUMIFS(BH$4:BH$40,$A$4:$A$40,$AR43) -> 787.58666
AR45: 2023 Campaign | AU45: =SUMIFS(AU$4:AU$40,$B$4:$B$40,$AR45) -> 773.58424 | AV45: =SUMIFS(AV$4:AV$40,$B$4:$B$40,$AR45) -> 224.61939 | AW45: =SUMIFS(AW$4:AW$40,$B$4:$B$40,$AR45) -> 577.5455 | AX45: =SUMIFS(AX$4:AX$40,$B$4:$B$40,$AR45) -> 350.74417 | AY45: =SUMIFS(AY$4:AY$40,$B$4:$B$40,$AR45) -> 174.63033 | AZ45: =SUMIFS(AZ$4:AZ$40,$B$4:$B$40,$AR45) -> 416.50987 | BA45: =SUMIFS(BA$4:BA$40,$B$4:$B$40,$AR45) -> 353.18306 | BB45: =SUMIFS(BB$4:BB$40,$B$4:$B$40,$AR45) -> 1374.021 | ... BH45: =SUMIFS(BH$4:BH$40,$B$4:$B$40,$AR45) -> 616.84484
AR46: 2024 Campaign | AU46: =SUMIFS(AU$4:AU$40,$B$4:$B$40,$AR46) -> 892.39149 | AV46: =SUMIFS(AV$4:AV$40,$B$4:$B$40,$AR46) -> 132.59158 | AW46: =SUMIFS(AW$4:AW$40,$B$4:$B$40,$AR46) -> 0 | AX46: =SUMIFS(AX$4:AX$40,$B$4:$B$40,$AR46) -> 0 | AY46: =SUMIFS(AY$4:AY$40,$B$4:$B$40,$AR46) -> 217.41295 | AZ46: =SUMIFS(AZ$4:AZ$40,$B$4:$B$40,$AR46) -> 514.69536 | BA46: =SUMIFS(BA$4:BA$40,$B$4:$B$40,$AR46) -> 362.44545 | BB46: =SUMIFS(BB$4:BB$40,$B$4:$B$40,$AR46) -> 1196.9666 | ... BH46: =SUMIFS(BH$4:BH$40,$B$4:$B$40,$AR46) -> 515.53178
AR48: 2023 | AU48: =SUMIFS(AU$4:AU$40,$C$4:$C$40,$AR48) -> 773.58424 | AV48: =SUMIFS(AV$4:AV$40,$C$4:$C$40,$AR48) -> 224.61939 | AW48: =SUMIFS(AW$4:AW$40,$C$4:$C$40,$AR48) -> 577.5455 | AX48: =SUMIFS(AX$4:AX$40,$C$4:$C$40,$AR48) -> 350.74417 | AY48: =SUMIFS(AY$4:AY$40,$C$4:$C$40,$AR48) -> 174.63033 | AZ48: =SUMIFS(AZ$4:AZ$40,$C$4:$C$40,$AR48) -> 416.50987 | BA48: =SUMIFS(BA$4:BA$40,$C$4:$C$40,$AR48) -> 353.18306 | BB48: =SUMIFS(BB$4:BB$40,$C$4:$C$40,$AR48) -> 1142.6885 | ... BH48: =SUMIFS(BH$4:BH$40,$C$4:$C$40,$AR48) -> 520.32465
AR49: 2024 | AU49: =SUMIFS(AU$4:AU$40,$C$4:$C$40,$AR49) -> 892.39149 | AV49: =SUMIFS(AV$4:AV$40,$C$4:$C$40,$AR49) -> 132.59158 | AW49: =SUMIFS(AW$4:AW$40,$C$4:$C$40,$AR49) -> 0 | AX49: =SUMIFS(AX$4:AX$40,$C$4:$C$40,$AR49) -> 0 | AY49: =SUMIFS(AY$4:AY$40,$C$4:$C$40,$AR49) -> 217.41295 | AZ49: =SUMIFS(AZ$4:AZ$40,$C$4:$C$40,$AR49) -> 514.69536 | BA49: =SUMIFS(BA$4:BA$40,$C$4:$C$40,$AR49) -> 362.44545 | BB49: =SUMIFS(BB$4:BB$40,$C$4:$C$40,$AR49) -> 1196.9666 | ... BH49: =SUMIFS(BH$4:BH$40,$C$4:$C$40,$AR49) -> 515.53178
BA57: Direct contribution | BB57: Lagged contribution | BC57: Direct contribution | BD57: Lagged contribution | BG57: Direct contribution | BH57: Lagged contribution | BI57: Direct contribution | BJ57: Lagged contribution
BA58: 2023 Campaign | BB58: 2023 Campaign | BC58: 2024 Campaign | BD58: 2024 Campaign | BG58: 2023 | BH58: 2023 | BI58: 2024 | BJ58: 2024
AW59: FY_2023 | AX59: FY_2024 | BA59: =_xlfn.TEXTJOIN(" - ",TRUE,BA58,BA57) -> 2023 Campaign - Direct contribution | BB59: =_xlfn.TEXTJOIN(" - ",TRUE,BB58,BB57) -> 2023 Campaign - Lagged contribution | BC59: =_xlfn.TEXTJOIN(" - ",TRUE,BC58,BC57) -> 2024 Campaign - Direct contribution | BD59: =_xlfn.TEXTJOIN(" - ",TRUE,BD58,BD57) -> 2024 Campaign - Lagged contribution | BG59: =_xlfn.TEXTJOIN(" - ",TRUE,BG58,BG57) -> 2023 - Direct contribution | BH59: =_xlfn.TEXTJOIN(" - ",TRUE,BH58,BH57) -> 2023 - Lagged contribution | BI59: =_xlfn.TEXTJOIN(" - ",TRUE,BI58,BI57) -> 2024 - Direct contribution | BJ59: =_xlfn.TEXTJOIN(" - ",TRUE,BJ58,BJ57) -> 2024 - Lagged contribution
AV60: YouTube + Facebook + Instagram - Direct Contribution | AW60: 773.58424 | AX60: 892.39149 | AZ60: YouTube + Facebook + Instagram | BA60: 773.58424 | BB60: 1374.021 | BC60: 892.39149 | BD60: 1196.9666 | BF60: YouTube + Facebook + Instagram | BG60: =SUMIFS(AU$4:AU$40,$C$4:$C$40,$AR48) -> 773.58424 | BH60: =SUMIFS(BB$4:BB$40,$C$4:$C$40,$AR48) -> 1142.6885 | BI60: =SUMIFS(AU$4:AU$40,$C$4:$C$40,$AR49) -> 892.39149 | BJ60: =SUMIFS(BB$4:BB$40,$C$4:$C$40,$AR49) -> 1196.9666
AV61: Paid Search - Direct Contribution | AW61: 224.61939 | AX61: 132.59158 | AZ61: Paid Search | BA61: 224.61939 | BB61: 158.45714 | BC61: 132.59158 | BD61: 67.428308 | BF61: Paid Search | BG61: =SUMIFS(AV$4:AV$40,$C$4:$C$40,$AR48) -> 224.61939 | BH61: =SUMIFS(BC$4:BC$40,$C$4:$C$40,$AR48) -> 158.45646 | BI61: =SUMIFS(AV$4:AV$40,$C$4:$C$40,$AR49) -> 132.59158 | BJ61: =SUMIFS(BC$4:BC$40,$C$4:$C$40,$AR49) -> 67.428308
AV62: Online Banners - Direct Contribution | AW62: 577.5455 | AX62: 0 | AZ62: Online Banners | BA62: 577.5455 | BB62: 476.69818 | BC62: 0 | BD62: 2.2246477e-07 | BF62: Online Banners | BG62: =SUMIFS(AW$4:AW$40,$C$4:$C$40,$AR48) -> 577.5455 | BH62: =SUMIFS(BD$4:BD$40,$C$4:$C$40,$AR48) -> 476.46067 | BI62: =SUMIFS(AW$4:AW$40,$C$4:$C$40,$AR49) -> 0 | BJ62: =SUMIFS(BD$4:BD$40,$C$4:$C$40,$AR49) -> 2.2246477e-07
AV63: OOH Large Format - Direct Contribution | AW63: 350.74417 | AX63: 0 | AZ63: OOH Large Format | BA63: 350.74417 | BB63: 876.61478 | BC63: 0 | BD63: 0.00098488837 | BF63: OOH Large Format | BG63: =SUMIFS(AX$4:AX$40,$C$4:$C$40,$AR48) -> 350.74417 | BH63: =SUMIFS(BE$4:BE$40,$C$4:$C$40,$AR48) -> 712.39713 | BI63: =SUMIFS(AX$4:AX$40,$C$4:$C$40,$AR49) -> 0 | BJ63: =SUMIFS(BE$4:BE$40,$C$4:$C$40,$AR49) -> 0.00098488837
AV64: OOH Retail - Direct Contribution | AW64: 164.76489 | AX64: 227.27839 | AZ64: OOH Retail | BA64: 174.63033 | BB64: 571.4762 | BC64: 217.41295 | BD64: 354.41373 | BF64: OOH Retail | BG64: =SUMIFS(AY$4:AY$40,$C$4:$C$40,$AR48) -> 174.63033 | BH64: =SUMIFS(BF$4:BF$40,$C$4:$C$40,$AR48) -> 256.54908 | BI64: =SUMIFS(AY$4:AY$40,$C$4:$C$40,$AR49) -> 217.41295 | BJ64: =SUMIFS(BF$4:BF$40,$C$4:$C$40,$AR49) -> 354.41373
AV65: YouTube + Facebook + Instagram - Lagged Contribution | AW65: 406.31878 | AX65: 1789.3193 | AZ65: Facebook + Instagram | BA65: 416.50987 | BB65: 761.06751 | BC65: 514.69536 | BD65: 696.68554 | BF65: Facebook + Instagram | BG65: =SUMIFS(AZ$4:AZ$40,$C$4:$C$40,$AR48) -> 416.50987 | BH65: =SUMIFS(BG$4:BG$40,$C$4:$C$40,$AR48) -> 626.2552 | BI65: =SUMIFS(AZ$4:AZ$40,$C$4:$C$40,$AR49) -> 514.69536 | BJ65: =SUMIFS(BG$4:BG$40,$C$4:$C$40,$AR49) -> 696.68554
AV66: Paid Search - Lagged Contribution | AW66: 133.09801 | AX66: 92.78463 | AZ66: YouTube | BA66: 353.18306 | BB66: 616.84484 | BC66: 362.44545 | BD66: 515.53178 | BF66: YouTube | BG66: =SUMIFS(BA$4:BA$40,$C$4:$C$40,$AR48) -> 353.18306 | BH66: =SUMIFS(BH$4:BH$40,$C$4:$C$40,$AR48) -> 520.32465 | BI66: =SUMIFS(BA$4:BA$40,$C$4:$C$40,$AR49) -> 362.44545 | BJ66: =SUMIFS(BH$4:BH$40,$C$4:$C$40,$AR49) -> 515.53178
AV67: Online Banners - Lagged Contribution | AW67: 223.92895 | AX67: 252.76922 | AZ67: YouTube + Facebook + Instagram - Lagged Contribution
AV68: OOH Large Format - Lagged Contribution | AW68: 307.71796 | AX68: 568.8978 | AZ68: Paid Search - Lagged Contribution
AV69: OOH Retail - Lagged Contribution | AW69: 65.366915 | AX69: 744.92317 | AZ69: Online Banners - Lagged Contribution
AZ70: OOH Large Format - Lagged Contribution
AZ71: OOH Retail - Lagged Contribution
AZ72: Facebook + Instagram - Lagged Contribution
AZ73: YouTube - Lagged Contribution
AW78: =_xlfn.TEXTJOIN(" ",TRUE,AW79:AW80) -> FY_2023 Direct contribution | AX78: =_xlfn.TEXTJOIN(" ",TRUE,AX79:AX80) -> FY_2023 Lagged contribution | AY78: =_xlfn.TEXTJOIN(" ",TRUE,AY79:AY80) -> FY_2024 Direct contribution | AZ78: =_xlfn.TEXTJOIN(" ",TRUE,AZ79:AZ80) -> FY_2024 Lagged contribution
AW79: FY_2023 | AX79: FY_2023 | AY79: FY_2024 | AZ79: FY_2024
AW80: Direct contribution | AX80: Lagged contribution | AY80: Direct contribution | AZ80: Lagged contribution
AV81: YouTube + Facebook + Instagram | AW81: 773.58424 | AX81: 406.31878 | AY81: 892.39149 | AZ81: 1789.3193
AV82: Paid Search | AW82: 224.61939 | AX82: 133.09801 | AY82: 132.59158 | AZ82: 92.78463
AV83: Online Banners | AW83: 577.5455 | AX83: 223.92895 | AY83: 0 | AZ83: 252.76922
AV84: OOH Large Format | AW84: 350.74417 | AX84: 307.71796 | AY84: 0 | AZ84: 568.8978
AV85: OOH Retail | AW85: 164.76489 | AX85: 65.366915 | AY85: 227.27839 | AZ85: 744.92317

Sheet Dinamica
B3: Column Labels
A4: Values | B4: FY_2022 | C4: FY_2023 | D4: FY_2024 | E4: FY_2025 | F4: Grand Total
A5: Sum of Discount PERIOD | B5: 7 | C5: 9 | D5: 3 | E5: 0 | F5: 19
A6: Average of Twinings_Price | B6: 88278.167 | C6: 92585.942 | D6: 95308.45 | E6: 95547.008 | F6: 92151.83
A7: Average of Discounts_5%_Min | B7: 0.060812735 | C7: 0.073015946 | D7: 0.016340343 | E7: 0 | F7: 0.048703467
A8: Average of Twinings_WD | B8: 76.932083 | C8: 76.607083 | D8: 79.410417 | E8: 83.384 | F8: 77.804838
A9: Sum of YouTube_FB_Spends | B9: 0 | C9: 50075894 | D9: 1.3719831e+08 | E9: 0 | F9: 1.872742e+08
A10: Sum of Google_Search_Spends | B10: 0 | C10: 7012253 | D10: 6869131 | E10: 0 | F10: 13881384
A11: Sum of Display_Spends | B11: 0 | C11: 18374818 | D11: 0 | E11: 0 | F11: 18374818
A12: Sum of OOH_Screen_Spends | B12: 0 | C12: 45574923 | D12: 0 | E12: 0 | F12: 45574923
A13: Sum of OOH_Retail_Spends | B13: 0 | C13: 18526087 | D13: 32173913 | E13: 0 | F13: 50700000
A14: Average of Covid_Index | B14: 31.908333 | C14: 5.75 | D14: 0 | E14: 0 | F14: 12.213514
A15: Average of Competitor_Price | B15: 15817.12 | C15: 18229.289 | D15: 19657.274 | E15: 20692.397 | F15: 17976.665
A16: Sum of Competitor_GRPs | B16: 3856.0564 | C16: 4943.1281 | D16: 4745.0781 | E16: 530.12079 | F16: 14074.383
A20: KPI | B20: FY 2022 | C20: FY 2023 | D20: FY 2024 | E20: Change FY'22 vs FY'23 | F20: Change FY'23 vs FY'24
A21: Average Twinings Price | B21: 88278.167 | C21: 92585.942 | D21: 95308.45 | E21: =C21/B21-1 -> 0.048797739 | F21: =D21/C21-1 -> 0.029405201
A22: Average Discounts | B22: 0.060812735 | C22: 0.073015946 | D22: 0.016340343 | E22: =C22/B22-1 -> 0.20066868 | F22: =D22/C22-1 -> -0.77620857
A23: Average Twinings WD | B23: 76.932083 | C23: 76.607083 | D23: 79.410417 | E23: =C23/B23-1 -> -0.0042245054 | F23: =D23/C23-1 -> 0.036593657
A24: Twinings Media Spend | B24: 0 | C24: 1.3956397e+08 | D24: 1.7624135e+08 | F24: =D24/C24-1 -> 0.26279975
A25: Average Covid Constringency Index | B25: 31.908333 | C25: 5.75 | D25: 0 | E25: =C25/B25-1 -> -0.81979629 | F25: =D25/C25-1 -> -1
A26: Average of Competitor_Price | B26: 15817.12 | C26: 18229.289 | D26: 19657.274 | E26: =C26/B26-1 -> 0.15250369 | F26: =D26/C26-1 -> 0.078334603
A27: Sum of Competitor_GRPs | B27: 3856.0564 | C27: 4943.1281 | D27: 4745.0781 | E27: =C27/B27-1 -> 0.28191281 | F27: =D27/C27-1 -> -0.04006573
E28: =C28/B28-1 -> #DIV/0! | F28: =D28/C28-1 -> #DIV/0!
B29: 7 | C29: 9 | D29: 3 | E29: =C29/B29-1 -> 0.28571429 | F29: =D29/C29-1 -> -0.66666667

Sheet Full Data
A1: Geography | B1: Period | C1: Year | D1: Twinings_Volume | E1: Twinings_Value | F1: Twinings_Price | G1: Competitor_Price | H1: Twinings_WD | I1: Dilmah_WD | J1: Te_Club_WD | K1: Competitor_WD | L1: Discounts_7%_Min | M1: Discounts_Price_Differential_vs_Year_Max | N1: Discounts_5%_Min | O1: Discount PERIOD | P1: Discounts_6%_Min | Q1: Facebook_Instagram_Impressions | R1: Facebook_Instagram_Spends | S1: YouTube_Impressions | T1: YouTube_Spends | U1: YouTube_FB_Impressions | V1: YouTube_FB_Spends | W1: Google_Search_Clicks | X1: Google_Search_Spends | Y1: Google_Organic_Search | Z1: Display_Impressions | AA1: Display_Spends | AB1: OOH_Screen_Spends | AC1: OOH_Screen_GRPs | AD1: OOH_Retail_Spends | AE1: OOH_Retail_GRPs | AF1: OOH_Cinema_Spends | AG1: OOH_Cinema_GRPs | AH1: Supremo_GRPs | AI1: Te_Club_GRPs | AJ1: Lipton_GRPs | AK1: Competitor_GRPs | AL1: Supremo_Spends | AM1: Te_Club_Spends | AN1: Lipton_Spends | AO1: Competitor_Spends | AP1: Inflation | AQ1: Temperature | AR1: Unployement_Index | AS1: GDP | AT1: Concumer_Trust_Index | AU1: Covid_Index | AV1: Winter_Solstice | AW1: Independence_Month | AX1: Christmas | AY1: APE | AZ1: Residual | BA1: Contribution-Base | BB1: Contribution-Twinings_Price | BC1: Contribution-Competitor_Price | BD1: Contribution-Twinings_WD | BE1: Contribution-Competitor_WD | BF1: Contribution-Discounts_5%_Min | BG1: Contribution-YouTube_FB_Impressions | BH1: Contribution-Google_Search_Clicks | BI1: Contribution-Display_Impressions | BJ1: Contribution-OOH_Screen_GRPs | BK1: Contribution-OOH_Retail_GRPs | BL1: Contribution-Competitor_GRPs | BM1: Contribution-Inflation | BN1: Contribution-Temperature | BO1: Contribution-Covid_Index | BP1: Contribution-Winter_Solstice | BQ1: Contribution-Independence_Month
A2: Chile | B2: 44440 | C2: FY_2022 | D2: 3309.968 | E2: 268358070 | F2: 81075.729 | G2: 15727.388 | H2: 75.557 | I2: 89.316 | J2: 57.873329 | K2: 77.15525 | L2: 0.14746772 | M2: 0.14746772 | N2: 0.14746772 | O2: =IF(N2>0,1,0) -> 1 | P2: 0.14746772 | Q2: 0 | R2: 0 | S2: 0 | T2: 0 | U2: 0 | V2: 0 | W2: 0 | X2: 0 | Y2: 0 | Z2: 0 | AA2: 0 | AB2: 0 | AC2: 0 | AD2: 0 | AE2: 0 | AF2: 0 | AG2: 0 | AH2: 468.2082 | AI2: 268.21275 | AJ2: 39.402786 | AK2: 775.82373 | AL2: 0 | AM2: 0 | AN2: 0 | AO2: 0 | AP2: 1.1778775 | AQ2: 12.1 | AR2: 8.4056112 | AS2: 16026.595 | AT2: 38.602875 | AU2: 58.1 | AV2: 0 | AW2: 1 | AX2: 0 | AY2: 0.020832139 | AZ2: -68.953714 | BA2: 2486.3069 | BB2: -405.80771 | BC2: 23.457837 | BD2: 88.337517 | BE2: -41.214992 | BF2: 602.36364 | BG2: 4.531819e-08 | BH2: 2.4060811e-08 | BI2: 3.5499081e-08 | BJ2: 2.0910124e-08 | BK2: 3.6233767e-09 | BL2: -72.034822 | BM2: -138.30448 | BN2: -190.76284 | BO2: 508.04528 | BP2: 0 | BQ2: 518.53543
A3: Chile | B3: 44470 | C3: FY_2022 | D3: 3028.298 | E3: 2.4899675e+08 | F3: 82223.331 | G3: 15195.163 | H3: 78.862 | I3: 91.333 | J3: 59.345455 | K3: 79.372791 | L3: 0.13540038 | M3: 0.13540038 | N3: 0.13540038 | O3: =IF(N3>0,1,0) -> 1 | P3: 0.13540038 | Q3: 0 | R3: 0 | S3: 0 | T3: 0 | U3: 0 | V3: 0 | W3: 0 | X3: 0 | Y3: 56 | Z3: 0 | AA3: 0 | AB3: 0 | AC3: 0 | AD3: 0 | AE3: 0 | AF3: 0 | AG3: 0 | AH3: 3.3770262 | AI3: 170.11277 | AJ3: 60.24991 | AK3: 233.7397 | AL3: 0 | AM3: 0 | AN3: 0 | AO3: 0 | AP3: 1.3410165 | AQ3: 14.8 | AR3: 8.0766005 | AS3: 16026.595 | AT3: 38.294675 | AU3: 37.7 | AV3: 0 | AW3: 0 | AX3: 0 | AY3: 0.030978031 | AZ3: 93.810709 | BA3: 2472.805 | BB3: -300.40606 | BC3: 3.2519825 | BD3: 348.14223 | BE3: -77.633851 | BF3: 662.25311 | BG3: 4.4237049e-08 | BH3: 2.3685674e-08 | BI3: 3.5473091e-08 | BJ3: 2.2251739e-08 | BK3: 3.9543283e-09 | BL3: -72.448133 | BM3: -156.9812 | BN3: -312.01809 | BO3: 367.52229 | BP3: 0 | BQ3: 0
A4: Chile | B4: 44501 | C4: FY_2022 | D4: 2525.561 | E4: 212570823 | F4: 84167.764 | G4: 15021.65 | H4: 78.118 | I4: 91.82 | J4: 59.635036 | K4: 80.879468 | L4: 0.11495417 | M4: 0.11495417 | N4: 0.11495417 | O4: =IF(N4>0,1,0) -> 1 | P4: 0.11495417 | Q4: 0 | R4: 0 | S4: 0 | T4: 0 | U4: 0 | V4: 0 | W4: 0 | X4: 0 | Y4: 96 | Z4: 0 | AA4: 0 | AB4: 0 | AC4: 0 | AD4: 0 | AE4: 0 | AF4: 0 | AG4: 0 | AH4: 581.69393 | AI4: 174.69948 | AJ4: 5.5167764 | AK4: 761.91019 | AL4: 0 | AM4: 0 | AN4: 0 | AO4: 0 | AP4: 0.49877719 | AQ4: 17.8 | AR4: 7.5276491 | AS4: 16026.595 | AT4: 34.230895 | AU4: 32.2 | AV4: 0 | AW4: 0 | AX4: 0 | AY4: 0.070298552 | AZ4: -177.54328 | BA4: 2469.04 | BB4: -296.87094 | BC4: 0 | BD4: 317.97258 | BE4: -106.07662 | BF4: 581.10768 | BG4: 4.3414245e-08 | BH4: 2.3657323e-08 | BI4: 3.5278081e-08 | BJ4: 2.3129084e-08 | BK4: 3.9226535e-09 | BL4: -79.62436 | BM4: -58.628364 | BN4: -450.0894 | BO4: 326.27371 | BP4: 0 | BQ4: 0
A5: Chile | B5: 44531 | C5: FY_2022 | D5: 2741.46 | E5: 260712553 | F5: 95099.893 | G5: 14951.082 | H5: 77.146 | I5: 91.677 | J5: 59.45317 | K5: 80.035332 | L5: 0 | M5: 0 | N5: 0 | O5: =IF(N5>0,1,0) -> 0 | P5: 0 | Q5: 0 | R5: 0 | S5: 0 | T5: 0 | U5: 0 | V5: 0 | W5: 0 | X5: 0 | Y5: 107 | Z5: 0 | AA5: 0 | AB5: 0 | AC5: 0 | AD5: 0 | AE5: 0 | AF5: 0 | AG5: 0 | AH5: 43.972823 | AI5: 179.24994 | AJ5: 10.022854 | AK5: 233.24562 | AL5: 0 | AM5: 0 | AN5: 0 | AO5: 0 | AP5: 0.78140216 | AQ5: 20 | AR5: 7.1898934 | AS5: 16026.595 | AT5: 33.701885 | AU5: 31.6 | AV5: 0 | AW5: 0 | AX5: 1 | AY5: 0.16290526 | AZ5: 446.59825 | BA5: 2447.4368 | BB5: -142.06705 | BC5: 16.15853 | BD5: 312.59825 | BE5: -82.661178 | BF5: 91.953482 | BG5: 4.2091654e-08 | BH5: 2.3005334e-08 | BI5: 3.5404535e-08 | BJ5: 2.4873794e-08 | BK5: 4.5340986e-09 | BL5: -86.216046 | BM5: -91.119559 | BN5: -540.29592 | BO5: 369.07441 | BP5: 0 | BQ5: 0
A6: Chile | B6: 44562 | C6: FY_2022 | D6: 2120.791 | E6: 178952366 | F6: 84380.01 | G6: 15075.673 | H6: 76.95 | I6: 89.609 | J6: 59.753445 | K6: 78.478416 | L6: 0.11272235 | M6: 0.11272235 | N6: 0.11272235 | O6: =IF(N6>0,1,0) -> 1 | P6: 0.11272235 | Q6: 0 | R6: 0 | S6: 0 | T6: 0 | U6: 0 | V6: 0 | W6: 0 | X6: 0 | Y6: 104 | Z6: 0 | AA6: 0 | AB6: 0 | AC6: 0 | AD6: 0 | AE6: 0 | AF6: 0 | AG6: 0 | AH6: 16.11189 | AI6: 0 | AJ6: 0 | AK6: 16.11189 | AL6: 4270269.5 | AM6: 0 | AN6: 0 | AO6: 4270269.5 | AP6: 1.2011129 | AQ6: 21.4 | AR6: 7.2714648 | AS6: 15268.746 | AT6: 34.95089 | AU6: 29.9 | AV6: 0 | AW6: 0 | AX6: 0 | AY6: 0.090961251 | AZ6: -192.9098 | BA6: 2469.8363 | BB6: -328.68596 | BC6: 11.907814 | BD6: 250.44131 | BE6: -67.563189 | BF6: 474.28451 | BG6: 4.216859e-08 | BH6: 2.3638541e-08 | BI6: 3.4775597e-08 | BJ6: 2.4087149e-08 | BK6: 3.8383432e-09 | BL6: -43.124682 | BM6: -142.97646 | BN6: -620.55192 | BO6: 310.13311 | BP6: 0 | BQ6: 0
A7: Chile | B7: 44593 | C7: FY_2022 | D7: 2025.474 | E7: 176413263 | F7: 87097.274 | G7: 15329.93 | H7: 77.934 | I7: 89.951 | J7: 58.502907 | K7: 78.67244 | L7: 0.084149611 | M7: 0.084149611 | N7: 0.084149611 | O7: =IF(N7>0,1,0) -> 1 | P7: 0.084149611 | Q7: 0 | R7: 0 | S7: 0 | T7: 0 | U7: 0 | V7: 0 | W7: 0 | X7: 0 | Y7: 110 | Z7: 0 | AA7: 0 | AB7: 0 | AC7: 0 | AD7: 0 | AE7: 0 | AF7: 0 | AG7: 0 | AH7: 2.624368 | AI7: 0 | AJ7: 0 | AK7: 2.624368 | AL7: 33047.972 | AM7: 0 | AN7: 0 | AO7: 33047.972 | AP7: 0.28933382 | AQ7: 20.7 | AR7: 7.4985219 | AS7: 15268.746 | AT7: 35.472745 | AU7: 29.4 | AV7: 0 | AW7: 0 | AX7: 0 | AY7: 0.19669296 | AZ7: -398.39648 | BA7: 2473.4603 | BB7: -401.39174 | BC7: 32.352805 | BD7: 312.15807 | BE7: -73.834497 | BF7: 407.44942 | BG7: 4.1765391e-08 | BH7: 2.3647195e-08 | BI7: 3.4416747e-08 | BJ7: 2.4321727e-08 | BK7: 3.7176595e-09 | BL7: -2.0469915 | BM7: -34.694541 | BN7: -591.38525 | BO7: 301.80291 | BP7: 0 | BQ7: 0
A8: Chile | B8: 44621 | C8: FY_2022 | D8: 2782.846 | E8: 253028625 | F8: 90924.408 | G8: 15728.361 | H8: 76.572 | I8: 90.073 | J8: 60 | K8: 79.395653 | L8: 0 | M8: 0.043906306 | N8: 0 | O8: =IF(N8>0,1,0) -> 0 | P8: 0 | Q8: 0 | R8: 0 | S8: 0 | T8: 0 | U8: 0 | V8: 0 | W8: 0 | X8: 0 | Y8: 122 | Z8: 0 | AA8: 0 | AB8: 0 | AC8: 0 | AD8: 0 | AE8: 0 | AF8: 0 | AG8: 0 | AH8: 0 | AI8: 0 | AJ8: 0 | AK8: 0 | AL8: 0 | AM8: 0 | AN8: 0 | AO8: 0 | AP8: 1.8545071 | AQ8: 18.9 | AR8: 7.7978652 | AS8: 15268.746 | AT8: 33.09346 | AU8: 29 | AV8: 0 | AW8: 0 | AX8: 0 | AY8: 0.13090128 | AZ8: 364.27812 | BA8: 2439.2559 | BB8: -78.363982 | BC8: 95.651762 | BD8: 302.2904 | BE8: -68.995241 | BF8: 67.796035 | BG8: 4.0555644e-08 | BH8: 2.2296515e-08 | BI8: 3.4657263e-08 | BJ8: 2.6368881e-08 | BK8: 4.9411717e-09 | BL8: -0.0099414147 | BM8: -217.05787 | BN8: -486.65614 | BO8: 364.65694 | BP8: 0 | BQ8: 0
A9: Chile | B9: 44652 | C9: FY_2022 | D9: 2487.264 | E9: 225519775 | F9: 90669.818 | G9: 15970.924 | H9: 74.961 | I9: 89.114 | J9: 61.594203 | K9: 77.175024 | L9: 0 | M9: 0.046583386 | N9: 0 | O9: =IF(N9>0,1,0) -> 0 | P9: 0 | Q9: 0 | R9: 0 | S9: 0 | T9: 0 | U9: 0 | V9: 0 | W9: 0 | X9: 0 | Y9: 141 | Z9: 0 | AA9: 0 | AB9: 0 | AC9: 0 | AD9: 0 | AE9: 0 | AF9: 0 | AG9: 0 | AH9: 0 | AI9: 0 | AJ9: 0 | AK9: 0 | AL9: 0 | AM9: 0 | AN9: 0 | AO9: 0 | AP9: 1.3982786 | AQ9: 15 | AR9: 7.7474932 | AS9: 15268.746 | AT9: 31.40742 | AU9: 27 | AV9: 0 | AW9: 0 | AX9: 0 | AY9: 0.015193871 | AZ9: -37.791168 | BA9: 2438.6478 | BB9: -75.960646 | BC9: 117.77452 | BD9: 192.71114 | BE9: -28.260112 | BF9: 10.168074 | BG9: 4.0245759e-08 | BH9: 2.1978655e-08 | BI9: 3.4332068e-08 | BJ9: 2.6549414e-08 | BK9: 5.1215194e-09 | BL9: -4.7360961e-05 | BM9: -164.29248 | BN9: -309.48337 | BO9: 343.75031 | BP9: 0 | BQ9: 0
A10: Chile | B10: 44682 | C10: FY_2022 | D10: 3227.268 | E10: 289506908 | F10: 89706.497 | G10: 16601.22 | H10: 77.554 | I10: 91.267 | J10: 62.807525 | K10: 78.787091 | L10: 0 | M10: 0.056712956 | N10: 0.056712956 | O10: =IF(N10>0,1,0) -> 1 | P10: 0 | Q10: 0 | R10: 0 | S10: 0 | T10: 0 | U10: 0 | V10: 0 | W10: 0 | X10: 0 | Y10: 222 | Z10: 0 | AA10: 0 | AB10: 0 | AC10: 0 | AD10: 0 | AE10: 0 | AF10: 0 | AG10: 0 | AH10: 0 | AI10: 0 | AJ10: 0 | AK10: 0 | AL10: 0 | AM10: 0 | AN10: 0 | AO10: 0 | AP10: 1.1988546 | AQ10: 11.5 | AR10: 7.8039798 | AS10: 15268.746 | AT10: 29.804635 | AU10: 27.1 | AV10: 0 | AW10: 0 | AX10: 0 | AY10: 0.0041514197 | AZ10: 13.397744 | BA10: 2434.8381 | BB10: -36.49203 | BC10: 171.79209 | BD10: 376.43802 | BE10: -54.308505 | BF10: 256.57738 | BG10: 3.9836385e-08 | BH10: 2.1548683e-08 | BI10: 3.4051022e-08 | BJ10: 2.6916924e-08 | BK10: 5.4112787e-09 | BL10: -1.1326818e-06 | BM10: -141.06156 | BN10: -149.1075 | BO10: 355.19429 | BP10: 0 | BQ10: 0
A11: Chile | B11: 44713 | C11: FY_2022 | D11: 3720.315 | E11: 348664012 | F11: 93718.949 | G11: 16463.369 | H11: 76.74 | I11: 90.72 | J11: 70.404624 | K11: 82.993615 | L11: 0 | M11: 0.014520984 | N11: 0 | O11: =IF(N11>0,1,0) -> 0 | P11: 0 | Q11: 0 | R11: 0 | S11: 0 | T11: 0 | U11: 0 | V11: 0 | W11: 0 | X11: 0 | Y11: 187 | Z11: 0 | AA11: 0 | AB11: 0 | AC11: 0 | AD11: 0 | AE11: 0 | AF11: 0 | AG11: 0 | AH11: 0 | AI11: 95.603473 | AJ11: 0 | AK11: 95.603473 | AL11: 0 | AM11: 0 | AN11: 0 | AO11: 0 | AP11: 0.9326304 | AQ11: 8.8 | AR11: 7.8114738 | AS11: 15268.746 | AT11: 29.377175 | AU11: 27 | AV11: 1 | AW11: 0 | AX11: 0 | AY11: 0.024908859 | AZ11: 92.6688 | BA11: 2432.474 | BB11: -30.561234 | BC11: 167.88313 | BD11: 324.65844 | BE11: -127.21848 | BF11: 38.675634 | BG11: 3.9499785e-08 | BH11: 2.1176057e-08 | BI11: 3.3759914e-08 | BJ11: 2.7183723e-08 | BK11: 5.6534115e-09 | BL11: -0.018397855 | BM11: -109.99467 | BN11: -25.598204 | BO11: 361.5561 | BP11: 595.78993 | BQ11: 0
A12: Chile | B12: 44743 | C12: FY_2022 | D12: 2943.439 | E12: 272636324 | F12: 92625.097 | G12: 16669.438 | H12: 76.757 | I12: 89.425 | J12: 72.170151 | K12: 82.864963 | L12: 0 | M12: 0.026023121 | N12: 0 | O12: =IF(N12>0,1,0) -> 0 | P12: 0 | Q12: 0 | R12: 0 | S12: 0 | T12: 0 | U12: 0 | V12: 0 | W12: 0 | X12: 0 | Y12: 189 | Z12: 0 | AA12: 0 | AB12: 0 | AC12: 0 | AD12: 0 | AE12: 0 | AF12: 0 | AG12: 0 | AH12: 812.98696 | AI12: 143.05752 | AJ12: 0 | AK12: 956.04448 | AL12: 1.1708773e+08 | AM12: 0 | AN12: 0 | AO12: 1.1708773e+08 | AP12: 1.3747565 | AQ12: 8.2 | AR12: 7.9188115 | AS12: 15268.746 | AT12: 26.919255 | AU12: 27 | AV12: 0 | AW12: 0 | AX12: 0 | AY12: 0.042860436 | AZ12: 126.15708 | BA12: 2437.3293 | BB12: -87.756429 | BC12: 182.68614 | BD12: 313.23141 | BE12: -126.241 | BF12: 5.7017983 | BG12: 3.9339584e-08 | BH12: 2.1027383e-08 | BI12: 3.3380169e-08 | BJ12: 2.706525e-08 | BK12: 5.6287082e-09 | BL12: -100.3737 | BM12: -163.51 | BN12: 0 | BO12: 356.21444 | BP12: 0 | BQ12: 0
A13: Chile | B13: 44774 | C13: FY_2022 | D13: 2856.853 | E13: 250400968 | F13: 87649.231 | G13: 17071.247 | H13: 76.034 | I13: 89.675 | J13: 71.305595 | K13: 80.801766 | L13: 0.07834564 | M13: 0.07834564 | N13: 0.07834564 | O13: =IF(N13>0,1,0) -> 1 | P13: 0.07834564 | Q13: 0 | R13: 0 | S13: 0 | T13: 0 | U13: 0 | V13: 0 | W13: 0 | X13: 0 | Y13: 169 | Z13: 0 | AA13: 0 | AB13: 0 | AC13: 0 | AD13: 0 | AE13: 0 | AF13: 0 | AG13: 0 | AH13: 584.78638 | AI13: 151.19719 | AJ13: 44.969406 | AK13: 780.95297 | AL13: 1.0962042e+08 | AM13: 0 | AN13: 0 | AO13: 1.0962042e+08 | AP13: 1.2109226 | AQ13: 9.7 | AR13: 7.9293998 | AS13: 15268.746 | AT13: 26.222545 | AU13: 26.9 | AV13: 0 | AW13: 0 | AX13: 0 | AY13: 0.02101976 | AZ13: -60.050363 | BA13: 2451.2042 | BB13: -224.97387 | BC13: 203.8549 | BD13: 231.93651 | BE13: -94.987085 | BF13: 333.45236 | BG13: 3.9434355e-08 | BH13: 2.1271468e-08 | BI13: 3.2746273e-08 | BJ13: 2.6559694e-08 | BK13: 5.2285826e-09 | BL13: -96.92285 | BM13: -146.27735 | BN13: -73.15946 | BO13: 332.77597 | BP13: 0 | BQ13: 0
... A38: Chile | B38: 45536 | C38: FY_2025 | D38: 4210.684 | E38: 402318259 | F38: 95547.008 | G38: 20692.397 | H38: 83.384 | I38: 92.72 | J38: 74.986103 | K38: 82.794983 | L38: 0 | M38: 0 | N38: 0 | O38: =IF(N38>0,1,0) -> 0 | P38: 0 | Q38: 0 | R38: 0 | S38: 0 | T38: 0 | U38: 0 | V38: 0 | W38: 0 | X38: 0 | Y38: 308 | Z38: 0 | AA38: 0 | AB38: 0 | AC38: 0 | AD38: 0 | AE38: 0 | AF38: 0 | AG38: 0 | AH38: 378.41224 | AI38: 151.70855 | AJ38: 0 | AK38: 530.12079 | AL38: 71858077 | AM38: 25948334 | AN38: 0 | AO38: 97806411 | AP38: 0.087768664 | AQ38: 12.1 | AR38: 8.7423149 | AS38: 0 | AT38: 31.836135 | AU38: 0 | AV38: 0 | AW38: 1 | AX38: 0 | AY38: 0.024494454 | AZ38: 103.13841 | BA38: 2444.9632 | BB38: 0 | BC38: 436.14917 | BD38: 640.40914 | BE38: -95.872775 | BF38: 0 | BG38: 375.34962 | BH38: 0.0028087807 | BI38: 2.7641688e-08 | BJ38: 2.1569365e-07 | BK38: 115.59984 | BL38: -111.0964 | BM38: -10.765847 | BN38: -203.37505 | BO38: 0 | BP38: 0 | BQ38: 516.18183
Q42: Facebook_Instagram_Impressions | R42: Facebook_Instagram_Spends | S42: YouTube_Impressions | T42: YouTube_Spends | U42: YouTube_FB_Impressions | V42: YouTube_FB_Spends | W42: Google_Search_Clicks | X42: Google_Search_Spends | Y42: Google_Organic_Search | Z42: Display_Impressions | AA42: Display_Spends | AB42: OOH_Screen_Spends | AC42: OOH_Screen_GRPs | AD42: OOH_Retail_Spends | AE42: OOH_Retail_GRPs | AF42: OOH_Cinema_Spends

Sheet Descriptivos
B1: Contribution - Residual | C1: Contribution - Base | D1: Contribution - Twinings_Price | E1: Contribution - Competitor_Price | F1: Contribution - Twinings_WD | G1: Contribution - Competitor_WD | H1: Contribution - Discounts_5%_Min | I1: Contribution - YouTube_FB_Impressions | J1: Contribution - Google_Search_Clicks | K1: Contribution - Display_Impressions | L1: Contribution - OOH_Screen_GRPs | M1: Contribution - OOH_Retail_GRPs | N1: Contribution - Competitor_GRPs | O1: Contribution - Inflation | P1: Contribution - Temperature | Q1: Contribution - Covid_Index | R1: Contribution - Winter_Solstice | S1: Contribution - Independence_Month
A2: count | B2: 37 | C2: 37 | D2: 37 | E2: 37 | F2: 37 | G2: 37 | H2: 37 | I2: 37 | J2: 37 | K2: 37 | L2: 37 | M2: 37 | N2: 37 | O2: 37 | P2: 37 | Q2: 37 | R2: 37 | S2: 37
A3: mean | B3: 2.0627168 | C3: 2465.1362 | D3: -310.39738 | E3: 243.0523 | F3: 270.4449 | G3: -121.31284 | H3: 234.69371 | I3: 114.51252 | J3: 15.759363 | K3: 28.493072 | L3: 33.17189 | M3: 35.619816 | N3: -70.145284 | O3: -73.844453 | P3: -327.04242 | Q3: 137.91776 | R3: 47.841519 | S3: 55.85127
A4: min | B4: -398.39648 | C4: 2432.474 | D4: -827.935 | E4: 0 | F4: 0 | G4: -256.99128 | H4: 0 | I4: 3.9018266e-08 | J4: 1.7443191e-08 | K4: 2.7641688e-08 | L4: 2.0910124e-08 | M4: 3.6233767e-09 | N4: -111.0964 | O4: -217.05787 | P4: -660.80319 | Q4: 0 | R4: 0 | S4: 0
A5: 0.25 | B5: -177.54328 | C5: 2452.5354 | D5: -447.04365 | E5: 171.79209 | F5: 173.30839 | G5: -182.00252 | H5: 38.675634 | I5: 3.9443678e-08 | J5: 2.1271468e-08 | K5: 3.14292e-08 | L5: 2.482858e-08 | M5: 5.1215194e-09 | N5: -96.92285 | O5: -109.99467 | P5: -533.64757 | Q5: 0 | R5: 0 | S5: 0
A6: 0.5 | B6: -2.2200222 | C6: 2466.5158 | D6: -300.40606 | E6: 288.00572 | F6: 231.93651 | G6: -95.872775 | H6: 256.57738 | I6: 4.3414245e-08 | J6: 2.3657323e-08 | K6: 3.4416747e-08 | L6: 2.6916924e-08 | M6: 7.61869e-09 | N6: -90.405011 | O6: -73.196175 | P6: -319.48025 | Q6: 0 | R6: 0 | S6: 0
A7: 0.75 | B7: 93.810709 | C7: 2472.805 | D7: -140.13616 | E7: 331.1934 | F7: 324.65844 | G7: -61.790385 | H7: 407.44942 | I7: 348.10024 | J7: 0.0028087807 | K7: 1.3983778e-07 | L7: 0.016276671 | M7: 77.838029 | N7: -43.124682 | O7: -33.168675 | P7: -149.1075 | Q7: 326.27371 | R7: 0 | S7: 0
A8: max | B8: 446.59825 | C8: 2512.4215 | D8: 0 | E8: 436.14917 | F8: 765.1333 | G8: 0 | H8: 662.25311 | I8: 396.7406 | J8: 174.83294 | K8: 271.09594 | L8: 224.1308 | M8: 129.3393 | N8: -1.1326818e-06 | O8: 65.043704 | P8: 0 | Q8: 508.04528 | R8: 595.78993 | S8: 519.93445
A9: std | B9: 213.77129 | C9: 19.617589 | D9: 217.03332 | E9: 130.75023 | F9: 168.20403 | G9: 75.931014 | H9: 223.24121 | I9: 169.87614 | J9: 40.766272 | K9: 80.622618 | L9: 74.928239 | M9: 49.746716 | N9: 40.772662 | O9: 61.565967 | P9: 218.47444 | Q9: 170.41025 | R9: 163.28505 | S9: 162.63658

Sheet Corr
B1: Twinings_Volume | C1: Twinings_Value | D1: Twinings_Price | E1: Competitor_Price | F1: Twinings_WD | G1: Dilmah_WD | H1: Te_Club_WD | I1: Competitor_WD | J1: Discounts_7%_Min | K1: Discounts_Price_Differential_vs_Year_Max | L1: Discounts_5%_Min | M1: Discounts_6%_Min | N1: Facebook_Instagram_Impressions | O1: Facebook_Instagram_Spends | P1: YouTube_Impressions | Q1: YouTube_Spends | R1: YouTube_FB_Impressions | S1: YouTube_FB_Spends | T1: Google_Search_Clicks | U1: Google_Search_Spends | V1: Google_Organic_Search | W1: Display_Impressions | X1: Display_Spends | Y1: OOH_Screen_Spends | Z1: OOH_Screen_GRPs | AA1: OOH_Retail_Spends | AB1: OOH_Retail_GRPs | AC1: OOH_Cinema_Spends | AD1: OOH_Cinema_GRPs | AE1: Supremo_GRPs | AF1: Te_Club_GRPs | AG1: Lipton_GRPs | AH1: Competitor_GRPs | AI1: Supremo_Spends | AJ1: Te_Club_Spends | AK1: Lipton_Spends | AL1: Competitor_Spends | AM1: Inflation | AN1: Temperature | AO1: Unployement_Index | AP1: GDP | AQ1: Concumer_Trust_Index | AR1: Covid_Index | AS1: Winter_Solstice | AT1: Independence_Month | AU1: Christmas | AV1: APE | AW1: Contribution - Residual | AX1: Contribution - Base | AY1: Contribution - Twinings_Price | AZ1: Contribution - Competitor_Price | BA1: Contribution - Twinings_WD | BB1: Contribution - Competitor_WD | BC1: Contribution - Discounts_5%_Min | BD1: Contribution - YouTube_FB_Impressions | BE1: Contribution - Google_Search_Clicks | BF1: Contribution - Display_Impressions | BG1: Contribution - OOH_Screen_GRPs | BH1: Contribution - OOH_Retail_GRPs | BI1: Contribution - Competitor_GRPs | BJ1: Contribution - Inflation | BK1: Contribution - Temperature | BL1: Contribution - Covid_Index | BM1: Contribution - Winter_Solstice | BN1: Contribution - Independence_Month
